Workbook

Sheet RENOVACIÓN TC FCS
B6: PROPUESTA DE RENOVACIÓN DOCENTE TC PARA SEMESTRE ACADÉMICO 2026-1 FACULTAD DE CIENCIAS DE LA SALUD
B8: N° | C8: DNI | D8: APELLIDOS Y NOMBRES | E8: FACULTAD | F8: ESCUELA PROFESIONAL | G8: LOCAL | H8: MODALIDAD | I8: N° HORAS LECTIVAS | J8: N° HORAS NO LECTIVAS | K8: TOAL DE HORAS | L8: NOTA EVALUACIÓN DEL DESEMPEÑO 2025-2 | M8: CARGO | N8: CORREO ELECTRÓNICO INSTITUCIONAL | O8: N° CELULAR | P8: OBSERVACIONES
B9: 1 | C9: 45549528 | D9: ACHARTE CHAMPI WALTER JESUS | E9: FCS | F9: ENFERMERÍA | G9: SEDE | H9: VIRTUAL | I9: 40 | K9: =+I9+J9 -> 40 | L9: 17.51 | N9: walter.acharte@autonomadeica.edu.pe | O9: 969804997
B10: 2 | C10: 40364065 | D10: ACOSTA VILLAVICENCIO BLANCA AURORA | E10: FCS | F10: OBSTETRICIA - EEGG | G10: SEDE | H10: MAS PRESENCIAL | I10: 32 | K10: =+I10+J10 -> 32 | L10: 15.96 | N10: blanca.acosta@autonomadeica.edu.pe | O10: 956 722222
B11: 3 | C11: 43041422 | D11: ANTEZANA CHINQUILLO JOSE GIANCARLO | E11: FCS | F11: MEDICINA HUMANA | G11: PORUMA | H11: PRESENCIAL | I11: 32 | K11: =+I11+J11 -> 32 | L11: 15.44 | N11: jose.antezana@autonomadeica.edu.pe | O11: 984949379
B12: 4 | C12: 42508963 | D12: APOLAYA PAREJA BERTHA ESTHER | E12: FCS | F12: OBSTETRICIA | G12: SEDE | H12: MAS PRESENCIAL | I12: 24 | K12: =+I12+J12 -> 24 | L12: 17.75 | N12: bertha.apolaya@autonomadeica.edu.pe | O12: 923395834
B13: 5 | C13: 21427721 | D13: ARQUIÑEGO SOLAR HENRRY MARCOS | E13: FCS | F13: ENFERMERÍA | G13: FILIAL | H13: MAS VIRTUAL | I13: 30 | K13: =+I13+J13 -> 30 | L13: 15.37 | N13: henrry.arquinego@autonomadeica.edu.pe | O13: 956467500
B14: 6 | C14: 40385643 | D14: ARREDONDO ZELA SONIA OLIVIA | E14: FCS | F14: OBSTETRICIA - EEGG | G14: SEDE | H14: PRESENCIAL | I14: 38 | K14: =+I14+J14 -> 38 | L14: 15.91 | N14: sonia.arredondo@autonomadeica.edu.pe | O14: 978 833677
B15: 7 | C15: 80034938 | D15: ARROYO PACHAS JOSE LUIS | E15: FCS | F15: ENFERMERÍA | G15: SEDE | H15: MAS PRESENCIAL | I15: 32 | K15: =+I15+J15 -> 32 | L15: 14.12 | N15: jose.arroyo@autonomadeica.edu.pe | O15: 965346069
B16: 8 | C16: 21536202 | D16: ATME ROJAS DAVEY RAUL | E16: FCS | F16: PSICOLOGÍA | G16: FILIAL | H16: MAS VIRTUAL | I16: 25 | K16: =+I16+J16 -> 25 | L16: 16.25 | N16: davey.atme@autonomadeica.edu.pe | O16: 956445166_x000D_
B17: 9 | C17: 21836179 | D17: ATUNCAR VASQUEZ RICARDO MANUEL | E17: FCS | F17: OBSTETRICIA | G17: SEDE | H17: MAS PRESENCIAL | I17: 34 | K17: =+I17+J17 -> 34 | L17: 15.73 | N17: ricardo.atuncar@autonomadeica.edu.pe | O17: 955923228
B18: 10 | C18: 8822479 | D18: AYBAR HUAMANI JUSTINIANO | E18: FCS | F18: ENFERMERÍA - EEGG | G18: SEDE | H18: MAS PRESENCIAL | I18: 39 | K18: =+I18+J18 -> 39 | L18: 17.06 | N18: justiniano.aybar@autonomadeica.edu.pe | O18: 995144584
B19: 11 | C19: 21416373 | D19: BARRIOS GABRIEL SONIA EDITH | E19: FCS | F19: MEDICINA HUMANA - EEGG | G19: PORUMA | H19: PRESENCIAL | I19: 30 | K19: =+I19+J19 -> 30 | L19: 15.57 | N19: sonia.barrios@autonomadeica.edu.pe | O19: 966713033
B20: 12 | C20: 15738929 | D20: BAZALAR GANOZA BEATRIZ ROSARIO | E20: FCS | F20: ENFERMERÍA - EEGG | G20: HUAURA | H20: PRESENCIAL | I20: 30 | K20: =+I20+J20 -> 30 | L20: 15.07 | N20: beatriz.bazalar@autonomadeica.edu.pe | O20: 5774800 / 940029503
B21: 13 | C21: 70431834 | D21: BELLIDO LEON FRANK JUNIOR | E21: FCS | F21: ENFERMERÍA | G21: SEDE | H21: PRESENCIAL | I21: 31 | K21: =+I21+J21 -> 31 | L21: 15.69 | N21: frank.bellido@autonomadeica.edu.pe | O21: 945102061
B22: 14 | C22: 72580385 | D22: BENAVIDES ESCRIBA VICTOR MANUEL | E22: FCS | F22: ENFERMERÍA | G22: SEDE | H22: MAS PRESENCIAL | I22: 32 | K22: =+I22+J22 -> 32 | L22: 16.31 | N22: manuel.benavides@autonomadeica.edu.pe | O22: 950357206
B23: 15 | C23: 71819567 | D23: BENDEZU HUAROTO ALEX RAUL | E23: FCS | F23: MEDICINA HUMANA - EEGG | G23: PORUMA | H23: MAS PRESENCIAL | I23: 37 | K23: =+I23+J23 -> 37 | L23: 16.53 | N23: alex.bendezu@autonomadeica.edu.pe | O23: 999558590
B24: 16 | C24: 42825709 | D24: CABRERA PIMENTEL HELGA ROXANA | E24: FCS | F24: ENFERMERÍA | G24: FILIAL | H24: AMBOS | I24: 32 | K24: =+I24+J24 -> 32 | L24: 15.60 | N24: helga.cabrera@autonomadeica.edu.pe | O24: 964743177
B25: 17 | C25: 21440811 | D25: CABRERA VIZARRETA MARTHA LUISA | E25: FCS | F25: MEDICINA HUMANA - EEGG | G25: PORUMA | H25: MAS PRESENCIAL | I25: 33 | K25: =+I25+J25 -> 33 | L25: 16.03 | N25: martha.cabrera@autonomadeica.edu.pe | O25: 976110252
B26: 18 | C26: 21567738 | D26: CAHUANA MUÑOZ BETTY MARISEL | E26: FCS | F26: OBSTETRICIA | G26: FILIAL | H26: PRESENCIAL | I26: 32 | K26: =+I26+J26 -> 32 | L26: 14.69 | N26: betty.cahuana@autonomadeica.edu.pe | O26: 953734738
B27: 19 | C27: 21453025 | D27: CALLAÑAUPA VARGAS JULIA ANTONIA | E27: FCS | F27: MEDICINA HUMANA | G27: SUNAMPE | H27: MAS VIRTUAL | I27: 22 | K27: =+I27+J27 -> 22 | L27: 14.91 | N27: julia.callanaupa@autonomadeica.edu.pe | O27: 955626346
B28: 20 | C28: 40056370 | D28: CAMPOS CARDENAS SANDRA GISELA | E28: FCS | F28: ENFERMERÍA | G28: SEDE | H28: MAS VIRTUAL | I28: 30 | K28: =+I28+J28 -> 30 | L28: 14.24 | N28: sandra.campos@autonomadeica.edu.pe | O28: 951988838
B29: 21 | C29: 46475398 | D29: CANDELA LEVANO CECIL MASSIEL | E29: FCS | F29: ENFERMERÍA | G29: FILIAL | H29: VIRTUAL | I29: 24 | K29: =+I29+J29 -> 24 | L29: 15.82 | N29: cecil.candela@autonomadeica.edu.pe | O29: 949369092
B30: 22 | C30: 21463142 | D30: CARRASCO VASQUEZ JOSE LUIS | E30: FCS | F30: OBSTETRICIA | G30: SEDE | H30: PRESENCIAL | I30: 38 | K30: =+I30+J30 -> 38 | L30: 13.91 | N30: jose.carrasco@autonomadeica.edu.pe | O30: 968974470
B31: 23 | C31: 41845220 | D31: CASTRO VILCAPUMA NATHIA ERIKA | E31: FCS | F31: OBSTETRICIA - EEGG | G31: SEDE | H31: PRESENCIAL | I31: 35 | K31: =+I31+J31 -> 35 | L31: 15.37 | N31: nathia.castro@autonomadeica.edu.pe | O31: 999642883
B32: 24 | C32: 21418654 | D32: CENTENO OCHOA FANNY EDITH | E32: FCS | F32: ENFERMERÍA | G32: FILIAL | H32: MAS VIRTUAL | I32: 28 | K32: =+I32+J32 -> 28 | L32: 14.44 | N32: fanny.centeno@autonomadeica.edu.pe | O32: 947827681
B33: 25 | C33: 45440179 | D33: CHACALTANA CORDERO HILDA GLORIA | E33: FCS | F33: ENFERMERÍA | G33: FILIAL | H33: MAS PRESENCIAL | I33: 32 | K33: =+I33+J33 -> 32 | L33: 16.54 | N33: hilda.chacaltana@autonomadeica.edu.pe | O33: 982739733_x000D_
B34: 26 | C34: 32111220 | D34: COLONIA OSORIO NIEVES PILAR | E34: FCS | F34: ENFERMERÍA - EEGG | G34: HUAURA | H34: PRESENCIAL | I34: 37 | K34: =+I34+J34 -> 37 | L34: 15.83 | N34: nieves.colonia@autonomadeica.edu.pe | O34: 966799630
B35: 27 | C35: 21426247 | D35: COMECA VILDOZO ANGEL ORLANDO | E35: FCS | F35: MEDICINA HUMANA | G35: SUNAMPE | H35: PRESENCIAL | I35: 39 | K35: =+I35+J35 -> 39 | L35: 14.69 | N35: angel.comeca@autonomadeica.edu.pe | O35: 992158166/956620126
B36: 28 | C36: 47849946 | D36: CORDOVA GUTIERREZ MARCO ANDREE | E36: FCS | F36: TECNOLOGÍA MÉDICA | G36: SUNAMPE | H36: MAS PRESENCIAL | I36: 32 | K36: =+I36+J36 -> 32 | L36: 15.84 | N36: marco.cordova@autonomadeica.edu.pe | O36: 934 260 986
B37: 29 | C37: 21533626 | D37: CUBA MAYURI RICHARD ALEJANDRO | E37: FCS | F37: ENFERMERÍA | G37: SEDE | H37: MAS VIRTUAL | I37: 33 | K37: =+I37+J37 -> 33 | L37: 15.56 | N37: richard.cuba@autonomadeica.edu.pe | O37: 942659212
B38: 30 | C38: 73039674 | D38: CUELLO GARCIA MEGALLY FIORELLA | E38: FCS | F38: MEDICINA HUMANA | G38: PORUMA | H38: VIRTUAL | I38: 28 | K38: =+I38+J38 -> 28 | L38: 16.23 | N38: megally.cuello@autonomadeica.edu.pe | O38: 951794771
B39: 31 | C39: 40689619 | D39: DEL PINO ASCONA DENNIS YVONNE | E39: FCS | F39: PSICOLOGÍA | G39: FILIAL | H39: VIRTUAL | I39: 39 | K39: =+I39+J39 -> 39 | L39: 16.47 | N39: dennis.delpino@autonomadeica.edu.pe | O39: 991041688
B40: 32 | C40: 15586796 | D40: DIAZ BAZALAR WILLIAM JESUS | E40: FCS | F40: ENFERMERÍA - EEGG | G40: HUAURA | H40: PRESENCIAL | I40: 32 | K40: =+I40+J40 -> 32 | L40: 14.67 | N40: william.diaz@autonomadeica.edu.pe | O40: 993456461
B41: 34 | C41: 41134475 | D41: DURAND DIEZ FRANCISCO | E41: FCS | F41: MEDICINA HUMANA | G41: PORUMA | H41: MAS VIRTUAL | I41: 36 | K41: =+I41+J41 -> 36 | L41: 15.86 | N41: francisco.durand@autonomadeica.edu.pe | O41: 991602985
B42: 35 | C42: 72254013 | D42: ESPINOZA ALARCON YADY | E42: FCS | F42: ENFERMERÍA | G42: SEDE | H42: VIRTUAL | I42: 40 | K42: =+I42+J42 -> 40 | L42: 18.06 | N42: yady.espinoza@autonomadeica.edu.pe | O42: 925777177
B43: 36 | C43: 42684701 | D43: ESPINOZA BARRIOS LUZ MARIANELA | E43: FCS | F43: ENFERMERÍA | G43: FILIAL | H43: MAS VIRTUAL | I43: 26 | K43: =+I43+J43 -> 26 | L43: 16.35 | N43: luz.espinoza@autonomadeica.edu.pe | O43: 948981510
B44: 37 | C44: 21529591 | D44: ESPINOZA TARQUI MAGDALENA | E44: FCS | F44: ENFERMERÍA | G44: FILIAL | H44: PRESENCIAL | I44: 32 | K44: =+I44+J44 -> 32 | L44: 15.28 | N44: magdalena.espinoza@autonomadeica.edu.pe | O44: 955601089
B45: 38 | C45: 6919367 | D45: GALVAN CANTA MARIA MAGDALENA | E45: FCS | F45: OBSTETRICIA | G45: SEDE | H45: PRESENCIAL | I45: 36 | K45: =+I45+J45 -> 36 | L45: 15.33 | N45: maria.galvan@autonomadeica.edu.pe | O45: 956217730
B46: 39 | C46: 21534061 | D46: GOMEZ HERNANDEZ FREDDY WILFREDO | E46: FCS | F46: MEDICINA HUMANA | G46: PORUMA | H46: VIRTUAL | I46: 26 | K46: =+I46+J46 -> 26 | L46: 15.42 | N46: wilfredo.hernandez@autonomadeica.edu.pe | O46: 961984611
B47: 40 | C47: 70324505 | D47: GUEVARA CARRILLO ANITA FUTINI | E47: FCS | F47: ENFERMERÍA | G47: SEDE | H47: PRESENCIAL | I47: 8 | K47: =+I47+J47 -> 8 | L47: 16.92 | N47: anita.guevara@autonomadeica.edu.pe | O47: 958 060 251
B48: 41 | C48: 43359675 | D48: GUILLEN USTUA LUZVID | E48: FCS | F48: ENFERMERÍA | G48: SEDE | H48: MAS PRESENCIAL | I48: 32 | K48: =+I48+J48 -> 32 | L48: 13.74 | N48: luzvid.guillen@autonomadeica.edu.pe | O48: 966503511
B49: 42 | C49: 43757708 | D49: GUTIERREZ DULANTO DE MUÑOZ JENIFER JESUS | E49: FCS | F49: OBSTETRICIA | G49: FILIAL | H49: MAS PRESENCIAL | I49: 24 | K49: =+I49+J49 -> 24 | L49: 17.33 | N49: jenifer.gutierrez@autonomadeica.edu.pe | O49: 956425117
B50: 43 | C50: 45228093 | D50: HERNANDEZ CHOCANO LLULIANA LEONOR | E50: FCS | F50: ENFERMERÍA | G50: FILIAL | H50: MAS PRESENCIAL | I50: 26 | K50: =+I50+J50 -> 26 | L50: 16.39 | N50: lluliana.hernandez@autonomadeica.edu.pe | O50: 944913505
B51: 44 | C51: 70306751 | D51: HERNANDEZ ESPINO RAUL JONATHAN | E51: FCS | F51: MEDICINA HUMANA - EEGG | G51: PORUMA | H51: VIRTUAL | I51: 13 | K51: =+I51+J51 -> 13 | L51: 15.72 | N51: raul.hernandez@autonomadeica.edu.pe | O51: 961820932
B52: 45 | C52: 21524698 | D52: HERNANDEZ PEÑA MARLENY | E52: FCS | F52: ENFERMERÍA | G52: FILIAL | H52: MAS VIRTUAL | I52: 31 | K52: =+I52+J52 -> 31 | L52: 15.48 | N52: marleny.hernandez@autonomadeica.edu.pe | O52: 980059833
B53: 46 | C53: 21461803 | D53: HUAMAN CAYO ALEX MARTIN | E53: FCS | F53: ENFERMERÍA | G53: SEDE | H53: MAS PRESENCIAL | I53: 37 | K53: =+I53+J53 -> 37 | L53: 15.20 | N53: alex.huaman@autonomadeica.edu.pe | O53: 956684292
B54: 47 | C54: 70302657 | D54: JERONIMO CASTILLO JORGE ANTONIO | E54: FCS | F54: PSICOLOGÍA - EEGG | G54: SEDE | H54: PRESENCIAL | I54: 32 | K54: =+I54+J54 -> 32 | L54: 16.08 | N54: jorge.jeronimo@autonomadeica.edu.pe | O54: 950156534
B55: 48 | C55: 46200886 | D55: LEON EURIBE PEDRO ENRIQUE | E55: FCS | F55: OBSTETRICIA | G55: FILIAL | H55: MAS VIRTUAL | I55: 32 | K55: =+I55+J55 -> 32 | L55: 15.79 | N55: enrique.leon@autonomadeica.edu.pe | O55: 956865364
B56: 49 | C56: 21815710 | D56: LEVANO DE PEÑA ELITA DEL PILAR | E56: FCS | F56: PSICOLOGÍA | G56: SEDE | H56: MAS PRESENCIAL | I56: 33 | K56: =+I56+J56 -> 33 | L56: 14.72 | N56: elita.levano@autonomadeica.edu.pe | O56: 956594972
B57: 50 | C57: 10508584 | D57: LLAUCA VALVERDE EDITH LUISA | E57: FCS | F57: ENFERMERÍA | G57: SEDE | H57: MAS VIRTUAL | I57: 31 | K57: =+I57+J57 -> 31 | L57: 15.47 | N57: edith.llauca@autonomadeica.edu.pe | O57: 999111489
B58: 51 | C58: 42573866 | D58: MARTINEZ LOZA CYNTHIA PAMELA | E58: FCS | F58: OBSTETRICIA - EEGG | G58: SEDE | H58: PRESENCIAL | I58: 8 | K58: =+I58+J58 -> 8 | L58: 16.49 | N58: cynthia.martinez@autonomadeica.edu.pe | O58: 952 400 502
B59: 52 | C59: 9916820 | D59: MARTINEZ PEREZ BRENDA LEE | E59: FCS | F59: OBSTETRICIA | G59: SEDE | H59: MAS PRESENCIAL | I59: 26 | K59: =+I59+J59 -> 26 | L59: 16.12 | N59: brenda.martinez@autonomadeica.edu.pe | O59: 950863543
B60: 53 | C60: 21556265 | D60: MATTA UCHUYA VICTOR HUGO | E60: FCS | F60: ENFERMERÍA | G60: FILIAL | H60: MAS VIRTUAL | I60: 30 | K60: =+I60+J60 -> 30 | L60: 15.04 | N60: victor.matta@autonomadeica.edu.pe | O60: 964506326
B61: 54 | C61: 41347751 | D61: MEDINA GUERRERO MERICI INGRID | E61: FCS | F61: MEDICINA HUMANA - EEGG | G61: PORUMA | H61: PRESENCIAL | I61: 30 | K61: =+I61+J61 -> 30 | L61: 16.50 | N61: merici.medina@autonomadeica.edu.pe | O61: 956001898
B62: 55 | C62: 21867757 | D62: MENDOZA SALVATIERRA ROSARIO VICTORIA | E62: FCS | F62: ENFERMERÍA | G62: SEDE | H62: PRESENCIAL | I62: 30 | K62: =+I62+J62 -> 30 | L62: 14.61 | N62: victoria.mendoza@autonomadeica.edu.pe | O62: 990678453
B63: 56 | C63: 40804375 | D63: MOQUILLAZA ALCA CARMEN ROSA | E63: FCS | F63: TECNOLOGÍA MÉDICA - EEGG | G63: SUNAMPE | H63: MAS PRESENCIAL | I63: 33 | K63: =+I63+J63 -> 33 | L63: 16.45 | N63: carmen.moquillaza@autonomadeica.edu.pe | O63: 956956984
B64: 57 | C64: 21404829 | D64: MORALES QUISPE HEDDY TERESA | E64: FCS | F64: ENFERMERÍA | G64: FILIAL | H64: VIRTUAL | I64: 40 | K64: =+I64+J64 -> 40 | L64: 14.07 | N64: heddy.morales@autonomadeica.edu.pe | O64: 993718503
B65: 58 | C65: 21815632 | D65: MUNAYCO MESIAS IRIS | E65: FCS | F65: ENFERMERÍA | G65: SEDE | H65: MAS PRESENCIAL | I65: 31 | K65: =+I65+J65 -> 31 | L65: 15.31 | N65: iris.munayco@autonomadeica.edu.pe | O65: 974140352
B66: 59 | C66: 44995918 | D66: NIETO GAVILANO PRISCILA LORENA | E66: FCS | F66: ENFERMERÍA | G66: FILIAL | H66: MAS VIRTUAL | I66: 28 | K66: =+I66+J66 -> 28 | L66: 16.23 | N66: priscila.nieto@autonomadeica.edu.pe | O66: 959436332
B67: 60 | C67: 40160212 | D67: ORELLANA AGUILAR CANDRY ARAZELY | E67: FCS | F67: ENFERMERÍA | G67: SEDE | H67: MAS VIRTUAL | I67: 32 | K67: =+I67+J67 -> 32 | L67: 16.56 | N67: candry.orellana@autonomadeica.edu.pe | O67: 955488293
B68: 61 | C68: 22255543 | D68: ORMEÑO QUIJANDRIA MARIA DEL CARMEN | E68: FCS | F68: ENFERMERÍA | G68: SEDE | H68: PRESENCIAL | I68: 30 | K68: =+I68+J68 -> 30 | L68: 14.11 | N68: maria.quijandria@autonomadeica.edu.pe | O68: 948647094
B69: 62 | C69: 44407156 | D69: ORTEGA PALOMINO JACKELINA TERESA | E69: FCS | F69: ENFERMERÍA | G69: FILIAL | H69: MAS VIRTUAL | I69: 33 | K69: =+I69+J69 -> 33 | N69: jackelina.ortega@autonomadeica.edu.pe | O69: 945288200
B70: 63 | C70: 45629797 | D70: ORTEGA PALOMINO NAYARITT YISELA | E70: FCS | F70: ENFERMERÍA | G70: FILIAL | H70: MAS VIRTUAL | I70: 32 | K70: =+I70+J70 -> 32 | N70: nayaritt.ortega@autonomadeica.edu.pe | O70: 944 477 311
B71: 64 | C71: 42781566 | D71: PACHAS ALMEYDA ELIZABETH DIONET | E71: FCS | F71: ENFERMERÍA | G71: SEDE | H71: MAS PRESENCIAL | I71: 32 | K71: =+I71+J71 -> 32 | L71: 15.53 | N71: elizabeth.pachas@autonomadeica.edu.pe | O71: 920017421_x000D_
B72: 65 | C72: 21887837 | D72: PACHAS RAMOS ALLINSON MARINA | E72: FCS | F72: MEDICINA HUMANA - EEGG | G72: SUNAMPE | H72: MAS PRESENCIAL | I72: 40 | K72: =+I72+J72 -> 40 | L72: 16.97 | N72: allinson.pachas@autonomadeica.edu.pe | O72: 955894726
B73: 66 | C73: 40639051 | D73: PERALTA ROLDAN ELVIS SERGIO | E73: FCS | F73: MEDICINA HUMANA | G73: PORUMA | H73: MAS PRESENCIAL | I73: 34 | K73: =+I73+J73 -> 34 | L73: 15.70 | N73: elvis.peralta@autonomadeica.edu.pe | O73: 952334264
B74: 67 | C74: 44866019 | D74: PEREZ CABRERA NURY SARAI | E74: FCS | F74: PSICOLOGÍA | G74: FILIAL | H74: MAS PRESENCIAL | I74: 31 | K74: =+I74+J74 -> 31 | L74: 15.46 | N74: nury.perez@autonomadeica.edu.pe | O74: 940440047
B75: 68 | C75: 40930821 | D75: PINO RAMOS MIRTHA LIDIA | E75: FCS | F75: OBSTETRICIA | G75: SEDE | H75: PRESENCIAL | I75: 33 | K75: =+I75+J75 -> 33 | L75: 16.74 | N75: mirtha.pino@autonomadeica.edu.pe | O75: 961 036 250
B76: 69 | C76: 21882544 | D76: POZO CANALES JOEL EMILIO | E76: FCS | F76: ENFERMERÍA - EEGG | G76: SEDE | H76: MAS PRESENCIAL | I76: 35 | K76: =+I76+J76 -> 35 | L76: 15.65 | N76: joel.pozo@autonomadeica.edu.pe
B77: 70 | C77: 22291445 | D77: QUEVEDO MEDINA HERCILIA | E77: FCS | F77: PSICOLOGÍA - EEGG | G77: SEDE | H77: PRESENCIAL | I77: 30 | K77: =+I77+J77 -> 30 | L77: 17.34 | N77: hercilia.quevedo@autonomadeica.edu.pe | O77: 956278699
B78: 71 | C78: 73213273 | D78: QUIJAITE MUNARRIZ LIZZETH THALIA | E78: FCS | F78: OBSTETRICIA | G78: FILIAL | H78: MAS PRESENCIAL | I78: 26 | K78: =+I78+J78 -> 26 | L78: 18.16 | N78: lizzeth.quijaite@autonomadeica.edu.pe | O78: 969646198
B79: 72 | C79: 44867656 | D79: QUINTANA ANGULO ALEXANDER LEONARDO | E79: FCS | F79: ENFERMERÍA | G79: FILIAL | H79: MAS VIRTUAL | I79: 30 | K79: =+I79+J79 -> 30 | L79: 14.53 | N79: alexander.quintana@autonomadeica.edu.pe | O79: 977525977
B80: 73 | C80: 9575456 | D80: QUIROZ MARCELO DAVID SAUL | E80: FCS | F80: ENFERMERÍA | G80: SEDE | H80: VIRTUAL | I80: 38 | K80: =+I80+J80 -> 38 | L80: 14.82 | N80: saul.quiroz@autonomadeica.edu.pe | O80: 991123043
B81: 74 | C81: 21808913 | D81: QUISPE PADILLA INES JESUS | E81: FCS | F81: ENFERMERÍA | G81: SEDE | H81: PRESENCIAL | I81: 24 | K81: =+I81+J81 -> 24 | L81: 14.61 | N81: ines.quispe@autonomadeica.edu.pe | O81: 956644625/056-782092
B82: 75 | C82: 21799101 | D82: QUISPE TORRES MARIA GLORIA | E82: FCS | F82: MEDICINA HUMANA | G82: SUNAMPE | H82: MAS PRESENCIAL | I82: 32 | K82: =+I82+J82 -> 32 | L82: 17.55 | N82: maria.quispe@autonomadeica.edu.pe | O82: 956 930 937
B83: 76 | C83: 7757185 | D83: RAMOS ESCAJADILLO XENIA KARIN | E83: FCS | F83: PSICOLOGÍA - EEGG | G83: FILIAL | H83: MAS PRESENCIAL | I83: 29 | K83: =+I83+J83 -> 29 | L83: 16.47 | N83: xenia.ramos@autonomadeica.edu.pe | O83: 947999918
B84: 77 | C84: 70768072 | D84: ROBLES CABRERA YOVER ELVIS | E84: FCS | F84: MEDICINA HUMANA - EEGG | G84: PORUMA | H84: MAS PRESENCIAL | I84: 33 | K84: =+I84+J84 -> 33 | L84: 16.10 | N84: yover.robles@autonomadeica.edu.pe | O84: 986244741
B85: 79 | C85: 43529608 | D85: RODRIGUEZ CALDERON RENZO EMERSON | E85: FCS | F85: ENFERMERÍA - EEGG | G85: HUAURA | H85: PRESENCIAL | I85: 30 | K85: =+I85+J85 -> 30 | L85: 15.09 | N85: renzo.rodriguez@autonomadeica.edu.pe | O85: 944572238
B86: 80 | C86: 70107322 | D86: RODRIGUEZ PALOMINO LUISA ANGELICA | E86: FCS | F86: PSICOLOGÍA | G86: SEDE | H86: PRESENCIAL | I86: 22 | K86: =+I86+J86 -> 22 | L86: 15.35 | N86: luisa.rodriguez@autonomadeica.edu.pe | O86: 910599947
B87: 81 | C87: 44565506 | D87: ROJAS RUIZ FRANCISCO BERNARDINO | E87: FCS | F87: ENFERMERÍA - EEGG | G87: HUAURA | H87: PRESENCIAL | I87: 32 | K87: =+I87+J87 -> 32 | L87: 15.56 | N87: francisco.rojas@autonomadeica.edu.pe
B88: 83 | C88: 41628245 | D88: RUIZ OCAMPO JUAN CARLOS | E88: FCS | F88: OBSTETRICIA | G88: SEDE | H88: PRESENCIAL | I88: 6 | K88: =+I88+J88 -> 6 | L88: 16.12 | N88: juancarlos.ruiz@autonomadeica.edu.pe | O88: 942106570
B89: 84 | C89: 21870533 | D89: SARAVIA YATACO CARMEN ROSA | E89: FCS | F89: PSICOLOGÍA - EEGG | G89: SEDE | H89: MAS PRESENCIAL | I89: 33 | K89: =+I89+J89 -> 33 | L89: 15.78 | N89: rosa.saravia@autonomadeica.edu.pe | O89: 988340696
B90: 85 | C90: 22096438 | D90: SARMIENTO GUILLEN PAUL ALEJANDRO | E90: FCS | F90: TECNOLOGÍA MÉDICA - EEGG | G90: SUNAMPE | H90: PRESENCIAL | I90: 39 | K90: =+I90+J90 -> 39 | L90: 16.78 | N90: paul.sarmiento@autonomadeica.edu.pe | O90: 956621896
B91: 86 | C91: 22520828 | D91: SEDANO MIRAVAL ENMA ZORAIDA | E91: FCS | F91: OBSTETRICIA | G91: FILIAL | H91: PRESENCIAL | I91: 36 | K91: =+I91+J91 -> 36 | L91: 14.53 | N91: enma.sedano@autonomadeica.edu.pe | O91: 966029623
B92: 87 | C92: 40572971 | D92: SOTELO OCHOA ADA VERONICA | E92: FCS | F92: ENFERMERÍA | G92: SEDE | H92: MAS VIRTUAL | I92: 32 | K92: =+I92+J92 -> 32 | L92: 14.97 | N92: ada.sotelo@autonomadeica.edu.pe | O92: 960310073
B93: 88 | C93: 21558762 | D93: SUCZO CHAIÑA MERVY LUCY | E93: FCS | F93: ENFERMERÍA | G93: FILIAL | H93: MAS VIRTUAL | I93: 32 | K93: =+I93+J93 -> 32 | L93: 15.20 | N93: mervy.suczo@autonomadeica.edu.pe | O93: 956533785/056771690
B94: 89 | C94: 18135807 | D94: TAMAYO ARTEAGA CARMEN ROSA JESUS | E94: FCS | F94: ENFERMERÍA | G94: SEDE | H94: VIRTUAL | I94: 30 | K94: =+I94+J94 -> 30 | L94: 15.65 | N94: carmen.tamayo@autonomadeica.edu.pe | O94: 975519936
B95: 90 | C95: 75375310 | D95: TITO LOAYZA KEYMA MARITHA | E95: FCS | F95: TECNOLOGÍA MÉDICA - EEGG | G95: PORUMA | H95: MAS PRESENCIAL | I95: 34 | K95: =+I95+J95 -> 34 | L95: 16.53 | N95: keyma.tito@autonomadeica.edu.pe | O95: 974682766
B96: 91 | C96: 44893085 | D96: URIBE SOTIL DIAMDRA OLGA | E96: FCS | F96: PSICOLOGÍA | G96: FILIAL | H96: MAS VIRTUAL | I96: 33 | K96: =+I96+J96 -> 33 | L96: 16.17 | N96: diamdra.uribe@autonomadeica.edu.pe | O96: 996177283
B97: 92 | C97: 22275169 | D97: VALDIVIEZO GUEVARA MARLITT | E97: FCS | F97: TECNOLOGÍA MÉDICA - EEGG | G97: SUNAMPE | H97: PRESENCIAL | I97: 33 | K97: =+I97+J97 -> 33 | L97: 15.89 | N97: marlitt.valdiviezo@autonomadeica.edu.pe | O97: 943460499
B98: 93 | C98: 41282651 | D98: ZEGARRA LEON NADIA LIANY | E98: FCS | F98: ENFERMERÍA | G98: FILIAL | H98: MAS VIRTUAL | I98: 37 | K98: =+I98+J98 -> 37 | L98: 14.11 | N98: nadia.zegarra@autonomadeica.edu.pe | O98: 955614542
B99: 94 | C99: 42721030 | D99: VARGAS PRADO KELLY FARA | E99: FCS | F99: PSICOLOGÍA | G99: FILIAL | H99: VIRTUAL | I99: 8 | K99: =+I99+J99 -> 8 | L99: 16.67 | N99: kelly.vargas@autonomadeica.edu.pe | O99: 972290521/ (056) 604284
B100: 95 | K100: =+I100+J100 -> 0
B101: 96 | K101: =+I101+J101 -> 0
B102: 97 | K102: =+I102+J102 -> 0
B103: 98 | K103: =+I103+J103 -> 0
B104: 99 | K104: =+I104+J104 -> 0
B105: 100 | K105: =+I105+J105 -> 0
B106: 101 | K106: =+I106+J106 -> 0
...

Sheet RENOVACIÓN TP FCS
B6: PROPUESTA DE RENOVACIÓN DOCENTE TP PARA SEMESTRE ACADÉMICO 2026-1 FACULTAD DE CIENCIAS DE LA SALUD
B8: N° | C8: DNI | D8: APELLIDOS Y NOMBRES | E8: FACULTAD | F8: ESCUELA PROFESIONAL | G8: LOCAL | H8: MODALIDAD | I8: N° HORAS LECTIVAS | J8: NOTA EVALUACIÓN DEL DESEMPEÑO 2025-2 | K8: CORREO ELECTRÓNICO INSTITUCIONAL | L8: N° CELULAR | M8: OBSERVACIONES
B9: 1 | C9: 45228337 | D9: ALIAGA RUIZ MINA ANGELICA | E9: FCS | F9: PSICOLOGÍA | G9: SEDE | H9: PRESENCIAL | I9: 13 | J9: 15.71 | K9: mina.aliaga@autonomadeica.edu.pe | L9: 936774790
B10: 2 | C10: 21525109 | D10: ALVAREZ GARCIA TERESA ELVIRA | E10: FCS | F10: MEDICINA HUMANA | G10: PORUMA | H10: PRESENCIAL | I10: 17 | J10: 14.27 | K10: teresa.alvarez@autonomadeica.edu.pe | L10: 998672766
B11: 3 | C11: 44371485 | D11: ANCAJIMA RUIZ ANDREA BETTY | E11: FCS | F11: ENFERMERÍA - EEGG | G11: FILIAL | H11: MAS PRESENCIAL | I11: 19 | J11: 16.82 | K11: andrea.ancajima@autonomadeica.edu.pe | L11: 973826973
B12: 4 | C12: 21560679 | D12: ANICAMA BERNAOLA PEDRO ARTURO | E12: FCS | F12: MEDICINA HUMANA | G12: PORUMA | H12: PRESENCIAL | I12: 14 | J12: 15.36 | K12: pedro.anicama@autonomadeica.edu.pe | L12: 959348713
B13: 5 | C13: 22299955 | D13: AQUIJE DAPOZZO EDWAR VIDAL | E13: FCS | F13: ENFERMERÍA | G13: FILIAL | H13: VIRTUAL | I13: 18 | J13: 15.92 | K13: edwar.aquije@autonomadeica.edu.pe | L13: 961510609
B14: 6 | C14: 21546746 | D14: ARIZOLA AGUADO ALICIA ANTOINETTE | E14: FCS | F14: MEDICINA HUMANA | G14: PORUMA | H14: PRESENCIAL | I14: 15 | J14: 15.17 | K14: alicia.arizola@autonomadeica.edu.pe | L14: 950999223
B15: 7 | C15: 42841966 | D15: AROTUMA GRANDA HECTOR JUAN CARLOS | E15: FCS | F15: MEDICINA HUMANA | G15: PORUMA | H15: PRESENCIAL | I15: 10 | J15: 16.46 | K15: hector.arotuma@autonomadeica.edu.pe | L15: 971616753
B16: 8 | C16: 7703595 | D16: ATUNCAR SUENG DORA ROSARIO | E16: FCS | F16: PSICOLOGÍA | G16: SEDE | H16: PRESENCIAL | I16: 14 | J16: 15.19 | K16: dora.atuncar@autonomadeica.edu.pe | L16: 997565823
B17: 9 | C17: 40139812 | D17: BAÑOS RAMOS JUAN CARLOS | E17: FCS | F17: PSICOLOGÍA | G17: SEDE | H17: PRESENCIAL | I17: 14 | J17: 15.01 | K17: juancarlos.ramos@autonomadeica.edu.pe | L17: 987967937
B18: 10 | C18: 21462854 | D18: BARRIENTOS RAMOS VICTOR HUGO | E18: FCS | F18: ENFERMERÍA | G18: FILIAL | H18: VIRTUAL | I18: 15 | J18: 13.02 | K18: victor.barrientos@autonomadeica.edu.pe | L18: 955823795
B19: 11 | C19: 9100625 | D19: BERROSPI VARGAS ANA ELVA | E19: FCS | F19: OBSTETRICIA | G19: FILIAL | H19: MAS PRESENCIAL | I19: 18 | J19: 16.73 | K19: ana.berrospi@autonomadeica.edu.pe | L19: 956001506/956722157
B20: 12 | C20: 41545772 | D20: CABRERA VELASQUEZ MEYLAN ALLIZA | E20: FCS | F20: MEDICINA HUMANA | G20: PORUMA | H20: PRESENCIAL | I20: 10 | J20: 14.05 | K20: meylan.cabrera@autonomadeica.edu.pe | L20: 948423070_x000D_
B21: 13 | C21: 72676034 | D21: CAHUA DIAZ DEYSI MARIBEL | E21: FCS | F21: OBSTETRICIA | G21: FILIAL | H21: MAS PRESENCIAL | I21: 12 | J21: 15.84 | K21: deysi.cahua@autonomadeica.edu.pe | L21: 979042565
B22: 14 | C22: 6160287 | D22: CAMPIAN LAZO YONAL IGNACIO | E22: FCS | F22: MEDICINA HUMANA - EEGG | G22: SUNAMPE | H22: PRESENCIAL | I22: 14 | J22: 15.33 | K22: yonal.campian@autonomadeica.edu.pe | L22: 999749496
B23: 15 | C23: 15727165 | D23: CANALES INGA WENDY VIVIANA | E23: FCS | F23: ENFERMERÍA - EEGG | G23: HUAURA | H23: MAS PRESENCIAL | I23: 16 | J23: 16.24 | K23: viviana.canales@autonomadeica.edu.pe | L23: 988490896
B24: 16 | C24: 6276541 | D24: CANDELA CUBILLAS HUBER AGUSTIN | E24: FCS | F24: PSICOLOGÍA | G24: SEDE | H24: MAS PRESENCIAL | I24: 14 | J24: 15.12 | K24: huber.candela@autonomadeica.edu.pe | L24: 988178147
B25: 17 | C25: 42363036 | D25: CARBONEL RAMIREZ HANS HENRY | E25: FCS | F25: MEDICINA HUMANA | G25: PORUMA | H25: PRESENCIAL | I25: 11 | J25: 13.48 | K25: hans.carbonel@autonomadeica.edu.pe | L25: 959858065
B26: 18 | C26: 10350121 | D26: CARDENAS GALVEZ YESE YOBANA | E26: FCS | F26: ENFERMERÍA | G26: SEDE | H26: VIRTUAL | I26: 12 | J26: 14.30 | K26: yese.cardenas@autonomadeica.edu.pe | L26: 949659055
B27: 19 | C27: 43036474 | D27: CARDENAS LANDEO NANCY | E27: FCS | F27: MEDICINA HUMANA | G27: SUNAMPE | H27: PRESENCIAL | I27: 15 | J27: 13.08 | K27: nancy.cardenas@autonomadeica.edu.pe | L27: 932948721
B28: 20 | C28: 43456897 | D28: CARDENAS ZEDANO WILLIAM JESUS | E28: FCS | F28: PSICOLOGÍA | G28: FILIAL | H28: PRESENCIAL | I28: 15 | J28: 15.53 | K28: willian.cardenas@autonomadeica.edu.pe | L28: 968974470
B29: 21 | C29: 41485219 | D29: CASTILLA TUBILLA JEANINA LISETH | E29: FCS | F29: OBSTETRICIA | G29: SEDE | H29: PRESENCIAL | I29: 12 | J29: 15.67 | K29: jeanina.castilla@autonomadeica.edu.pe | L29: 957905278
B30: 22 | C30: 22309591 | D30: CASTILLO ESPINOZA GUILLERMO EMILIO | E30: FCS | F30: MEDICINA HUMANA | G30: SUNAMPE | H30: PRESENCIAL | I30: 15 | J30: 14.77 | K30: guillermo.castillo@autonomadeica.edu.pe | L30: 984474904
B31: 23 | C31: 7469293 | D31: CASTRO ANTEZANA HARDY TERESA | E31: FCS | F31: OBSTETRICIA | G31: FILIAL | H31: PRESENCIAL | I31: 12 | J31: 14.33 | K31: hardy.castro@autonomadeica.edu.pe
B32: 24 | C32: 21522829 | D32: CHACALTANA ESCATE CARMEN EDELMIRA | E32: FCS | F32: OBSTETRICIA | G32: FILIAL | H32: PRESENCIAL | I32: 16 | J32: 15.13 | K32: carmen.chacaltana@autonomadeica.edu.pe | L32: 978580911
B33: 25 | C33: 70504650 | D33: CHAVARRIA DELGADO JANIS JAVIER TOMAS | E33: FCS | F33: MEDICINA HUMANA | G33: SUNAMPE | H33: PRESENCIAL | I33: 18 | J33: 16.76 | K33: janis.chavarria@autonomadeica.edu.pe | L33: 930516314
B34: 26 | C34: 43429701 | D34: CHECCLLO TENORIO ADIN MEZOLLAM | E34: FCS | F34: PSICOLOGÍA | G34: FILIAL | H34: PRESENCIAL | I34: 17 | J34: 14.36 | K34: adin.checcllo@autonomadeica.edu.pe | L34: 923913515
B35: 27 | C35: 41222348 | D35: COCHACHI PURAY JAQUELINE NOEMI | E35: FCS | F35: ENFERMERÍA - EEGG | G35: FILIAL | H35: PRESENCIAL | I35: 14 | J35: 15.87 | K35: jaqueline.cochachi@autonomadeica.edu.pe | L35: 931900971
B36: 28 | C36: 40965725 | D36: COLQUEPISCO PAUCAR NILO TEODORICO | E36: FCS | F36: ENFERMERÍA - EEGG;PSICOLOGÍA - EEGG;OBSTETRICIA - EEGG | G36: SEDE | H36: PRESENCIAL | I36: 15 | J36: 15.98 | K36: nilo.colquepisco@autonomadeica.edu.pe | L36: 961851421
B37: 29 | C37: 42657141 | D37: CORNEJO PURILLA SUGEY PILAR | E37: FCS | F37: PSICOLOGÍA - EEGG | G37: FILIAL | H37: PRESENCIAL | I37: 12 | J37: 15.79 | K37: sugey.cornejo@autonomadeica.edu.pe | L37: 994331971
B38: 30 | C38: 46941666 | D38: CORREA VERGARA JORGE LUIS | E38: FCS | F38: MEDICINA HUMANA | G38: PORUMA | H38: PRESENCIAL | I38: 11 | J38: 16.29 | K38: jorge.correa@autonomadeica.edu.pe | L38: 949680011_x000D_
B39: 31 | C39: 71472171 | D39: COSIATADO URBANO RAUL JESUS | E39: FCS | F39: PSICOLOGÍA - EEGG | G39: FILIAL | H39: MAS PRESENCIAL | I39: 16 | J39: 16.82 | K39: raul.cosiatado@autonomadeica.edu.pe | L39: 990636567
B40: 32 | C40: 21560357 | D40: CRISOSTOMO POMA PEDRO GUSTAVO | E40: FCS | F40: MEDICINA HUMANA | G40: PORUMA | H40: PRESENCIAL | I40: 16 | J40: 15.50 | K40: pedro.crisostomo@autonomadeica.edu.pe | L40: 939473322
B41: 33 | C41: 70539299 | D41: CUBA CARRILLO FATIMA ELIZABETH | E41: FCS | F41: OBSTETRICIA | G41: FILIAL | H41: MAS PRESENCIAL | I41: 16 | J41: 15.34 | K41: fatima.cuba@autonomadeica.edu.pe | L41: 922933831
B42: 34 | C42: 41430382 | D42: DE LA CRUZ CHIPANA DE RAMIREZ MARIA DEL ROSARIO | E42: FCS | F42: MEDICINA HUMANA - EEGG | G42: PORUMA | H42: PRESENCIAL | I42: 8 | J42: 14.93 | K42: delrosario.delacruz@autonomadeica.edu.pe | L42: 056-403026 / 951530280
B43: 35 | C43: 21547326 | D43: DE LA CRUZ CHIPANA HILDA MILAGRITOS | E43: FCS | F43: PSICOLOGÍA | G43: SEDE | H43: VIRTUAL | I43: 15 | J43: 16.90 | K43: milagritos.delacruz@autonomadeica.edu.pe | L43: 956998231_x000D_
B44: 36 | C44: 21800872 | D44: DEL RIO MENDOZA JENY ROSANNA JULIA | E44: FCS | F44: MEDICINA HUMANA | G44: PORUMA | H44: PRESENCIAL | I44: 11 | J44: 14.22 | K44: jeny.delrio@autonomadeica.edu.pe | L44: 956622171
B45: 37 | C45: 40509747 | D45: DELGADO RIOS FATIMA NATALIA | E45: FCS | F45: JEFE DE PRACTICAS | G45: JEFE DE PRACTICAS | H45: PRESENCIAL | I45: 16 | K45: #N/A | L45: #N/A
B46: 38 | C46: 45813502 | D46: DIAZ RODRIGUEZ JUAN JOSE | E46: FCS | F46: PSICOLOGÍA | G46: FILIAL | H46: MAS VIRTUAL | I46: 13 | J46: 15.06 | K46: juanjose.diaz@autonomadeica.edu.pe | L46: 910548973
B47: 39 | C47: 21541988 | D47: ECOS ESPINO JULIO CESAR | E47: FCS | F47: ENFERMERÍA | G47: FILIAL | H47: VIRTUAL | I47: 12 | J47: 15.45 | K47: julio.ecos@autonomadeica.edu.pe | L47: 953796413
B48: 40 | C48: 15738847 | D48: FABIÁN RAMÍREZ JENNER | E48: FCS | F48: ENFERMERÍA - EEGG | G48: HUAURA | H48: PRESENCIAL | I48: 19 | J48: 16.40 | K48: jenner.fabian@autonomadeica.edu.pe | L48: 938439418
B49: 41 | C49: 42709906 | D49: FERNANDEZ CABRERA ERIKA MERLY | E49: FCS | F49: OBSTETRICIA - EEGG | G49: FILIAL | H49: PRESENCIAL | I49: 14 | J49: 16.40 | K49: erika.fernandez@autonomadeica.edu.pe | L49: 945351845
B50: 42 | C50: 43809799 | D50: FRANCO SARDON SHIRLEY JANE | E50: FCS | F50: ENFERMERÍA | G50: FILIAL | H50: MAS PRESENCIAL | I50: 14 | J50: 15.96 | K50: shirley.franco@autonomadeica.edu.pe | L50: 953804610
B51: 43 | C51: 42670596 | D51: GALVEZ ARQUIÑIVA EDWIN JOSE | E51: FCS | F51: ENFERMERÍA - EEGG | G51: FILIAL | H51: PRESENCIAL | I51: 15 | J51: 16.51 | K51: edwin.galvez@autonomadeica.edu.pe | L51: 916694707
B52: 44 | C52: 70271781 | D52: GERÓNIMO ACUACHE BRYAN WILBERTO | E52: FCS | F52: PSICOLOGÍA | G52: FILIAL | H52: PRESENCIAL | I52: 19 | J52: 14.39 | K52: bryan.geronimo@autonomadeica.edu.pe | L52: 933954913
B53: 45 | C53: 15722656 | D53: GIRONZINI PECHIAROVICH DAVID ALDO | E53: FCS | F53: PSICOLOGÍA - EEGG | G53: HUAURA | H53: PRESENCIAL | I53: 15 | J53: 16.23 | K53: david.gironzini@autonomadeica.edu.pe | L53: 992560811
B54: 46 | C54: 21461801 | D54: GOMEZ DONAYRE MARITZA YOVANA | E54: FCS | F54: MEDICINA HUMANA | G54: SUNAMPE | H54: VIRTUAL | I54: 16 | J54: 14.91 | K54: yovana.gomez@autonomadeica.edu.pe | L54: 951357156
B55: 47 | C55: 15617206 | D55: GONZALES CHUNG LUIS ENRIQUE | E55: FCS | F55: PSICOLOGÍA - EEGG | G55: HUAURA | H55: PRESENCIAL | I55: 16 | J55: 15.86 | K55: luis.gonzales@autonomadeica.edu.pe | L55: 998944084
B56: 48 | C56: 18160918 | D56: GUEVARA SANCHEZ ANA CECILIA | E56: FCS | F56: ENFERMERÍA | G56: SEDE | H56: VIRTUAL | I56: 13 | J56: 16.62 | K56: cecilia.guevara@autonomadeica.edu.pe | L56: 948485979
B57: 49 | C57: 21541361 | D57: GUGLIERMINO GALLEGOS LORENA MILAGROS | E57: FCS | F57: PSICOLOGÍA | G57: FILIAL | H57: MAS PRESENCIAL | I57: 16 | J57: 15.58 | K57: lorena.gugliermino@autonomadeica.edu.pe | L57: 972976145
... B64: 56 | C64: 41717794 | D64: JUAREZ DE TIPACTI JULIA ELIZABETH | E64: FCS | F64: PSICOLOGÍA | G64: SEDE | H64: MAS PRESENCIAL | I64: 14 | J64: 16.51 | K64: julia.juarez@autonomadeica.edu.pe | L64: 960309853
B65: 57 | C65: 21461262 | D65: LAMA LANDABURU GERARDO SANTIAGO | E65: FCS | F65: MEDICINA HUMANA | G65: PORUMA | H65: PRESENCIAL | I65: 18 | J65: 15.89 | K65: gerardo.lama@autonomadeica.edu.pe | L65: 991 874 828
B66: 58 | C66: 44467415 | D66: LARIOS MENDOZA JAVIER IVAN | E66: FCS | F66: MEDICINA HUMANA | G66: SUNAMPE | H66: VIRTUAL | I66: 8 | J66: 14.79 | K66: javier.larios@autonomadeica.edu.pe | L66: 902356581
B67: 59 | C67: 21463227 | D67: LEGUA BARRIOS MIRIAM JESUS | E67: FCS | F67: ENFERMERÍA - EEGG | G67: FILIAL | H67: PRESENCIAL | I67: 17 | J67: 16.14 | K67: miriam.legua@autonomadeica.edu.pe | L67: 955604667
B68: 60 | C68: 21435456 | D68: LENGUA SOTELO MARIA YSABEL | E68: FCS | F68: OBSTETRICIA | G68: FILIAL | H68: VIRTUAL | I68: 18 | J68: 15.78 | K68: maria.lengua@autonomadeica.edu.pe | L68: 972019885
B69: 61 | C69: 21797410 | D69: LEVANO LEVANO VICTOR ALEJANDRO | E69: FCS | F69: TECNOLOGÍA MÉDICA - EEGG | G69: SUNAMPE | H69: PRESENCIAL | I69: 12 | J69: 15.56 | K69: alejandro.levano@autonomadeica.edu.pe | L69: 987371641_x000D_
B70: 62 | C70: 25431048 | D70: LEVANO SARMIENTO HECTOR EDUARDO | E70: FCS | F70: ENFERMERÍA - EEGG | G70: SEDE | H70: AMBOS | I70: 16 | J70: 16.02 | K70: hector.levano@autonomadeica.edu.pe | L70: 992410265
B71: 63 | C71: 21403002 | D71: LEY GARCIA CESAR ALBERTO | E71: FCS | F71: MEDICINA HUMANA | G71: PORUMA | H71: PRESENCIAL | I71: 11 | J71: 13.25 | K71: cesar.ley@autonomadeica.edu.pe | L71: 945567047
B72: 64 | C72: 21548063 | D72: LLANTO CANCHOS JOSE ANGEL | E72: FCS | F72: MEDICINA HUMANA | G72: PORUMA | H72: PRESENCIAL | I72: 14 | J72: 16.26 | K72: jose.llanto@autonomadeica.edu.pe | L72: 945018845
B73: 65 | C73: 45077896 | D73: LOPEZ CUADROS MARIA FIORELLA | E73: FCS | F73: OBSTETRICIA - EEGG | G73: SEDE | H73: PRESENCIAL | I73: 20 | J73: 16.62 | K73: fiorella.lopez@autonomadeica.edu.pe | L73: 960860997
B74: 66 | C74: 21881309 | D74: LOYOLA ALMEYDA VICTOR MANUEL | E74: FCS | F74: ENFERMERÍA - EEGG | G74: SEDE | H74: PRESENCIAL | I74: 15 | J74: 16.03 | K74: victor.loyola@autonomadeica.edu.pe | L74: 956698838
B75: 67 | C75: 45469052 | D75: MAGALLANES MENDOZA LISSET DIONELA | E75: FCS | F75: PSICOLOGÍA | G75: SEDE | H75: MAS PRESENCIAL | I75: 17 | J75: 14.07 | K75: lisset.magallanes@autonomadeica.edu.pe | L75: 946403616
B76: 68 | C76: 44481285 | D76: MARTINEZ MUÑANTE RICARDO DAVID | E76: FCS | F76: ENFERMERÍA | G76: SEDE | H76: VIRTUAL | I76: 12 | J76: 15.65 | K76: ricardo.martinez@autonomadeica.edu.pe | L76: 965 393 846
B77: 69 | C77: 21868076 | D77: MATTA GONZALES LOURDES EVELINA | E77: FCS | F77: ENFERMERÍA | G77: SEDE | H77: MAS PRESENCIAL | I77: 14 | J77: 15.34 | K77: lourdes.matta@autonomadeica.edu.pe | L77: 936694754
B78: 70 | C78: 10552634 | D78: MAYTA FRANCIA JOSE LUIS REYNALDO | E78: FCS | F78: TECNOLOGÍA MÉDICA - EEGG | G78: SUNAMPE | H78: VIRTUAL | I78: 15 | J78: 16.61 | K78: jose.mayta@autonomadeica.edu.pe | L78: 941007883
B79: 71 | C79: 22064239 | D79: MEJÍA GAMBOA DANY MARGOT | E79: FCS | F79: ENFERMERÍA - EEGG | G79: SEDE | H79: MAS PRESENCIAL | I79: 14 | J79: 16.01 | K79: dany.mejia@autonomadeica.edu.pe | L79: 998981824
B80: 72 | C80: 15421738 | D80: MENDOZA LUYO MAX ANTONIO | E80: FCS | F80: PSICOLOGÍA | G80: SEDE | H80: MAS VIRTUAL | I80: 12 | J80: 13.56 | K80: max.mendoza@autonomadeica.edu.pe | L80: 988563446
B81: 73 | C81: 21887665 | D81: MENESES JIMENEZ JOSE ANGEL | E81: FCS | F81: PSICOLOGÍA | G81: SEDE | H81: VIRTUAL | I81: 8 | J81: 16.11 | K81: jose.meneses@autonomadeica.edu.pe | L81: 981794511
B82: 74 | C82: 40078328 | D82: MEZA HUAYAPOMA GLADYS MARLENE | E82: FCS | F82: PSICOLOGÍA | G82: FILIAL | H82: MAS VIRTUAL | I82: 13 | J82: 14.02 | K82: gladys.meza@autonomadeica.edu.pe | L82: 935496086
B83: 75 | C83: 70089866 | D83: MIRANDA SILVERIO ROSA ISABEL | E83: FCS | F83: PSICOLOGÍA - EEGG | G83: FILIAL | H83: MAS PRESENCIAL | I83: 13 | J83: 16.09 | K83: rosa.miranda@autonomadeica.edu.pe | L83: 959046077
B84: 76 | C84: 46604461 | D84: MORON SALCEDO YSABEL CECILIA | E84: FCS | F84: ENFERMERÍA | G84: SEDE | H84: MAS VIRTUAL | I84: 15 | J84: 14.94 | K84: ysabel.moron@autonomadeica.edu.pe | L84: 945859627
B85: 77 | C85: 72373220 | D85: MUCHAYPIÑA SUAREZ LOURDES LIZETH | E85: FCS | F85: ENFERMERÍA | G85: SEDE | H85: VIRTUAL | I85: 15 | J85: 16.81 | K85: lourdes.muchaypina@autonomadeica.edu.pe | L85: 987547073
B86: 78 | C86: 43540130 | D86: MUÑANTE NEYRA ROSARIO DEL PILAR | E86: FCS | F86: MEDICINA HUMANA | G86: PORUMA | H86: PRESENCIAL | I86: 18 | J86: 15.48 | K86: rosario.munante@autonomadeica.edu.pe | L86: 999113609
B87: 79 | C87: 21417302 | D87: ORMEÑO FLORES ROSARIO MARIA | E87: FCS | F87: ENFERMERÍA | G87: SEDE | H87: MAS PRESENCIAL | I87: 12 | J87: 13.22 | K87: rosariomaria.ormeno@autonomadeica.edu.pe | L87: 956823552
B88: 80 | C88: 15580142 | D88: PABLO AGAMA ELIZABETH JUDITH | E88: FCS | F88: ENFERMERÍA | G88: HUAURA | H88: PRESENCIAL | I88: 16 | J88: 16.24 | K88: elizabeth.pablo@autonomadeica.edu.pe | L88: 982260077
... B92: 84 | C92: 21452959 | D92: PAITAN CAHUA ANTONIO WILMER | E92: FCS | F92: ENFERMERÍA - EEGG | G92: FILIAL | H92: PRESENCIAL | I92: 14 | J92: 15.81 | K92: antonio.paitan@autonomadeica.edu.pe | L92: 956808791
B93: 85 | C93: 45477699 | D93: PARIONA ESPINO KAREM JULISSA | E93: FCS | F93: PSICOLOGÍA | G93: SEDE | H93: MAS PRESENCIAL | I93: 13 | J93: 15.67 | K93: julissa.pariona@autonomadeica.edu.pe | L93: 904 576 637
B94: 86 | C94: 45121977 | D94: PEÑALOZA REYNAGA RHOY CROSSMER | E94: FCS | F94: MEDICINA HUMANA | G94: PORUMA | H94: PRESENCIAL | I94: 15 | J94: 16.21 | K94: rhoy.penaloza@autonomadeica.edu.pe | L94: 942020226
B95: 87 | C95: 15863203 | D95: PINTO BORJA JAIME AUGUSTO | E95: FCS | F95: ENFERMERÍA - EEGG | G95: HUAURA | H95: PRESENCIAL | I95: 15 | J95: 16.42 | K95: jaime.pinto@autonomadeica.edu.pe | L95: 980534138
B96: 88 | C96: 10860253 | D96: PIZARRO MONCADA CHRISTIAN DAVID | E96: FCS | F96: ENFERMERÍA | G96: FILIAL | H96: VIRTUAL | I96: 15 | J96: 14.25 | K96: christian.pizarro@autonomadeica.edu.pe | L96: 941185753
B97: 89 | C97: 75928709 | D97: PORTAL ALMEYDA ELSIE ESTEFANNI | E97: FCS | F97: OBSTETRICIA | G97: SEDE | H97: MAS VIRTUAL | I97: 13 | J97: 15.90 | K97: elsie.portal@autonomadeica.edu.pe | L97: 966604053
B98: 90 | C98: 46406209 | D98: PRADO MINCHOLA GUILLERMO OSCAR | E98: FCS | F98: PSICOLOGÍA | G98: SEDE | H98: PRESENCIAL | I98: 12 | J98: 14.41 | K98: guillermo.prado@autonomadeica.edu.pe | L98: 959647077
B99: 91 | C99: 21882745 | D99: QUIJANO SAENZ DENNIS WLADIMIR | E99: FCS | F99: ENFERMERÍA - EEGG | G99: SEDE | H99: PRESENCIAL | I99: 19 | J99: 15.40 | K99: dennis.quijano@autonomadeica.edu.pe | L99: 952400677
B100: 92 | C100: 41678332 | D100: QUIJANO SAENZ DEYSI MARIBEL | E100: FCS | F100: ENFERMERÍA - EEGG | G100: SEDE | H100: PRESENCIAL | I100: 12 | J100: 16.69 | K100: deysi.quijano@autonomadeica.edu.pe | L100: 924102090
B101: 93 | C101: 21880907 | D101: QUISPE PACHAS MILLY SOLEDAD | E101: FCS | F101: PSICOLOGÍA | G101: SEDE | H101: MAS PRESENCIAL | I101: 13 | J101: 14.73 | K101: milly.quispe@autonomadeica.edu.pe | L101: 965064516
B102: 94 | C102: 41641661 | D102: RAMOS CHAVEZ GIOVANA PILAR | E102: FCS | F102: PSICOLOGÍA - EEGG | G102: SEDE | H102: PRESENCIAL | I102: 14 | J102: 16.15 | K102: giovana.ramos@autonomadeica.edu.pe | L102: 914378288
B103: 95 | C103: 45944273 | D103: RAMOS DE LA ROSA KAROL KRISTEL | E103: FCS | F103: OBSTETRICIA | G103: FILIAL | H103: MAS VIRTUAL | I103: 11 | J103: 16.68 | K103: karol.ramos@autonomadeica.edu.pe | L103: 990877899
B104: 96 | C104: 21405273 | D104: RAMOS TAYPE MIGUEL ANGEL | E104: FCS | F104: ENFERMERÍA | G104: FILIAL | H104: PRESENCIAL | I104: 10 | J104: 12.43 | K104: angel.ramos@autonomadeica.edu.pe | L104: 956460118
B105: 97 | C105: 21569878 | D105: RAYME MENESES JOSE LUIS | E105: FCS | F105: ENFERMERÍA - EEGG | G105: FILIAL | H105: MAS PRESENCIAL | I105: 15 | J105: 16.26 | K105: jose.rayme@autonomadeica.edu.pe | L105: 969825455
... B109: 101 | C109: 10526690 | D109: ROJAS HILARIO JIMMY SERVULO | E109: FCS | F109: OBSTETRICIA | G109: SEDE | H109: PRESENCIAL | I109: 12 | J109: 14.98 | K109: jimmy.rojas@autonomadeica.edu.pe | L109: 938118968
B110: 102 | C110: 21422320 | D110: ROJAS MENDIVIL MIGUEL ANGEL | E110: FCS | F110: ENFERMERÍA | G110: FILIAL | H110: PRESENCIAL | I110: 12 | J110: 14.68 | K110: miguel.rojas@autonomadeica.edu.pe | L110: 975 577580
B111: 103 | C111: 44788147 | D111: ROMANI PILLPE GUILLERMO | E111: FCS | F111: ENFERMERÍA | G111: SEDE | H111: VIRTUAL | I111: 15 | J111: 14.75 | K111: guillermo.romani@autonomadeica.edu.pe | L111: 956043387
B112: 104 | C112: 20048536 | D112: SALOME BARZOLA VICTOR RAUL | E112: FCS | F112: ENFERMERÍA | G112: SEDE | H112: VIRTUAL | I112: 15 | J112: 16.19 | K112: victor.salome@autonomadeica.edu.pe | L112: 994402163
B113: 105 | C113: 21534238 | D113: SUAREZ CAJO JULIA RUTH | E113: FCS | F113: OBSTETRICIA | G113: FILIAL | H113: MAS VIRTUAL | I113: 14 | J113: 14.96 | K113: ruth.suarez@autonomadeica.edu.pe | L113: 978851648
B114: 106 | C114: 43374447 | D114: SUAREZ QUIROZ RONAL ELVIS | E114: FCS | F114: TECNOLOGÍA MÉDICA - EEGG | G114: SUNAMPE | H114: VIRTUAL | I114: 13 | J114: 15.78 | K114: ronal.suarez@autonomadeica.edu.pe | L114: 956092411
B115: 107 | C115: 40572937 | D115: SULCA ROJAS JULIO CESAR | E115: FCS | F115: PSICOLOGÍA | G115: FILIAL | H115: PRESENCIAL | I115: 12 | J115: 16.11 | K115: julio.sulca@autonomadeica.edu.pe | L115: 988028524
B116: 108 | C116: 44360108 | D116: TIRADO BARRON OSCAR MIGUEL | E116: FCS | F116: MEDICINA HUMANA | G116: PORUMA | H116: PRESENCIAL | I116: 8 | J116: 15.78 | K116: oscar.tirado@autonomadeica.edu.pe | L116: 990146270_x000D_
B117: 109 | C117: 22309302 | D117: TORNERO MEDINA BELISA ROSALBA | E117: FCS | F117: ENFERMERÍA | G117: FILIAL | H117: MAS PRESENCIAL | I117: 16 | J117: 14.75 | K117: belisa.tornero@autonomadeica.edu.pe | L117: 944653174
B118: 110 | C118: 21553238 | D118: URBANO LUCANA SEFERINA SARAFINA | E118: FCS | F118: OBSTETRICIA - EEGG | G118: FILIAL | H118: PRESENCIAL | I118: 15 | J118: 15.19 | K118: seferina.urbano@autonomadeica.edu.pe
...

Sheet RENOVAC TC FICA
B6: PROPUESTA DE RENOVACIÓN DOCENTE TC PARA SEMESTRE ACADÉMICO 2026-1 FACULTAD DE INGENIERÍA, CIENCIAS Y ADMINISTRACIÓN
B8: N° | C8: DNI | D8: APELLIDOS Y NOMBRES | E8: FACULTAD | F8: ESCUELA PROFESIONAL | G8: LOCAL | H8: MODALIDAD | I8: N° HORAS LECTIVAS | J8: N° HORAS NO LECTIVAS | K8: TOAL DE HORAS | L8: NOTA EVALUACIÓN DEL DESEMPEÑO 2025-2 | M8: CARGO | N8: CORREO ELECTRÓNICO INSTITUCIONAL | O8: N° CELULAR | P8: OBSERVACIONES
B9: 1 | C9: 43517817 | D9: DE LA CRUZ SOSA JAKELINE MELINA | E9: FICA | F9: DERECHO - EEGG | G9: HUAURA | H9: PRESENCIAL | I9: 32 | K9: =+I9+J9 -> 32 | L9: 15.76 | N9: jakeline.delacruz@autonomadeica.edu.pe | O9: 951222024 | P9: -
B10: 2 | C10: 40428220 | D10: MANDAMIENTO GRADOS DAMARIS TELMA | E10: FICA | F10: DERECHO - EEGG | G10: HUAURA | H10: PRESENCIAL | I10: 32 | K10: =+I10+J10 -> 32 | L10: 15.89 | N10: damaris.mandamiento@autonomadeica.edu.pe | O10: 992990608 | P10: -
B11: 3 | C11: 21814775 | D11: ALMEYDA AVALOS CESAR AUGUSTO | E11: FICA | F11: DERECHO | G11: SEDE | H11: MAS PRESENCIAL | I11: 33 | K11: =+I11+J11 -> 33 | L11: 16.7 | N11: cesar.almeyda@autonomadeica.edu.pe | O11: 955906921 | P11: -
B12: 4 | E12: FICA
B13: 5 | E13: FICA
B14: 6 | E14: FICA
B15: 7 | E15: FICA
B16: 8 | E16: FICA
B17: 9 | E17: FICA
B18: 10 | E18: FICA
B19: 11 | E19: FICA
B20: 12 | E20: FICA
B21: 13 | E21: FICA
B22: 14 | E22: FICA
B23: 15 | E23: FICA
... B57: 50 | E57: FICA

Sheet RENOVAC TP FICA
B6: PROPUESTA DE RENOVACIÓN DOCENTE TP PARA SEMESTRE ACADÉMICO 2026-1 FACULTAD DE INGENIERÍA, CIENCIAS Y ADMINISTRACIÓN
B8: N° | C8: DNI | D8: APELLIDOS Y NOMBRES | E8: FACULTAD | F8: ESCUELA PROFESIONAL | G8: LOCAL | H8: MODALIDAD | I8: N° HORAS LECTIVAS | J8: NOTA EVALUACIÓN DEL DESEMPEÑO 2025-2 | K8: CORREO ELECTRÓNICO INSTITUCIONAL | L8: N° CELULAR | M8: OBSERVACIONES
B9: 1 | C9: 41239504 | D9: PADILLA HIZO PEDRO HERNAN | E9: FICA | F9: ADMINISTRACION DE EMPRESAS | G9: HUAURA | H9: PRESENCIAL | I9: 16 | J9: 15.14 | K9: pedro.padilla@autonomadeica.edu.pe | L9: 992085961 | M9: -
B10: 2 | C10: 33826021 | D10: PARIHUAMAN QUINDE GERALDINA REBECA | E10: FICA | F10: ADMINISTRACION DE EMPRESAS - EEGG | G10: HUAURA | H10: PRESENCIAL | I10: 15 | J10: 15.29 | K10: geraldina.parihuaman@autonomadeica.edu.pe | L10: 989038202 | M10: -
B11: 3 | C11: 42212783 | D11: PEREZ RETUERTO RONY GEANCARLO | E11: FICA | F11: DERECHO - EEGG | G11: HUAURA | H11: PRESENCIAL | I11: 10 | J11: 14.41 | K11: rony.perez@autonomadeica.edu.pe | L11: 960064109 | M11: -
B12: 4 | C12: 40822577 | D12: PIMENTEL RETUERTO CARMEN ANDREA | E12: FICA | F12: DERECHO - EEGG | G12: HUAURA | H12: PRESENCIAL | I12: 16 | J12: 14.53 | K12: carmen.pimentel@autonomadeica.edu.pe | L12: 957786821 | M12: -
B13: 5 | C13: 08684196 | D13: REQUENA GARCIA MARIA DEL ROSARIO | E13: FICA | F13: ADMINISTRACION DE EMPRESAS - EEGG | G13: HUAURA | H13: PRESENCIAL | I13: 10 | J13: 15.5 | K13: maria.requena@autonomadeica.edu.pe | L13: 940716638 | M13: -
B14: 6 | C14: 41208519 | D14: REYES ROMAN CARLOS ARTURO | E14: FICA | F14: DERECHO - EEGG | G14: HUAURA | H14: PRESENCIAL | I14: 15 | J14: 15.19 | K14: arturo.reyes@autonomadeica.edu.pe | L14: 985001402 | M14: -
B15: 7 | C15: 44398451 | D15: RIOS SANTIAGO WILSON CESAR | E15: FICA | F15: DERECHO - EEGG | G15: HUAURA | H15: PRESENCIAL | I15: 14 | J15: 14.84 | K15: wilson.rios@autonomadeica.edu.pe | L15: 989336775 | M15: -
B16: 8 | C16: 45165102 | D16: SANCHEZ SOTIL KENNICK ENRIQUE | E16: FICA | F16: DERECHO - EEGG | G16: HUAURA | H16: PRESENCIAL | I16: 8 | J16: 14.51 | K16: kennick.sanchez@autonomadeica.edu.pe | L16: 952944920 | M16: -
B17: 9 | C17: 21814921 | D17: AGUADO APOLAYA RAUL HERNANDO | E17: FICA | F17: INGENIERIA INDUSTRIAL | G17: SEDE | H17: PRESENCIAL | I17: 19 | J17: 16.35 | K17: raul.aguado@autonomadeica.edu.pe | L17: 906408102 | M17: -
B18: 10 | C18: 21522173 | D18: AGUIRRE ESPINOZA MONICA WENDY | E18: FICA | F18: DERECHO | G18: FILIAL | H18: VIRTUAL | I18: 16 | J18: 15.61 | K18: monica.aguirre@autonomadeica.edu.pe | L18: 920660685 | M18: -
B19: 11 | C19: 21569287 | D19: ALCANTARA FARFAN JUAN CARLOS | E19: FICA | F19: DERECHO | G19: SEDE | H19: VIRTUAL | I19: 8 | J19: 14.07 | K19: juan.alcantara@autonomadeica.edu.pe | L19: 956083663 | M19: -
B20: 12 | C20: 41461731 | D20: ALFARO CAYLLAHUA CARLOS HUGO | E20: FICA | F20: INGENIERIA CIVIL | G20: FILIAL | H20: PRESENCIAL | I20: 15 | J20: 16.24 | K20: carlos.alfaro@autonomadeica.edu.pe | M20: -
B21: 13
B22: 14
B23: 15
B24: 16
B25: 17
B26: 18
B27: 19
B28: 20
B29: 21
B30: 22
B31: 23
B32: 24
... B137: 129

Sheet CONCURSO
B6: PROPUESTA DE INVITACION DOCENTE TP PARA SEMESTRE ACADÉMICO 2026-1 FACULTAD DE INGENIERÍA, CIENCIAS Y ADMINISTRACIÓN
B8: N° | C8: DNI | D8: APELLIDOS Y NOMBRES | E8: FACULTAD | F8: ESCUELA PROFESIONAL | G8: LOCAL | H8: MODALIDAD | I8: N° HORAS LECTIVAS | J8: ESCUELA PROFESIONAL | K8: LOCAL | L8: MODALIDAD | M8: CORREO ELECTRÓNICO INSTITUCIONAL | N8: N° CELULAR | O8: OBSERVACIONES
B9: 1 | C9: 72176698 | D9: ESPINOZA MORE CARLA MILAGROS | I9: 6 | J9: ADMINISTRACION DE EMPRESAS | K9: HUAURA | L9: VIRTUAL | M9: - | N9: 956383530 | O9: Horas limitadas por disponibilidad docente
B10: 2 | C10: 41807593 | D10: EVANGELISTA HUAYNALAYA FRANCISCO DE JESUS | I10: 12 | J10: DERECHO | K10: HUAURA | L10: PRESENCIAL | M10: - | N10: 940392058 | O10: -
B11: 3 | C11: 75168136 | D11: GAVINO SANCHEZ JOHN STEVENS | I11: 6 | J11: DERECHO - EEGG | K11: HUAURA | L11: PRESENCIAL | M11: - | N11: 906809788 | O11: Horas limitadas por disponibilidad docente
B12: 4 | C12: 42146692 | D12: LINO FLORES LUIS ANTONIO | I12: 8 | J12: ADMINISTRACION DE EMPRESAS - EEGG | K12: HUAURA | L12: PRESENCIAL | M12: - | N12: 984374438 | O12: Horas limitadas por disponibilidad docente
B13: 5 | C13: 43608561 | D13: MENDOZA CASTILLO JUAN JOSE | I13: 5 | J13: ADMINISTRACION DE EMPRESAS | K13: HUAURA | L13: VIRTUAL | M13: - | N13: 964859651 | O13: Horas limitadas por disponibilidad docente
B14: 6 | C14: 15591781 | D14: QUINTEROS NICHO LUIS FERNANDO | I14: 4 | J14: DERECHO - EEGG | K14: HUAURA | L14: PRESENCIAL | M14: - | N14: 970427179 | O14: Horas limitadas por disponibilidad docente
B15: 7 | C15: 15590660 | D15: RODRIGUEZ RAMIREZ MARIA ISABEL | I15: 4 | J15: ADMINISTRACION DE EMPRESAS | K15: HUAURA | L15: PRESENCIAL | M15: - | N15: 987923259 | O15: Horas limitadas por disponibilidad docente
B16: 8 | C16: 15688249 | D16: ROJAS GUZMAN TITO | I16: 9 | J16: ADMINISTRACION DE EMPRESAS | K16: HUAURA | L16: PRESENCIAL | M16: - | N16: 961433324 | O16: Horas limitadas por disponibilidad docente
B17: 9 | C17: 40740790 | D17: SACRAMENTO LAZARO ROSA ALBINA | I17: 20 | J17: DERECHO | K17: HUAURA | L17: PRESENCIAL | M17: - | N17: 924012573 | O17: -
B18: 10 | C18: 15725118 | D18: SAMANAMUD VALENTIN MIGUEL ANGEL MOISES | I18: 4 | J18: ADMINISTRACION DE EMPRESAS | K18: HUAURA | L18: PRESENCIAL | M18: - | N18: 970656047 | O18: Horas limitadas por disponibilidad docente
B19: 11 | C19: 43027985 | D19: TRUJILLO APONTE WAGNER ABRAHAM | I19: 9 | J19: DERECHO | K19: HUAURA | L19: VIRTUAL | M19: - | N19: 964034650 | O19: Horas limitadas por disponibilidad docente
B20: 12 | C20: 70179483 | D20: VILLANUEVA CAMAC GUILLERMO ARTURO | I20: 20 | J20: ADMINISTRACION DE EMPRESAS - EEGG | K20: HUAURA | L20: PRESENCIAL | M20: - | N20: 983861568 | O20: -
... B25: 17 | C25: 16756416 | D25: SALCEDO RODAS PERCY ISMAEL | I25: 18 | J25: ADMINISTRACION DE EMPRESAS | K25: SEDE | L25: VIRTUAL | M25: - | N25: 972627821 | O25: -
B26: 18 | C26: 70108675 | D26: BUITRON LLACSA JOSE MANUEL | I26: 9 | J26: DERECHO - EEGG | K26: SEDE | L26: MAS PRESENCIAL | N26: 977518295 | O26: Horas limitadas por disponibilidad docente
B27: 19 | C27: 46075693 | D27: MORALES CHAVEZ GISSEL JOCELINE | I27: 5 | J27: ADMINISTRACION Y FINANZAS | K27: SEDE | L27: VIRTUAL | N27: 958691349 | O27: Horas limitadas por disponibilidad docente
B28: 20 | C28: 21435528 | D28: ZUMAETA BERAMENDI JACQUELINE DIANA | I28: 8 | J28: ADMINISTRACION Y FINANZAS | K28: SEDE | L28: VIRTUAL | N28: 989365672 | O28: Horas limitadas por disponibilidad docente
B29: 21 | C29: 70786643 | D29: DIAZ VELASQUEZ JULIO CESAR | I29: 12 | J29: ADMINISTRACION Y FINANZAS | K29: FILIAL | L29: VIRTUAL | N29: 924849452 | O29: -
B30: 22 | C30: 46590523 | D30: ROMERO CARAZAS RAFAEL | I30: 5 | J30: ADMINISTRACION Y FINANZAS | K30: SEDE | L30: VIRTUAL | N30: 982315013 | O30: Horas limitadas por disponibilidad docente
B31: 23 | C31: 46825060 | D31: CALLAN BACILIO RICHARD | I31: 5 | J31: ADMINISTRACION Y FINANZAS | K31: FILIAL | L31: VIRTUAL | N31: 946042178 | O31: Horas limitadas por disponibilidad docente
B32: 24 | C32: 72681156 | D32: MAS VILLANUEVA KENY ARNOLD | I32: 5 | J32: CONTABILIDAD | K32: FILIAL | L32: VIRTUAL | N32: 953362861 | O32: Horas limitadas por disponibilidad docente
B33: 25 | C33: 02885494 | D33: QUIROGA PAIVA DAVID EDUARDO | I33: 3 | J33: CONTABILIDAD | K33: FILIAL | L33: VIRTUAL | N33: 933531483 | O33: Horas limitadas por disponibilidad docente
B34: 26 | C34: 45156306 | D34: ZAFRA SALAS MARCO ANDRE | I34: 17 | J34: ADMINISTRACION DE EMPRESAS | K34: SEDE | L34: VIRTUAL | N34: 969551419 | O34: -
B35: 27 | C35: 41519363 | D35: MANRIQUE CERVANTES JOSE ANTONIO | I35: 4 | J35: DERECHO | K35: FILIAL | L35: VIRTUAL | N35: 987202320 | O35: Horas limitadas por disponibilidad docente
B36: 28 | C36: 46730566 | D36: SALAZAR GAMBOA OSCAR FRITZ ALEXANDER | I36: 15 | J36: DERECHO - EEGG | K36: SEDE | L36: VIRTUAL | N36: 983582045 | O36: -
B37: 29 | C37: 41536992 | D37: CABEZA MOLINA LUIS FELIPE | I37: 8 | J37: DERECHO | K37: FILIAL | L37: VIRTUAL | N37: 969042565 | O37: Horas limitadas por disponibilidad docente
B38: 30 | C38: 40105460 | D38: MUÑANTE SIHUES CESAR ARTURO | I38: 10 | J38: DERECHO - EEGG | K38: SEDE | L38: VIRTUAL | N38: 950058593 | O38: Horas limitadas por disponibilidad docente
B39: 31 | C39: 42515290 | D39: PIZARRO OSORIO BETSABE LILIA | I39: 32 | J39: DERECHO | K39: SEDE | L39: MAS PRESENCIAL | N39: 976805104 | O39: -
B40: 32 | C40: 45007560 | D40: ULLOQUE SAMATELO CARLOS AUGUSTO | I40: 8 | J40: DERECHO - EEGG | K40: SEDE | L40: VIRTUAL | N40: 969015640 | O40: Horas limitadas por disponibilidad docente
B41: 33 | C41: 29726614 | D41: BAHAMONDES GARCIA SINOE GEOFREY | I41: 15 | J41: INGENIERIA DE SISTEMAS - EEGG | K41: SEDE | L41: VIRTUAL | N41: 971450905 | O41: -
B42: 34 | C42: 76129345 | D42: VELASQUEZ CHUNGA JOSE LUIS EDUARDO | I42: 8 | J42: INGENIERIA CIVIL - EEGG | K42: SEDE | L42: VIRTUAL | N42: 921933801 | O42: Horas limitadas por disponibilidad docente
B43: 35 | C43: 72049382 | D43: APAZA CHINO GRIMALDO | I43: 10 | J43: DERECHO - EEGG | K43: SEDE | L43: VIRTUAL | N43: 988602424 | O43: Horas limitadas por disponibilidad docente
B44: 36 | C44: 15981186 | D44: MARTINEZ ZULOAGA NORA TERESA | I44: 5 | J44: INGENIERIA DE SISTEMAS - EEGG | K44: SEDE | L44: VIRTUAL | N44: 992296790 | O44: Horas limitadas por disponibilidad docente
B45: 37 | C45: 40583004 | D45: SOTOMAYOR ALBITES GEORGE ANTONHY | I45: 8 | J45: ADMINISTRACION DE EMPRESAS - EEGG | K45: SEDE | L45: VIRTUAL | N45: 992575130 | O45: Horas limitadas por disponibilidad docente
... B47: 39 | C47: 15428250 | D47: CHAVEZ CARRAZCO CECILIA MARCELINA | I47: 10 | J47: INGENIERIA INDUSTRIAL - EEGG | K47: SEDE | L47: PRESENCIAL | N47: 953294332 | O47: Horas limitadas por disponibilidad docente
B48: 40 | C48: 08689170 | D48: ACERO CARDENAS ANA MARIA | I48: 10 | J48: INGENIERIA INDUSTRIAL - EEGG | K48: FILIAL | L48: MAS PRESENCIAL | N48: 991299956 | O48: Horas limitadas por disponibilidad docente
B49: 41 | C49: 45303683 | D49: GUTIERREZ JIMENEZ CINDY FIORELLA | I49: 9 | J49: INGENIERIA CIVIL - EEGG | K49: FILIAL | L49: VIRTUAL | N49: 989918045 | O49: Horas limitadas por disponibilidad docente
B50: 42 | C50: 70277443 | D50: OSCCO INJANTE JOSE LUIS | I50: 9 | J50: CONTABILIDAD - EEGG | K50: FILIAL | L50: MAS VIRTUAL | N50: 943858181 | O50: Horas limitadas por disponibilidad docente
B51: 43 | C51: 43958773 | D51: HUAMANI CANALES ANALI MARIELLA | I51: 5 | J51: INGENIERIA CIVIL | K51: FILIAL | L51: PRESENCIAL | N51: 946862930 | O51: Horas limitadas por disponibilidad docente
B52: 44 | C52: 06708096 | D52: FRIAS LIAU HING MELVA | I52: 5 | J52: INGENIERIA CIVIL | K52: FILIAL | L52: PRESENCIAL | N52: 952833970 | O52: Horas limitadas por disponibilidad docente
B53: 45 | C53: 43596886 | D53: PASACHE LAGOS SERGIO LUIS | I53: 4 | J53: INGENIERIA CIVIL | K53: FILIAL | L53: PRESENCIAL | N53: 983730610 | O53: Horas limitadas por disponibilidad docente
B54: 46 | C54: 41060828 | D54: BEJARANO PEREZ JUDITH ROSSANA | I54: 15 | J54: INGENIERIA CIVIL | K54: SEDE | L54: MAS PRESENCIAL | N54: 984399500 | O54: -
B55: 47 | C55: 21447676 | D55: CONDORCHOA CAMACHO CARLOS JOHN | I55: 37 | J55: INGENIERIA CIVIL | K55: FILIAL | L55: MAS PRESENCIAL | N55: 956634229 | O55: -
B56: 48 | C56: 46078496 | D56: JAYO HIGA JOSE JUAN | I56: 11 | J56: INGENIERIA DE SISTEMAS | K56: SEDE | L56: MAS VIRTUAL | N56: 991604262 | O56: Horas limitadas por disponibilidad docente
B57: 49 | C57: 45221222 | D57: VEGA ROSALES JORGE MARTIN | I57: 14 | J57: INGENIERIA INDUSTRIAL | K57: SEDE | L57: VIRTUAL | N57: 940193258 | O57: -
B58: 50 | C58: 45023124 | D58: GUARDIA PANIURA CANDY HAYDEE | I58: 16 | J58: INGENIERIA INDUSTRIAL | K58: SEDE | L58: VIRTUAL | N58: 916461195 | O58: -
B59: 51 | C59: 16662940 | D59: ORDINOLA BRENIS JUAN MANUEL | I59: 16 | J59: INGENIERIA INDUSTRIAL | K59: SEDE | L59: VIRTUAL | N59: 998008120 | O59: -
B60: 52 | C60: 44859703 | D60: SANCHEZ NAVARRETE CARLOS RICARDO | I60: 11 | J60: INGENIERIA CIVIL | K60: FILIAL | L60: PRESENCIAL | N60: 972717272 | O60: Horas limitadas por disponibilidad docente
B61: 53 | C61: 18071852 | D61: PESANTES SALAVARRIA MARCO ALFONSO | I61: 40 | J61: INGENIERIA INDUSTRIAL | K61: SEDE | L61: PRESENCIAL | N61: 964297579 | O61: -

Sheet INVITACION
B6: PROPUESTA DE INVITACION DOCENTE TP PARA SEMESTRE ACADÉMICO 2026-1 FACULTAD DE INGENIERÍA, CIENCIAS Y ADMINISTRACIÓN
B8: N° | C8: DNI | D8: APELLIDOS Y NOMBRES | E8: FACULTAD | F8: ESCUELA PROFESIONAL | G8: LOCAL | H8: MODALIDAD | I8: N° HORAS LECTIVAS | J8: ESCUELA PROFESIONAL | K8: LOCAL | L8: MODALIDAD | M8: CORREO ELECTRÓNICO INSTITUCIONAL | N8: N° CELULAR | O8: OBSERVACIONES
B9: 1 | C9: 15607309 | D9: BERRIOS VEGA CARMEN LUZ | I9: 12 | J9: DERECHO | K9: HUAURA | L9: PRESENCIAL | M9: - | N9: 968857951 | O9: - | P9: CV
B10: 2 | C10: 29384319 | D10: CHUNG RODRIGUEZ JOSE MARTIN | I10: 18 | J10: DERECHO - EEGG | K10: HUAURA | L10: PRESENCIAL | M10: - | N10: 991165153 | O10: - | P10: CV
B11: 3 | C11: 44006023 | D11: CONDE REYES JORGE LUIS | I11: 8 | J11: DERECHO | K11: HUAURA | L11: PRESENCIAL | M11: - | N11: 989390670 | O11: JUSTIFICAR | P11: CV
B12: 4 | C12: 44822572 | D12: DURAN RIOS SANDRO ANIBAL | I12: 9 | J12: DERECHO | K12: HUAURA | L12: VIRTUAL | M12: - | N12: 944457776 | O12: JUSTIFICAR | P12: CV
B13: 5 | C13: 42711303 | D13: FABIAN SOBERANIS MIGUEL ANGEL | I13: 20 | J13: DERECHO - EEGG | K13: HUAURA | L13: PRESENCIAL | M13: - | N13: 978177488 | O13: - | P13: CV
B14: 7 | C14: 40432935 | D14: MIRANDA BAZALAR ROBERTO WILLIAM | I14: 4 | J14: DERECHO | K14: HUAURA | L14: PRESENCIAL | M14: - | N14: 994985272 | O14: JUSTIFICAR | P14: CV
B15: 8 | C15: 40382257 | D15: REA MORENO FLOR MAGALY | I15: 12 | J15: DERECHO | K15: HUAURA | L15: PRESENCIAL | M15: - | N15: 936649961 | O15: - | P15: CV
B16: 9 | D16: CASTILLON SIGUAS LUIS ALFREDO
B17: 10 | D17: CHANG HERNANDEZ GUILLERMO ANDRES
B18: 11 | D18: FERREYROS YUCRA JAIR EMERSON
B19: 12 | D19: GARAYAR TTITO ANA MELIZA
B20: 13 | D20: HUANCAHUIRE BRAVO CLAUDIO ISAIAS
B21: 14
B22: 15
B23: 16
B24: 17
B25: 18
B26: 19
B27: 20
B28: 21
B29: 22
B30: 23
B31: 24
B32: 25
... B136: 129

Sheet REINCORPORACION
B6: PROPUESTA DE INVITACION DOCENTE TP PARA SEMESTRE ACADÉMICO 2026-1 FACULTAD DE INGENIERÍA, CIENCIAS Y ADMINISTRACIÓN
B8: N° | C8: DNI | D8: APELLIDOS Y NOMBRES | E8: FACULTAD | F8: ESCUELA PROFESIONAL | G8: LOCAL | H8: MODALIDAD | I8: N° HORAS LECTIVAS | J8: ESCUELA PROFESIONAL | K8: LOCAL | L8: MODALIDAD | M8: CORREO ELECTRÓNICO INSTITUCIONAL | N8: N° CELULAR | O8: OBSERVACIONES
B9: 1 | D9: CASTILLO ORMEÑO ENZO RENAN | I9: 18 | J9: INGENIERIA DE SISTEMAS | K9: SEDE | L9: PRESENCIAL | O9: -
B10: 2
B11: 3
B12: 4
B13: 5
B14: 6
B15: 7
B16: 8
B17: 9
B18: 10
B19: 11
B20: 12
B21: 13
... B137: 129

Sheet OGTH
C2: Datos para ser llenados por la OGTH
C3: Datos para ser llenados por Vicerrectorado y/o facultades
B4: INFORMACIÓN DE DOCENTES 2026-I PARA ASIGNACIÓN DE PAGOS
B6: N° | C6: DOCENTES UAI | D6: ALTA RANKMI | E6: ENRROLAR | F6: CONTRATO CREADO EN RANKMI | G6: CONTRATO ENVIADO | H6: CONTRATO FIRMADO | I6: ALTA SUNAT | J6: FOTOCHECK LISTO | K6: ¿SE ENTREGÓ EL FOTOCHECK? | L6: ¿SE CARGÓ DOCUMENTOS DE INGRESO? | M6: ENVIÓ SUS DOCUMENTOS DE INGRESO | N6: DOCENTE / JEFE DE PRÁCTICA | O6: DNI | P6: NUMERO DE CELULAR | Q6: CORREO PERSONAL | R6: CORREO INSTITUCIONAL | S6: HORAS 2025-II | T6: HORAS 2026-I | U6: DEDICACIÓN 2025-II | V6: DEDICACIÓN 2026-I | W6: MODALIDAD DE INGRESO | X6: CATEGORIA | Y6: FECHA DE INGRESO | Z6: RCU DE INGRESO 2026-I | AA6: FECHA DE RCU DE INGRESO | AB6: LOCAL 2025-II | AC6: LOCAL 2026-I | AD6: PROGRAMA ACADEMICO 2025-II | AE6: GRADO ACADEMICO 2025-II | AF6: PROGRAMA ACADEMICO 2026-I | AG6: GRADO ACADEMICO 2026-I | AH6: MODALIDAD 2025-II | AI6: MODALIDAD 2026-I | AK6: SUELDO BASICO | AL6: ASIGNACION FAMILIAR / BONO POR CARGO | AM6: PLUXEE | AN6: TOTAL BRUTO MENSUAL | AP6: VALOR DE HORA | AQ6: SEMANA | AR6: TOTAL MENSUAL | AS6: AF / BONO POR INVESTIGACION | AT6: PLUXEE | AU6: TOTAL BRUTO MENSUAL | AW6: OBSERVACIONES OGTH
B7: 1 | C7: BERRIOS VEGA CARMEN LUZ | N7: DOCENTE | O7: 15607309 | P7: 968857951 | Q7: berriosvegacarmenluz7@gmail.com | R7: - | S7: - | T7: 12 | U7: - | V7: TP | W7: INVITACION | X7: CONTRATADO | AB7: - | AC7: HUAURA | AD7: - | AE7: - | AF7: DERECHO | AG7: MAESTRIA | AH7: - | AI7: PRESENCIAL | AK7: 0 | AL7: 0 | AM7: 0 | AN7: =AK7+AL7+AM7 -> 0 | AP7: 0 | AQ7: =AP7*T7 -> 0 | AR7: =AQ7*4 -> 0 | AS7: 0 | AT7: 0 | AU7: =AR7+AS7+AT7 -> 0
B8: 2 | C8: CHUNG RODRIGUEZ JOSE MARTIN | N8: DOCENTE | O8: 29384319 | P8: 991165153 | Q8: chungjose675@gmail.com | R8: - | S8: - | T8: 18 | U8: - | V8: TP | W8: INVITACION | X8: CONTRATADO | AB8: - | AC8: HUAURA | AD8: - | AE8: - | AF8: DERECHO - EEGG | AG8: MAESTRIA | AH8: - | AI8: PRESENCIAL | AK8: 0 | AL8: 0 | AM8: 0 | AN8: =AK8+AL8+AM8 -> 0 | AP8: 0 | AQ8: =AP8*T8 -> 0 | AR8: =AQ8*4 -> 0 | AS8: 0 | AT8: 0 | AU8: =AR8+AS8+AT8 -> 0
B9: 3 | C9: CONDE REYES JORGE LUIS | N9: DOCENTE | O9: 44006023 | P9: 989390670 | Q9: jorgecondereyes@gmail.com | R9: - | S9: - | T9: 8 | U9: - | V9: TP | W9: INVITACION | X9: CONTRATADO | AB9: - | AC9: HUAURA | AD9: - | AE9: - | AF9: DERECHO | AG9: MAESTRIA | AH9: - | AI9: PRESENCIAL | AK9: 0 | AL9: 0 | AM9: 0 | AN9: =AK9+AL9+AM9 -> 0 | AP9: 0 | AQ9: =AP9*T9 -> 0 | AR9: =AQ9*4 -> 0 | AS9: 0 | AT9: 0 | AU9: =AR9+AS9+AT9 -> 0
B10: 4 | C10: DE LA CRUZ SOSA JAKELINE MELINA | N10: DOCENTE | O10: 43517817 | P10: 951222024 | Q10: jakimeli@outlook.com | R10: jakeline.delacruz@autonomadeica.edu.pe | S10: 37 | T10: 32 | U10: TC | V10: TC | W10: RENOVACION | X10: CONTRATADO | Y10: 45915 | AB10: HUAURA | AC10: HUAURA | AD10: PSICOLOGIA - EEGG | AE10: MAESTRIA | AF10: DERECHO - EEGG | AG10: MAESTRIA | AH10: PRESENCIAL | AI10: PRESENCIAL | AK10: 0 | AL10: 0 | AM10: 0 | AN10: =AK10+AL10+AM10 -> 0 | AP10: 0 | AQ10: =AP10*T10 -> 0 | AR10: =AQ10*4 -> 0 | AS10: 0 | AT10: 0 | AU10: =AR10+AS10+AT10 -> 0
B11: 5 | C11: DURAN RIOS SANDRO ANIBAL | N11: DOCENTE | O11: 44822572 | P11: 944457776 | Q11: durisandroanibal@gmail.com | R11: - | S11: - | T11: 9 | U11: - | V11: TP | W11: INVITACION | X11: CONTRATADO | AB11: - | AC11: HUAURA | AD11: - | AE11: - | AF11: DERECHO | AG11: MAESTRIA | AH11: - | AI11: VIRTUAL | AK11: 0 | AL11: 0 | AM11: 0 | AN11: =AK11+AL11+AM11 -> 0 | AP11: 0 | AQ11: =AP11*T11 -> 0 | AR11: =AQ11*4 -> 0 | AS11: 0 | AT11: 0 | AU11: =AR11+AS11+AT11 -> 0
B12: 6 | C12: ESPINOZA MORE CARLA MILAGROS | N12: DOCENTE | O12: 72176698 | P12: 956383530 | Q12: emc1291@gmail.com | R12: - | S12: - | T12: 6 | U12: - | V12: TP | W12: CONCURSO | X12: CONTRATADO | Y12: 46125 | Z12: RCU 097-2026 | AA12: 46083 | AB12: - | AC12: HUAURA | AD12: - | AE12: - | AF12: ADMINISTRACION DE EMPRESAS | AG12: MAESTRIA | AH12: - | AI12: VIRTUAL | AK12: 0 | AL12: 0 | AM12: 0 | AN12: =AK12+AL12+AM12 -> 0 | AP12: 0 | AQ12: =AP12*T12 -> 0 | AR12: =AQ12*4 -> 0 | AS12: 0 | AT12: 0 | AU12: =AR12+AS12+AT12 -> 0
B13: 7 | C13: EVANGELISTA HUAYNALAYA FRANCISCO DE JESUS | N13: DOCENTE | O13: 41807593 | P13: 940392058 | Q13: fraancisco.evngelista1@gmail.com | R13: - | S13: - | T13: 12 | U13: - | V13: TP | W13: CONCURSO | X13: CONTRATADO | Y13: 46125 | Z13: RCU 097-2026 | AA13: 46083 | AB13: - | AC13: HUAURA | AD13: - | AE13: - | AF13: DERECHO | AG13: MAESTRIA | AH13: - | AI13: PRESENCIAL | AK13: 0 | AL13: 0 | AM13: 0 | AN13: =AK13+AL13+AM13 -> 0 | AP13: 0 | AQ13: =AP13*T13 -> 0 | AR13: =AQ13*4 -> 0 | AS13: 0 | AT13: 0 | AU13: =AR13+AS13+AT13 -> 0
B14: 8 | C14: FABIAN SOBERANIS MIGUEL ANGEL | N14: DOCENTE | O14: 42711303 | P14: 978177488 | Q14: fabiancip304301@gmail.com | R14: - | S14: - | T14: 20 | U14: - | V14: TP | W14: INVITACION | X14: CONTRATADO | AB14: - | AC14: HUAURA | AD14: - | AE14: - | AF14: DERECHO - EEGG | AG14: MAESTRIA | AH14: - | AI14: PRESENCIAL | AK14: 0 | AL14: 0 | AM14: 0 | AN14: =AK14+AL14+AM14 -> 0 | AP14: 0 | AQ14: =AP14*T14 -> 0 | AR14: =AQ14*4 -> 0 | AS14: 0 | AT14: 0 | AU14: =AR14+AS14+AT14 -> 0
B15: 9 | C15: GAVINO SANCHEZ JOHN STEVENS | N15: DOCENTE | O15: 75168136 | P15: 906809788 | Q15: johnstevensgavino1101@gmail.com | R15: - | S15: - | T15: 6 | U15: - | V15: TP | W15: CONCURSO | X15: CONTRATADO | Y15: 46125 | Z15: RCU 097-2026 | AA15: 46083 | AB15: - | AC15: HUAURA | AD15: - | AE15: - | AF15: DERECHO - EEGG | AG15: MAESTRIA | AH15: - | AI15: PRESENCIAL | AK15: 0 | AL15: 0 | AM15: 0 | AN15: =AK15+AL15+AM15 -> 0 | AP15: 0 | AQ15: =AP15*T15 -> 0 | AR15: =AQ15*4 -> 0 | AS15: 0 | AT15: 0 | AU15: =AR15+AS15+AT15 -> 0
B16: 10 | C16: LINO FLORES LUIS ANTONIO | N16: DOCENTE | O16: 42146692 | P16: 984374438 | Q16: luis.lino@cip.org.pe | R16: - | S16: - | T16: 8 | U16: - | V16: TP | W16: CONCURSO | X16: CONTRATADO | Y16: 46125 | Z16: RCU 097-2026 | AA16: 46083 | AB16: - | AC16: HUAURA | AD16: - | AE16: - | AF16: ADMINISTRACION DE EMPRESAS - EEGG | AG16: DOCTOR | AH16: - | AI16: PRESENCIAL | AK16: 0 | AL16: 0 | AM16: 0 | AN16: =AK16+AL16+AM16 -> 0 | AP16: 0 | AQ16: =AP16*T16 -> 0 | AR16: =AQ16*4 -> 0 | AS16: 0 | AT16: 0 | AU16: =AR16+AS16+AT16 -> 0
B17: 11 | C17: MANDAMIENTO GRADOS DAMARIS TELMA | N17: DOCENTE | O17: 40428220 | P17: 992990608 | Q17: damarismandamiento44@gmail.com | R17: damaris.mandamiento@autonomadeica.edu.pe | S17: 16 | T17: 32 | U17: TP | V17: TC | W17: RENOVACION | X17: CONTRATADO | Y17: 45922 | AB17: HUAURA | AC17: HUAURA | AD17: ENFERMERIA - EEGG | AE17: MAESTRIA | AF17: DERECHO - EEGG | AG17: MAESTRIA | AH17: PRESENCIAL | AI17: PRESENCIAL | AK17: 0 | AL17: 0 | AM17: 0 | AN17: =AK17+AL17+AM17 -> 0 | AP17: 0 | AQ17: =AP17*T17 -> 0 | AR17: =AQ17*4 -> 0 | AS17: 0 | AT17: 0 | AU17: =AR17+AS17+AT17 -> 0
B18: 12 | C18: MENDOZA CASTILLO JUAN JOSE | N18: DOCENTE | O18: 43608561 | P18: 964859651 | Q18: mendozacastillojuanjose@gmail.com | R18: - | S18: - | T18: 5 | U18: - | V18: TP | W18: CONCURSO | X18: CONTRATADO | Y18: 46125 | Z18: RCU 097-2026 | AA18: 46083 | AB18: - | AC18: HUAURA | AD18: - | AE18: - | AF18: ADMINISTRACION DE EMPRESAS | AG18: MAESTRIA | AH18: - | AI18: VIRTUAL | AK18: 0 | AL18: 0 | AM18: 0 | AN18: =AK18+AL18+AM18 -> 0 | AP18: 0 | AQ18: =AP18*T18 -> 0 | AR18: =AQ18*4 -> 0 | AS18: 0 | AT18: 0 | AU18: =AR18+AS18+AT18 -> 0
B19: 13 | C19: MIRANDA BAZALAR ROBERTO WILLIAM | N19: DOCENTE | O19: 40432935 | P19: 994985272 | Q19: mirandabazalar19@gmail.com | R19: - | S19: - | T19: 4 | U19: - | V19: TP | W19: INVITACION | X19: CONTRATADO | AB19: - | AC19: HUAURA | AD19: - | AE19: - | AF19: DERECHO | AG19: MAESTRIA | AH19: - | AI19: PRESENCIAL | AK19: 0 | AL19: 0 | AM19: 0 | AN19: =AK19+AL19+AM19 -> 0 | AP19: 0 | AQ19: =AP19*T19 -> 0 | AR19: =AQ19*4 -> 0 | AS19: 0 | AT19: 0 | AU19: =AR19+AS19+AT19 -> 0
B20: 14 | C20: PADILLA HIZO PEDRO HERNAN | N20: DOCENTE | O20: 41239504 | P20: 992085961 | Q20: ppadilla1580@gmail.com | R20: pedro.padilla@autonomadeica.edu.pe | S20: 8 | T20: 16 | U20: TP | V20: TP | W20: RENOVACION | X20: CONTRATADO | Y20: 45771 | AB20: HUAURA | AC20: HUAURA | AD20: ENFERMERIA - EEGG | AE20: MAESTRIA | AF20: ADMINISTRACION DE EMPRESAS - EEGG | AG20: MAESTRIA | AH20: PRESENCIAL | AI20: PRESENCIAL | AK20: 0 | AL20: 0 | AM20: 0 | AN20: =AK20+AL20+AM20 -> 0 | AP20: 0 | AQ20: =AP20*T20 -> 0 | AR20: =AQ20*4 -> 0 | AS20: 0 | AT20: 0 | AU20: =AR20+AS20+AT20 -> 0
B21: 15 | C21: PARIHUAMAN QUINDE GERALDINA REBECA | N21: DOCENTE | O21: 33826021 | P21: 989038202 | Q21: geraldinaparihuaman@gmail.com | R21: geraldina.parihuaman@autonomadeica.edu.pe | S21: 13 | T21: 15 | U21: TP | V21: TP | W21: RENOVACION | X21: CONTRATADO | Y21: 45771 | AB21: HUAURA | AC21: HUAURA | AD21: ENFERMERIA - EEGG | AE21: DOCTOR | AF21: ADMINISTRACION DE EMPRESAS - EEGG | AG21: DOCTOR | AH21: PRESENCIAL | AI21: PRESENCIAL | AK21: 0 | AL21: 0 | AM21: 0 | AN21: =AK21+AL21+AM21 -> 0 | AP21: 0 | AQ21: =AP21*T21 -> 0 | AR21: =AQ21*4 -> 0 | AS21: 0 | AT21: 0 | AU21: =AR21+AS21+AT21 -> 0
B22: 16 | C22: PEREZ RETUERTO RONY GEANCARLO | N22: DOCENTE | O22: 42212783 | P22: 960064109 | Q22: rperezr30@gmail.com | R22: rony.perez@autonomadeica.edu.pe | S22: 15 | T22: 10 | U22: TP | V22: TP | W22: RENOVACION | X22: CONTRATADO | Y22: 45771 | AB22: HUAURA | AC22: HUAURA | AD22: DERECHO - EEGG | AE22: MAESTRIA | AF22: DERECHO - EEGG | AG22: MAESTRIA | AH22: PRESENCIAL | AI22: PRESENCIAL | AK22: 0 | AL22: 0 | AM22: 0 | AN22: =AK22+AL22+AM22 -> 0 | AP22: 0 | AQ22: =AP22*T22 -> 0 | AR22: =AQ22*4 -> 0 | AS22: 0 | AT22: 0 | AU22: =AR22+AS22+AT22 -> 0
B23: 17 | C23: PIMENTEL RETUERTO CARMEN ANDREA | N23: DOCENTE | O23: 40822577 | P23: 957786821 | Q23: hay1sociologa@gmail.com | R23: carmen.pimentel@autonomadeica.edu.pe | S23: 36 | T23: 16 | U23: TC | V23: TP | W23: RENOVACION | X23: CONTRATADO | Y23: 45771 | AB23: HUAURA | AC23: HUAURA | AD23: ENFERMERIA - EEGG | AE23: MAESTRIA | AF23: DERECHO - EEGG | AG23: MAESTRIA | AH23: PRESENCIAL | AI23: PRESENCIAL | AK23: 0 | AL23: 0 | AM23: 0 | AN23: =AK23+AL23+AM23 -> 0 | AP23: 0 | AQ23: =AP23*T23 -> 0 | AR23: =AQ23*4 -> 0 | AS23: 0 | AT23: 0 | AU23: =AR23+AS23+AT23 -> 0
B24: 18 | C24: QUINTEROS NICHO LUIS FERNANDO | N24: DOCENTE | O24: 15591781 | P24: 970427179 | Q24: luisferquinic@gmail.com | R24: - | S24: - | T24: 4 | U24: - | V24: TP | W24: CONCURSO | X24: CONTRATADO | Y24: 46125 | Z24: RCU 097-2026 | AA24: 46083 | AB24: - | AC24: HUAURA | AD24: - | AE24: - | AF24: DERECHO - EEGG | AG24: MAESTRIA | AH24: - | AI24: PRESENCIAL | AK24: 0 | AL24: 0 | AM24: 0 | AN24: =AK24+AL24+AM24 -> 0 | AP24: 0 | AQ24: =AP24*T24 -> 0 | AR24: =AQ24*4 -> 0 | AS24: 0 | AT24: 0 | AU24: =AR24+AS24+AT24 -> 0
B25: 19 | C25: REA MORENO FLOR MAGALY | N25: DOCENTE | O25: 40382257 | P25: 936649961 | Q25: flormagaly021179@gmail.com | R25: - | S25: - | T25: 12 | U25: - | V25: TP | W25: INVITACION | X25: CONTRATADO | AB25: - | AC25: HUAURA | AD25: - | AE25: - | AF25: DERECHO | AG25: MAESTRIA | AH25: - | AI25: PRESENCIAL | AK25: 0 | AL25: 0 | AM25: 0 | AN25: =AK25+AL25+AM25 -> 0 | AP25: 0 | AQ25: =AP25*T25 -> 0 | AR25: =AQ25*4 -> 0 | AS25: 0 | AT25: 0 | AU25: =AR25+AS25+AT25 -> 0
B26: 20 | C26: REQUENA GARCIA MARIA DEL ROSARIO | N26: DOCENTE | O26: 08684196 | P26: 940716638 | Q26: mrequena@unjfsc.edu.pe | R26: maria.requena@autonomadeica.edu.pe | S26: 15 | T26: 10 | U26: TP | V26: TP | W26: RENOVACION | X26: CONTRATADO | Y26: 45782 | AB26: HUAURA | AC26: HUAURA | AD26: DERECHO - EEGG | AE26: MAESTRIA | AF26: ADMINISTRACION DE EMPRESAS - EEGG | AG26: MAESTRIA | AH26: PRESENCIAL | AI26: PRESENCIAL | AK26: 0 | AL26: 0 | AM26: 0 | AN26: =AK26+AL26+AM26 -> 0 | AP26: 0 | AQ26: =AP26*T26 -> 0 | AR26: =AQ26*4 -> 0 | AS26: 0 | AT26: 0 | AU26: =AR26+AS26+AT26 -> 0
B27: 21 | C27: REYES ROMAN CARLOS ARTURO | N27: DOCENTE | O27: 41208519 | P27: 985001402 | Q27: econ.carlosrr@gmail.com | R27: arturo.reyes@autonomadeica.edu.pe | S27: 17 | T27: 15 | U27: TP | V27: TP | W27: RENOVACION | X27: CONTRATADO | Y27: 45922 | AB27: HUAURA | AC27: HUAURA | AD27: ADMINISTRACION DE EMPRESAS - EEGG | AE27: MAESTRIA | AF27: DERECHO - EEGG | AG27: MAESTRIA | AH27: VIRTUAL | AI27: PRESENCIAL | AK27: 0 | AL27: 0 | AM27: 0 | AN27: =AK27+AL27+AM27 -> 0 | AP27: 0 | AQ27: =AP27*T27 -> 0 | AR27: =AQ27*4 -> 0 | AS27: 0 | AT27: 0 | AU27: =AR27+AS27+AT27 -> 0
B28: 22 | C28: RIOS SANTIAGO WILSON CESAR | N28: DOCENTE | O28: 44398451 | P28: 989336775 | Q28: cesarxavy14@gmail.com | R28: wilson.rios@autonomadeica.edu.pe | S28: 13 | T28: 14 | U28: TP | V28: TP | W28: RENOVACION | X28: CONTRATADO | Y28: 45771 | AB28: HUAURA | AC28: HUAURA | AD28: PSICOLOGIA - EEGG | AE28: MAESTRIA | AF28: DERECHO - EEGG | AG28: MAESTRIA | AH28: PRESENCIAL | AI28: PRESENCIAL | AK28: 0 | AL28: 0 | AM28: 0 | AN28: =AK28+AL28+AM28 -> 0 | AP28: 0 | AQ28: =AP28*T28 -> 0 | AR28: =AQ28*4 -> 0 | AS28: 0 | AT28: 0 | AU28: =AR28+AS28+AT28 -> 0
B29: 23 | C29: RODRIGUEZ RAMIREZ MARIA ISABEL | N29: DOCENTE | O29: 15590660 | P29: 987923259 | Q29: rodrisag18@gmail.com | R29: - | S29: - | T29: 4 | U29: - | V29: TP | W29: CONCURSO | X29: CONTRATADO | Y29: 46125 | Z29: RCU 097-2026 | AA29: 46083 | AB29: - | AC29: HUAURA | AD29: - | AE29: - | AF29: ADMINISTRACION DE EMPRESAS | AG29: DOCTOR | AH29: - | AI29: PRESENCIAL | AK29: 0 | AL29: 0 | AM29: 0 | AN29: =AK29+AL29+AM29 -> 0 | AP29: 0 | AQ29: =AP29*T29 -> 0 | AR29: =AQ29*4 -> 0 | AS29: 0 | AT29: 0 | AU29: =AR29+AS29+AT29 -> 0
B30: 24 | C30: ROJAS GUZMAN TITO | N30: DOCENTE | O30: 15688249 | P30: 961433324 | Q30: titorojas189@gmail.com | R30: - | S30: - | T30: 9 | U30: - | V30: TP | W30: CONCURSO | X30: CONTRATADO | Y30: 46125 | Z30: RCU 097-2026 | AA30: 46083 | AB30: - | AC30: HUAURA | AD30: - | AE30: - | AF30: ADMINISTRACION DE EMPRESAS | AG30: DOCTOR | AH30: - | AI30: PRESENCIAL | AK30: 0 | AL30: 0 | AM30: 0 | AN30: =AK30+AL30+AM30 -> 0 | AP30: 0 | AQ30: =AP30*T30 -> 0 | AR30: =AQ30*4 -> 0 | AS30: 0 | AT30: 0 | AU30: =AR30+AS30+AT30 -> 0
B31: 25 | C31: SACRAMENTO LAZARO ROSA ALBINA | N31: DOCENTE | O31: 40740790 | P31: 924012573 | Q31: rosa.sacramento1612@gmail.com | R31: - | S31: - | T31: 20 | U31: - | V31: TP | W31: CONCURSO | X31: CONTRATADO | Y31: 46125 | Z31: RCU 097-2026 | AA31: 46083 | AB31: - | AC31: HUAURA | AD31: - | AE31: - | AF31: DERECHO | AG31: MAESTRIA | AH31: - | AI31: PRESENCIAL | AK31: 0 | AL31: 0 | AM31: 0 | AN31: =AK31+AL31+AM31 -> 0 | AP31: 0 | AQ31: =AP31*T31 -> 0 | AR31: =AQ31*4 -> 0 | AS31: 0 | AT31: 0 | AU31: =AR31+AS31+AT31 -> 0
B32: 26 | C32: SAMANAMUD VALENTIN MIGUEL ANGEL MOISES | N32: DOCENTE | O32: 15725118 | P32: 970656047 | Q32: miguel.samanamud.efcn@gmail.com | R32: - | S32: - | T32: 4 | U32: - | V32: TP | W32: CONCURSO | X32: CONTRATADO | Y32: 46125 | Z32: RCU 097-2026 | AA32: 46083 | AB32: - | AC32: HUAURA | AD32: - | AE32: - | AF32: ADMINISTRACION DE EMPRESAS | AG32: MAESTRIA | AH32: - | AI32: PRESENCIAL | AK32: 0 | AL32: 0 | AM32: 0 | AN32: =AK32+AL32+AM32 -> 0 | AP32: 0 | AQ32: =AP32*T32 -> 0 | AR32: =AQ32*4 -> 0 | AS32: 0 | AT32: 0 | AU32: =AR32+AS32+AT32 -> 0
B33: 27 | C33: SANCHEZ SOTIL KENNICK ENRIQUE | N33: DOCENTE | O33: 45165102 | P33: 952944920 | Q33: folkennick34@gmail.com | R33: kennick.sanchez@autonomadeica.edu.pe | S33: 16 | T33: 8 | U33: TP | V33: TP | W33: RENOVACION | X33: CONTRATADO | Y33: 45771 | AB33: HUAURA | AC33: HUAURA | AD33: ENFERMERIA - EEGG | AE33: MAESTRIA | AF33: DERECHO - EEGG | AG33: DOCTOR | AH33: PRESENCIAL | AI33: PRESENCIAL | AK33: 0 | AL33: 0 | AM33: 0 | AN33: =AK33+AL33+AM33 -> 0 | AP33: 0 | AQ33: =AP33*T33 -> 0 | AR33: =AQ33*4 -> 0 | AS33: 0 | AT33: 0 | AU33: =AR33+AS33+AT33 -> 0
B34: 28 | C34: TRUJILLO APONTE WAGNER ABRAHAM | N34: DOCENTE | O34: 43027985 | P34: 964034650 | Q34: wagnertrujillo7@hotmail.com | R34: - | S34: - | T34: 9 | U34: - | V34: TP | W34: CONCURSO | X34: CONTRATADO | Y34: 46125 | Z34: RCU 097-2026 | AA34: 46083 | AB34: - | AC34: HUAURA | AD34: - | AE34: - | AF34: DERECHO | AG34: MAESTRIA | AH34: - | AI34: VIRTUAL | AK34: 0 | AL34: 0 | AM34: 0 | AN34: =AK34+AL34+AM34 -> 0 | AP34: 0 | AQ34: =AP34*T34 -> 0 | AR34: =AQ34*4 -> 0 | AS34: 0 | AT34: 0 | AU34: =AR34+AS34+AT34 -> 0
B35: 29 | C35: VILLANUEVA CAMAC GUILLERMO ARTURO | N35: DOCENTE | O35: 70179483 | P35: 983861568 | Q35: guille.villa.vc12@gmail.com | R35: - | S35: - | T35: 20 | U35: - | V35: TP | W35: CONCURSO | X35: CONTRATADO | Y35: 46125 | Z35: RCU 097-2026 | AA35: 46083 | AB35: - | AC35: HUAURA | AD35: - | AE35: - | AF35: ADMINISTRACION DE EMPRESAS - EEGG | AG35: MAESTRIA | AH35: - | AI35: PRESENCIAL | AK35: 0 | AL35: 0 | AM35: 0 | AN35: =AK35+AL35+AM35 -> 0 | AP35: 0 | AQ35: =AP35*T35 -> 0 | AR35: =AQ35*4 -> 0 | AS35: 0 | AT35: 0 | AU35: =AR35+AS35+AT35 -> 0
B36: 30 | C36: GUERRERO CERVERA JULIA DEL PILAR | N36: DOCENTE | O36: 15738084 | P36: 996174294 | Q36: j1511guerrero@gmial.com | R36: - | S36: - | T36: 14 | U36: - | V36: TP | W36: CONCURSO | X36: CONTRATADO | Y36: 46125 | Z36: RCU 097-2026 | AA36: 46083 | AB36: - | AC36: HUAURA | AD36: - | AE36: - | AF36: ADMINISTRACION DE EMPRESAS - EEGG | AG36: MAESTRIA | AH36: - | AI36: MAS VIRTUAL | AK36: 0 | AL36: 0 | AM36: 0 | AN36: =AK36+AL36+AM36 -> 0 | AP36: 0 | AQ36: =AP36*T36 -> 0 | AR36: =AQ36*4 -> 0 | AS36: 0 | AT36: 0 | AU36: =AR36+AS36+AT36 -> 0
B37: 31 | C37: ABANTO MERINO LUIS ALFREDO | N37: DOCENTE | O37: 26629386 | P37: 982604568 | Q37: alfredo.abantomerino@gmail.com | R37: - | S37: - | T37: 8 | U37: - | V37: TP | W37: CONCURSO | X37: CONTRATADO | Y37: 46125 | Z37: RCU 116-2026 | AA37: 46105 | AB37: - | AC37: SEDE | AD37: - | AE37: - | AF37: ADMINISTRACION Y FINANZAS | AG37: DOCTOR | AH37: - | AI37: VIRTUAL | AK37: 0 | AL37: 0 | AM37: 0 | AN37: =AK37+AL37+AM37 -> 0 | AP37: 0 | AQ37: =AP37*T37 -> 0 | AR37: =AQ37*4 -> 0 | AS37: 0 | AT37: 0 | AU37: =AR37+AS37+AT37 -> 0
B38: 32 | C38: AGUADO APOLAYA RAUL HERNANDO | N38: DOCENTE | O38: 21814921 | P38: 906408102 | Q38: - | R38: raul.aguado@autonomadeica.edu.pe | S38: 15 | T38: 19 | U38: TP | V38: TP | W38: RENOVACION | X38: CONTRATADO | Y38: 41821 | AB38: SEDE | AC38: SEDE | AD38: INGENIERIA INDUSTRIAL | AE38: MAESTRIA | AF38: INGENIERIA INDUSTRIAL | AG38: MAESTRIA | AH38: PRESENCIAL | AI38: PRESENCIAL | AK38: 0 | AL38: 0 | AM38: 0 | AN38: =AK38+AL38+AM38 -> 0 | AP38: 0 | AQ38: =AP38*T38 -> 0 | AR38: =AQ38*4 -> 0 | AS38: 0 | AT38: 0 | AU38: =AR38+AS38+AT38 -> 0
B39: 33 | C39: AGUIRRE ESPINOZA MONICA WENDY | N39: DOCENTE | O39: 21522173 | P39: 920660685 | Q39: - | R39: monica.aguirre@autonomadeica.edu.pe | S39: 16 | T39: 16 | U39: TP | V39: TP | W39: RENOVACION | X39: CONTRATADO | Y39: 44634 | AB39: FILIAL | AC39: FILIAL | AD39: DERECHO | AE39: DOCTOR | AF39: DERECHO | AG39: DOCTOR | AH39: VIRTUAL | AI39: VIRTUAL | AK39: 0 | AL39: 0 | AM39: 0 | AN39: =AK39+AL39+AM39 -> 0 | AP39: 0 | AQ39: =AP39*T39 -> 0 | AR39: =AQ39*4 -> 0 | AS39: 0 | AT39: 0 | AU39: =AR39+AS39+AT39 -> 0
B40: 34 | C40: ALCANTARA FARFAN JUAN CARLOS | N40: DOCENTE | O40: 21569287 | P40: 956083663 | Q40: - | R40: juan.alcantara@autonomadeica.edu.pe | S40: 9 | T40: 8 | U40: TP | V40: TP | W40: RENOVACION | X40: CONTRATADO | Y40: 45922 | AB40: SEDE | AC40: SEDE | AD40: DERECHO | AE40: MAESTRIA | AF40: DERECHO | AG40: MAESTRIA | AH40: PRESENCIAL | AI40: VIRTUAL | AK40: 0 | AL40: 0 | AM40: 0 | AN40: =AK40+AL40+AM40 -> 0 | AP40: 0 | AQ40: =AP40*T40 -> 0 | AR40: =AQ40*4 -> 0 | AS40: 0 | AT40: 0 | AU40: =AR40+AS40+AT40 -> 0
B41: 35 | C41: GOMERO MANCESIDOR JOHNNY MITCHELL | N41: DOCENTE | O41: 44114929 | P41: 992110895 | Q41: jgomero@unab.ed.pe | R41: - | S41: - | T41: 10 | U41: - | V41: TP | W41: CONCURSO | X41: CONTRATADO | Y41: 46125 | Z41: RCU 116-2026 | AA41: 46105 | AB41: - | AC41: SEDE | AD41: - | AE41: - | AF41: ADMINISTRACION DE EMPRESAS | AG41: DOCTOR | AH41: - | AI41: VIRTUAL | AK41: 0 | AL41: 0 | AM41: 0 | AN41: =AK41+AL41+AM41 -> 0 | AP41: 0 | AQ41: =AP41*T41 -> 0 | AR41: =AQ41*4 -> 0 | AS41: 0 | AT41: 0 | AU41: =AR41+AS41+AT41 -> 0
B42: 36 | C42: RECUAY SALAZAR CARLOS ALBERTO | N42: DOCENTE | O42: 40435228 | P42: 990935896 | Q42: carlos.recuay@gmail.com | R42: - | S42: - | T42: 4 | U42: - | V42: TP | W42: CONCURSO | X42: CONTRATADO | Y42: 46125 | Z42: RCU 116-2026 | AA42: 46105 | AB42: - | AC42: SEDE | AD42: - | AE42: - | AF42: ADMINISTRACION DE EMPRESAS - EEGG | AG42: MAESTRIA | AH42: - | AI42: VIRTUAL | AK42: 0 | AL42: 0 | AM42: 0 | AN42: =AK42+AL42+AM42 -> 0 | AP42: 0 | AQ42: =AP42*T42 -> 0 | AR42: =AQ42*4 -> 0 | AS42: 0 | AT42: 0 | AU42: =AR42+AS42+AT42 -> 0
B43: 37 | C43: SALCEDO RODAS PERCY ISMAEL | N43: DOCENTE | O43: 16756416 | P43: 972627821 | Q43: percysr219@gmail.com | R43: - | S43: - | T43: 18 | U43: - | V43: TP | W43: CONCURSO | X43: CONTRATADO | Y43: 46125 | Z43: RCU 116-2026 | AA43: 46105 | AB43: - | AC43: SEDE | AD43: - | AE43: - | AF43: ADMINISTRACION DE EMPRESAS | AG43: MAESTRIA | AH43: - | AI43: VIRTUAL | AK43: 0 | AL43: 0 | AM43: 0 | AN43: =AK43+AL43+AM43 -> 0 | AP43: 0 | AQ43: =AP43*T43 -> 0 | AR43: =AQ43*4 -> 0 | AS43: 0 | AT43: 0 | AU43: =AR43+AS43+AT43 -> 0
B44: 38 | C44: BUITRON LLACSA JOSE MANUEL | N44: DOCENTE | O44: 70108675 | P44: 977518295 | Q44: josemabuitron@gmail.com | R44: - | S44: - | T44: 9 | U44: - | V44: TP | W44: CONCURSO | X44: CONTRATADO | Y44: 46125 | Z44: RCU 116-2026 | AA44: 46105 | AB44: - | AC44: SEDE | AD44: - | AE44: - | AF44: DERECHO - EEGG | AG44: MAESTRIA | AH44: - | AI44: MAS PRESENCIAL | AK44: 0 | AL44: 0 | AM44: 0 | AN44: =AK44+AL44+AM44 -> 0 | AP44: 0 | AQ44: =AP44*T44 -> 0 | AR44: =AQ44*4 -> 0 | AS44: 0 | AT44: 0 | AU44: =AR44+AS44+AT44 -> 0
B45: 39 | C45: MORALES CHAVEZ GISSEL JOCELINE | N45: DOCENTE | O45: 46075693 | P45: 958691349 | Q45: moraleschavezgissel@gmail.com | R45: - | S45: - | T45: 5 | U45: - | V45: TP | W45: CONCURSO | X45: CONTRATADO | Y45: 46125 | Z45: RCU 116-2026 | AA45: 46105 | AB45: - | AC45: SEDE | AD45: - | AE45: - | AF45: ADMINISTRACION Y FINANZAS | AG45: MAESTRIA | AH45: - | AI45: VIRTUAL | AK45: 0 | AL45: 0 | AM45: 0 | AN45: =AK45+AL45+AM45 -> 0 | AP45: 0 | AQ45: =AP45*T45 -> 0 | AR45: =AQ45*4 -> 0 | AS45: 0 | AT45: 0 | AU45: =AR45+AS45+AT45 -> 0
B46: 40 | C46: ZUMAETA BERAMENDI JACQUELINE DIANA | N46: DOCENTE | O46: 21435528 | P46: 989365672 | Q46: jzumaeta01@gmail.com | R46: - | S46: - | T46: 8 | U46: - | V46: TP | W46: CONCURSO | X46: CONTRATADO | Y46: 46125 | Z46: RCU 116-2026 | AA46: 46105 | AB46: - | AC46: SEDE | AD46: - | AE46: - | AF46: ADMINISTRACION Y FINANZAS | AG46: MAESTRIA | AH46: - | AI46: VIRTUAL | AK46: 0 | AL46: 0 | AM46: 0 | AN46: =AK46+AL46+AM46 -> 0 | AP46: 0 | AQ46: =AP46*T46 -> 0 | AR46: =AQ46*4 -> 0 | AS46: 0 | AT46: 0 | AU46: =AR46+AS46+AT46 -> 0
B47: 41 | C47: DIAZ VELASQUEZ JULIO CESAR | N47: DOCENTE | O47: 70786643 | P47: 924849452 | Q47: cvjuliodiaz@gmail.com | R47: - | S47: - | T47: 12 | U47: - | V47: TP | W47: CONCURSO | X47: CONTRATADO | Y47: 46125 | Z47: RCU 116-2026 | AA47: 46105 | AB47: - | AC47: FILIAL | AD47: - | AE47: - | AF47: ADMINISTRACION Y FINANZAS | AG47: MAESTRIA | AH47: - | AI47: VIRTUAL | AK47: 0 | AL47: 0 | AM47: 0 | AN47: =AK47+AL47+AM47 -> 0 | AP47: 0 | AQ47: =AP47*T47 -> 0 | AR47: =AQ47*4 -> 0 | AS47: 0 | AT47: 0 | AU47: =AR47+AS47+AT47 -> 0
B48: 42 | C48: ROMERO CARAZAS RAFAEL | N48: DOCENTE | O48: 46590523 | P48: 982315013 | Q48: rafaelromerocarazas@gmail.com | R48: - | S48: - | T48: 5 | U48: - | V48: TP | W48: CONCURSO | X48: CONTRATADO | Y48: 46125 | Z48: RCU 116-2026 | AA48: 46105 | AB48: - | AC48: SEDE | AD48: - | AE48: - | AF48: ADMINISTRACION Y FINANZAS | AG48: MAESTRIA | AH48: - | AI48: VIRTUAL | AK48: 0 | AL48: 0 | AM48: 0 | AN48: =AK48+AL48+AM48 -> 0 | AP48: 0 | AQ48: =AP48*T48 -> 0 | AR48: =AQ48*4 -> 0 | AS48: 0 | AT48: 0 | AU48: =AR48+AS48+AT48 -> 0
B49: 43 | C49: CALLAN BACILIO RICHARD | N49: DOCENTE | O49: 46825060 | P49: 946042178 | Q49: richardcallanbacilio@gmail.com | R49: - | S49: - | T49: 5 | U49: - | V49: TP | W49: CONCURSO | X49: CONTRATADO | Y49: 46125 | Z49: RCU 116-2026 | AA49: 46105 | AB49: - | AC49: FILIAL | AD49: - | AE49: - | AF49: ADMINISTRACION Y FINANZAS | AG49: MAESTRIA | AH49: - | AI49: VIRTUAL | AK49: 0 | AL49: 0 | AM49: 0 | AN49: =AK49+AL49+AM49 -> 0 | AP49: 0 | AQ49: =AP49*T49 -> 0 | AR49: =AQ49*4 -> 0 | AS49: 0 | AT49: 0 | AU49: =AR49+AS49+AT49 -> 0
B50: 44 | C50: MAS VILLANUEVA KENY ARNOLD | N50: DOCENTE | O50: 72681156 | P50: 953362861 | Q50: vilmaskear@outlook.com | R50: - | S50: - | T50: 5 | U50: - | V50: TP | W50: CONCURSO | X50: CONTRATADO | Y50: 46125 | Z50: RCU 116-2026 | AA50: 46105 | AB50: - | AC50: FILIAL | AD50: - | AE50: - | AF50: CONTABILIDAD | AG50: MAESTRIA | AH50: - | AI50: VIRTUAL | AK50: 0 | AL50: 0 | AM50: 0 | AN50: =AK50+AL50+AM50 -> 0 | AP50: 0 | AQ50: =AP50*T50 -> 0 | AR50: =AQ50*4 -> 0 | AS50: 0 | AT50: 0 | AU50: =AR50+AS50+AT50 -> 0
B51: 45 | C51: QUIROGA PAIVA DAVID EDUARDO | N51: DOCENTE | O51: 02885494 | P51: 933531483 | Q51: dequiroga09@gmail.com | R51: - | S51: - | T51: 3 | U51: - | V51: TP | W51: CONCURSO | X51: CONTRATADO | Y51: 46125 | Z51: RCU 116-2026 | AA51: 46105 | AB51: - | AC51: FILIAL | AD51: - | AE51: - | AF51: CONTABILIDAD | AG51: MAESTRIA | AH51: - | AI51: VIRTUAL | AK51: 0 | AL51: 0 | AM51: 0 | AN51: =AK51+AL51+AM51 -> 0 | AP51: 0 | AQ51: =AP51*T51 -> 0 | AR51: =AQ51*4 -> 0 | AS51: 0 | AT51: 0 | AU51: =AR51+AS51+AT51 -> 0
B52: 46 | C52: ZAFRA SALAS MARCO ANDRE | N52: DOCENTE | O52: 45156306 | P52: 969551419 | Q52: marco.zafra@gmail.com | R52: - | S52: - | T52: 17 | U52: - | V52: TP | W52: CONCURSO | X52: CONTRATADO | Y52: 46125 | Z52: RCU 116-2026 | AA52: 46105 | AB52: - | AC52: SEDE | AD52: - | AE52: - | AF52: ADMINISTRACION DE EMPRESAS | AG52: MAESTRIA | AH52: - | AI52: VIRTUAL | AK52: 0 | AL52: 0 | AM52: 0 | AN52: =AK52+AL52+AM52 -> 0 | AP52: 0 | AQ52: =AP52*T52 -> 0 | AR52: =AQ52*4 -> 0 | AS52: 0 | AT52: 0 | AU52: =AR52+AS52+AT52 -> 0
B53: 47 | C53: MANRIQUE CERVANTES JOSE ANTONIO | N53: DOCENTE | O53: 41519363 | P53: 987202320 | Q53: joseantoniolaw@gmail.com | R53: - | S53: - | T53: 4 | U53: - | V53: TP | W53: CONCURSO | X53: CONTRATADO | Y53: 46125 | Z53: RCU 116-2026 | AA53: 46105 | AB53: - | AC53: FILIAL | AD53: - | AE53: - | AF53: DERECHO | AG53: DOCTOR | AH53: - | AI53: VIRTUAL | AK53: 0 | AL53: 0 | AM53: 0 | AN53: =AK53+AL53+AM53 -> 0 | AP53: 0 | AQ53: =AP53*T53 -> 0 | AR53: =AQ53*4 -> 0 | AS53: 0 | AT53: 0 | AU53: =AR53+AS53+AT53 -> 0
B54: 48 | C54: SALAZAR GAMBOA OSCAR FRITZ ALEXANDER | N54: DOCENTE | O54: 46730566 | P54: 983582045 | Q54: osg@estudio-salazar.com | R54: - | S54: - | T54: 15 | U54: - | V54: TP | W54: CONCURSO | X54: CONTRATADO | Y54: 46125 | Z54: RCU 116-2026 | AA54: 46105 | AB54: - | AC54: SEDE | AD54: - | AE54: - | AF54: DERECHO - EEGG | AG54: MAESTRIA | AH54: - | AI54: VIRTUAL | AK54: 0 | AL54: 0 | AM54: 0 | AN54: =AK54+AL54+AM54 -> 0 | AP54: 0 | AQ54: =AP54*T54 -> 0 | AR54: =AQ54*4 -> 0 | AS54: 0 | AT54: 0 | AU54: =AR54+AS54+AT54 -> 0
B55: 49 | C55: CABEZA MOLINA LUIS FELIPE | N55: DOCENTE | O55: 41536992 | P55: 969042565 | Q55: luisfelipe0007@hotmail.com | R55: - | S55: - | T55: 8 | U55: - | V55: TP | W55: CONCURSO | X55: CONTRATADO | Y55: 46125 | Z55: RCU 116-2026 | AA55: 46105 | AB55: - | AC55: FILIAL | AD55: - | AE55: - | AF55: DERECHO | AG55: DOCTOR | AH55: - | AI55: VIRTUAL | AK55: 0 | AL55: 0 | AM55: 0 | AN55: =AK55+AL55+AM55 -> 0 | AP55: 0 | AQ55: =AP55*T55 -> 0 | AR55: =AQ55*4 -> 0 | AS55: 0 | AT55: 0 | AU55: =AR55+AS55+AT55 -> 0
B56: 50 | C56: MUÑANTE SIHUES CESAR ARTURO | N56: DOCENTE | O56: 40105460 | P56: 950058593 | Q56: cesararturo2112@gmail.com | R56: - | S56: - | T56: 10 | U56: - | V56: TP | W56: CONCURSO | X56: CONTRATADO | Y56: 46125 | Z56: RCU 116-2026 | AA56: 46105 | AB56: - | AC56: SEDE | AD56: - | AE56: - | AF56: DERECHO - EEGG | AG56: MAESTRIA | AH56: - | AI56: VIRTUAL | AK56: 0 | AL56: 0 | AM56: 0 | AN56: =AK56+AL56+AM56 -> 0 | AP56: 0 | AQ56: =AP56*T56 -> 0 | AR56: =AQ56*4 -> 0 | AS56: 0 | AT56: 0 | AU56: =AR56+AS56+AT56 -> 0
B57: 51 | C57: PIZARRO OSORIO BETSABE LILIA | N57: DOCENTE | O57: 42515290 | P57: 976805104 | Q57: abogada.betsabe.pizarro@gmail.com | R57: - | S57: - | T57: 32 | U57: - | V57: TC | W57: CONCURSO | X57: CONTRATADO | Y57: 46125 | Z57: RCU 116-2026 | AA57: 46105 | AB57: - | AC57: SEDE | AD57: - | AE57: - | AF57: DERECHO | AG57: DOCTOR | AH57: - | AI57: MAS PRESENCIAL | AK57: 0 | AL57: 0 | AM57: 0 | AN57: =AK57+AL57+AM57 -> 0 | AP57: 0 | AQ57: =AP57*T57 -> 0 | AR57: =AQ57*4 -> 0 | AS57: 0 | AT57: 0 | AU57: =AR57+AS57+AT57 -> 0
B58: 52 | C58: ULLOQUE SAMATELO CARLOS AUGUSTO | N58: DOCENTE | O58: 45007560 | P58: 969015640 | Q58: carlosulloque88@gmail.com | R58: - | S58: - | T58: 8 | U58: - | V58: TP | W58: CONCURSO | X58: CONTRATADO | Y58: 46125 | Z58: RCU 116-2026 | AA58: 46105 | AB58: - | AC58: SEDE | AD58: - | AE58: - | AF58: DERECHO - EEGG | AG58: MAESTRIA | AH58: - | AI58: VIRTUAL | AK58: 0 | AL58: 0 | AM58: 0 | AN58: =AK58+AL58+AM58 -> 0 | AP58: 0 | AQ58: =AP58*T58 -> 0 | AR58: =AQ58*4 -> 0 | AS58: 0 | AT58: 0 | AU58: =AR58+AS58+AT58 -> 0
B59: 53 | C59: BAHAMONDES GARCIA SINOE GEOFREY | N59: DOCENTE | O59: 29726614 | P59: 971450905 | Q59: sinoebg@gmail.com | R59: - | S59: - | T59: 15 | U59: - | V59: TP | W59: CONCURSO | X59: CONTRATADO | Y59: 46125 | Z59: RCU 116-2026 | AA59: 46105 | AB59: - | AC59: SEDE | AD59: - | AE59: - | AF59: INGENIERIA DE SISTEMAS - EEGG | AG59: DOCTOR | AH59: - | AI59: VIRTUAL | AK59: 0 | AL59: 0 | AM59: 0 | AN59: =AK59+AL59+AM59 -> 0 | AP59: 0 | AQ59: =AP59*T59 -> 0 | AR59: =AQ59*4 -> 0 | AS59: 0 | AT59: 0 | AU59: =AR59+AS59+AT59 -> 0
B60: 54 | C60: VELASQUEZ CHUNGA JOSE LUIS EDUARDO | N60: DOCENTE | O60: 76129345 | P60: 921933801 | Q60: eduardo_velasquez_12@hotmail.com | R60: - | S60: - | T60: 8 | U60: - | V60: TP | W60: CONCURSO | X60: CONTRATADO | Y60: 46125 | Z60: RCU 116-2026 | AA60: 46105 | AB60: - | AC60: SEDE | AD60: - | AE60: - | AF60: INGENIERIA CIVIL - EEGG | AG60: DOCTOR | AH60: - | AI60: VIRTUAL | AK60: 0 | AL60: 0 | AM60: 0 | AN60: =AK60+AL60+AM60 -> 0 | AP60: 0 | AQ60: =AP60*T60 -> 0 | AR60: =AQ60*4 -> 0 | AS60: 0 | AT60: 0 | AU60: =AR60+AS60+AT60 -> 0
B61: 55 | C61: APAZA CHINO GRIMALDO | N61: DOCENTE | O61: 72049382 | P61: 988602424 | Q61: grim866@gmail.com | R61: - | S61: - | T61: 10 | U61: - | V61: TP | W61: CONCURSO | X61: CONTRATADO | Y61: 46125 | Z61: RCU 116-2026 | AA61: 46105 | AB61: - | AC61: SEDE | AD61: - | AE61: - | AF61: DERECHO - EEGG | AG61: MAESTRIA | AH61: - | AI61: VIRTUAL | AK61: 0 | AL61: 0 | AM61: 0 | AN61: =AK61+AL61+AM61 -> 0 | AP61: 0 | AQ61: =AP61*T61 -> 0 | AR61: =AQ61*4 -> 0 | AS61: 0 | AT61: 0 | AU61: =AR61+AS61+AT61 -> 0
B62: 56 | C62: MARTINEZ ZULOAGA NORA TERESA | N62: DOCENTE | O62: 15981186 | P62: 992296790 | Q62: noramz2025@gmail.com | R62: - | S62: - | T62: 5 | U62: - | V62: TP | W62: CONCURSO | X62: CONTRATADO | Y62: 46125 | Z62: RCU 116-2026 | AA62: 46105 | AB62: - | AC62: SEDE | AD62: - | AE62: - | AF62: INGENIERIA DE SISTEMAS - EEGG | AG62: DOCTOR | AH62: - | AI62: VIRTUAL | AK62: 0 | AL62: 0 | AM62: 0 | AN62: =AK62+AL62+AM62 -> 0 | AP62: 0 | AQ62: =AP62*T62 -> 0 | AR62: =AQ62*4 -> 0 | AS62: 0 | AT62: 0 | AU62: =AR62+AS62+AT62 -> 0
B63: 57 | C63: SOTOMAYOR ALBITES GEORGE ANTONHY | N63: DOCENTE | O63: 40583004 | P63: 992575130 | Q63: sotomayorgeo@gmail.com | R63: - | S63: - | T63: 8 | U63: - | V63: TP | W63: CONCURSO | X63: CONTRATADO | Y63: 46125 | Z63: RCU 116-2026 | AA63: 46105 | AB63: - | AC63: SEDE | AD63: - | AE63: - | AF63: ADMINISTRACION DE EMPRESAS - EEGG | AG63: MAESTRIA | AH63: - | AI63: VIRTUAL | AK63: 0 | AL63: 0 | AM63: 0 | AN63: =AK63+AL63+AM63 -> 0 | AP63: 0 | AQ63: =AP63*T63 -> 0 | AR63: =AQ63*4 -> 0 | AS63: 0 | AT63: 0 | AU63: =AR63+AS63+AT63 -> 0
... B65: 59 | C65: CHAVEZ CARRAZCO CECILIA MARCELINA | N65: DOCENTE | O65: 15428250 | P65: 953294332 | Q65: cecimarzz28@gmail.com | R65: - | S65: - | T65: 10 | U65: - | V65: TP | W65: CONCURSO | X65: CONTRATADO | Y65: 46125 | Z65: RCU 116-2026 | AA65: 46105 | AB65: - | AC65: SEDE | AD65: - | AE65: - | AF65: INGENIERIA INDUSTRIAL - EEGG | AG65: DOCTOR | AH65: - | AI65: PRESENCIAL | AK65: 0 | AL65: 0 | AM65: 0 | AN65: =AK65+AL65+AM65 -> 0 | AP65: 0 | AQ65: =AP65*T65 -> 0 | AR65: =AQ65*4 -> 0 | AS65: 0 | AT65: 0 | AU65: =AR65+AS65+AT65 -> 0
B66: 60 | C66: ACERO CARDENAS ANA MARIA | N66: DOCENTE | O66: 08689170 | P66: 991299956 | Q66: acero.am@pucp.edu.pe | R66: - | S66: - | T66: 10 | U66: - | V66: TP | W66: CONCURSO | X66: CONTRATADO | Y66: 46125 | Z66: RCU 116-2026 | AA66: 46105 | AB66: - | AC66: FILIAL | AD66: - | AE66: - | AF66: INGENIERIA INDUSTRIAL - EEGG | AG66: MAESTRIA | AH66: - | AI66: MAS PRESENCIAL | AK66: 0 | AL66: 0 | AM66: 0 | AN66: =AK66+AL66+AM66 -> 0 | AP66: 0 | AQ66: =AP66*T66 -> 0 | AR66: =AQ66*4 -> 0 | AS66: 0 | AT66: 0 | AU66: =AR66+AS66+AT66 -> 0
B67: 61 | C67: GUTIERREZ JIMENEZ CINDY FIORELLA | N67: DOCENTE | O67: 45303683 | P67: 989918045 | Q67: c.f.g.jimenez@gmail.com | R67: - | S67: - | T67: 9 | U67: - | V67: TP | W67: CONCURSO | X67: CONTRATADO | Y67: 46125 | Z67: RCU 116-2026 | AA67: 46105 | AB67: - | AC67: FILIAL | AD67: - | AE67: - | AF67: INGENIERIA CIVIL - EEGG | AG67: DOCTOR | AH67: - | AI67: VIRTUAL | AK67: 0 | AL67: 0 | AM67: 0 | AN67: =AK67+AL67+AM67 -> 0 | AP67: 0 | AQ67: =AP67*T67 -> 0 | AR67: =AQ67*4 -> 0 | AS67: 0 | AT67: 0 | AU67: =AR67+AS67+AT67 -> 0
B68: 62 | C68: OSCCO INJANTE JOSE LUIS | N68: DOCENTE | O68: 70277443 | P68: 943858181 | Q68: joseluisoscco_injante@hotmail.com | R68: - | S68: - | T68: 9 | U68: - | V68: TP | W68: CONCURSO | X68: CONTRATADO | Y68: 46125 | Z68: RCU 116-2026 | AA68: 46105 | AB68: - | AC68: FILIAL | AD68: - | AE68: - | AF68: CONTABILIDAD - EEGG | AG68: MAESTRIA | AH68: - | AI68: MAS VIRTUAL | AK68: 0 | AL68: 0 | AM68: 0 | AN68: =AK68+AL68+AM68 -> 0 | AP68: 0 | AQ68: =AP68*T68 -> 0 | AR68: =AQ68*4 -> 0 | AS68: 0 | AT68: 0 | AU68: =AR68+AS68+AT68 -> 0
B69: 63 | C69: HUAMANI CANALES ANALI MARIELLA | N69: DOCENTE | O69: 43958773 | P69: 946862930 | Q69: anali_2486@hotmail.com | R69: - | S69: - | T69: 5 | U69: - | V69: TP | W69: CONCURSO | X69: CONTRATADO | Y69: 46125 | Z69: RCU 116-2026 | AA69: 46105 | AB69: - | AC69: FILIAL | AD69: - | AE69: - | AF69: INGENIERIA CIVIL | AG69: MAESTRIA | AH69: - | AI69: PRESENCIAL | AK69: 0 | AL69: 0 | AM69: 0 | AN69: =AK69+AL69+AM69 -> 0 | AP69: 0 | AQ69: =AP69*T69 -> 0 | AR69: =AQ69*4 -> 0 | AS69: 0 | AT69: 0 | AU69: =AR69+AS69+AT69 -> 0
B70: 64 | C70: FRIAS LIAU HING MELVA | N70: DOCENTE | O70: 06708096 | P70: 952833970 | Q70: melvalejandra@hotmail.com | R70: - | S70: - | T70: 5 | U70: - | V70: TP | W70: CONCURSO | X70: CONTRATADO | Y70: 46125 | Z70: RCU 116-2026 | AA70: 46105 | AB70: - | AC70: FILIAL | AD70: - | AE70: - | AF70: INGENIERIA CIVIL | AG70: DOCTOR | AH70: - | AI70: PRESENCIAL | AK70: 0 | AL70: 0 | AM70: 0 | AN70: =AK70+AL70+AM70 -> 0 | AP70: 0 | AQ70: =AP70*T70 -> 0 | AR70: =AQ70*4 -> 0 | AS70: 0 | AT70: 0 | AU70: =AR70+AS70+AT70 -> 0
B71: 65 | C71: PASACHE LAGOS SERGIO LUIS | N71: DOCENTE | O71: 43596886 | P71: 983730610 | Q71: sergiopasache@gmail.com | R71: - | S71: - | T71: 4 | U71: - | V71: TP | W71: CONCURSO | X71: CONTRATADO | Y71: 46125 | Z71: RCU 116-2026 | AA71: 46105 | AB71: - | AC71: FILIAL | AD71: - | AE71: - | AF71: INGENIERIA CIVIL | AG71: MAESTRIA | AH71: - | AI71: PRESENCIAL | AK71: 0 | AL71: 0 | AM71: 0 | AN71: =AK71+AL71+AM71 -> 0 | AP71: 0 | AQ71: =AP71*T71 -> 0 | AR71: =AQ71*4 -> 0 | AS71: 0 | AT71: 0 | AU71: =AR71+AS71+AT71 -> 0
B72: 66 | C72: BEJARANO PEREZ JUDITH ROSSANA | N72: DOCENTE | O72: 41060828 | P72: 984399500 | Q72: judithfiq2809@gmail.com | R72: - | S72: - | T72: 15 | U72: - | V72: TP | W72: CONCURSO | X72: CONTRATADO | Y72: 46125 | Z72: RCU 116-2026 | AA72: 46105 | AB72: - | AC72: SEDE | AD72: - | AE72: - | AF72: INGENIERIA CIVIL | AG72: MAESTRIA | AH72: - | AI72: MAS PRESENCIAL | AK72: 0 | AL72: 0 | AM72: 0 | AN72: =AK72+AL72+AM72 -> 0 | AP72: 0 | AQ72: =AP72*T72 -> 0 | AR72: =AQ72*4 -> 0 | AS72: 0 | AT72: 0 | AU72: =AR72+AS72+AT72 -> 0
B73: 67 | C73: CONDORCHOA CAMACHO CARLOS JOHN | N73: DOCENTE | O73: 21447676 | P73: 956634229 | Q73: jcarlos2504@hotmail.com | R73: - | S73: - | T73: 37 | U73: - | V73: TC | W73: CONCURSO | X73: CONTRATADO | Y73: 46125 | Z73: RCU 116-2026 | AA73: 46105 | AB73: - | AC73: FILIAL | AD73: - | AE73: - | AF73: INGENIERIA CIVIL | AG73: MAESTRIA | AH73: - | AI73: MAS PRESENCIAL | AK73: 0 | AL73: 0 | AM73: 0 | AN73: =AK73+AL73+AM73 -> 0 | AP73: 0 | AQ73: =AP73*T73 -> 0 | AR73: =AQ73*4 -> 0 | AS73: 0 | AT73: 0 | AU73: =AR73+AS73+AT73 -> 0
B74: 68 | C74: JAYO HIGA JOSE JUAN | N74: DOCENTE | O74: 46078496 | P74: 991604262 | Q74: jose.jayo89@gmail.com | R74: - | S74: - | T74: 11 | U74: - | V74: TP | W74: CONCURSO | X74: CONTRATADO | Y74: 46125 | Z74: RCU 116-2026 | AA74: 46105 | AB74: - | AC74: SEDE | AD74: - | AE74: - | AF74: INGENIERIA DE SISTEMAS | AG74: MAESTRIA | AH74: - | AI74: MAS VIRTUAL | AK74: 0 | AL74: 0 | AM74: 0 | AN74: =AK74+AL74+AM74 -> 0 | AP74: 0 | AQ74: =AP74*T74 -> 0 | AR74: =AQ74*4 -> 0 | AS74: 0 | AT74: 0 | AU74: =AR74+AS74+AT74 -> 0
B75: 69 | C75: VEGA ROSALES JORGE MARTIN | N75: DOCENTE | O75: 45221222 | P75: 940193258 | Q75: jorgemartinvegar@gmail.com | R75: - | S75: - | T75: 14 | U75: - | V75: TP | W75: CONCURSO | X75: CONTRATADO | Y75: 46125 | Z75: RCU 116-2026 | AA75: 46105 | AB75: - | AC75: SEDE | AD75: - | AE75: - | AF75: INGENIERIA INDUSTRIAL | AG75: MAESTRIA | AH75: - | AI75: VIRTUAL | AK75: 0 | AL75: 0 | AM75: 0 | AN75: =AK75+AL75+AM75 -> 0 | AP75: 0 | AQ75: =AP75*T75 -> 0 | AR75: =AQ75*4 -> 0 | AS75: 0 | AT75: 0 | AU75: =AR75+AS75+AT75 -> 0
B76: 70 | C76: GUARDIA PANIURA CANDY HAYDEE | N76: DOCENTE | O76: 45023124 | P76: 916461195 | Q76: candy-guardia@hotmail.com | R76: - | S76: - | T76: 16 | U76: - | V76: TP | W76: CONCURSO | X76: CONTRATADO | Y76: 46125 | Z76: RCU 116-2026 | AA76: 46105 | AB76: - | AC76: SEDE | AD76: - | AE76: - | AF76: INGENIERIA INDUSTRIAL | AG76: MAESTRIA | AH76: - | AI76: VIRTUAL | AK76: 0 | AL76: 0 | AM76: 0 | AN76: =AK76+AL76+AM76 -> 0 | AP76: 0 | AQ76: =AP76*T76 -> 0 | AR76: =AQ76*4 -> 0 | AS76: 0 | AT76: 0 | AU76: =AR76+AS76+AT76 -> 0
B77: 71 | C77: ORDINOLA BRENIS JUAN MANUEL | N77: DOCENTE | O77: 16662940 | P77: 998008120 | Q77: jmordinola@outlook.es | R77: - | S77: - | T77: 16 | U77: - | V77: TP | W77: CONCURSO | X77: CONTRATADO | Y77: 46125 | Z77: RCU 116-2026 | AA77: 46105 | AB77: - | AC77: SEDE | AD77: - | AE77: - | AF77: INGENIERIA INDUSTRIAL | AG77: MAESTRIA | AH77: - | AI77: VIRTUAL | AK77: 0 | AL77: 0 | AM77: 0 | AN77: =AK77+AL77+AM77 -> 0 | AP77: 0 | AQ77: =AP77*T77 -> 0 | AR77: =AQ77*4 -> 0 | AS77: 0 | AT77: 0 | AU77: =AR77+AS77+AT77 -> 0
B78: 72 | C78: SANCHEZ NAVARRETE CARLOS RICARDO | N78: DOCENTE | O78: 44859703 | P78: 972717272 | Q78: ricardosnxz@gmail.com | R78: - | S78: - | T78: 11 | U78: - | V78: TP | W78: CONCURSO | X78: CONTRATADO | Y78: 46125 | Z78: RCU 116-2026 | AA78: 46105 | AB78: - | AC78: FILIAL | AD78: - | AE78: - | AF78: INGENIERIA CIVIL | AG78: MAESTRIA | AH78: - | AI78: PRESENCIAL | AK78: 0 | AL78: 0 | AM78: 0 | AN78: =AK78+AL78+AM78 -> 0 | AP78: 0 | AQ78: =AP78*T78 -> 0 | AR78: =AQ78*4 -> 0 | AS78: 0 | AT78: 0 | AU78: =AR78+AS78+AT78 -> 0
B79: 73 | C79: PESANTES SALAVARRIA MARCO ALFONSO | N79: DOCENTE | O79: 18071852 | P79: 964297579 | Q79: marcopesantes131@gmail.com | R79: - | S79: - | T79: 40 | U79: - | V79: TC | W79: CONCURSO | X79: CONTRATADO | Y79: 46125 | Z79: RCU 116-2026 | AA79: 46105 | AB79: - | AC79: SEDE | AD79: - | AE79: - | AF79: INGENIERIA INDUSTRIAL | AG79: MAESTRIA | AI79: PRESENCIAL | AK79: 0 | AL79: 0 | AM79: 0 | AN79: =AK79+AL79+AM79 -> 0 | AP79: 0 | AQ79: =AP79*T79 -> 0 | AR79: =AQ79*4 -> 0 | AS79: 0 | AT79: 0 | AU79: =AR79+AS79+AT79 -> 0
B80: 74 | C80: ALFARO CAYLLAHUA CARLOS HUGO | N80: DOCENTE | O80: 41461731 | R80: carlos.alfaro@autonomadeica.edu.pe | S80: 10 | T80: 15 | U80: TP | V80: TP | W80: RENOVACION | X80: CONTRATADO | Y80: 45769 | AB80: FILIAL | AC80: FILIAL | AD80: INGENIERIA CIVIL | AE80: MAESTRIA | AF80: INGENIERIA CIVIL | AG80: MAESTRIA | AH80: PRESENCIAL | AI80: PRESENCIAL | AK80: 0 | AL80: 0 | AM80: 0 | AN80: =AK80+AL80+AM80 -> 0 | AP80: 0 | AQ80: =AP80*T80 -> 0 | AR80: =AQ80*4 -> 0 | AS80: 0 | AT80: 0 | AU80: =AR80+AS80+AT80 -> 0
B81: 75 | C81: ALMEYDA AVALOS CESAR AUGUSTO | N81: DOCENTE | O81: 21814775 | P81: 955906921 | R81: cesar.almeyda@autonomadeica.edu.pe | S81: 30 | T81: 33 | U81: TC | V81: TC | W81: RENOVACION | X81: CONTRATADO | Y81: 41722 | AB81: FILIAL | AC81: SEDE | AD81: DERECHO | AE81: MAESTRIA | AF81: DERECHO | AG81: MAESTRIA | AH81: MAS VIRTUAL | AI81: MAS PRESENCIAL | AK81: 0 | AL81: 0 | AM81: 0 | AN81: =AK81+AL81+AM81 -> 0 | AP81: 0 | AQ81: =AP81*T81 -> 0 | AR81: =AQ81*4 -> 0 | AS81: 0 | AT81: 0 | AU81: =AR81+AS81+AT81 -> 0
B82: 76 | C82: ALMEYDA CARBAJAL JOSE ARMANDO | N82: DOCENTE | O82: 21783999 | R82: jose.almeyda@autonomadeica.edu.pe | S82: 35 | T82: 35 | U82: TC | V82: TC | W82: RENOVACION | X82: CONTRATADO | Y82: 44655 | AB82: SEDE | AC82: SEDE | AD82: INGENIERIA INDUSTRIAL - EEGG | AE82: MAESTRIA | AF82: INGENIERIA INDUSTRIAL - EEGG | AG82: MAESTRIA | AH82: PRESENCIAL | AI82: PRESENCIAL | AK82: 0 | AL82: 0 | AM82: 0 | AN82: =AK82+AL82+AM82 -> 0 | AP82: 0 | AQ82: =AP82*T82 -> 0 | AR82: =AQ82*4 -> 0 | AS82: 0 | AT82: 0 | AU82: =AR82+AS82+AT82 -> 0
B83: 77 | C83: ALMEYDA MAGALLANES JESUS NEMESIO | N83: DOCENTE | O83: 41074586 | P83: 949325972 | R83: jesus.almeyda@autonomadeica.edu.pe | S83: 17 | T83: 19 | U83: TP | V83: TP | W83: RENOVACION | X83: CONTRATADO | Y83: 44655 | AB83: SEDE | AC83: SEDE | AD83: INGENIERIA INDUSTRIAL | AE83: MAESTRIA | AF83: INGENIERIA INDUSTRIAL | AG83: MAESTRIA | AH83: PRESENCIAL | AI83: PRESENCIAL | AK83: 0 | AL83: 0 | AM83: 0 | AN83: =AK83+AL83+AM83 -> 0 | AP83: 0 | AQ83: =AP83*T83 -> 0 | AR83: =AQ83*4 -> 0 | AS83: 0 | AT83: 0 | AU83: =AR83+AS83+AT83 -> 0
B84: 78 | C84: ALMEYDA MORENO JOSE JOSE | N84: DOCENTE | O84: 45912781 | P84: 924178638 | R84: jose.moreno@autonomadeica.edu.pe | S84: 15 | T84: 37 | U84: TP | V84: TC | W84: RENOVACION | X84: CONTRATADO | Y84: 45922 | AB84: SEDE | AC84: SEDE | AD84: INGENIERIA INDUSTRIAL | AE84: MAESTRIA | AF84: ARQUITECTURA - EEGG | AG84: MAESTRIA | AH84: PRESENCIAL | AI84: PRESENCIAL | AK84: 0 | AL84: 0 | AM84: 0 | AN84: =AK84+AL84+AM84 -> 0 | AP84: 0 | AQ84: =AP84*T84 -> 0 | AR84: =AQ84*4 -> 0 | AS84: 0 | AT84: 0 | AU84: =AR84+AS84+AT84 -> 0
B85: 79 | C85: AMORETTI ARTEAGA ALEJANDRA GUADALUPE | N85: DOCENTE | O85: 43650447 | P85: 930417027 | Q85: guadalupe.amoretti@gmail.com | R85: alejandra.amoretti@autonomadeica.edu.pe | S85: 28 | T85: 35 | U85: TC | V85: TC | W85: RENOVACION | X85: CONTRATADO | Y85: 45264 | AB85: SEDE | AC85: SEDE | AD85: ADMINISTRACION Y FINANZAS | AE85: MAESTRIA | AF85: ADMINISTRACION Y FINANZAS | AG85: MAESTRIA | AH85: PRESENCIAL | AI85: MAS PRESENCIAL | AK85: 0 | AL85: 0 | AM85: 0 | AN85: =AK85+AL85+AM85 -> 0 | AP85: 0 | AQ85: =AP85*T85 -> 0 | AR85: =AQ85*4 -> 0 | AS85: 0 | AT85: 0 | AU85: =AR85+AS85+AT85 -> 0
B86: 80 | C86: ANAMPA ZAMORA SILVIA MARILU | N86: DOCENTE | O86: 45493343 | P86: 949961793 | R86: silvia.anampa@autonomadeica.edu.pe | S86: 12 | T86: 19 | U86: TP | V86: TP | W86: RENOVACION | X86: CONTRATADO | Y86: 44823 | AB86: SEDE | AC86: SEDE | AD86: INGENIERIA INDUSTRIAL | AE86: MAESTRIA | AF86: INGENIERIA INDUSTRIAL | AG86: MAESTRIA | AH86: VIRTUAL | AI86: VIRTUAL | AK86: 0 | AL86: 0 | AM86: 0 | AN86: =AK86+AL86+AM86 -> 0 | AP86: 0 | AQ86: =AP86*T86 -> 0 | AR86: =AQ86*4 -> 0 | AS86: 0 | AT86: 0 | AU86: =AR86+AS86+AT86 -> 0
B87: 81 | C87: ANDRADE GONZALES VICTOR MANUEL | N87: DOCENTE | O87: 71431209 | S87: 16 | T87: 10 | U87: TP | V87: TP | W87: RENOVACION | X87: CONTRATADO | Y87: 45769 | AB87: SEDE | AC87: SEDE | AD87: DERECHO - EEGG | AE87: MAESTRIA | AF87: DERECHO - EEGG | AG87: MAESTRIA | AH87: MAS PRESENCIAL | AI87: MAS PRESENCIAL | AK87: 0 | AL87: 0 | AM87: 0 | AN87: =AK87+AL87+AM87 -> 0 | AP87: 0 | AQ87: =AP87*T87 -> 0 | AR87: =AQ87*4 -> 0 | AS87: 0 | AT87: 0 | AU87: =AR87+AS87+AT87 -> 0
B88: 82 | C88: ANICAMA NAVARRETE EVELYN ALINA | N88: DOCENTE | O88: 44435992 | P88: 952210640 | R88: evelyn.anicama@autonomadeica.edu.pe | T88: 14 | V88: TP | AC88: SEDE | AF88: INGENIERIA INDUSTRIAL | AG88: DOCTOR | AI88: VIRTUAL | AK88: 0 | AL88: 0 | AM88: 0 | AN88: =AK88+AL88+AM88 -> 0 | AP88: 0 | AQ88: =AP88*T88 -> 0 | AR88: =AQ88*4 -> 0 | AS88: 0 | AT88: 0 | AU88: =AR88+AS88+AT88 -> 0
B89: 83 | C89: ANICAMA QUISIVERDE GERALDINE ISABEL | N89: DOCENTE | O89: 45879356 | P89: 949449706 | R89: geraldine.anicama@autonomadeica.edu.pe | T89: 39 | V89: TC | AC89: SEDE | AF89: INGENIERIA DE SISTEMAS | AG89: MAESTRIA | AI89: PRESENCIAL | AK89: 0 | AL89: 0 | AM89: 0 | AN89: =AK89+AL89+AM89 -> 0 | AP89: 0 | AQ89: =AP89*T89 -> 0 | AR89: =AQ89*4 -> 0 | AS89: 0 | AT89: 0 | AU89: =AR89+AS89+AT89 -> 0
B90: 84 | C90: ARIAS LOPEZ SILVIA LUISA | N90: DOCENTE | O90: 21865174 | P90: 941555202 | R90: silvia.arias@autonomadeica.edu.pe | T90: 32 | V90: TC | AC90: SEDE | AF90: INGENIERIA DE SISTEMAS | AG90: MAESTRIA | AI90: MAS VIRTUAL | AK90: 0 | AL90: 0 | AM90: 0 | AN90: =AK90+AL90+AM90 -> 0 | AP90: 0 | AQ90: =AP90*T90 -> 0 | AR90: =AQ90*4 -> 0 | AS90: 0 | AT90: 0 | AU90: =AR90+AS90+AT90 -> 0
B91: 85 | C91: AYLLON CARDENAS MARIELA LISSETH | N91: DOCENTE | O91: 44933501 | P91: 934959263 | Q91: maylloncr@gmail.com | R91: mariela.ayllon@autonomadeica.edu.pe | T91: 15 | V91: TP | AC91: SEDE | AF91: ADMINISTRACION Y FINANZAS | AG91: MAESTRIA | AI91: VIRTUAL
B92: 86 | C92: BALBUENA CARRASCO LUIS ANTONIO | N92: DOCENTE | O92: 41973116 | R92: luis.balbuena@autonomadeica.edu.pe | T92: 8 | V92: TP | AC92: SEDE | AF92: DERECHO | AG92: MAESTRIA | AI92: VIRTUAL | AK92: 0 | AL92: 0 | AM92: 0 | AN92: =AK92+AL92+AM92 -> 0 | AP92: 0 | AQ92: =AP92*T92 -> 0 | AR92: =AQ92*4 -> 0 | AS92: 0 | AT92: 0 | AU92: =AR92+AS92+AT92 -> 0
B93: 87 | C93: BARRERA SIGUAS EDGAR DANIEL | N93: DOCENTE | O93: 21884864 | T93: 15 | V93: TP | AC93: SEDE | AF93: INGENIERIA INDUSTRIAL - EEGG | AG93: DOCTOR | AI93: PRESENCIAL | AK93: 0 | AL93: 0 | AM93: 0 | AN93: =AK93+AL93+AM93 -> 0 | AP93: 0 | AQ93: =AP93*T93 -> 0 | AR93: =AQ93*4 -> 0 | AS93: 0 | AT93: 0 | AU93: =AR93+AS93+AT93 -> 0
B94: 88 | C94: BARTRA BAUTISTA MADELEINE KARIN | N94: DOCENTE | O94: 40978490 | T94: 16 | V94: TP | AC94: FILIAL | AF94: DERECHO | AG94: MAESTRIA | AI94: PRESENCIAL | AK94: 0 | AL94: 0 | AM94: 0 | AN94: =AK94+AL94+AM94 -> 0 | AP94: 0 | AQ94: =AP94*T94 -> 0 | AR94: =AQ94*4 -> 0 | AS94: 0 | AT94: 0 | AU94: =AR94+AS94+AT94 -> 0
B95: 89 | C95: BECERRA GUTIERREZ ETHEEL ROMILA | N95: DOCENTE | O95: 07253926 | T95: 18 | V95: TP | AC95: SEDE | AF95: ARQUITECTURA - EEGG | AG95: DOCTOR | AI95: MAS PRESENCIAL | AK95: 0 | AL95: 0 | AM95: 0 | AN95: =AK95+AL95+AM95 -> 0 | AP95: 0 | AQ95: =AP95*T95 -> 0 | AR95: =AQ95*4 -> 0 | AS95: 0 | AT95: 0 | AU95: =AR95+AS95+AT95 -> 0
B96: 90 | C96: BENAVIDES MIKKELSEN JORGE LUIS | N96: DOCENTE | O96: 08222581 | P96: 998248120 | R96: jorge.benavides@autonomadeica.edu.pe | T96: 15 | V96: TP | AC96: SEDE | AF96: INGENIERIA INDUSTRIAL | AG96: MAESTRIA | AI96: PRESENCIAL | AK96: 0 | AL96: 0 | AM96: 0 | AN96: =AK96+AL96+AM96 -> 0 | AP96: 0 | AQ96: =AP96*T96 -> 0 | AR96: =AQ96*4 -> 0 | AS96: 0 | AT96: 0 | AU96: =AR96+AS96+AT96 -> 0
B97: 91 | C97: BENDEZU HERNANDEZ JAVIER ORLANDO | N97: DOCENTE | O97: 40012522 | T97: 10 | V97: TP | AC97: SEDE | AF97: INGENIERIA INDUSTRIAL | AG97: MAESTRIA | AI97: PRESENCIAL | AK97: 0 | AL97: 0 | AM97: 0 | AN97: =AK97+AL97+AM97 -> 0 | AP97: 0 | AQ97: =AP97*T97 -> 0 | AR97: =AQ97*4 -> 0 | AS97: 0 | AT97: 0 | AU97: =AR97+AS97+AT97 -> 0
B98: 92 | C98: BRAVO SENDER RAUL ANTONIO | N98: DOCENTE | O98: 43133448 | T98: 14 | V98: TP | AC98: FILIAL | AF98: DERECHO | AG98: MAESTRIA | AI98: MAS PRESENCIAL | AK98: 0 | AL98: 0 | AM98: 0 | AN98: =AK98+AL98+AM98 -> 0 | AP98: 0 | AQ98: =AP98*T98 -> 0 | AR98: =AQ98*4 -> 0 | AS98: 0 | AT98: 0 | AU98: =AR98+AS98+AT98 -> 0
B99: 93 | C99: BUENDIA APARCANA ROBERTO REYMUNDO | N99: DOCENTE | O99: 21576727 | P99: 956927698 | Q99: rrbuendia@hotmail.com | R99: roberto.buendia@autonomadeica.edu.pe | T99: 12 | V99: TP | AC99: SEDE | AF99: ADMINISTRACION Y FINANZAS | AG99: DOCTOR | AI99: VIRTUAL | AK99: 0 | AL99: 0 | AM99: 0 | AN99: =AK99+AL99+AM99 -> 0 | AP99: 0 | AQ99: =AP99*T99 -> 0 | AR99: =AQ99*4 -> 0 | AS99: 0 | AT99: 0 | AU99: =AR99+AS99+AT99 -> 0
B100: 94 | C100: BUSTAMANTE MATEO MARIA YSABEL | N100: DOCENTE | O100: 21854029 | P100: 975512116 | R100: maria.bustamante@autonomadeica.edu.pe | T100: 16 | V100: TP | AC100: SEDE | AF100: INGENIERIA INDUSTRIAL | AG100: MAESTRIA | AI100: MAS VIRTUAL | AK100: 0 | AL100: 0 | AM100: 0 | AN100: =AK100+AL100+AM100 -> 0 | AP100: 0 | AQ100: =AP100*T100 -> 0 | AR100: =AQ100*4 -> 0 | AS100: 0 | AT100: 0 | AU100: =AR100+AS100+AT100 -> 0
B101: 95 | C101: CABRERA HUAMAN GISELLA ROSA | N101: DOCENTE | O101: 21505996 | T101: 14 | V101: TP | AC101: SEDE | AF101: DERECHO - EEGG | AG101: MAESTRIA | AI101: VIRTUAL | AK101: 0 | AL101: 0 | AM101: 0 | AN101: =AK101+AL101+AM101 -> 0 | AP101: 0 | AQ101: =AP101*T101 -> 0 | AR101: =AQ101*4 -> 0 | AS101: 0 | AT101: 0 | AU101: =AR101+AS101+AT101 -> 0
B102: 96 | C102: CABRERA ZEGOVIA YESSICA JEANETH | N102: DOCENTE | O102: 44296086 | T102: 12 | V102: TP | AC102: SEDE | AF102: DERECHO | AG102: MAESTRIA | AI102: VIRTUAL | AK102: 0 | AL102: 0 | AM102: 0 | AN102: =AK102+AL102+AM102 -> 0 | AP102: 0 | AQ102: =AP102*T102 -> 0 | AR102: =AQ102*4 -> 0 | AS102: 0 | AT102: 0 | AU102: =AR102+AS102+AT102 -> 0
B103: 97 | C103: CACHO RIOS LUIS ANTONIO | N103: DOCENTE | O103: 44579560 | T103: 35 | V103: TC | AC103: FILIAL | AF103: DERECHO | AG103: MAESTRIA | AI103: VIRTUAL | AK103: 0 | AL103: 0 | AM103: 0 | AN103: =AK103+AL103+AM103 -> 0 | AP103: 0 | AQ103: =AP103*T103 -> 0 | AR103: =AQ103*4 -> 0 | AS103: 0 | AT103: 0 | AU103: =AR103+AS103+AT103 -> 0
...

Sheet %D
B4: HUAURA
C5: ADMINISTRACION DE EMPRESAS | D5: DERECHO | E5: TOTAL | F5: %
B6: TC | C6: =+SUM(COUNTIFS(OGTH!$AC:$AC,$B4,OGTH!$AF:$AF,"ADMINISTRACION DE EMPRESAS",OGTH!$V:$V,"TC"),COUNTIFS(OGTH!$AC:$AC,$B4,OGTH!$AF:$AF,"ADMINISTRACION DE EMPRESAS - EEGG",OGTH!$V:$V,"TC")) -> 0 | D6: =+SUM(COUNTIFS(OGTH!$AC:$AC,$B4,OGTH!$AF:$AF,"DERECHO",OGTH!$V:$V,"TC"),COUNTIFS(OGTH!$AC:$AC,$B4,OGTH!$AF:$AF,"DERECHO - EEGG",OGTH!$V:$V,"TC")) -> 2 | E6: =+SUM(C6:D6) -> 2 | F6: =+E6/E8 -> 0.066666667
B7: TP | C7: =+SUM(COUNTIFS(OGTH!$AC:$AC,$B4,OGTH!$AF:$AF,"ADMINISTRACION DE EMPRESAS",OGTH!$V:$V,"TP"),COUNTIFS(OGTH!$AC:$AC,$B4,OGTH!$AF:$AF,"ADMINISTRACION DE EMPRESAS - EEGG",OGTH!$V:$V,"TP")) -> 11 | D7: =+SUM(COUNTIFS(OGTH!$AC:$AC,$B4,OGTH!$AF:$AF,"DERECHO",OGTH!$V:$V,"TP"),COUNTIFS(OGTH!$AC:$AC,$B4,OGTH!$AF:$AF,"DERECHO - EEGG",OGTH!$V:$V,"TP")) -> 17 | E7: =+SUM(C7:D7) -> 28 | F7: =+E7/E8 -> 0.93333333
B8: TOTAL | C8: =+C6+C7 -> 11 | D8: =+D6+D7 -> 19 | E8: =+E6+E7 -> 30 | F8: =+F6+F7 -> 1
B9: %TC | C9: =+C6/C8 -> 0 | D9: =+D6/D8 -> 0.10526316
B10: %TP | C10: =+C7/C8 -> 1 | D10: =+D7/D8 -> 0.89473684
B11: % | C11: =+C9+C10 -> 1 | D11: =+D9+D10 -> 1
B14: FILIAL
C15: ADMINISTRACION DE EMPRESAS | D15: ADMINISTRACION Y FINANZAS | E15: INGENIERIA INDUSTRIAL | F15: CONTABILIDAD | G15: DERECHO | H15: INGENIERIA CIVIL | I15: TOTAL | J15: %
B16: TC | C16: =+SUM(COUNTIFS(OGTH!$AC:$AC,$B14,OGTH!$AF:$AF,"ADMINISTRACION DE EMPRESAS",OGTH!$V:$V,"TC"),COUNTIFS(OGTH!$AC:$AC,$B14,OGTH!$AF:$AF,"ADMINISTRACION DE EMPRESAS - EEGG",OGTH!$V:$V,"TC")) -> 0 | D16: =+SUM(COUNTIFS(OGTH!$AC:$AC,$B14,OGTH!$AF:$AF,"ADMINISTRACION Y FINANZAS",OGTH!$V:$V,"TC"),COUNTIFS(OGTH!$AC:$AC,$B14,OGTH!$AF:$AF,"ADMINISTRACION Y FINANZAS - EEGG",OGTH!$V:$V,"TC")) -> 0 | E16: =+SUM(COUNTIFS(OGTH!$AC:$AC,$B14,OGTH!$AF:$AF,"INGENIERIA INDUSTRIAL",OGTH!$V:$V,"TC"),COUNTIFS(OGTH!$AC:$AC,$B14,OGTH!$AF:$AF,"INGENIERIA INDUSTRIAL - EEGG",OGTH!$V:$V,"TC")) -> 0 | F16: =+SUM(COUNTIFS(OGTH!$AC:$AC,$B14,OGTH!$AF:$AF,"CONTABILIDAD",OGTH!$V:$V,"TC"),COUNTIFS(OGTH!$AC:$AC,$B14,OGTH!$AF:$AF,"CONTABILIDAD - EEGG",OGTH!$V:$V,"TC")) -> 0 | G16: =+SUM(COUNTIFS(OGTH!$AC:$AC,$B14,OGTH!$AF:$AF,"DERECHO",OGTH!$V:$V,"TC"),COUNTIFS(OGTH!$AC:$AC,$B14,OGTH!$AF:$AF,"DERECHO - EEGG",OGTH!$V:$V,"TC")) -> 3 | H16: =+SUM(COUNTIFS(OGTH!$AC:$AC,$B14,OGTH!$AF:$AF,"INGENIERIA CIVIL",OGTH!$V:$V,"TC"),COUNTIFS(OGTH!$AC:$AC,$B14,OGTH!$AF:$AF,"INGENIERIA CIVIL - EEGG",OGTH!$V:$V,"TC")) -> 2 | I16: =+SUM(C16:H16) -> 5 | J16: =+I16/I18 -> 0.12820513
B17: TP | C17: =+SUM(COUNTIFS(OGTH!$AC:$AC,$B14,OGTH!$AF:$AF,"ADMINISTRACION DE EMPRESAS",OGTH!$V:$V,"TP"),COUNTIFS(OGTH!$AC:$AC,$B14,OGTH!$AF:$AF,"ADMINISTRACION DE EMPRESAS - EEGG",OGTH!$V:$V,"TP")) -> 0 | D17: =+SUM(COUNTIFS(OGTH!$AC:$AC,$B14,OGTH!$AF:$AF,"ADMINISTRACION Y FINANZAS",OGTH!$V:$V,"TP"),COUNTIFS(OGTH!$AC:$AC,$B14,OGTH!$AF:$AF,"ADMINISTRACION Y FINANZAS - EEGG",OGTH!$V:$V,"TP")) -> 2 | E17: =+SUM(COUNTIFS(OGTH!$AC:$AC,$B14,OGTH!$AF:$AF,"INGENIERIA INDUSTRIAL",OGTH!$V:$V,"TP"),COUNTIFS(OGTH!$AC:$AC,$B14,OGTH!$AF:$AF,"INGENIERIA INDUSTRIAL - EEGG",OGTH!$V:$V,"TP")) -> 2 | F17: =+SUM(COUNTIFS(OGTH!$AC:$AC,$B14,OGTH!$AF:$AF,"CONTABILIDAD",OGTH!$V:$V,"TP"),COUNTIFS(OGTH!$AC:$AC,$B14,OGTH!$AF:$AF,"CONTABILIDAD - EEGG",OGTH!$V:$V,"TP")) -> 6 | G17: =+SUM(COUNTIFS(OGTH!$AC:$AC,$B14,OGTH!$AF:$AF,"DERECHO",OGTH!$V:$V,"TP"),COUNTIFS(OGTH!$AC:$AC,$B14,OGTH!$AF:$AF,"DERECHO - EEGG",OGTH!$V:$V,"TP")) -> 15 | H17: =+SUM(COUNTIFS(OGTH!$AC:$AC,$B14,OGTH!$AF:$AF,"INGENIERIA CIVIL",OGTH!$V:$V,"TP"),COUNTIFS(OGTH!$AC:$AC,$B14,OGTH!$AF:$AF,"INGENIERIA CIVIL - EEGG",OGTH!$V:$V,"TP")) -> 9 | I17: =+SUM(C17:H17) -> 34 | J17: =+I17/I18 -> 0.87179487
B18: TOTAL | C18: =+C16+C17 -> 0 | D18: =+D16+D17 -> 2 | E18: =+E16+E17 -> 2 | F18: =+F16+F17 -> 6 | G18: =+G16+G17 -> 18 | H18: =+H16+H17 -> 11 | I18: =+I16+I17 -> 39 | J18: =+J16+J17 -> 1
B19: %TC | C19: =+C16/C18 -> #DIV/0! | D19: =+D16/D18 -> 0 | E19: =+E16/E18 -> 0 | F19: =+F16/F18 -> 0 | G19: =+G16/G18 -> 0.16666667 | H19: =+H16/H18 -> 0.18181818
B20: %TP | C20: =+C17/C18 -> #DIV/0! | D20: =+D17/D18 -> 1 | E20: =+E17/E18 -> 1 | F20: =+F17/F18 -> 1 | G20: =+G17/G18 -> 0.83333333 | H20: =+H17/H18 -> 0.81818182
B21: % | C21: =+C19+C20 -> #DIV/0! | D21: =+D19+D20 -> 1 | E21: =+E19+E20 -> 1 | F21: =+F19+F20 -> 1 | G21: =+G19+G20 -> 1 | H21: =+H19+H20 -> 1
B24: SEDE
C25: ADMINISTRACION DE EMPRESAS | D25: ADMINISTRACION Y FINANZAS | E25: INGENIERIA DE SISTEMAS | F25: INGENIERIA INDUSTRIAL | G25: DERECHO | H25: INGENIERIA CIVIL | I25: ARQUITECTURA | J25: TOTAL | K25: %
B26: TC | C26: =+SUM(COUNTIFS(OGTH!$AC:$AC,$B24,OGTH!$AF:$AF,"ADMINISTRACION DE EMPRESAS",OGTH!$V:$V,"TC"),COUNTIFS(OGTH!$AC:$AC,$B24,OGTH!$AF:$AF,"ADMINISTRACION DE EMPRESAS - EEGG",OGTH!$V:$V,"TC")) -> 1 | D26: =+SUM(COUNTIFS(OGTH!$AC:$AC,$B24,OGTH!$AF:$AF,"ADMINISTRACION Y FINANZAS",OGTH!$V:$V,"TC"),COUNTIFS(OGTH!$AC:$AC,$B24,OGTH!$AF:$AF,"ADMINISTRACION Y FINANZAS - EEGG",OGTH!$V:$V,"TC")) -> 3 | E26: =+SUM(COUNTIFS(OGTH!$AC:$AC,$B24,OGTH!$AF:$AF,"INGENIERIA DE SISTEMAS",OGTH!$V:$V,"TC"),COUNTIFS(OGTH!$AC:$AC,$B24,OGTH!$AF:$AF,"INGENIERIA DE SISTEMAS - EEGG",OGTH!$V:$V,"TC")) -> 4 | F26: =+SUM(COUNTIFS(OGTH!$AC:$AC,$B24,OGTH!$AF:$AF,"INGENIERIA INDUSTRIAL",OGTH!$V:$V,"TC"),COUNTIFS(OGTH!$AC:$AC,$B24,OGTH!$AF:$AF,"INGENIERIA INDUSTRIAL - EEGG",OGTH!$V:$V,"TC")) -> 8 | G26: =+SUM(COUNTIFS(OGTH!$AC:$AC,$B24,OGTH!$AF:$AF,"DERECHO",OGTH!$V:$V,"TC"),COUNTIFS(OGTH!$AC:$AC,$B24,OGTH!$AF:$AF,"DERECHO - EEGG",OGTH!$V:$V,"TC")) -> 3 | H26: =+SUM(COUNTIFS(OGTH!$AC:$AC,$B24,OGTH!$AF:$AF,"INGENIERIA CIVIL",OGTH!$V:$V,"TC"),COUNTIFS(OGTH!$AC:$AC,$B24,OGTH!$AF:$AF,"INGENIERIA CIVIL - EEGG",OGTH!$V:$V,"TC")) -> 2 | I26: =+SUM(COUNTIFS(OGTH!$AC:$AC,$B24,OGTH!$AF:$AF,"ARQUITECTURA",OGTH!$V:$V,"TC"),COUNTIFS(OGTH!$AC:$AC,$B24,OGTH!$AF:$AF,"ARQUITECTURA - EEGG",OGTH!$V:$V,"TC")) -> 1 | J26: =+SUM(C26:I26) -> 22 | K26: =+J26/J28 -> 0.2244898
B27: TP | C27: =+SUM(COUNTIFS(OGTH!$AC:$AC,$B24,OGTH!$AF:$AF,"ADMINISTRACION DE EMPRESAS",OGTH!$V:$V,"TP"),COUNTIFS(OGTH!$AC:$AC,$B24,OGTH!$AF:$AF,"ADMINISTRACION DE EMPRESAS - EEGG",OGTH!$V:$V,"TP")) -> 7 | D27: =+SUM(COUNTIFS(OGTH!$AC:$AC,$B24,OGTH!$AF:$AF,"ADMINISTRACION Y FINANZAS",OGTH!$V:$V,"TP"),COUNTIFS(OGTH!$AC:$AC,$B24,OGTH!$AF:$AF,"ADMINISTRACION Y FINANZAS - EEGG",OGTH!$V:$V,"TP")) -> 11 | E27: =+SUM(COUNTIFS(OGTH!$AC:$AC,$B24,OGTH!$AF:$AF,"INGENIERIA DE SISTEMAS",OGTH!$V:$V,"TP"),COUNTIFS(OGTH!$AC:$AC,$B24,OGTH!$AF:$AF,"INGENIERIA DE SISTEMAS - EEGG",OGTH!$V:$V,"TP")) -> 12 | F27: =+SUM(COUNTIFS(OGTH!$AC:$AC,$B24,OGTH!$AF:$AF,"INGENIERIA INDUSTRIAL",OGTH!$V:$V,"TP"),COUNTIFS(OGTH!$AC:$AC,$B24,OGTH!$AF:$AF,"INGENIERIA INDUSTRIAL - EEGG",OGTH!$V:$V,"TP")) -> 27 | G27: =+SUM(COUNTIFS(OGTH!$AC:$AC,$B24,OGTH!$AF:$AF,"DERECHO",OGTH!$V:$V,"TP"),COUNTIFS(OGTH!$AC:$AC,$B24,OGTH!$AF:$AF,"DERECHO - EEGG",OGTH!$V:$V,"TP")) -> 11 | H27: =+SUM(COUNTIFS(OGTH!$AC:$AC,$B24,OGTH!$AF:$AF,"INGENIERIA CIVIL",OGTH!$V:$V,"TP"),COUNTIFS(OGTH!$AC:$AC,$B24,OGTH!$AF:$AF,"INGENIERIA CIVIL - EEGG",OGTH!$V:$V,"TP")) -> 5 | I27: =+SUM(COUNTIFS(OGTH!$AC:$AC,$B24,OGTH!$AF:$AF,"ARQUITECTURA",OGTH!$V:$V,"TP"),COUNTIFS(OGTH!$AC:$AC,$B24,OGTH!$AF:$AF,"ARQUITECTURA - EEGG",OGTH!$V:$V,"TP")) -> 3 | J27: =+SUM(C27:I27) -> 76 | K27: =+J27/J28 -> 0.7755102
B28: TOTAL | C28: =+C26+C27 -> 8 | D28: =+D26+D27 -> 14 | E28: =+E26+E27 -> 16 | F28: =+F26+F27 -> 35 | G28: =+G26+G27 -> 14 | H28: =+H26+H27 -> 7 | I28: =+I26+I27 -> 4 | J28: =+J26+J27 -> 98 | K28: =+K26+K27 -> 1
B29: %TC | C29: =+C26/C28 -> 0.125 | D29: =+D26/D28 -> 0.21428571 | E29: =+E26/E28 -> 0.25 | F29: =+F26/F28 -> 0.22857143 | G29: =+G26/G28 -> 0.21428571 | H29: =+H26/H28 -> 0.28571429 | I29: =+I26/I28 -> 0.25
B30: %TP | C30: =+C27/C28 -> 0.875 | D30: =+D27/D28 -> 0.78571429 | E30: =+E27/E28 -> 0.75 | F30: =+F27/F28 -> 0.77142857 | G30: =+G27/G28 -> 0.78571429 | H30: =+H27/H28 -> 0.71428571 | I30: =+I27/I28 -> 0.75
B31: % | C31: =+C29+C30 -> 1 | D31: =+D29+D30 -> 1 | E31: =+E29+E30 -> 1 | F31: =+F29+F30 -> 1 | G31: =+G29+G30 -> 1 | H31: =+H29+H30 -> 1 | I31: =+I29+I30 -> 1
B34: CONSOLIDADO
C35: ADMINISTRACION DE EMPRESAS | D35: ADMINISTRACION Y FINANZAS | E35: INGENIERIA DE SISTEMAS | F35: INGENIERIA INDUSTRIAL | G35: CONTABILIDAD | H35: DERECHO | I35: INGENIERIA CIVIL | J35: ARQUITECTURA | K35: TOTAL | L35: %
B36: TC | C36: =+SUM(COUNTIFS(OGTH!$AF:$AF,"ADMINISTRACION DE EMPRESAS",OGTH!$V:$V,"TC"),COUNTIFS(OGTH!$AF:$AF,"ADMINISTRACION DE EMPRESAS - EEGG",OGTH!$V:$V,"TC")) -> 1 | D36: =+SUM(COUNTIFS(OGTH!$AF:$AF,"ADMINISTRACION Y FINANZAS",OGTH!$V:$V,"TC"),COUNTIFS(OGTH!$AF:$AF,"ADMINISTRACION Y FINANZAS - EEGG",OGTH!$V:$V,"TC")) -> 3 | E36: =+SUM(COUNTIFS(OGTH!$AF:$AF,"INGENIERIA DE SISTEMAS",OGTH!$V:$V,"TC"),COUNTIFS(OGTH!$AF:$AF,"INGENIERIA DE SISTEMAS - EEGG",OGTH!$V:$V,"TC")) -> 4 | F36: =+SUM(COUNTIFS(OGTH!$AF:$AF,"INGENIERIA INDUSTRIAL",OGTH!$V:$V,"TC"),COUNTIFS(OGTH!$AF:$AF,"INGENIERIA INDUSTRIAL - EEGG",OGTH!$V:$V,"TC")) -> 8 | G36: =+SUM(COUNTIFS(OGTH!$AF:$AF,"CONTABILIDAD",OGTH!$V:$V,"TC"),COUNTIFS(OGTH!$AF:$AF,"CONTABILIDAD - EEGG",OGTH!$V:$V,"TC")) -> 0 | H36: =+SUM(COUNTIFS(OGTH!$AF:$AF,"DERECHO",OGTH!$V:$V,"TC"),COUNTIFS(OGTH!$AF:$AF,"DERECHO - EEGG",OGTH!$V:$V,"TC")) -> 8 | I36: =+SUM(COUNTIFS(OGTH!$AF:$AF,"INGENIERIA CIVIL",OGTH!$V:$V,"TC"),COUNTIFS(OGTH!$AF:$AF,"INGENIERIA CIVIL - EEGG",OGTH!$V:$V,"TC")) -> 4 | J36: =+SUM(COUNTIFS(OGTH!$AF:$AF,"ARQUITECTURA",OGTH!$V:$V,"TC"),COUNTIFS(OGTH!$AF:$AF,"ARQUITECTURA - EEGG",OGTH!$V:$V,"TC")) -> 1 | K36: =+SUM(C36:J36) -> 29 | L36: =+K36/K38 -> 0.17365269
B37: TP | C37: =+SUM(COUNTIFS(OGTH!$AF:$AF,"ADMINISTRACION DE EMPRESAS",OGTH!$V:$V,"TP"),COUNTIFS(OGTH!$AF:$AF,"ADMINISTRACION DE EMPRESAS - EEGG",OGTH!$V:$V,"TP")) -> 18 | D37: =+SUM(COUNTIFS(OGTH!$AF:$AF,"ADMINISTRACION Y FINANZAS",OGTH!$V:$V,"TP"),COUNTIFS(OGTH!$AF:$AF,"ADMINISTRACION Y FINANZAS - EEGG",OGTH!$V:$V,"TP")) -> 13 | E37: =+SUM(COUNTIFS(OGTH!$AF:$AF,"INGENIERIA DE SISTEMAS",OGTH!$V:$V,"TP"),COUNTIFS(OGTH!$AF:$AF,"INGENIERIA DE SISTEMAS - EEGG",OGTH!$V:$V,"TP")) -> 12 | F37: =+SUM(COUNTIFS(OGTH!$AF:$AF,"INGENIERIA INDUSTRIAL",OGTH!$V:$V,"TP"),COUNTIFS(OGTH!$AF:$AF,"INGENIERIA INDUSTRIAL - EEGG",OGTH!$V:$V,"TP")) -> 29 | G37: =+SUM(COUNTIFS(OGTH!$AF:$AF,"CONTABILIDAD",OGTH!$V:$V,"TP"),COUNTIFS(OGTH!$AF:$AF,"CONTABILIDAD - EEGG",OGTH!$V:$V,"TP")) -> 6 | H37: =+SUM(COUNTIFS(OGTH!$AF:$AF,"DERECHO",OGTH!$V:$V,"TP"),COUNTIFS(OGTH!$AF:$AF,"DERECHO - EEGG",OGTH!$V:$V,"TP")) -> 43 | I37: =+SUM(COUNTIFS(OGTH!$AF:$AF,"INGENIERIA CIVIL",OGTH!$V:$V,"TP"),COUNTIFS(OGTH!$AF:$AF,"INGENIERIA CIVIL - EEGG",OGTH!$V:$V,"TP")) -> 14 | J37: =+SUM(COUNTIFS(OGTH!$AF:$AF,"ARQUITECTURA",OGTH!$V:$V,"TP"),COUNTIFS(OGTH!$AF:$AF,"ARQUITECTURA - EEGG",OGTH!$V:$V,"TP")) -> 3 | K37: =+SUM(C37:J37) -> 138 | L37: =+K37/K38 -> 0.82634731
B38: TOTAL | C38: =+C36+C37 -> 19 | D38: =+D36+D37 -> 16 | E38: =+E36+E37 -> 16 | F38: =+F36+F37 -> 37 | G38: =+G36+G37 -> 6 | H38: =+H36+H37 -> 51 | I38: =+I36+I37 -> 18 | J38: =+J36+J37 -> 4 | ... L38: =+L36+L37 -> 1
B39: %TC | C39: =+C36/C38 -> 0.052631579 | D39: =+D36/D38 -> 0.1875 | E39: =+E36/E38 -> 0.25 | F39: =+F36/F38 -> 0.21621622 | G39: =+G36/G38 -> 0 | H39: =+H36/H38 -> 0.15686275 | I39: =+I36/I38 -> 0.22222222 | J39: =+J36/J38 -> 0.25
B40: %TP | C40: =+C37/C38 -> 0.94736842 | D40: =+D37/D38 -> 0.8125 | E40: =+E37/E38 -> 0.75 | F40: =+F37/F38 -> 0.78378378 | G40: =+G37/G38 -> 1 | H40: =+H37/H38 -> 0.84313725 | I40: =+I37/I38 -> 0.77777778 | J40: =+J37/J38 -> 0.75
B41: % | C41: =+C39+C40 -> 1 | D41: =+D39+D40 -> 1 | E41: =+E39+E40 -> 1 | F41: =+F39+F40 -> 1 | G41: =+G39+G40 -> 1 | H41: =+H39+H40 -> 1 | I41: =+I39+I40 -> 1 | J41: =+J39+J40 -> 1
C44: TOTAL | D44: %
B45: TC | C45: =+E6+I16+J26 -> 29 | D45: =+C45/C47 -> 0.17365269
B46: TP | C46: =+E7+I17+J27 -> 138 | D46: =+C46/C47 -> 0.82634731
B47: TOTAL | C47: =+C45+C46 -> 167 | D47: =+D45+D46 -> 1

Sheet RENOVACIÓN TC Contrat anticipad
B6: PROPUESTA DE RENOVACIÓN ANTICIPADA DE DOCENTES DE TIEMPO COMPLETO PARA SEMESTRE ACADÉMICO 2026-1
I8: FECHAS, HORARIOS Y ACTIVIDADES ADMINISTRATIVAS HASTA EL XXXXXXX
B9: N° | C9: DNI | D9: APELLIDOS Y NOMBRES | E9: FACULTAD | F9: ESCUELA PROFESIONAL | G9: LOCAL | H9: MODALIDAD | I9: FECHAS (23 al 27 de Marzo) | J9: DÍAS Y HORARIOS (48 horas/semana) | K9: ACTIVIDADES ESPECÍFICAS A DESARROLLAR
B10: 2
B11: 3
B12: 4
B13: 5
B14: 6
B15: 7
B16: 8
B17: 9
B18: 10
B19: 11
B20: 12
B21: 13
... B58: 50
