Workbook

Sheet Planes y aulas 2026
B2: RESUMEN PLANIFICACIÓN X CICLOS Y SECCIONES 2025-1 | K2: RESUMEN PLANIFICACIÓN X CICLOS Y SECCIONES 2025-2 | T2: RESUMEN PLANIFICACIÓN X CICLOS Y SECCIONES 2026-1
B4: SEMESTRE | C4: PLAN DE ESTUDIOS | D4: CODIGO DE PLAN | E4: LOCAL | F4: COD FACU | G4: PROGRAMA ACADÉMICO | H4: CICLO | I4: SECCIÓN | K4: SEMESTRE | L4: PLAN DE ESTUDIOS | M4: CODIGO DE PLAN | N4: LOCAL | O4: COD FACU | P4: PROGRAMA ACADÉMICO | Q4: CICLO | R4: SECCIÓN | T4: SEMESTRE | U4: PLAN DE ESTUDIOS | V4: CODIGO DE PLAN | W4: LOCAL | X4: COD FACU | Y4: PROGRAMA ACADÉMICO | Z4: CICLO | AA4: SECCIÓN
B5: 2025-1 | C5: RCU N° 344-2024-UAI-CU/P | D5: 20242 | E5: FILIAL | F5: I | G5: AF | H5: 3 | I5: A | K5: 2025-2 | L5: RCU Nº 354-2024-UAI-CU/P | M5: 20242 | N5: HUAURA | O5: FICA | P5: AE | Q5: 2 | R5: A
B6: 2025-1 | C6: RCU N° 249-2019-UAI-CU/P | D6: 202011 | E6: FILIAL | F6: I | G6: AF | H6: 6 | I6: A | K6: 2025-2 | L6: RCU Nº 354-2024-UAI-CU/P | M6: 20242 | N6: HUAURA | O6: FICA | P6: AE | Q6: 3 | R6: A
B7: 2025-1 | C7: RCU N° 249-2019-UAI-CU/P | D7: 202011 | E7: FILIAL | F7: I | G7: AF | H7: 7 | I7: A | K7: 2025-2 | L7: RCU Nº 354-2024-UAI-CU/P | M7: 20242 | N7: PRINCIPAL | O7: FICA | P7: AE | Q7: 2 | R7: A
B8: 2025-1 | C8: RCU N° 533-2024-UAI-CU/P | D8: 20251 | E8: FILIAL | F8: I | G8: CA | H8: 1 | I8: A | K8: 2025-2 | L8: RCU Nº 354-2024-UAI-CU/P | M8: 20242 | N8: PRINCIPAL | O8: FICA | P8: AE | Q8: 2 | R8: B
B9: 2025-1 | C9: RCU Nº 018-2021-UAI-CU/P | D9: 201722 | E9: FILIAL | F9: I | G9: CA | H9: 9 | I9: A | K9: 2025-2 | L9: RCU Nº 354-2024-UAI-CU/P | M9: 20242 | N9: PRINCIPAL | O9: FICA | P9: AE | Q9: 3 | R9: A
B10: 2025-1 | C10: RCU N° 348-2024-UAI-CU/P | D10: 20242 | E10: FILIAL | F10: I | G10: CA | H10: 9 | I10: B | K10: 2025-2 | L10: RCU Nº 354-2024-UAI-CU/P | M10: 20242 | N10: PRINCIPAL | O10: FICA | P10: AE | Q10: 3 | R10: B
B11: 2025-1 | C11: RCU N° 349-2024-UAI-CU/P | D11: 20242 | E11: FILIAL | F11: I | G11: DE | H11: 1 | I11: A | K11: 2025-2 | L11: RCU Nº 532-2024-UAI-CU/P | M11: 20251 | N11: PRINCIPAL | O11: FICA | P11: AE | Q11: 3 | R11: C
B12: 2025-1 | C12: RCU N° 349-2024-UAI-CU/P | D12: 20242 | E12: FILIAL | F12: I | G12: DE | H12: 1 | I12: B | K12: 2025-2 | L12: RCU Nº 354-2024-UAI-CU/P | M12: 20242 | N12: PRINCIPAL | O12: FICA | P12: AE | Q12: 4 | R12: A
B13: 2025-1 | C13: RCU N° 349-2024-UAI-CU/P | D13: 20242 | E13: FILIAL | F13: I | G13: DE | H13: 2 | I13: A | K13: 2025-2 | L13: RCU Nº 344-2024-UAI-CU/P | M13: 20242 | N13: FILIAL | O13: FICA | P13: AF | Q13: 5 | R13: A
B14: 2025-1 | C14: RCU N° 349-2024-UAI-CU/P | D14: 20242 | E14: FILIAL | F14: I | G14: DE | H14: 3 | I14: A | K14: 2025-2 | L14: RCU Nº 249-2019-UAI-CU/P | M14: 202011 | N14: FILIAL | O14: FICA | P14: AF | Q14: 8 | R14: A
B15: 2025-1 | C15: RCU N° 349-2024-UAI-CU/P | D15: 20242 | E15: FILIAL | F15: I | G15: DE | H15: 3 | I15: B | K15: 2025-2 | L15: RCU Nº 249-2019-UAI-CU/P | M15: 202011 | N15: FILIAL | O15: FICA | P15: AF | Q15: 9 | R15: A
B16: 2025-1 | C16: RCU N° 032-2023-UAI-CU/P | D16: 202312 | E16: FILIAL | F16: I | G16: DE | H16: 5 | I16: A | K16: 2025-2 | L16: RCU Nº 344-2024-UAI-CU/P | M16: 20242 | N16: PRINCIPAL | O16: FICA | P16: AF | Q16: 5 | R16: A
... B286: 2025-1 | C286: RCU Nº 069-2025-UAI-CU/P | D286: 20251 | E286: SUNAMPE | F286: S | G286: MH | H286: 3 | I286: C | K286: 2025-2 | L286: RCU Nº 346-2024-UAI-CU/P | M286: 20242 | N286: PRINCIPAL | O286: FCS | P286: PS | Q286: 5 | R286: B
K287: 2025-2 | L287: RCU Nº 346-2024-UAI-CU/P | M287: 20242 | N287: PRINCIPAL | O287: FCS | P287: PS | Q287: 6 | R287: A
H288: 282 | I288: Aulas | K288: 2025-2 | L288: RCU Nº 346-2024-UAI-CU/P | M288: 20242 | N288: PRINCIPAL | O288: FCS | P288: PS | Q288: 7 | R288: A
K289: 2025-2 | L289: RCU Nº 346-2024-UAI-CU/P | M289: 20242 | N289: PRINCIPAL | O289: FCS | P289: PS | Q289: 7 | R289: B
K290: 2025-2 | L290: RCU Nº 249-2019-UAI-CU/P | M290: 202011 | N290: PRINCIPAL | O290: FCS | P290: PS | Q290: 8 | R290: A
K291: 2025-2 | L291: RCU Nº 249-2019-UAI-CU/P | M291: 202011 | N291: PRINCIPAL | O291: FCS | P291: PS | Q291: 8 | R291: X
K292: 2025-2 | L292: RCU Nº 249-2019-UAI-CU/P | M292: 202011 | N292: PRINCIPAL | O292: FCS | P292: PS | Q292: 9 | R292: A
K293: 2025-2 | L293: RCU Nº 249-2019-UAI-CU/P | M293: 202011 | N293: PRINCIPAL | O293: FCS | P293: PS | Q293: 9 | R293: B
K294: 2025-2 | L294: RCU Nº 249-2019-UAI-CU/P | M294: 202011 | N294: PRINCIPAL | O294: FCS | P294: PS | Q294: 9 | R294: C
K295: 2025-2 | L295: RCU Nº 249-2019-UAI-CU/P | M295: 202011 | N295: PRINCIPAL | O295: FCS | P295: PS | Q295: 10 | R295: A
K296: 2025-2 | L296: RCU Nº 364-2024-UAI-CU/P | M296: 20251 | N296: FILIAL | O296: FCS | P296: T1 | Q296: 3 | R296: A
K297: 2025-2 | L297: RCU Nº 364-2024-UAI-CU/P | M297: 20251 | N297: PRINCIPAL | O297: FCS | P297: T1 | Q297: 3 | R297: A
K298: 2025-2 | L298: RCU Nº 365-2024-UAI-CU/P | M298: 20251 | N298: FILIAL | O298: FCS | P298: T2 | Q298: 3 | R298: A
K299: 2025-2 | L299: RCU Nº 366-2024-UAI-CU/P | M299: 20251 | N299: FILIAL | O299: FCS | P299: T3 | Q299: 2 | R299: A
K300: 2025-2 | L300: RCU Nº 366-2024-UAI-CU/P | M300: 20251 | N300: FILIAL | O300: FCS | P300: T3 | Q300: 3 | R300: A
... K307: 2025-2 | L307: RCU Nº 531-2024-UAI-CU/P | M307: 20251 | N307: PRINCIPAL | O307: FCS | P307: T4 | Q307: 3 | R307: D

Sheet EDITABLE
I2: SEDE | Z2: FILIAL | AQ2: SUNAMPE | BH2: HUAURA | BY2: HORAS POR CARRERA | CO2: HORAS POR CARRERA EEGG | EC2: EEGG
B3: N° | C3: DOCENTES UAI | D3: HORAS | E3: DEDICACIÓN | F3: CONDICIÓN | G3: LOCAL 2025-2 | H3: PROGRAMA ACADÉMICO 2025-2 | I3: ADM | J3: ENF | K3: ING SIS | L3: PS | M3: IND AL | N3: IND | O3: CONT | P3: DE | Q3: OBS | R3: MEDICINA | S3: ING CIVIL | T3: ARQUI | U3: LAB. CLIN | V3: TERAPIA FIS. | W3: TERAPIA LEN. | X3: ADM. EMP | Y3: OPTOM. | Z3: ADM | AA3: ENF | AB3: ING SIS | AC3: PS | AD3: IND AL | AE3: IND | AF3: CONT | AG3: DE | AH3: OBS | AI3: MEDICINA | AJ3: ING CIVIL | AK3: ARQUI | AL3: LAB. CLIN | AM3: TERAPIA FIS. | AN3: TERAPIA LEN. | AO3: ADM. EMP | AP3: OPTOM. | AQ3: ADM | AR3: ENF | AS3: ING SIS | AT3: PS | AU3: IND AL | AV3: IND | AW3: CONT | AX3: DE | AY3: OBS | AZ3: MEDICINA | BA3: ING CIVIL | BB3: ARQUI | BC3: LAB. CLIN | BD3: TERAPIA FIS. | BE3: TERAPIA LEN. | BF3: ADM. EMP | BG3: OPTOM. | BH3: ADM | BI3: ENF | BJ3: ING SIS | BK3: PS | BL3: IND AL | BM3: IND | BN3: CONT | BO3: DE | BP3: OBS | BQ3: MEDICINA | BR3: ING CIVIL | BS3: ARQUI | BT3: LAB. CLIN | BU3: TERAPIA FIS. | BV3: TERAPIA LEN. | BW3: ADM. EMP | BX3: OPTOM. | BY3: ADMINISTRACIÓN Y FINANZAS | BZ3: ENFERMERÍA | CA3: INGENIERÍA DE SISTEMAS | CB3: PSICOLOGÍA | CC3: INGENIERÍA INDUSTRIAL | CD3: CONTABILIDAD | CE3: DERECHO | CF3: OBSTETRICIA | CG3: MEDICINA HUMANA | CH3: INGENIERÍA CIVIL | CI3: ARQUITECTURA | CJ3: TECNOLOGÍA MEDICA EN LABORATORIO CLÍNICO Y ANATOMÍA PATOLÓGICA | CK3: TECNOLOGÍA MEDICA EN TERAPIA FÍSICA Y REHABILITACIÓN | CL3: TECNOLOGÍA MEDICA EN TERAPIA DE LENGUAJE | CM3: ADMINISTRACIÓN DE EMPRESAS | CN3: TECNOLOGÍA MEDICA EN OPTOMETRÍA | CO3: ADMINISTRACIÓN Y FINANZAS - EEGG | CP3: ENFERMERÍA - EEGG | CQ3: INGENIERÍA DE SISTEMAS - EEGG | CR3: PSICOLOGÍA - EEGG | CS3: INGENIERÍA INDUSTRIAL - EEGG | CT3: CONTABILIDAD - EEGG | CU3: DERECHO - EEGG | CV3: OBSTETRICIA - EEGG | CW3: MEDICINA HUMANA - EEGG | CX3: INGENIERÍA CIVIL - EEGG | CY3: ARQUITECTURA - EEGG | CZ3: TECNOLOGÍA MEDICA EN LABORATORIO CLÍNICO Y ANATOMÍA PATOLÓGICA - EEGG | DA3: TECNOLOGÍA MEDICA EN TERAPIA FÍSICA Y REHABILITACIÓN - EEGG | DB3: TECNOLOGÍA MEDICA EN TERAPIA DE LENGUAJE - EEGG | DC3: ADMINISTRACIÓN DE EMPRESAS - EEGG | DD3: TECNOLOGÍA MEDICA EN OPTOMETRÍA - EEGG | DE3: SEDE | DF3: HORAS VIRTUAL | DG3: HORAS PRESENCIAL | DH3: HORAS HIBRIDAS | DI3: FILIAL | DJ3: HORAS VIRTUAL | DK3: HORAS PRESENCIAL | DL3: HORAS HIBRIDAS | DM3: SUNAMPE | DN3: HORAS VIRTUAL | DO3: HORAS PRESENCIAL | DP3: HUAURA | DQ3: HORAS VIRTUAL | DR3: HORAS PRESENCIAL | DS3: SEDE-VIRTUAL | DT3: SEDE-PRESENCIAL | DU3: SUNAMPE-VIRTUAL | DV3: SUNAMPE-PRESENCIAL | DW3: FILIAL-VIRTUAL | DX3: FILIAL-PRESENCIAL | DY3: PORUMA-VIRTUAL | DZ3: PORUMA-PRESENCIAL | EA3: HUAURA-VIRTUAL | EB3: HUAURA-PRESENCIAL | EC3: SEDE-VIRTUAL | ED3: SEDE-PRESENCIAL | EE3: SUNAMPE-VIRTUAL | EF3: SUNAMPE-PRESENCIAL | EG3: FILIAL-VIRTUAL | EH3: FILIAL-PRESENCIAL | EI3: PORUMA-VIRTUAL | EJ3: PORUMA-PRESENCIAL | EK3: HUAURA-VIRTUAL | EL3: HUAURA-PRESENCIAL | EN3: VIRTUAL | EO3: PRESENCIAL
B4: 1 | C4: ACEVEDO CRUZ EVELYN CRISPINA | D4: =SUMIF('Planificación 2026-1'!W:W,C4,'Planificación 2026-1'!R:R) -> 0 | E4: TP | F4: RENOVACIÓN | G4: FILIAL | H4: OBSTETRICIA - EEGG | I4: =IF(SUM(COUNTIFS('Planificación 2026-1'!F:F,"PRINCIPAL",'Planificación 2026-1'!W:W,C4,'Planificación 2026-1'!H:H,"AF"))>0,"P01"," ") | J4: =IF(SUM(COUNTIFS('Planificación 2026-1'!F:F,"PRINCIPAL",'Planificación 2026-1'!W:W,C4,'Planificación 2026-1'!H:H,"EN"))>0,"P02"," ") | K4: =IF(SUM(COUNTIFS('Planificación 2026-1'!F:F,"PRINCIPAL",'Planificación 2026-1'!W:W,C4,'Planificación 2026-1'!H:H,"IS"))>0,"P03"," ") | L4: =IF(SUM(COUNTIFS('Planificación 2026-1'!F:F,"PRINCIPAL",'Planificación 2026-1'!W:W,C4,'Planificación 2026-1'!H:H,"PS"))>0,"P04"," ") | N4: =IF(SUM(COUNTIFS('Planificación 2026-1'!F:F,"PRINCIPAL",'Planificación 2026-1'!W:W,C4,'Planificación 2026-1'!H:H,"IN"))>0,"P06"," ") | O4: =IF(SUM(COUNTIFS('Planificación 2026-1'!F:F,"PRINCIPAL",'Planificación 2026-1'!W:W,C4,'Planificación 2026-1'!H:H,"CA"))>0,"P07"," ") | P4: =IF(SUM(COUNTIFS('Planificación 2026-1'!F:F,"PRINCIPAL",'Planificación 2026-1'!W:W,C4,'Planificación 2026-1'!H:H,"DE"))>0,"P08"," ") | Q4: =IF(SUM(COUNTIFS('Planificación 2026-1'!F:F,"PRINCIPAL",'Planificación 2026-1'!W:W,C4,'Planificación 2026-1'!H:H,"OB"))>0,"P09"," ") | R4: =IF(SUM(COUNTIFS('Planificación 2026-1'!F:F,"PRINCIPAL",'Planificación 2026-1'!W:W,C4,'Planificación 2026-1'!H:H,"MH"))>0,"P31"," ") | S4: =IF(SUM(COUNTIFS('Planificación 2026-1'!F:F,"PRINCIPAL",'Planificación 2026-1'!W:W,C4,'Planificación 2026-1'!H:H,"IC"))>0,"P32"," ") | T4: =IF(SUM(COUNTIFS('Planificación 2026-1'!F:F,"PRINCIPAL",'Planificación 2026-1'!W:W,C4,'Planificación 2026-1'!H:H,"AR"))>0,"P34"," ") | U4: =IF(SUM(COUNTIFS('Planificación 2026-1'!F:F,"PRINCIPAL",'Planificación 2026-1'!W:W,C4,'Planificación 2026-1'!H:H,"T1"))>0,"P35"," ") | V4: =IF(SUM(COUNTIFS('Planificación 2026-1'!F:F,"PRINCIPAL",'Planificación 2026-1'!W:W,C4,'Planificación 2026-1'!H:H,"T3"))>0,"P36"," ") | W4: =IF(SUM(COUNTIFS('Planificación 2026-1'!F:F,"PRINCIPAL",'Planificación 2026-1'!W:W,C4,'Planificación 2026-1'!H:H,"T2"))>0,"P37"," ") | X4: =IF(SUM(COUNTIFS('Planificación 2026-1'!F:F,"PRINCIPAL",'Planificación 2026-1'!W:W,C4,'Planificación 2026-1'!H:H,"AE"))>0,"P38"," ") | Y4: =IF(SUM(COUNTIFS('Planificación 2026-1'!F:F,"PRINCIPAL",'Planificación 2026-1'!W:W,C4,'Planificación 2026-1'!H:H,"T4"))>0,"P55"," ") | Z4: =IF(SUM(COUNTIFS('Planificación 2026-1'!F:F,"FILIAL",'Planificación 2026-1'!W:W,C4,'Planificación 2026-1'!H:H,"AF"))>0," P01"," ") | AA4: =IF(SUM(COUNTIFS('Planificación 2026-1'!F:F,"FILIAL",'Planificación 2026-1'!W:W,C4,'Planificación 2026-1'!H:H,"EN"))>0,"P02"," ") | AB4: =IF(SUM(COUNTIFS('Planificación 2026-1'!F:F,"FILIAL",'Planificación 2026-1'!W:W,C4,'Planificación 2026-1'!H:H,"IS"))>0,"P03"," ") | AC4: =IF(SUM(COUNTIFS('Planificación 2026-1'!F:F,"FILIAL",'Planificación 2026-1'!W:W,C4,'Planificación 2026-1'!H:H,"PS"))>0,"P04"," ") | AE4: =IF(SUM(COUNTIFS('Planificación 2026-1'!F:F,"FILIAL",'Planificación 2026-1'!W:W,C4,'Planificación 2026-1'!H:H,"IN"))>0,"P06"," ") | AF4: =IF(SUM(COUNTIFS('Planificación 2026-1'!F:F,"FILIAL",'Planificación 2026-1'!W:W,C4,'Planificación 2026-1'!H:H,"CA"))>0,"P07"," ") | AG4: =IF(SUM(COUNTIFS('Planificación 2026-1'!F:F,"FILIAL",'Planificación 2026-1'!W:W,C4,'Planificación 2026-1'!H:H,"DE"))>0,"P08"," ") | AH4: =IF(SUM(COUNTIFS('Planificación 2026-1'!F:F,"FILIAL",'Planificación 2026-1'!W:W,C4,'Planificación 2026-1'!H:H,"OB"))>0,"P09"," ") | AI4: =IF(SUM(COUNTIFS('Planificación 2026-1'!F:F,"FILIAL",'Planificación 2026-1'!W:W,C4,'Planificación 2026-1'!H:H,"MH"))>0,"P31"," ") | AJ4: =IF(SUM(COUNTIFS('Planificación 2026-1'!F:F,"FILIAL",'Planificación 2026-1'!W:W,C4,'Planificación 2026-1'!H:H,"IC"))>0,"P32"," ") | AK4: =IF(SUM(COUNTIFS('Planificación 2026-1'!F:F,"FILIAL",'Planificación 2026-1'!W:W,C4,'Planificación 2026-1'!H:H,"AR"))>0,"P34"," ") | AL4: =IF(SUM(COUNTIFS('Planificación 2026-1'!F:F,"FILIAL",'Planificación 2026-1'!W:W,C4,'Planificación 2026-1'!H:H,"T1"))>0,"P35"," ") | AM4: =IF(SUM(COUNTIFS('Planificación 2026-1'!F:F,"FILIAL",'Planificación 2026-1'!W:W,C4,'Planificación 2026-1'!H:H,"T3"))>0,"P36"," ") | AN4: =IF(SUM(COUNTIFS('Planificación 2026-1'!F:F,"FILIAL",'Planificación 2026-1'!W:W,C4,'Planificación 2026-1'!H:H,"T2"))>0,"P37"," ") | AO4: =IF(SUM(COUNTIFS('Planificación 2026-1'!F:F,"FILIAL",'Planificación 2026-1'!W:W,C4,'Planificación 2026-1'!H:H,"AE"))>0,"P38"," ") | AP4: =IF(SUM(COUNTIFS('Planificación 2026-1'!F:F,"FILIAL",'Planificación 2026-1'!W:W,C4,'Planificación 2026-1'!H:H,"T4"))>0,"P55"," ") | AQ4: =IF(SUM(COUNTIFS('Planificación 2026-1'!F:F,"SUNAMPE",'Planificación 2026-1'!W:W,C4,'Planificación 2026-1'!H:H,"AF"))>0," P01"," ") | AR4: =IF(SUM(COUNTIFS('Planificación 2026-1'!F:F,"SUNAMPE",'Planificación 2026-1'!W:W,C4,'Planificación 2026-1'!H:H,"EN"))>0,"P02"," ") | AS4: =IF(SUM(COUNTIFS('Planificación 2026-1'!F:F,"SUNAMPE",'Planificación 2026-1'!W:W,C4,'Planificación 2026-1'!H:H,"IS"))>0,"P03"," ") | AT4: =IF(SUM(COUNTIFS('Planificación 2026-1'!F:F,"SUNAMPE",'Planificación 2026-1'!W:W,C4,'Planificación 2026-1'!H:H,"PS"))>0,"P04"," ") | AV4: =IF(SUM(COUNTIFS('Planificación 2026-1'!F:F,"SUNAMPE",'Planificación 2026-1'!W:W,C4,'Planificación 2026-1'!H:H,"IN"))>0,"P06"," ") | AW4: =IF(SUM(COUNTIFS('Planificación 2026-1'!F:F,"SUNAMPE",'Planificación 2026-1'!W:W,C4,'Planificación 2026-1'!H:H,"CA"))>0,"P07"," ") | AX4: =IF(SUM(COUNTIFS('Planificación 2026-1'!F:F,"SUNAMPE",'Planificación 2026-1'!W:W,C4,'Planificación 2026-1'!H:H,"DE"))>0,"P08"," ") | AY4: =IF(SUM(COUNTIFS('Planificación 2026-1'!F:F,"SUNAMPE",'Planificación 2026-1'!W:W,C4,'Planificación 2026-1'!H:H,"OB"))>0,"P09"," ") | AZ4: =IF(SUM(COUNTIFS('Planificación 2026-1'!F:F,"SUNAMPE",'Planificación 2026-1'!W:W,C4,'Planificación 2026-1'!H:H,"MH"))>0,"P31"," ") | BA4: =IF(SUM(COUNTIFS('Planificación 2026-1'!F:F,"SUNAMPE",'Planificación 2026-1'!W:W,C4,'Planificación 2026-1'!H:H,"IC"))>0,"P32"," ") | BB4: =IF(SUM(COUNTIFS('Planificación 2026-1'!F:F,"SUNAMPE",'Planificación 2026-1'!W:W,C4,'Planificación 2026-1'!H:H,"AR"))>0,"P34"," ") | BC4: =IF(SUM(COUNTIFS('Planificación 2026-1'!F:F,"SUNAMPE",'Planificación 2026-1'!W:W,C4,'Planificación 2026-1'!H:H,"T1"))>0,"P35"," ") | BD4: =IF(SUM(COUNTIFS('Planificación 2026-1'!F:F,"SUNAMPE",'Planificación 2026-1'!W:W,C4,'Planificación 2026-1'!H:H,"T3"))>0,"P36"," ") | BE4: =IF(SUM(COUNTIFS('Planificación 2026-1'!F:F,"SUNAMPE",'Planificación 2026-1'!W:W,C4,'Planificación 2026-1'!H:H,"T2"))>0,"P37"," ") | BF4: =IF(SUM(COUNTIFS('Planificación 2026-1'!F:F,"SUNAMPE",'Planificación 2026-1'!W:W,C4,'Planificación 2026-1'!H:H,"AE"))>0,"P38"," ") | BG4: =IF(SUM(COUNTIFS('Planificación 2026-1'!F:F,"SUNAMPE",'Planificación 2026-1'!W:W,C4,'Planificación 2026-1'!H:H,"T4"))>0,"P55"," ") | BH4: =IF(SUM(COUNTIFS('Planificación 2026-1'!F:F,"HUAURA",'Planificación 2026-1'!W:W,C4,'Planificación 2026-1'!H:H,"AF"))>0," P01"," ") | BI4: =IF(SUM(COUNTIFS('Planificación 2026-1'!F:F,"HUAURA",'Planificación 2026-1'!W:W,C4,'Planificación 2026-1'!H:H,"EN"))>0,"P02"," ") | BJ4: =IF(SUM(COUNTIFS('Planificación 2026-1'!F:F,"HUAURA",'Planificación 2026-1'!W:W,C4,'Planificación 2026-1'!H:H,"IS"))>0,"P03"," ") | BK4: =IF(SUM(COUNTIFS('Planificación 2026-1'!F:F,"HUAURA",'Planificación 2026-1'!W:W,C4,'Planificación 2026-1'!H:H,"PS"))>0,"P04"," ") | BM4: =IF(SUM(COUNTIFS('Planificación 2026-1'!F:F,"HUAURA",'Planificación 2026-1'!W:W,C4,'Planificación 2026-1'!H:H,"IN"))>0,"P06"," ") | BN4: =IF(SUM(COUNTIFS('Planificación 2026-1'!F:F,"HUAURA",'Planificación 2026-1'!W:W,C4,'Planificación 2026-1'!H:H,"CA"))>0,"P07"," ") | BO4: =IF(SUM(COUNTIFS('Planificación 2026-1'!F:F,"HUAURA",'Planificación 2026-1'!W:W,C4,'Planificación 2026-1'!H:H,"DE"))>0,"P08"," ") | BP4: =IF(SUM(COUNTIFS('Planificación 2026-1'!F:F,"HUAURA",'Planificación 2026-1'!W:W,C4,'Planificación 2026-1'!H:H,"OB"))>0,"P09"," ") | BQ4: =IF(SUM(COUNTIFS('Planificación 2026-1'!F:F,"HUAURA",'Planificación 2026-1'!W:W,C4,'Planificación 2026-1'!H:H,"MH"))>0,"P31"," ") | BR4: =IF(SUM(COUNTIFS('Planificación 2026-1'!F:F,"HUAURA",'Planificación 2026-1'!W:W,C4,'Planificación 2026-1'!H:H,"IC"))>0,"P32"," ") | BS4: =IF(SUM(COUNTIFS('Planificación 2026-1'!F:F,"HUAURA",'Planificación 2026-1'!W:W,C4,'Planificación 2026-1'!H:H,"AR"))>0,"P34"," ") | BT4: =IF(SUM(COUNTIFS('Planificación 2026-1'!F:F,"HUAURA",'Planificación 2026-1'!W:W,C4,'Planificación 2026-1'!H:H,"T1"))>0,"P35"," ") | BU4: =IF(SUM(COUNTIFS('Planificación 2026-1'!F:F,"HUAURA",'Planificación 2026-1'!W:W,C4,'Planificación 2026-1'!H:H,"T3"))>0,"P36"," ") | BV4: =IF(SUM(COUNTIFS('Planificación 2026-1'!F:F,"HUAURA",'Planificación 2026-1'!W:W,C4,'Planificación 2026-1'!H:H,"T2"))>0,"P37"," ") | BW4: =IF(SUM(COUNTIFS('Planificación 2026-1'!F:F,"HUAURA",'Planificación 2026-1'!W:W,C4,'Planificación 2026-1'!H:H,"AE"))>0,"P38"," ") | BX4: =IF(SUM(COUNTIFS('Planificación 2026-1'!F:F,"HUAURA",'Planificación 2026-1'!W:W,C4,'Planificación 2026-1'!H:H,"T4"))>0,"P55"," ") | BY4: =SUMIFS('Planificación 2026-1'!R:R,'Planificación 2026-1'!W:W,C4,'Planificación 2026-1'!H:H,"AF",'Planificación 2026-1'!I:I,">2") -> 0 | BZ4: =SUMIFS('Planificación 2026-1'!R:R,'Planificación 2026-1'!W:W,C4,'Planificación 2026-1'!H:H,"EN",'Planificación 2026-1'!I:I,">2") -> 0 | CA4: =SUMIFS('Planificación 2026-1'!R:R,'Planificación 2026-1'!W:W,C4,'Planificación 2026-1'!H:H,"IS",'Planificación 2026-1'!I:I,">2") -> 0 | CB4: =SUMIFS('Planificación 2026-1'!R:R,'Planificación 2026-1'!W:W,C4,'Planificación 2026-1'!H:H,"PS",'Planificación 2026-1'!I:I,">2") -> 0 | CC4: =SUMIFS('Planificación 2026-1'!R:R,'Planificación 2026-1'!W:W,C4,'Planificación 2026-1'!H:H,"IN",'Planificación 2026-1'!I:I,">2") -> 0 | CD4: =SUMIFS('Planificación 2026-1'!R:R,'Planificación 2026-1'!W:W,C4,'Planificación 2026-1'!H:H,"CA",'Planificación 2026-1'!I:I,">2") -> 0 | CE4: =SUMIFS('Planificación 2026-1'!R:R,'Planificación 2026-1'!W:W,C4,'Planificación 2026-1'!H:H,"DE",'Planificación 2026-1'!I:I,">2") -> 0 | CF4: =SUMIFS('Planificación 2026-1'!R:R,'Planificación 2026-1'!W:W,C4,'Planificación 2026-1'!H:H,"OB",'Planificación 2026-1'!I:I,">2") -> 0 | CG4: =SUMIFS('Planificación 2026-1'!R:R,'Planificación 2026-1'!W:W,C4,'Planificación 2026-1'!H:H,"MH",'Planificación 2026-1'!I:I,">2") -> 0 | CH4: =SUMIFS('Planificación 2026-1'!R:R,'Planificación 2026-1'!W:W,C4,'Planificación 2026-1'!H:H,"IC",'Planificación 2026-1'!I:I,">2") -> 0 | CI4: =SUMIFS('Planificación 2026-1'!R:R,'Planificación 2026-1'!W:W,C4,'Planificación 2026-1'!H:H,"AR",'Planificación 2026-1'!I:I,">2") -> 0 | CJ4: =SUMIFS('Planificación 2026-1'!R:R,'Planificación 2026-1'!W:W,C4,'Planificación 2026-1'!H:H,"T1",'Planificación 2026-1'!I:I,">2") -> 0 | CK4: =SUMIFS('Planificación 2026-1'!R:R,'Planificación 2026-1'!W:W,C4,'Planificación 2026-1'!H:H,"T3",'Planificación 2026-1'!I:I,">2") -> 0 | CL4: =SUMIFS('Planificación 2026-1'!R:R,'Planificación 2026-1'!W:W,C4,'Planificación 2026-1'!H:H,"T2",'Planificación 2026-1'!I:I,">2") -> 0 | CM4: =SUMIFS('Planificación 2026-1'!R:R,'Planificación 2026-1'!W:W,C4,'Planificación 2026-1'!H:H,"AE",'Planificación 2026-1'!I:I,">2") -> 0 | CN4: =SUMIFS('Planificación 2026-1'!R:R,'Planificación 2026-1'!W:W,C4,'Planificación 2026-1'!H:H,"T4",'Planificación 2026-1'!I:I,">2") -> 0 | CO4: =SUMIFS('Planificación 2026-1'!R:R,'Planificación 2026-1'!W:W,C4,'Planificación 2026-1'!H:H,"AF",'Planificación 2026-1'!I:I,"<3") -> 0 | CP4: =SUMIFS('Planificación 2026-1'!R:R,'Planificación 2026-1'!W:W,C4,'Planificación 2026-1'!H:H,"EN",'Planificación 2026-1'!I:I,"<3") -> 0 | CQ4: =SUMIFS('Planificación 2026-1'!R:R,'Planificación 2026-1'!W:W,C4,'Planificación 2026-1'!H:H,"IS",'Planificación 2026-1'!I:I,"<3") -> 0 | CR4: =SUMIFS('Planificación 2026-1'!R:R,'Planificación 2026-1'!W:W,C4,'Planificación 2026-1'!H:H,"PS",'Planificación 2026-1'!I:I,"<3") -> 0 | CS4: =SUMIFS('Planificación 2026-1'!R:R,'Planificación 2026-1'!W:W,C4,'Planificación 2026-1'!H:H,"IN",'Planificación 2026-1'!I:I,"<3") -> 0 | CT4: =SUMIFS('Planificación 2026-1'!R:R,'Planificación 2026-1'!W:W,C4,'Planificación 2026-1'!H:H,"CA",'Planificación 2026-1'!I:I,"<3") -> 0 | CU4: =SUMIFS('Planificación 2026-1'!R:R,'Planificación 2026-1'!W:W,C4,'Planificación 2026-1'!H:H,"DE",'Planificación 2026-1'!I:I,"<3") -> 0 | CV4: =SUMIFS('Planificación 2026-1'!R:R,'Planificación 2026-1'!W:W,C4,'Planificación 2026-1'!H:H,"OB",'Planificación 2026-1'!I:I,"<3") -> 0 | CW4: =SUMIFS('Planificación 2026-1'!R:R,'Planificación 2026-1'!W:W,C4,'Planificación 2026-1'!H:H,"MH",'Planificación 2026-1'!I:I,"<3") -> 0 | CX4: =SUMIFS('Planificación 2026-1'!R:R,'Planificación 2026-1'!W:W,C4,'Planificación 2026-1'!H:H,"IC",'Planificación 2026-1'!I:I,"<3") -> 0 | CY4: =SUMIFS('Planificación 2026-1'!R:R,'Planificación 2026-1'!W:W,C4,'Planificación 2026-1'!H:H,"AR",'Planificación 2026-1'!I:I,"<3") -> 0 | CZ4: =SUMIFS('Planificación 2026-1'!R:R,'Planificación 2026-1'!W:W,C4,'Planificación 2026-1'!H:H,"T1",'Planificación 2026-1'!I:I,"<3") -> 0 | DA4: =SUMIFS('Planificación 2026-1'!R:R,'Planificación 2026-1'!W:W,C4,'Planificación 2026-1'!H:H,"T3",'Planificación 2026-1'!I:I,"<3") -> 0 | DB4: =SUMIFS('Planificación 2026-1'!R:R,'Planificación 2026-1'!W:W,C4,'Planificación 2026-1'!H:H,"T2",'Planificación 2026-1'!I:I,"<3") -> 0 | DC4: =SUMIFS('Planificación 2026-1'!R:R,'Planificación 2026-1'!W:W,C4,'Planificación 2026-1'!H:H,"AE",'Planificación 2026-1'!I:I,"<3") -> 0 | DD4: =SUMIFS('Planificación 2026-1'!R:R,'Planificación 2026-1'!W:W,C4,'Planificación 2026-1'!H:H,"T4",'Planificación 2026-1'!I:I,"<3") -> 0 | DE4: =TRIM(CONCATENATE(I4,J4,K4,L4,M4,N4,O4,P4,Q4,R4,S4,T4,U4,V4,W4,X4,Y4)) | DF4: =IF(C4="","",SUMIFS('Planificación 2026-1'!R:R,'Planificación 2026-1'!W:W,C4,'Planificación 2026-1'!F:F,"PRINCIPAL",'Planificación 2026-1'!X:X,"VIRTUAL")) -> 0 | DG4: =IF(C4="","",SUMIFS('Planificación 2026-1'!R:R,'Planificación 2026-1'!W:W,C4,'Planificación 2026-1'!F:F,"PRINCIPAL",'Planificación 2026-1'!X:X,"PRESENCIAL")) -> 0 | DH4: =IF(C4="","",SUMIFS('Planificación 2026-1'!R:R,'Planificación 2026-1'!W:W,C4,'Planificación 2026-1'!F:F,"PRINCIPAL",'Planificación 2026-1'!X:X,"HIBRIDO PRESENCIAL")) -> 0 | DI4: =TRIM(CONCATENATE(Z4,AA4,AB4,AC4,AD4,AE4,AF4,AG4,AH4,AI4,AJ4,AK4,AL4,AM4,AN4,AO4,AP4)) | DJ4: =IF(C4="","",SUMIFS('Planificación 2026-1'!R:R,'Planificación 2026-1'!W:W,C4,'Planificación 2026-1'!F:F,"FILIAL",'Planificación 2026-1'!X:X,"VIRTUAL")) -> 0 | DK4: =IF(C4="","",SUMIFS('Planificación 2026-1'!R:R,'Planificación 2026-1'!W:W,C4,'Planificación 2026-1'!F:F,"FILIAL",'Planificación 2026-1'!X:X,"PRESENCIAL")) -> 0 | DL4: =IF(C4="","",SUMIFS('Planificación 2026-1'!R:R,'Planificación 2026-1'!W:W,C4,'Planificación 2026-1'!F:F,"FILIAL",'Planificación 2026-1'!X:X,"HIBRIDO PRESENCIAL")) -> 0 | DM4: =TRIM(CONCATENATE(AQ4,AR4,AS4,AT4,AU4,AV4,AW4,AX4,AY4,AZ4,BA4,BB4,BC4,BD4,BE4,BF4,BG4)) | DN4: =IF(C4="","",SUMIFS('Planificación 2026-1'!R:R,'Planificación 2026-1'!W:W,C4,'Planificación 2026-1'!F:F,"SUNAMPE",'Planificación 2026-1'!X:X,"VIRTUAL")) -> 0 | DO4: =IF(C4="","",SUMIFS('Planificación 2026-1'!R:R,'Planificación 2026-1'!W:W,C4,'Planificación 2026-1'!F:F,"SUNAMPE",'Planificación 2026-1'!X:X,"PRESENCIAL")) -> 0 | DP4: =TRIM(CONCATENATE(BH4,BI4,BJ4,BK4,BL4,BM4,BN4,BO4,BP4,BQ4,BR4,BS4,BT4,BU4,BV4,BW4,BX4)) | DQ4: =IF(C4="","",SUMIFS('Planificación 2026-1'!R:R,'Planificación 2026-1'!W:W,C4,'Planificación 2026-1'!F:F,"HUAURA",'Planificación 2026-1'!X:X,"VIRTUAL")) -> 0 | DR4: =IF(C4="","",SUMIFS('Planificación 2026-1'!R:R,'Planificación 2026-1'!W:W,C4,'Planificación 2026-1'!F:F,"HUAURA",'Planificación 2026-1'!X:X,"PRESENCIAL")) -> 0 | DS4: =SUMIFS('Planificación 2026-1'!R:R,'Planificación 2026-1'!W:W,C4,'Planificación 2026-1'!F:F,"PRINCIPAL",'Planificación 2026-1'!X:X,"VIRTUAL",'Planificación 2026-1'!I:I,">2") -> 0 | DT4: =SUMIFS('Planificación 2026-1'!R:R,'Planificación 2026-1'!W:W,C4,'Planificación 2026-1'!F:F,"PRINCIPAL",'Planificación 2026-1'!X:X,"<>VIRTUAL",'Planificación 2026-1'!I:I,">2") -> 0 | DU4: =SUMIFS('Planificación 2026-1'!R:R,'Planificación 2026-1'!W:W,C4,'Planificación 2026-1'!F:F,"SUNAMPE",'Planificación 2026-1'!X:X,"VIRTUAL",'Planificación 2026-1'!I:I,">2") -> 0 | DV4: =SUMIFS('Planificación 2026-1'!R:R,'Planificación 2026-1'!W:W,C4,'Planificación 2026-1'!F:F,"SUNAMPE",'Planificación 2026-1'!X:X,"<>VIRTUAL",'Planificación 2026-1'!I:I,">2") -> 0 | DW4: =SUMIFS('Planificación 2026-1'!R:R,'Planificación 2026-1'!W:W,C4,'Planificación 2026-1'!F:F,"FILIAL",'Planificación 2026-1'!X:X,"VIRTUAL",'Planificación 2026-1'!I:I,">2") -> 0 | DX4: =SUMIFS('Planificación 2026-1'!R:R,'Planificación 2026-1'!W:W,C4,'Planificación 2026-1'!F:F,"FILIAL",'Planificación 2026-1'!X:X,"<>VIRTUAL",'Planificación 2026-1'!I:I,">2") -> 0 | DY4: =SUMIFS('Planificación 2026-1'!R:R,'Planificación 2026-1'!W:W,C4,'Planificación 2026-1'!F:F,"PORUMA",'Planificación 2026-1'!X:X,"VIRTUAL",'Planificación 2026-1'!I:I,">2") -> 0 | DZ4: =SUMIFS('Planificación 2026-1'!R:R,'Planificación 2026-1'!W:W,C4,'Planificación 2026-1'!F:F,"PORUMA",'Planificación 2026-1'!X:X,"<>VIRTUAL",'Planificación 2026-1'!I:I,">2") -> 0 | EA4: =SUMIFS('Planificación 2026-1'!R:R,'Planificación 2026-1'!W:W,C4,'Planificación 2026-1'!F:F,"HUAURA",'Planificación 2026-1'!X:X,"VIRTUAL",'Planificación 2026-1'!I:I,">2") -> 0 | EB4: =SUMIFS('Planificación 2026-1'!R:R,'Planificación 2026-1'!W:W,C4,'Planificación 2026-1'!F:F,"HUAURA",'Planificación 2026-1'!X:X,"<>VIRTUAL",'Planificación 2026-1'!I:I,">2") -> 0 | EC4: =SUMIFS('Planificación 2026-1'!R:R,'Planificación 2026-1'!W:W,C4,'Planificación 2026-1'!F:F,"PRINCIPAL",'Planificación 2026-1'!X:X,"VIRTUAL",'Planificación 2026-1'!I:I,"<3") -> 0 | ED4: =SUMIFS('Planificación 2026-1'!R:R,'Planificación 2026-1'!W:W,C4,'Planificación 2026-1'!F:F,"PRINCIPAL",'Planificación 2026-1'!X:X,"<>VIRTUAL",'Planificación 2026-1'!I:I,"<3") -> 0 | EE4: =SUMIFS('Planificación 2026-1'!R:R,'Planificación 2026-1'!W:W,C4,'Planificación 2026-1'!F:F,"SUNAMPE",'Planificación 2026-1'!X:X,"VIRTUAL",'Planificación 2026-1'!I:I,"<3") -> 0 | EF4: =SUMIFS('Planificación 2026-1'!R:R,'Planificación 2026-1'!W:W,C4,'Planificación 2026-1'!F:F,"SUNAMPE",'Planificación 2026-1'!X:X,"<>VIRTUAL",'Planificación 2026-1'!I:I,"<3") -> 0 | EG4: =SUMIFS('Planificación 2026-1'!R:R,'Planificación 2026-1'!W:W,C4,'Planificación 2026-1'!F:F,"FILIAL",'Planificación 2026-1'!X:X,"VIRTUAL",'Planificación 2026-1'!I:I,"<3") -> 0 | EH4: =SUMIFS('Planificación 2026-1'!R:R,'Planificación 2026-1'!W:W,C4,'Planificación 2026-1'!F:F,"FILIAL",'Planificación 2026-1'!X:X,"<>VIRTUAL",'Planificación 2026-1'!I:I,"<3") -> 0 | EI4: =SUMIFS('Planificación 2026-1'!R:R,'Planificación 2026-1'!W:W,C4,'Planificación 2026-1'!F:F,"PORUMA",'Planificación 2026-1'!X:X,"VIRTUAL",'Planificación 2026-1'!I:I,"<3") -> 0 | EJ4: =SUMIFS('Planificación 2026-1'!R:R,'Planificación 2026-1'!W:W,C4,'Planificación 2026-1'!F:F,"PORUMA",'Planificación 2026-1'!X:X,"<>VIRTUAL",'Planificación 2026-1'!I:I,"<3") -> 0 | EK4: =SUMIFS('Planificación 2026-1'!R:R,'Planificación 2026-1'!W:W,C4,'Planificación 2026-1'!F:F,"HUAURA",'Planificación 2026-1'!X:X,"VIRTUAL",'Planificación 2026-1'!I:I,"<3") -> 0 | EL4: =SUMIFS('Planificación 2026-1'!R:R,'Planificación 2026-1'!W:W,C4,'Planificación 2026-1'!F:F,"HUAURA",'Planificación 2026-1'!X:X,"<>VIRTUAL",'Planificación 2026-1'!I:I,"<3") -> 0 | EN4: =DS4+DW4+EA4+EC4+EG4+EK4+DU4+EE4 -> 0 | EO4: =DT4+DX4+EB4+ED4+EH4+EL4+DV4+EF4 -> 0 | EP4: =EXACT(SUM(EN4:EO4),D4) -> TRUE | EQ4: =IF(AND(DT4=0,DX4=0,EB4=0),"",IF(COUNTIF(DT4:EB4,">0")=1,IF(DT4>0,"SEDE",IF(DX4>0,"FILIAL","HUAURA")),IF(COUNTIF(DT4:EB4,">0")=2,IF(AND(DT4>0,DX4>0),"SEDE-FILIAL",IF(AND(DT4>0,EB4>0),"SEDE-HUAURA","FILIAL-HUAURA")),"SEDE-FILIAL-HUAURA"))) | ER4: =IF(EN4=0,"PRESENCIAL",IF(EO4=0,"VIRTUAL",IF(EN4>EO4,"MAS VIRTUAL",IF(EO4>EN4,"MAS PRESENCIAL","AMBOS")))) -> PRESENCIAL
B5: 2 | C5: ACHARTE CHAMPI WALTER JESUS | D5: =SUMIF('Planificación 2026-1'!W:W,C5,'Planificación 2026-1'!R:R) -> 0 | E5: TC | F5: RENOVACIÓN | G5: SEDE | H5: ENFERMERÍA | I5: =IF(SUM(COUNTIFS('Planificación 2026-1'!F:F,"PRINCIPAL",'Planificación 2026-1'!W:W,C5,'Planificación 2026-1'!H:H,"AF"))>0,"P01"," ") | J5: =IF(SUM(COUNTIFS('Planificación 2026-1'!F:F,"PRINCIPAL",'Planificación 2026-1'!W:W,C5,'Planificación 2026-1'!H:H,"EN"))>0,"P02"," ") | K5: =IF(SUM(COUNTIFS('Planificación 2026-1'!F:F,"PRINCIPAL",'Planificación 2026-1'!W:W,C5,'Planificación 2026-1'!H:H,"IS"))>0,"P03"," ") | L5: =IF(SUM(COUNTIFS('Planificación 2026-1'!F:F,"PRINCIPAL",'Planificación 2026-1'!W:W,C5,'Planificación 2026-1'!H:H,"PS"))>0,"P04"," ") | N5: =IF(SUM(COUNTIFS('Planificación 2026-1'!F:F,"PRINCIPAL",'Planificación 2026-1'!W:W,C5,'Planificación 2026-1'!H:H,"IN"))>0,"P06"," ") | O5: =IF(SUM(COUNTIFS('Planificación 2026-1'!F:F,"PRINCIPAL",'Planificación 2026-1'!W:W,C5,'Planificación 2026-1'!H:H,"CA"))>0,"P07"," ") | P5: =IF(SUM(COUNTIFS('Planificación 2026-1'!F:F,"PRINCIPAL",'Planificación 2026-1'!W:W,C5,'Planificación 2026-1'!H:H,"DE"))>0,"P08"," ") | Q5: =IF(SUM(COUNTIFS('Planificación 2026-1'!F:F,"PRINCIPAL",'Planificación 2026-1'!W:W,C5,'Planificación 2026-1'!H:H,"OB"))>0,"P09"," ") | R5: =IF(SUM(COUNTIFS('Planificación 2026-1'!F:F,"PRINCIPAL",'Planificación 2026-1'!W:W,C5,'Planificación 2026-1'!H:H,"MH"))>0,"P31"," ") | S5: =IF(SUM(COUNTIFS('Planificación 2026-1'!F:F,"PRINCIPAL",'Planificación 2026-1'!W:W,C5,'Planificación 2026-1'!H:H,"IC"))>0,"P32"," ") | T5: =IF(SUM(COUNTIFS('Planificación 2026-1'!F:F,"PRINCIPAL",'Planificación 2026-1'!W:W,C5,'Planificación 2026-1'!H:H,"AR"))>0,"P34"," ") | U5: =IF(SUM(COUNTIFS('Planificación 2026-1'!F:F,"PRINCIPAL",'Planificación 2026-1'!W:W,C5,'Planificación 2026-1'!H:H,"T1"))>0,"P35"," ") | V5: =IF(SUM(COUNTIFS('Planificación 2026-1'!F:F,"PRINCIPAL",'Planificación 2026-1'!W:W,C5,'Planificación 2026-1'!H:H,"T3"))>0,"P36"," ") | W5: =IF(SUM(COUNTIFS('Planificación 2026-1'!F:F,"PRINCIPAL",'Planificación 2026-1'!W:W,C5,'Planificación 2026-1'!H:H,"T2"))>0,"P37"," ") | X5: =IF(SUM(COUNTIFS('Planificación 2026-1'!F:F,"PRINCIPAL",'Planificación 2026-1'!W:W,C5,'Planificación 2026-1'!H:H,"AE"))>0,"P38"," ") | Y5: =IF(SUM(COUNTIFS('Planificación 2026-1'!F:F,"PRINCIPAL",'Planificación 2026-1'!W:W,C5,'Planificación 2026-1'!H:H,"T4"))>0,"P55"," ") | Z5: =IF(SUM(COUNTIFS('Planificación 2026-1'!F:F,"FILIAL",'Planificación 2026-1'!W:W,C5,'Planificación 2026-1'!H:H,"AF"))>0," P01"," ") | AA5: =IF(SUM(COUNTIFS('Planificación 2026-1'!F:F,"FILIAL",'Planificación 2026-1'!W:W,C5,'Planificación 2026-1'!H:H,"EN"))>0,"P02"," ") | AB5: =IF(SUM(COUNTIFS('Planificación 2026-1'!F:F,"FILIAL",'Planificación 2026-1'!W:W,C5,'Planificación 2026-1'!H:H,"IS"))>0,"P03"," ") | AC5: =IF(SUM(COUNTIFS('Planificación 2026-1'!F:F,"FILIAL",'Planificación 2026-1'!W:W,C5,'Planificación 2026-1'!H:H,"PS"))>0,"P04"," ") | AE5: =IF(SUM(COUNTIFS('Planificación 2026-1'!F:F,"FILIAL",'Planificación 2026-1'!W:W,C5,'Planificación 2026-1'!H:H,"IN"))>0,"P06"," ") | AF5: =IF(SUM(COUNTIFS('Planificación 2026-1'!F:F,"FILIAL",'Planificación 2026-1'!W:W,C5,'Planificación 2026-1'!H:H,"CA"))>0,"P07"," ") | AG5: =IF(SUM(COUNTIFS('Planificación 2026-1'!F:F,"FILIAL",'Planificación 2026-1'!W:W,C5,'Planificación 2026-1'!H:H,"DE"))>0,"P08"," ") | AH5: =IF(SUM(COUNTIFS('Planificación 2026-1'!F:F,"FILIAL",'Planificación 2026-1'!W:W,C5,'Planificación 2026-1'!H:H,"OB"))>0,"P09"," ") | AI5: =IF(SUM(COUNTIFS('Planificación 2026-1'!F:F,"FILIAL",'Planificación 2026-1'!W:W,C5,'Planificación 2026-1'!H:H,"MH"))>0,"P31"," ") | AJ5: =IF(SUM(COUNTIFS('Planificación 2026-1'!F:F,"FILIAL",'Planificación 2026-1'!W:W,C5,'Planificación 2026-1'!H:H,"IC"))>0,"P32"," ") | AK5: =IF(SUM(COUNTIFS('Planificación 2026-1'!F:F,"FILIAL",'Planificación 2026-1'!W:W,C5,'Planificación 2026-1'!H:H,"AR"))>0,"P34"," ") | AL5: =IF(SUM(COUNTIFS('Planificación 2026-1'!F:F,"FILIAL",'Planificación 2026-1'!W:W,C5,'Planificación 2026-1'!H:H,"T1"))>0,"P35"," ") | AM5: =IF(SUM(COUNTIFS('Planificación 2026-1'!F:F,"FILIAL",'Planificación 2026-1'!W:W,C5,'Planificación 2026-1'!H:H,"T3"))>0,"P36"," ") | AN5: =IF(SUM(COUNTIFS('Planificación 2026-1'!F:F,"FILIAL",'Planificación 2026-1'!W:W,C5,'Planificación 2026-1'!H:H,"T2"))>0,"P37"," ") | AO5: =IF(SUM(COUNTIFS('Planificación 2026-1'!F:F,"FILIAL",'Planificación 2026-1'!W:W,C5,'Planificación 2026-1'!H:H,"AE"))>0,"P38"," ") | AP5: =IF(SUM(COUNTIFS('Planificación 2026-1'!F:F,"FILIAL",'Planificación 2026-1'!W:W,C5,'Planificación 2026-1'!H:H,"T4"))>0,"P55"," ") | AQ5: =IF(SUM(COUNTIFS('Planificación 2026-1'!F:F,"SUNAMPE",'Planificación 2026-1'!W:W,C5,'Planificación 2026-1'!H:H,"AF"))>0," P01"," ") | AR5: =IF(SUM(COUNTIFS('Planificación 2026-1'!F:F,"SUNAMPE",'Planificación 2026-1'!W:W,C5,'Planificación 2026-1'!H:H,"EN"))>0,"P02"," ") | AS5: =IF(SUM(COUNTIFS('Planificación 2026-1'!F:F,"SUNAMPE",'Planificación 2026-1'!W:W,C5,'Planificación 2026-1'!H:H,"IS"))>0,"P03"," ") | AT5: =IF(SUM(COUNTIFS('Planificación 2026-1'!F:F,"SUNAMPE",'Planificación 2026-1'!W:W,C5,'Planificación 2026-1'!H:H,"PS"))>0,"P04"," ") | AV5: =IF(SUM(COUNTIFS('Planificación 2026-1'!F:F,"SUNAMPE",'Planificación 2026-1'!W:W,C5,'Planificación 2026-1'!H:H,"IN"))>0,"P06"," ") | AW5: =IF(SUM(COUNTIFS('Planificación 2026-1'!F:F,"SUNAMPE",'Planificación 2026-1'!W:W,C5,'Planificación 2026-1'!H:H,"CA"))>0,"P07"," ") | AX5: =IF(SUM(COUNTIFS('Planificación 2026-1'!F:F,"SUNAMPE",'Planificación 2026-1'!W:W,C5,'Planificación 2026-1'!H:H,"DE"))>0,"P08"," ") | AY5: =IF(SUM(COUNTIFS('Planificación 2026-1'!F:F,"SUNAMPE",'Planificación 2026-1'!W:W,C5,'Planificación 2026-1'!H:H,"OB"))>0,"P09"," ") | AZ5: =IF(SUM(COUNTIFS('Planificación 2026-1'!F:F,"SUNAMPE",'Planificación 2026-1'!W:W,C5,'Planificación 2026-1'!H:H,"MH"))>0,"P31"," ") | BA5: =IF(SUM(COUNTIFS('Planificación 2026-1'!F:F,"SUNAMPE",'Planificación 2026-1'!W:W,C5,'Planificación 2026-1'!H:H,"IC"))>0,"P32"," ") | BB5: =IF(SUM(COUNTIFS('Planificación 2026-1'!F:F,"SUNAMPE",'Planificación 2026-1'!W:W,C5,'Planificación 2026-1'!H:H,"AR"))>0,"P34"," ") | BC5: =IF(SUM(COUNTIFS('Planificación 2026-1'!F:F,"SUNAMPE",'Planificación 2026-1'!W:W,C5,'Planificación 2026-1'!H:H,"T1"))>0,"P35"," ") | BD5: =IF(SUM(COUNTIFS('Planificación 2026-1'!F:F,"SUNAMPE",'Planificación 2026-1'!W:W,C5,'Planificación 2026-1'!H:H,"T3"))>0,"P36"," ") | BE5: =IF(SUM(COUNTIFS('Planificación 2026-1'!F:F,"SUNAMPE",'Planificación 2026-1'!W:W,C5,'Planificación 2026-1'!H:H,"T2"))>0,"P37"," ") | BF5: =IF(SUM(COUNTIFS('Planificación 2026-1'!F:F,"SUNAMPE",'Planificación 2026-1'!W:W,C5,'Planificación 2026-1'!H:H,"AE"))>0,"P38"," ") | BG5: =IF(SUM(COUNTIFS('Planificación 2026-1'!F:F,"SUNAMPE",'Planificación 2026-1'!W:W,C5,'Planificación 2026-1'!H:H,"T4"))>0,"P55"," ") | BH5: =IF(SUM(COUNTIFS('Planificación 2026-1'!F:F,"HUAURA",'Planificación 2026-1'!W:W,C5,'Planificación 2026-1'!H:H,"AF"))>0," P01"," ") | BI5: =IF(SUM(COUNTIFS('Planificación 2026-1'!F:F,"HUAURA",'Planificación 2026-1'!W:W,C5,'Planificación 2026-1'!H:H,"EN"))>0,"P02"," ") | BJ5: =IF(SUM(COUNTIFS('Planificación 2026-1'!F:F,"HUAURA",'Planificación 2026-1'!W:W,C5,'Planificación 2026-1'!H:H,"IS"))>0,"P03"," ") | BK5: =IF(SUM(COUNTIFS('Planificación 2026-1'!F:F,"HUAURA",'Planificación 2026-1'!W:W,C5,'Planificación 2026-1'!H:H,"PS"))>0,"P04"," ") | BM5: =IF(SUM(COUNTIFS('Planificación 2026-1'!F:F,"HUAURA",'Planificación 2026-1'!W:W,C5,'Planificación 2026-1'!H:H,"IN"))>0,"P06"," ") | BN5: =IF(SUM(COUNTIFS('Planificación 2026-1'!F:F,"HUAURA",'Planificación 2026-1'!W:W,C5,'Planificación 2026-1'!H:H,"CA"))>0,"P07"," ") | BO5: =IF(SUM(COUNTIFS('Planificación 2026-1'!F:F,"HUAURA",'Planificación 2026-1'!W:W,C5,'Planificación 2026-1'!H:H,"DE"))>0,"P08"," ") | BP5: =IF(SUM(COUNTIFS('Planificación 2026-1'!F:F,"HUAURA",'Planificación 2026-1'!W:W,C5,'Planificación 2026-1'!H:H,"OB"))>0,"P09"," ") | BQ5: =IF(SUM(COUNTIFS('Planificación 2026-1'!F:F,"HUAURA",'Planificación 2026-1'!W:W,C5,'Planificación 2026-1'!H:H,"MH"))>0,"P31"," ") | BR5: =IF(SUM(COUNTIFS('Planificación 2026-1'!F:F,"HUAURA",'Planificación 2026-1'!W:W,C5,'Planificación 2026-1'!H:H,"IC"))>0,"P32"," ") | BS5: =IF(SUM(COUNTIFS('Planificación 2026-1'!F:F,"HUAURA",'Planificación 2026-1'!W:W,C5,'Planificación 2026-1'!H:H,"AR"))>0,"P34"," ") | BT5: =IF(SUM(COUNTIFS('Planificación 2026-1'!F:F,"HUAURA",'Planificación 2026-1'!W:W,C5,'Planificación 2026-1'!H:H,"T1"))>0,"P35"," ") | BU5: =IF(SUM(COUNTIFS('Planificación 2026-1'!F:F,"HUAURA",'Planificación 2026-1'!W:W,C5,'Planificación 2026-1'!H:H,"T3"))>0,"P36"," ") | BV5: =IF(SUM(COUNTIFS('Planificación 2026-1'!F:F,"HUAURA",'Planificación 2026-1'!W:W,C5,'Planificación 2026-1'!H:H,"T2"))>0,"P37"," ") | BW5: =IF(SUM(COUNTIFS('Planificación 2026-1'!F:F,"HUAURA",'Planificación 2026-1'!W:W,C5,'Planificación 2026-1'!H:H,"AE"))>0,"P38"," ") | BX5: =IF(SUM(COUNTIFS('Planificación 2026-1'!F:F,"HUAURA",'Planificación 2026-1'!W:W,C5,'Planificación 2026-1'!H:H,"T4"))>0,"P55"," ") | BY5: =SUMIFS('Planificación 2026-1'!R:R,'Planificación 2026-1'!W:W,C5,'Planificación 2026-1'!H:H,"AF",'Planificación 2026-1'!I:I,">2") -> 0 | BZ5: =SUMIFS('Planificación 2026-1'!R:R,'Planificación 2026-1'!W:W,C5,'Planificación 2026-1'!H:H,"EN",'Planificación 2026-1'!I:I,">2") -> 0 | CA5: =SUMIFS('Planificación 2026-1'!R:R,'Planificación 2026-1'!W:W,C5,'Planificación 2026-1'!H:H,"IS",'Planificación 2026-1'!I:I,">2") -> 0 | CB5: =SUMIFS('Planificación 2026-1'!R:R,'Planificación 2026-1'!W:W,C5,'Planificación 2026-1'!H:H,"PS",'Planificación 2026-1'!I:I,">2") -> 0 | CC5: =SUMIFS('Planificación 2026-1'!R:R,'Planificación 2026-1'!W:W,C5,'Planificación 2026-1'!H:H,"IN",'Planificación 2026-1'!I:I,">2") -> 0 | CD5: =SUMIFS('Planificación 2026-1'!R:R,'Planificación 2026-1'!W:W,C5,'Planificación 2026-1'!H:H,"CA",'Planificación 2026-1'!I:I,">2") -> 0 | CE5: =SUMIFS('Planificación 2026-1'!R:R,'Planificación 2026-1'!W:W,C5,'Planificación 2026-1'!H:H,"DE",'Planificación 2026-1'!I:I,">2") -> 0 | CF5: =SUMIFS('Planificación 2026-1'!R:R,'Planificación 2026-1'!W:W,C5,'Planificación 2026-1'!H:H,"OB",'Planificación 2026-1'!I:I,">2") -> 0 | CG5: =SUMIFS('Planificación 2026-1'!R:R,'Planificación 2026-1'!W:W,C5,'Planificación 2026-1'!H:H,"MH",'Planificación 2026-1'!I:I,">2") -> 0 | CH5: =SUMIFS('Planificación 2026-1'!R:R,'Planificación 2026-1'!W:W,C5,'Planificación 2026-1'!H:H,"IC",'Planificación 2026-1'!I:I,">2") -> 0 | CI5: =SUMIFS('Planificación 2026-1'!R:R,'Planificación 2026-1'!W:W,C5,'Planificación 2026-1'!H:H,"AR",'Planificación 2026-1'!I:I,">2") -> 0 | CJ5: =SUMIFS('Planificación 2026-1'!R:R,'Planificación 2026-1'!W:W,C5,'Planificación 2026-1'!H:H,"T1",'Planificación 2026-1'!I:I,">2") -> 0 | CK5: =SUMIFS('Planificación 2026-1'!R:R,'Planificación 2026-1'!W:W,C5,'Planificación 2026-1'!H:H,"T3",'Planificación 2026-1'!I:I,">2") -> 0 | CL5: =SUMIFS('Planificación 2026-1'!R:R,'Planificación 2026-1'!W:W,C5,'Planificación 2026-1'!H:H,"T2",'Planificación 2026-1'!I:I,">2") -> 0 | CM5: =SUMIFS('Planificación 2026-1'!R:R,'Planificación 2026-1'!W:W,C5,'Planificación 2026-1'!H:H,"AE",'Planificación 2026-1'!I:I,">2") -> 0 | CN5: =SUMIFS('Planificación 2026-1'!R:R,'Planificación 2026-1'!W:W,C5,'Planificación 2026-1'!H:H,"T4",'Planificación 2026-1'!I:I,">2") -> 0 | CO5: =SUMIFS('Planificación 2026-1'!R:R,'Planificación 2026-1'!W:W,C5,'Planificación 2026-1'!H:H,"AF",'Planificación 2026-1'!I:I,"<3") -> 0 | CP5: =SUMIFS('Planificación 2026-1'!R:R,'Planificación 2026-1'!W:W,C5,'Planificación 2026-1'!H:H,"EN",'Planificación 2026-1'!I:I,"<3") -> 0 | CQ5: =SUMIFS('Planificación 2026-1'!R:R,'Planificación 2026-1'!W:W,C5,'Planificación 2026-1'!H:H,"IS",'Planificación 2026-1'!I:I,"<3") -> 0 | CR5: =SUMIFS('Planificación 2026-1'!R:R,'Planificación 2026-1'!W:W,C5,'Planificación 2026-1'!H:H,"PS",'Planificación 2026-1'!I:I,"<3") -> 0 | CS5: =SUMIFS('Planificación 2026-1'!R:R,'Planificación 2026-1'!W:W,C5,'Planificación 2026-1'!H:H,"IN",'Planificación 2026-1'!I:I,"<3") -> 0 | CT5: =SUMIFS('Planificación 2026-1'!R:R,'Planificación 2026-1'!W:W,C5,'Planificación 2026-1'!H:H,"CA",'Planificación 2026-1'!I:I,"<3") -> 0 | CU5: =SUMIFS('Planificación 2026-1'!R:R,'Planificación 2026-1'!W:W,C5,'Planificación 2026-1'!H:H,"DE",'Planificación 2026-1'!I:I,"<3") -> 0 | CV5: =SUMIFS('Planificación 2026-1'!R:R,'Planificación 2026-1'!W:W,C5,'Planificación 2026-1'!H:H,"OB",'Planificación 2026-1'!I:I,"<3") -> 0 | CW5: =SUMIFS('Planificación 2026-1'!R:R,'Planificación 2026-1'!W:W,C5,'Planificación 2026-1'!H:H,"MH",'Planificación 2026-1'!I:I,"<3") -> 0 | CX5: =SUMIFS('Planificación 2026-1'!R:R,'Planificación 2026-1'!W:W,C5,'Planificación 2026-1'!H:H,"IC",'Planificación 2026-1'!I:I,"<3") -> 0 | CY5: =SUMIFS('Planificación 2026-1'!R:R,'Planificación 2026-1'!W:W,C5,'Planificación 2026-1'!H:H,"AR",'Planificación 2026-1'!I:I,"<3") -> 0 | CZ5: =SUMIFS('Planificación 2026-1'!R:R,'Planificación 2026-1'!W:W,C5,'Planificación 2026-1'!H:H,"T1",'Planificación 2026-1'!I:I,"<3") -> 0 | DA5: =SUMIFS('Planificación 2026-1'!R:R,'Planificación 2026-1'!W:W,C5,'Planificación 2026-1'!H:H,"T3",'Planificación 2026-1'!I:I,"<3") -> 0 | DB5: =SUMIFS('Planificación 2026-1'!R:R,'Planificación 2026-1'!W:W,C5,'Planificación 2026-1'!H:H,"T2",'Planificación 2026-1'!I:I,"<3") -> 0 | DC5: =SUMIFS('Planificación 2026-1'!R:R,'Planificación 2026-1'!W:W,C5,'Planificación 2026-1'!H:H,"AE",'Planificación 2026-1'!I:I,"<3") -> 0 | DD5: =SUMIFS('Planificación 2026-1'!R:R,'Planificación 2026-1'!W:W,C5,'Planificación 2026-1'!H:H,"T4",'Planificación 2026-1'!I:I,"<3") -> 0 | DE5: =TRIM(CONCATENATE(I5,J5,K5,L5,M5,N5,O5,P5,Q5,R5,S5,T5,U5,V5,W5,X5,Y5)) | DF5: =IF(C5="","",SUMIFS('Planificación 2026-1'!R:R,'Planificación 2026-1'!W:W,C5,'Planificación 2026-1'!F:F,"PRINCIPAL",'Planificación 2026-1'!X:X,"VIRTUAL")) -> 0 | DG5: =IF(C5="","",SUMIFS('Planificación 2026-1'!R:R,'Planificación 2026-1'!W:W,C5,'Planificación 2026-1'!F:F,"PRINCIPAL",'Planificación 2026-1'!X:X,"PRESENCIAL")) -> 0 | DH5: =IF(C5="","",SUMIFS('Planificación 2026-1'!R:R,'Planificación 2026-1'!W:W,C5,'Planificación 2026-1'!F:F,"PRINCIPAL",'Planificación 2026-1'!X:X,"HIBRIDO PRESENCIAL")) -> 0 | DI5: =TRIM(CONCATENATE(Z5,AA5,AB5,AC5,AD5,AE5,AF5,AG5,AH5,AI5,AJ5,AK5,AL5,AM5,AN5,AO5,AP5)) | DJ5: =IF(C5="","",SUMIFS('Planificación 2026-1'!R:R,'Planificación 2026-1'!W:W,C5,'Planificación 2026-1'!F:F,"FILIAL",'Planificación 2026-1'!X:X,"VIRTUAL")) -> 0 | DK5: =IF(C5="","",SUMIFS('Planificación 2026-1'!R:R,'Planificación 2026-1'!W:W,C5,'Planificación 2026-1'!F:F,"FILIAL",'Planificación 2026-1'!X:X,"PRESENCIAL")) -> 0 | DL5: =IF(C5="","",SUMIFS('Planificación 2026-1'!R:R,'Planificación 2026-1'!W:W,C5,'Planificación 2026-1'!F:F,"FILIAL",'Planificación 2026-1'!X:X,"HIBRIDO PRESENCIAL")) -> 0 | DM5: =TRIM(CONCATENATE(AQ5,AR5,AS5,AT5,AU5,AV5,AW5,AX5,AY5,AZ5,BA5,BB5,BC5,BD5,BE5,BF5,BG5)) | DN5: =IF(C5="","",SUMIFS('Planificación 2026-1'!R:R,'Planificación 2026-1'!W:W,C5,'Planificación 2026-1'!F:F,"SUNAMPE",'Planificación 2026-1'!X:X,"VIRTUAL")) -> 0 | DO5: =IF(C5="","",SUMIFS('Planificación 2026-1'!R:R,'Planificación 2026-1'!W:W,C5,'Planificación 2026-1'!F:F,"SUNAMPE",'Planificación 2026-1'!X:X,"PRESENCIAL")) -> 0 | DP5: =TRIM(CONCATENATE(BH5,BI5,BJ5,BK5,BL5,BM5,BN5,BO5,BP5,BQ5,BR5,BS5,BT5,BU5,BV5,BW5,BX5)) | DQ5: =IF(C5="","",SUMIFS('Planificación 2026-1'!R:R,'Planificación 2026-1'!W:W,C5,'Planificación 2026-1'!F:F,"HUAURA",'Planificación 2026-1'!X:X,"VIRTUAL")) -> 0 | DR5: =IF(C5="","",SUMIFS('Planificación 2026-1'!R:R,'Planificación 2026-1'!W:W,C5,'Planificación 2026-1'!F:F,"HUAURA",'Planificación 2026-1'!X:X,"PRESENCIAL")) -> 0 | DS5: =SUMIFS('Planificación 2026-1'!R:R,'Planificación 2026-1'!W:W,C5,'Planificación 2026-1'!F:F,"PRINCIPAL",'Planificación 2026-1'!X:X,"VIRTUAL",'Planificación 2026-1'!I:I,">2") -> 0 | DT5: =SUMIFS('Planificación 2026-1'!R:R,'Planificación 2026-1'!W:W,C5,'Planificación 2026-1'!F:F,"PRINCIPAL",'Planificación 2026-1'!X:X,"<>VIRTUAL",'Planificación 2026-1'!I:I,">2") -> 0 | DU5: =SUMIFS('Planificación 2026-1'!R:R,'Planificación 2026-1'!W:W,C5,'Planificación 2026-1'!F:F,"SUNAMPE",'Planificación 2026-1'!X:X,"VIRTUAL",'Planificación 2026-1'!I:I,">2") -> 0 | DV5: =SUMIFS('Planificación 2026-1'!R:R,'Planificación 2026-1'!W:W,C5,'Planificación 2026-1'!F:F,"SUNAMPE",'Planificación 2026-1'!X:X,"<>VIRTUAL",'Planificación 2026-1'!I:I,">2") -> 0 | DW5: =SUMIFS('Planificación 2026-1'!R:R,'Planificación 2026-1'!W:W,C5,'Planificación 2026-1'!F:F,"FILIAL",'Planificación 2026-1'!X:X,"VIRTUAL",'Planificación 2026-1'!I:I,">2") -> 0 | DX5: =SUMIFS('Planificación 2026-1'!R:R,'Planificación 2026-1'!W:W,C5,'Planificación 2026-1'!F:F,"FILIAL",'Planificación 2026-1'!X:X,"<>VIRTUAL",'Planificación 2026-1'!I:I,">2") -> 0 | DY5: =SUMIFS('Planificación 2026-1'!R:R,'Planificación 2026-1'!W:W,C5,'Planificación 2026-1'!F:F,"PORUMA",'Planificación 2026-1'!X:X,"VIRTUAL",'Planificación 2026-1'!I:I,">2") -> 0 | DZ5: =SUMIFS('Planificación 2026-1'!R:R,'Planificación 2026-1'!W:W,C5,'Planificación 2026-1'!F:F,"PORUMA",'Planificación 2026-1'!X:X,"<>VIRTUAL",'Planificación 2026-1'!I:I,">2") -> 0 | EA5: =SUMIFS('Planificación 2026-1'!R:R,'Planificación 2026-1'!W:W,C5,'Planificación 2026-1'!F:F,"HUAURA",'Planificación 2026-1'!X:X,"VIRTUAL",'Planificación 2026-1'!I:I,">2") -> 0 | EB5: =SUMIFS('Planificación 2026-1'!R:R,'Planificación 2026-1'!W:W,C5,'Planificación 2026-1'!F:F,"HUAURA",'Planificación 2026-1'!X:X,"<>VIRTUAL",'Planificación 2026-1'!I:I,">2") -> 0 | EC5: =SUMIFS('Planificación 2026-1'!R:R,'Planificación 2026-1'!W:W,C5,'Planificación 2026-1'!F:F,"PRINCIPAL",'Planificación 2026-1'!X:X,"VIRTUAL",'Planificación 2026-1'!I:I,"<3") -> 0 | ED5: =SUMIFS('Planificación 2026-1'!R:R,'Planificación 2026-1'!W:W,C5,'Planificación 2026-1'!F:F,"PRINCIPAL",'Planificación 2026-1'!X:X,"<>VIRTUAL",'Planificación 2026-1'!I:I,"<3") -> 0 | EE5: =SUMIFS('Planificación 2026-1'!R:R,'Planificación 2026-1'!W:W,C5,'Planificación 2026-1'!F:F,"SUNAMPE",'Planificación 2026-1'!X:X,"VIRTUAL",'Planificación 2026-1'!I:I,"<3") -> 0 | EF5: =SUMIFS('Planificación 2026-1'!R:R,'Planificación 2026-1'!W:W,C5,'Planificación 2026-1'!F:F,"SUNAMPE",'Planificación 2026-1'!X:X,"<>VIRTUAL",'Planificación 2026-1'!I:I,"<3") -> 0 | EG5: =SUMIFS('Planificación 2026-1'!R:R,'Planificación 2026-1'!W:W,C5,'Planificación 2026-1'!F:F,"FILIAL",'Planificación 2026-1'!X:X,"VIRTUAL",'Planificación 2026-1'!I:I,"<3") -> 0 | EH5: =SUMIFS('Planificación 2026-1'!R:R,'Planificación 2026-1'!W:W,C5,'Planificación 2026-1'!F:F,"FILIAL",'Planificación 2026-1'!X:X,"<>VIRTUAL",'Planificación 2026-1'!I:I,"<3") -> 0 | EI5: =SUMIFS('Planificación 2026-1'!R:R,'Planificación 2026-1'!W:W,C5,'Planificación 2026-1'!F:F,"PORUMA",'Planificación 2026-1'!X:X,"VIRTUAL",'Planificación 2026-1'!I:I,"<3") -> 0 | EJ5: =SUMIFS('Planificación 2026-1'!R:R,'Planificación 2026-1'!W:W,C5,'Planificación 2026-1'!F:F,"PORUMA",'Planificación 2026-1'!X:X,"<>VIRTUAL",'Planificación 2026-1'!I:I,"<3") -> 0 | EK5: =SUMIFS('Planificación 2026-1'!R:R,'Planificación 2026-1'!W:W,C5,'Planificación 2026-1'!F:F,"HUAURA",'Planificación 2026-1'!X:X,"VIRTUAL",'Planificación 2026-1'!I:I,"<3") -> 0 | EL5: =SUMIFS('Planificación 2026-1'!R:R,'Planificación 2026-1'!W:W,C5,'Planificación 2026-1'!F:F,"HUAURA",'Planificación 2026-1'!X:X,"<>VIRTUAL",'Planificación 2026-1'!I:I,"<3") -> 0 | EN5: =DS5+DW5+EA5+EC5+EG5+EK5+DU5+EE5 -> 0 | EO5: =DT5+DX5+EB5+ED5+EH5+EL5+DV5+EF5 -> 0 | EP5: =EXACT(SUM(EN5:EO5),D5) -> TRUE | EQ5: =IF(AND(DT5=0,DX5=0,EB5=0),"",IF(COUNTIF(DT5:EB5,">0")=1,IF(DT5>0,"SEDE",IF(DX5>0,"FILIAL","HUAURA")),IF(COUNTIF(DT5:EB5,">0")=2,IF(AND(DT5>0,DX5>0),"SEDE-FILIAL",IF(AND(DT5>0,EB5>0),"SEDE-HUAURA","FILIAL-HUAURA")),"SEDE-FILIAL-HUAURA"))) | ER5: =IF(EN5=0,"PRESENCIAL",IF(EO5=0,"VIRTUAL",IF(EN5>EO5,"MAS VIRTUAL",IF(EO5>EN5,"MAS PRESENCIAL","AMBOS")))) -> PRESENCIAL
B6: 3 | C6: ACOSTA VILLAVICENCIO BLANCA AURORA | D6: =SUMIF('Planificación 2026-1'!W:W,C6,'Planificación 2026-1'!R:R) -> 0 | E6: TC | F6: RENOVACIÓN | G6: SEDE | H6: PSICOLOGÍA - EEGG | I6: =IF(SUM(COUNTIFS('Planificación 2026-1'!F:F,"PRINCIPAL",'Planificación 2026-1'!W:W,C6,'Planificación 2026-1'!H:H,"AF"))>0,"P01"," ") | J6: =IF(SUM(COUNTIFS('Planificación 2026-1'!F:F,"PRINCIPAL",'Planificación 2026-1'!W:W,C6,'Planificación 2026-1'!H:H,"EN"))>0,"P02"," ") | K6: =IF(SUM(COUNTIFS('Planificación 2026-1'!F:F,"PRINCIPAL",'Planificación 2026-1'!W:W,C6,'Planificación 2026-1'!H:H,"IS"))>0,"P03"," ") | L6: =IF(SUM(COUNTIFS('Planificación 2026-1'!F:F,"PRINCIPAL",'Planificación 2026-1'!W:W,C6,'Planificación 2026-1'!H:H,"PS"))>0,"P04"," ") | N6: =IF(SUM(COUNTIFS('Planificación 2026-1'!F:F,"PRINCIPAL",'Planificación 2026-1'!W:W,C6,'Planificación 2026-1'!H:H,"IN"))>0,"P06"," ") | O6: =IF(SUM(COUNTIFS('Planificación 2026-1'!F:F,"PRINCIPAL",'Planificación 2026-1'!W:W,C6,'Planificación 2026-1'!H:H,"CA"))>0,"P07"," ") | P6: =IF(SUM(COUNTIFS('Planificación 2026-1'!F:F,"PRINCIPAL",'Planificación 2026-1'!W:W,C6,'Planificación 2026-1'!H:H,"DE"))>0,"P08"," ") | Q6: =IF(SUM(COUNTIFS('Planificación 2026-1'!F:F,"PRINCIPAL",'Planificación 2026-1'!W:W,C6,'Planificación 2026-1'!H:H,"OB"))>0,"P09"," ") | R6: =IF(SUM(COUNTIFS('Planificación 2026-1'!F:F,"PRINCIPAL",'Planificación 2026-1'!W:W,C6,'Planificación 2026-1'!H:H,"MH"))>0,"P31"," ") | S6: =IF(SUM(COUNTIFS('Planificación 2026-1'!F:F,"PRINCIPAL",'Planificación 2026-1'!W:W,C6,'Planificación 2026-1'!H:H,"IC"))>0,"P32"," ") | T6: =IF(SUM(COUNTIFS('Planificación 2026-1'!F:F,"PRINCIPAL",'Planificación 2026-1'!W:W,C6,'Planificación 2026-1'!H:H,"AR"))>0,"P34"," ") | U6: =IF(SUM(COUNTIFS('Planificación 2026-1'!F:F,"PRINCIPAL",'Planificación 2026-1'!W:W,C6,'Planificación 2026-1'!H:H,"T1"))>0,"P35"," ") | V6: =IF(SUM(COUNTIFS('Planificación 2026-1'!F:F,"PRINCIPAL",'Planificación 2026-1'!W:W,C6,'Planificación 2026-1'!H:H,"T3"))>0,"P36"," ") | W6: =IF(SUM(COUNTIFS('Planificación 2026-1'!F:F,"PRINCIPAL",'Planificación 2026-1'!W:W,C6,'Planificación 2026-1'!H:H,"T2"))>0,"P37"," ") | X6: =IF(SUM(COUNTIFS('Planificación 2026-1'!F:F,"PRINCIPAL",'Planificación 2026-1'!W:W,C6,'Planificación 2026-1'!H:H,"AE"))>0,"P38"," ") | Y6: =IF(SUM(COUNTIFS('Planificación 2026-1'!F:F,"PRINCIPAL",'Planificación 2026-1'!W:W,C6,'Planificación 2026-1'!H:H,"T4"))>0,"P55"," ") | Z6: =IF(SUM(COUNTIFS('Planificación 2026-1'!F:F,"FILIAL",'Planificación 2026-1'!W:W,C6,'Planificación 2026-1'!H:H,"AF"))>0," P01"," ") | AA6: =IF(SUM(COUNTIFS('Planificación 2026-1'!F:F,"FILIAL",'Planificación 2026-1'!W:W,C6,'Planificación 2026-1'!H:H,"EN"))>0,"P02"," ") | AB6: =IF(SUM(COUNTIFS('Planificación 2026-1'!F:F,"FILIAL",'Planificación 2026-1'!W:W,C6,'Planificación 2026-1'!H:H,"IS"))>0,"P03"," ") | AC6: =IF(SUM(COUNTIFS('Planificación 2026-1'!F:F,"FILIAL",'Planificación 2026-1'!W:W,C6,'Planificación 2026-1'!H:H,"PS"))>0,"P04"," ") | AE6: =IF(SUM(COUNTIFS('Planificación 2026-1'!F:F,"FILIAL",'Planificación 2026-1'!W:W,C6,'Planificación 2026-1'!H:H,"IN"))>0,"P06"," ") | AF6: =IF(SUM(COUNTIFS('Planificación 2026-1'!F:F,"FILIAL",'Planificación 2026-1'!W:W,C6,'Planificación 2026-1'!H:H,"CA"))>0,"P07"," ") | AG6: =IF(SUM(COUNTIFS('Planificación 2026-1'!F:F,"FILIAL",'Planificación 2026-1'!W:W,C6,'Planificación 2026-1'!H:H,"DE"))>0,"P08"," ") | AH6: =IF(SUM(COUNTIFS('Planificación 2026-1'!F:F,"FILIAL",'Planificación 2026-1'!W:W,C6,'Planificación 2026-1'!H:H,"OB"))>0,"P09"," ") | AI6: =IF(SUM(COUNTIFS('Planificación 2026-1'!F:F,"FILIAL",'Planificación 2026-1'!W:W,C6,'Planificación 2026-1'!H:H,"MH"))>0,"P31"," ") | AJ6: =IF(SUM(COUNTIFS('Planificación 2026-1'!F:F,"FILIAL",'Planificación 2026-1'!W:W,C6,'Planificación 2026-1'!H:H,"IC"))>0,"P32"," ") | AK6: =IF(SUM(COUNTIFS('Planificación 2026-1'!F:F,"FILIAL",'Planificación 2026-1'!W:W,C6,'Planificación 2026-1'!H:H,"AR"))>0,"P34"," ") | AL6: =IF(SUM(COUNTIFS('Planificación 2026-1'!F:F,"FILIAL",'Planificación 2026-1'!W:W,C6,'Planificación 2026-1'!H:H,"T1"))>0,"P35"," ") | AM6: =IF(SUM(COUNTIFS('Planificación 2026-1'!F:F,"FILIAL",'Planificación 2026-1'!W:W,C6,'Planificación 2026-1'!H:H,"T3"))>0,"P36"," ") | AN6: =IF(SUM(COUNTIFS('Planificación 2026-1'!F:F,"FILIAL",'Planificación 2026-1'!W:W,C6,'Planificación 2026-1'!H:H,"T2"))>0,"P37"," ") | AO6: =IF(SUM(COUNTIFS('Planificación 2026-1'!F:F,"FILIAL",'Planificación 2026-1'!W:W,C6,'Planificación 2026-1'!H:H,"AE"))>0,"P38"," ") | AP6: =IF(SUM(COUNTIFS('Planificación 2026-1'!F:F,"FILIAL",'Planificación 2026-1'!W:W,C6,'Planificación 2026-1'!H:H,"T4"))>0,"P55"," ") | AQ6: =IF(SUM(COUNTIFS('Planificación 2026-1'!F:F,"SUNAMPE",'Planificación 2026-1'!W:W,C6,'Planificación 2026-1'!H:H,"AF"))>0," P01"," ") | AR6: =IF(SUM(COUNTIFS('Planificación 2026-1'!F:F,"SUNAMPE",'Planificación 2026-1'!W:W,C6,'Planificación 2026-1'!H:H,"EN"))>0,"P02"," ") | AS6: =IF(SUM(COUNTIFS('Planificación 2026-1'!F:F,"SUNAMPE",'Planificación 2026-1'!W:W,C6,'Planificación 2026-1'!H:H,"IS"))>0,"P03"," ") | AT6: =IF(SUM(COUNTIFS('Planificación 2026-1'!F:F,"SUNAMPE",'Planificación 2026-1'!W:W,C6,'Planificación 2026-1'!H:H,"PS"))>0,"P04"," ") | AV6: =IF(SUM(COUNTIFS('Planificación 2026-1'!F:F,"SUNAMPE",'Planificación 2026-1'!W:W,C6,'Planificación 2026-1'!H:H,"IN"))>0,"P06"," ") | AW6: =IF(SUM(COUNTIFS('Planificación 2026-1'!F:F,"SUNAMPE",'Planificación 2026-1'!W:W,C6,'Planificación 2026-1'!H:H,"CA"))>0,"P07"," ") | AX6: =IF(SUM(COUNTIFS('Planificación 2026-1'!F:F,"SUNAMPE",'Planificación 2026-1'!W:W,C6,'Planificación 2026-1'!H:H,"DE"))>0,"P08"," ") | AY6: =IF(SUM(COUNTIFS('Planificación 2026-1'!F:F,"SUNAMPE",'Planificación 2026-1'!W:W,C6,'Planificación 2026-1'!H:H,"OB"))>0,"P09"," ") | AZ6: =IF(SUM(COUNTIFS('Planificación 2026-1'!F:F,"SUNAMPE",'Planificación 2026-1'!W:W,C6,'Planificación 2026-1'!H:H,"MH"))>0,"P31"," ") | BA6: =IF(SUM(COUNTIFS('Planificación 2026-1'!F:F,"SUNAMPE",'Planificación 2026-1'!W:W,C6,'Planificación 2026-1'!H:H,"IC"))>0,"P32"," ") | BB6: =IF(SUM(COUNTIFS('Planificación 2026-1'!F:F,"SUNAMPE",'Planificación 2026-1'!W:W,C6,'Planificación 2026-1'!H:H,"AR"))>0,"P34"," ") | BC6: =IF(SUM(COUNTIFS('Planificación 2026-1'!F:F,"SUNAMPE",'Planificación 2026-1'!W:W,C6,'Planificación 2026-1'!H:H,"T1"))>0,"P35"," ") | BD6: =IF(SUM(COUNTIFS('Planificación 2026-1'!F:F,"SUNAMPE",'Planificación 2026-1'!W:W,C6,'Planificación 2026-1'!H:H,"T3"))>0,"P36"," ") | BE6: =IF(SUM(COUNTIFS('Planificación 2026-1'!F:F,"SUNAMPE",'Planificación 2026-1'!W:W,C6,'Planificación 2026-1'!H:H,"T2"))>0,"P37"," ") | BF6: =IF(SUM(COUNTIFS('Planificación 2026-1'!F:F,"SUNAMPE",'Planificación 2026-1'!W:W,C6,'Planificación 2026-1'!H:H,"AE"))>0,"P38"," ") | BG6: =IF(SUM(COUNTIFS('Planificación 2026-1'!F:F,"SUNAMPE",'Planificación 2026-1'!W:W,C6,'Planificación 2026-1'!H:H,"T4"))>0,"P55"," ") | BH6: =IF(SUM(COUNTIFS('Planificación 2026-1'!F:F,"HUAURA",'Planificación 2026-1'!W:W,C6,'Planificación 2026-1'!H:H,"AF"))>0," P01"," ") | BI6: =IF(SUM(COUNTIFS('Planificación 2026-1'!F:F,"HUAURA",'Planificación 2026-1'!W:W,C6,'Planificación 2026-1'!H:H,"EN"))>0,"P02"," ") | BJ6: =IF(SUM(COUNTIFS('Planificación 2026-1'!F:F,"HUAURA",'Planificación 2026-1'!W:W,C6,'Planificación 2026-1'!H:H,"IS"))>0,"P03"," ") | BK6: =IF(SUM(COUNTIFS('Planificación 2026-1'!F:F,"HUAURA",'Planificación 2026-1'!W:W,C6,'Planificación 2026-1'!H:H,"PS"))>0,"P04"," ") | BM6: =IF(SUM(COUNTIFS('Planificación 2026-1'!F:F,"HUAURA",'Planificación 2026-1'!W:W,C6,'Planificación 2026-1'!H:H,"IN"))>0,"P06"," ") | BN6: =IF(SUM(COUNTIFS('Planificación 2026-1'!F:F,"HUAURA",'Planificación 2026-1'!W:W,C6,'Planificación 2026-1'!H:H,"CA"))>0,"P07"," ") | BO6: =IF(SUM(COUNTIFS('Planificación 2026-1'!F:F,"HUAURA",'Planificación 2026-1'!W:W,C6,'Planificación 2026-1'!H:H,"DE"))>0,"P08"," ") | BP6: =IF(SUM(COUNTIFS('Planificación 2026-1'!F:F,"HUAURA",'Planificación 2026-1'!W:W,C6,'Planificación 2026-1'!H:H,"OB"))>0,"P09"," ") | BQ6: =IF(SUM(COUNTIFS('Planificación 2026-1'!F:F,"HUAURA",'Planificación 2026-1'!W:W,C6,'Planificación 2026-1'!H:H,"MH"))>0,"P31"," ") | BR6: =IF(SUM(COUNTIFS('Planificación 2026-1'!F:F,"HUAURA",'Planificación 2026-1'!W:W,C6,'Planificación 2026-1'!H:H,"IC"))>0,"P32"," ") | BS6: =IF(SUM(COUNTIFS('Planificación 2026-1'!F:F,"HUAURA",'Planificación 2026-1'!W:W,C6,'Planificación 2026-1'!H:H,"AR"))>0,"P34"," ") | BT6: =IF(SUM(COUNTIFS('Planificación 2026-1'!F:F,"HUAURA",'Planificación 2026-1'!W:W,C6,'Planificación 2026-1'!H:H,"T1"))>0,"P35"," ") | BU6: =IF(SUM(COUNTIFS('Planificación 2026-1'!F:F,"HUAURA",'Planificación 2026-1'!W:W,C6,'Planificación 2026-1'!H:H,"T3"))>0,"P36"," ") | BV6: =IF(SUM(COUNTIFS('Planificación 2026-1'!F:F,"HUAURA",'Planificación 2026-1'!W:W,C6,'Planificación 2026-1'!H:H,"T2"))>0,"P37"," ") | BW6: =IF(SUM(COUNTIFS('Planificación 2026-1'!F:F,"HUAURA",'Planificación 2026-1'!W:W,C6,'Planificación 2026-1'!H:H,"AE"))>0,"P38"," ") | BX6: =IF(SUM(COUNTIFS('Planificación 2026-1'!F:F,"HUAURA",'Planificación 2026-1'!W:W,C6,'Planificación 2026-1'!H:H,"T4"))>0,"P55"," ") | BY6: =SUMIFS('Planificación 2026-1'!R:R,'Planificación 2026-1'!W:W,C6,'Planificación 2026-1'!H:H,"AF",'Planificación 2026-1'!I:I,">2") -> 0 | BZ6: =SUMIFS('Planificación 2026-1'!R:R,'Planificación 2026-1'!W:W,C6,'Planificación 2026-1'!H:H,"EN",'Planificación 2026-1'!I:I,">2") -> 0 | CA6: =SUMIFS('Planificación 2026-1'!R:R,'Planificación 2026-1'!W:W,C6,'Planificación 2026-1'!H:H,"IS",'Planificación 2026-1'!I:I,">2") -> 0 | CB6: =SUMIFS('Planificación 2026-1'!R:R,'Planificación 2026-1'!W:W,C6,'Planificación 2026-1'!H:H,"PS",'Planificación 2026-1'!I:I,">2") -> 0 | CC6: =SUMIFS('Planificación 2026-1'!R:R,'Planificación 2026-1'!W:W,C6,'Planificación 2026-1'!H:H,"IN",'Planificación 2026-1'!I:I,">2") -> 0 | CD6: =SUMIFS('Planificación 2026-1'!R:R,'Planificación 2026-1'!W:W,C6,'Planificación 2026-1'!H:H,"CA",'Planificación 2026-1'!I:I,">2") -> 0 | CE6: =SUMIFS('Planificación 2026-1'!R:R,'Planificación 2026-1'!W:W,C6,'Planificación 2026-1'!H:H,"DE",'Planificación 2026-1'!I:I,">2") -> 0 | CF6: =SUMIFS('Planificación 2026-1'!R:R,'Planificación 2026-1'!W:W,C6,'Planificación 2026-1'!H:H,"OB",'Planificación 2026-1'!I:I,">2") -> 0 | CG6: =SUMIFS('Planificación 2026-1'!R:R,'Planificación 2026-1'!W:W,C6,'Planificación 2026-1'!H:H,"MH",'Planificación 2026-1'!I:I,">2") -> 0 | CH6: =SUMIFS('Planificación 2026-1'!R:R,'Planificación 2026-1'!W:W,C6,'Planificación 2026-1'!H:H,"IC",'Planificación 2026-1'!I:I,">2") -> 0 | CI6: =SUMIFS('Planificación 2026-1'!R:R,'Planificación 2026-1'!W:W,C6,'Planificación 2026-1'!H:H,"AR",'Planificación 2026-1'!I:I,">2") -> 0 | CJ6: =SUMIFS('Planificación 2026-1'!R:R,'Planificación 2026-1'!W:W,C6,'Planificación 2026-1'!H:H,"T1",'Planificación 2026-1'!I:I,">2") -> 0 | CK6: =SUMIFS('Planificación 2026-1'!R:R,'Planificación 2026-1'!W:W,C6,'Planificación 2026-1'!H:H,"T3",'Planificación 2026-1'!I:I,">2") -> 0 | CL6: =SUMIFS('Planificación 2026-1'!R:R,'Planificación 2026-1'!W:W,C6,'Planificación 2026-1'!H:H,"T2",'Planificación 2026-1'!I:I,">2") -> 0 | CM6: =SUMIFS('Planificación 2026-1'!R:R,'Planificación 2026-1'!W:W,C6,'Planificación 2026-1'!H:H,"AE",'Planificación 2026-1'!I:I,">2") -> 0 | CN6: =SUMIFS('Planificación 2026-1'!R:R,'Planificación 2026-1'!W:W,C6,'Planificación 2026-1'!H:H,"T4",'Planificación 2026-1'!I:I,">2") -> 0 | CO6: =SUMIFS('Planificación 2026-1'!R:R,'Planificación 2026-1'!W:W,C6,'Planificación 2026-1'!H:H,"AF",'Planificación 2026-1'!I:I,"<3") -> 0 | CP6: =SUMIFS('Planificación 2026-1'!R:R,'Planificación 2026-1'!W:W,C6,'Planificación 2026-1'!H:H,"EN",'Planificación 2026-1'!I:I,"<3") -> 0 | CQ6: =SUMIFS('Planificación 2026-1'!R:R,'Planificación 2026-1'!W:W,C6,'Planificación 2026-1'!H:H,"IS",'Planificación 2026-1'!I:I,"<3") -> 0 | CR6: =SUMIFS('Planificación 2026-1'!R:R,'Planificación 2026-1'!W:W,C6,'Planificación 2026-1'!H:H,"PS",'Planificación 2026-1'!I:I,"<3") -> 0 | CS6: =SUMIFS('Planificación 2026-1'!R:R,'Planificación 2026-1'!W:W,C6,'Planificación 2026-1'!H:H,"IN",'Planificación 2026-1'!I:I,"<3") -> 0 | CT6: =SUMIFS('Planificación 2026-1'!R:R,'Planificación 2026-1'!W:W,C6,'Planificación 2026-1'!H:H,"CA",'Planificación 2026-1'!I:I,"<3") -> 0 | CU6: =SUMIFS('Planificación 2026-1'!R:R,'Planificación 2026-1'!W:W,C6,'Planificación 2026-1'!H:H,"DE",'Planificación 2026-1'!I:I,"<3") -> 0 | CV6: =SUMIFS('Planificación 2026-1'!R:R,'Planificación 2026-1'!W:W,C6,'Planificación 2026-1'!H:H,"OB",'Planificación 2026-1'!I:I,"<3") -> 0 | CW6: =SUMIFS('Planificación 2026-1'!R:R,'Planificación 2026-1'!W:W,C6,'Planificación 2026-1'!H:H,"MH",'Planificación 2026-1'!I:I,"<3") -> 0 | CX6: =SUMIFS('Planificación 2026-1'!R:R,'Planificación 2026-1'!W:W,C6,'Planificación 2026-1'!H:H,"IC",'Planificación 2026-1'!I:I,"<3") -> 0 | CY6: =SUMIFS('Planificación 2026-1'!R:R,'Planificación 2026-1'!W:W,C6,'Planificación 2026-1'!H:H,"AR",'Planificación 2026-1'!I:I,"<3") -> 0 | CZ6: =SUMIFS('Planificación 2026-1'!R:R,'Planificación 2026-1'!W:W,C6,'Planificación 2026-1'!H:H,"T1",'Planificación 2026-1'!I:I,"<3") -> 0 | DA6: =SUMIFS('Planificación 2026-1'!R:R,'Planificación 2026-1'!W:W,C6,'Planificación 2026-1'!H:H,"T3",'Planificación 2026-1'!I:I,"<3") -> 0 | DB6: =SUMIFS('Planificación 2026-1'!R:R,'Planificación 2026-1'!W:W,C6,'Planificación 2026-1'!H:H,"T2",'Planificación 2026-1'!I:I,"<3") -> 0 | DC6: =SUMIFS('Planificación 2026-1'!R:R,'Planificación 2026-1'!W:W,C6,'Planificación 2026-1'!H:H,"AE",'Planificación 2026-1'!I:I,"<3") -> 0 | DD6: =SUMIFS('Planificación 2026-1'!R:R,'Planificación 2026-1'!W:W,C6,'Planificación 2026-1'!H:H,"T4",'Planificación 2026-1'!I:I,"<3") -> 0 | DE6: =TRIM(CONCATENATE(I6,J6,K6,L6,M6,N6,O6,P6,Q6,R6,S6,T6,U6,V6,W6,X6,Y6)) | DF6: =IF(C6="","",SUMIFS('Planificación 2026-1'!R:R,'Planificación 2026-1'!W:W,C6,'Planificación 2026-1'!F:F,"PRINCIPAL",'Planificación 2026-1'!X:X,"VIRTUAL")) -> 0 | DG6: =IF(C6="","",SUMIFS('Planificación 2026-1'!R:R,'Planificación 2026-1'!W:W,C6,'Planificación 2026-1'!F:F,"PRINCIPAL",'Planificación 2026-1'!X:X,"PRESENCIAL")) -> 0 | DH6: =IF(C6="","",SUMIFS('Planificación 2026-1'!R:R,'Planificación 2026-1'!W:W,C6,'Planificación 2026-1'!F:F,"PRINCIPAL",'Planificación 2026-1'!X:X,"HIBRIDO PRESENCIAL")) -> 0 | DI6: =TRIM(CONCATENATE(Z6,AA6,AB6,AC6,AD6,AE6,AF6,AG6,AH6,AI6,AJ6,AK6,AL6,AM6,AN6,AO6,AP6)) | DJ6: =IF(C6="","",SUMIFS('Planificación 2026-1'!R:R,'Planificación 2026-1'!W:W,C6,'Planificación 2026-1'!F:F,"FILIAL",'Planificación 2026-1'!X:X,"VIRTUAL")) -> 0 | DK6: =IF(C6="","",SUMIFS('Planificación 2026-1'!R:R,'Planificación 2026-1'!W:W,C6,'Planificación 2026-1'!F:F,"FILIAL",'Planificación 2026-1'!X:X,"PRESENCIAL")) -> 0 | DL6: =IF(C6="","",SUMIFS('Planificación 2026-1'!R:R,'Planificación 2026-1'!W:W,C6,'Planificación 2026-1'!F:F,"FILIAL",'Planificación 2026-1'!X:X,"HIBRIDO PRESENCIAL")) -> 0 | DM6: =TRIM(CONCATENATE(AQ6,AR6,AS6,AT6,AU6,AV6,AW6,AX6,AY6,AZ6,BA6,BB6,BC6,BD6,BE6,BF6,BG6)) | DN6: =IF(C6="","",SUMIFS('Planificación 2026-1'!R:R,'Planificación 2026-1'!W:W,C6,'Planificación 2026-1'!F:F,"SUNAMPE",'Planificación 2026-1'!X:X,"VIRTUAL")) -> 0 | DO6: =IF(C6="","",SUMIFS('Planificación 2026-1'!R:R,'Planificación 2026-1'!W:W,C6,'Planificación 2026-1'!F:F,"SUNAMPE",'Planificación 2026-1'!X:X,"PRESENCIAL")) -> 0 | DP6: =TRIM(CONCATENATE(BH6,BI6,BJ6,BK6,BL6,BM6,BN6,BO6,BP6,BQ6,BR6,BS6,BT6,BU6,BV6,BW6,BX6)) | DQ6: =IF(C6="","",SUMIFS('Planificación 2026-1'!R:R,'Planificación 2026-1'!W:W,C6,'Planificación 2026-1'!F:F,"HUAURA",'Planificación 2026-1'!X:X,"VIRTUAL")) -> 0 | DR6: =IF(C6="","",SUMIFS('Planificación 2026-1'!R:R,'Planificación 2026-1'!W:W,C6,'Planificación 2026-1'!F:F,"HUAURA",'Planificación 2026-1'!X:X,"PRESENCIAL")) -> 0 | DS6: =SUMIFS('Planificación 2026-1'!R:R,'Planificación 2026-1'!W:W,C6,'Planificación 2026-1'!F:F,"PRINCIPAL",'Planificación 2026-1'!X:X,"VIRTUAL",'Planificación 2026-1'!I:I,">2") -> 0 | DT6: =SUMIFS('Planificación 2026-1'!R:R,'Planificación 2026-1'!W:W,C6,'Planificación 2026-1'!F:F,"PRINCIPAL",'Planificación 2026-1'!X:X,"<>VIRTUAL",'Planificación 2026-1'!I:I,">2") -> 0 | DU6: =SUMIFS('Planificación 2026-1'!R:R,'Planificación 2026-1'!W:W,C6,'Planificación 2026-1'!F:F,"SUNAMPE",'Planificación 2026-1'!X:X,"VIRTUAL",'Planificación 2026-1'!I:I,">2") -> 0 | DV6: =SUMIFS('Planificación 2026-1'!R:R,'Planificación 2026-1'!W:W,C6,'Planificación 2026-1'!F:F,"SUNAMPE",'Planificación 2026-1'!X:X,"<>VIRTUAL",'Planificación 2026-1'!I:I,">2") -> 0 | DW6: =SUMIFS('Planificación 2026-1'!R:R,'Planificación 2026-1'!W:W,C6,'Planificación 2026-1'!F:F,"FILIAL",'Planificación 2026-1'!X:X,"VIRTUAL",'Planificación 2026-1'!I:I,">2") -> 0 | DX6: =SUMIFS('Planificación 2026-1'!R:R,'Planificación 2026-1'!W:W,C6,'Planificación 2026-1'!F:F,"FILIAL",'Planificación 2026-1'!X:X,"<>VIRTUAL",'Planificación 2026-1'!I:I,">2") -> 0 | DY6: =SUMIFS('Planificación 2026-1'!R:R,'Planificación 2026-1'!W:W,C6,'Planificación 2026-1'!F:F,"PORUMA",'Planificación 2026-1'!X:X,"VIRTUAL",'Planificación 2026-1'!I:I,">2") -> 0 | DZ6: =SUMIFS('Planificación 2026-1'!R:R,'Planificación 2026-1'!W:W,C6,'Planificación 2026-1'!F:F,"PORUMA",'Planificación 2026-1'!X:X,"<>VIRTUAL",'Planificación 2026-1'!I:I,">2") -> 0 | EA6: =SUMIFS('Planificación 2026-1'!R:R,'Planificación 2026-1'!W:W,C6,'Planificación 2026-1'!F:F,"HUAURA",'Planificación 2026-1'!X:X,"VIRTUAL",'Planificación 2026-1'!I:I,">2") -> 0 | EB6: =SUMIFS('Planificación 2026-1'!R:R,'Planificación 2026-1'!W:W,C6,'Planificación 2026-1'!F:F,"HUAURA",'Planificación 2026-1'!X:X,"<>VIRTUAL",'Planificación 2026-1'!I:I,">2") -> 0 | EC6: =SUMIFS('Planificación 2026-1'!R:R,'Planificación 2026-1'!W:W,C6,'Planificación 2026-1'!F:F,"PRINCIPAL",'Planificación 2026-1'!X:X,"VIRTUAL",'Planificación 2026-1'!I:I,"<3") -> 0 | ED6: =SUMIFS('Planificación 2026-1'!R:R,'Planificación 2026-1'!W:W,C6,'Planificación 2026-1'!F:F,"PRINCIPAL",'Planificación 2026-1'!X:X,"<>VIRTUAL",'Planificación 2026-1'!I:I,"<3") -> 0 | EE6: =SUMIFS('Planificación 2026-1'!R:R,'Planificación 2026-1'!W:W,C6,'Planificación 2026-1'!F:F,"SUNAMPE",'Planificación 2026-1'!X:X,"VIRTUAL",'Planificación 2026-1'!I:I,"<3") -> 0 | EF6: =SUMIFS('Planificación 2026-1'!R:R,'Planificación 2026-1'!W:W,C6,'Planificación 2026-1'!F:F,"SUNAMPE",'Planificación 2026-1'!X:X,"<>VIRTUAL",'Planificación 2026-1'!I:I,"<3") -> 0 | EG6: =SUMIFS('Planificación 2026-1'!R:R,'Planificación 2026-1'!W:W,C6,'Planificación 2026-1'!F:F,"FILIAL",'Planificación 2026-1'!X:X,"VIRTUAL",'Planificación 2026-1'!I:I,"<3") -> 0 | EH6: =SUMIFS('Planificación 2026-1'!R:R,'Planificación 2026-1'!W:W,C6,'Planificación 2026-1'!F:F,"FILIAL",'Planificación 2026-1'!X:X,"<>VIRTUAL",'Planificación 2026-1'!I:I,"<3") -> 0 | EI6: =SUMIFS('Planificación 2026-1'!R:R,'Planificación 2026-1'!W:W,C6,'Planificación 2026-1'!F:F,"PORUMA",'Planificación 2026-1'!X:X,"VIRTUAL",'Planificación 2026-1'!I:I,"<3") -> 0 | EJ6: =SUMIFS('Planificación 2026-1'!R:R,'Planificación 2026-1'!W:W,C6,'Planificación 2026-1'!F:F,"PORUMA",'Planificación 2026-1'!X:X,"<>VIRTUAL",'Planificación 2026-1'!I:I,"<3") -> 0 | EK6: =SUMIFS('Planificación 2026-1'!R:R,'Planificación 2026-1'!W:W,C6,'Planificación 2026-1'!F:F,"HUAURA",'Planificación 2026-1'!X:X,"VIRTUAL",'Planificación 2026-1'!I:I,"<3") -> 0 | EL6: =SUMIFS('Planificación 2026-1'!R:R,'Planificación 2026-1'!W:W,C6,'Planificación 2026-1'!F:F,"HUAURA",'Planificación 2026-1'!X:X,"<>VIRTUAL",'Planificación 2026-1'!I:I,"<3") -> 0 | EN6: =DS6+DW6+EA6+EC6+EG6+EK6+DU6+EE6 -> 0 | EO6: =DT6+DX6+EB6+ED6+EH6+EL6+DV6+EF6 -> 0 | EP6: =EXACT(SUM(EN6:EO6),D6) -> TRUE | EQ6: =IF(AND(DT6=0,DX6=0,EB6=0),"",IF(COUNTIF(DT6:EB6,">0")=1,IF(DT6>0,"SEDE",IF(DX6>0,"FILIAL","HUAURA")),IF(COUNTIF(DT6:EB6,">0")=2,IF(AND(DT6>0,DX6>0),"SEDE-FILIAL",IF(AND(DT6>0,EB6>0),"SEDE-HUAURA","FILIAL-HUAURA")),"SEDE-FILIAL-HUAURA"))) | ER6: =IF(EN6=0,"PRESENCIAL",IF(EO6=0,"VIRTUAL",IF(EN6>EO6,"MAS VIRTUAL",IF(EO6>EN6,"MAS PRESENCIAL","AMBOS")))) -> PRESENCIAL
B7: 4 | C7: AGUADO APOLAYA RAUL HERNANDO | D7: =SUMIF('Planificación 2026-1'!W:W,C7,'Planificación 2026-1'!R:R) -> 19 | E7: TP | F7: RENOVACIÓN | G7: SEDE | H7: INGENIERÍA INDUSTRIAL | I7: =IF(SUM(COUNTIFS('Planificación 2026-1'!F:F,"PRINCIPAL",'Planificación 2026-1'!W:W,C7,'Planificación 2026-1'!H:H,"AF"))>0,"P01"," ") | J7: =IF(SUM(COUNTIFS('Planificación 2026-1'!F:F,"PRINCIPAL",'Planificación 2026-1'!W:W,C7,'Planificación 2026-1'!H:H,"EN"))>0,"P02"," ") | K7: =IF(SUM(COUNTIFS('Planificación 2026-1'!F:F,"PRINCIPAL",'Planificación 2026-1'!W:W,C7,'Planificación 2026-1'!H:H,"IS"))>0,"P03"," ") | L7: =IF(SUM(COUNTIFS('Planificación 2026-1'!F:F,"PRINCIPAL",'Planificación 2026-1'!W:W,C7,'Planificación 2026-1'!H:H,"PS"))>0,"P04"," ") | N7: =IF(SUM(COUNTIFS('Planificación 2026-1'!F:F,"PRINCIPAL",'Planificación 2026-1'!W:W,C7,'Planificación 2026-1'!H:H,"IN"))>0,"P06"," ") -> P06 | O7: =IF(SUM(COUNTIFS('Planificación 2026-1'!F:F,"PRINCIPAL",'Planificación 2026-1'!W:W,C7,'Planificación 2026-1'!H:H,"CA"))>0,"P07"," ") | P7: =IF(SUM(COUNTIFS('Planificación 2026-1'!F:F,"PRINCIPAL",'Planificación 2026-1'!W:W,C7,'Planificación 2026-1'!H:H,"DE"))>0,"P08"," ") | Q7: =IF(SUM(COUNTIFS('Planificación 2026-1'!F:F,"PRINCIPAL",'Planificación 2026-1'!W:W,C7,'Planificación 2026-1'!H:H,"OB"))>0,"P09"," ") | R7: =IF(SUM(COUNTIFS('Planificación 2026-1'!F:F,"PRINCIPAL",'Planificación 2026-1'!W:W,C7,'Planificación 2026-1'!H:H,"MH"))>0,"P31"," ") | S7: =IF(SUM(COUNTIFS('Planificación 2026-1'!F:F,"PRINCIPAL",'Planificación 2026-1'!W:W,C7,'Planificación 2026-1'!H:H,"IC"))>0,"P32"," ") | T7: =IF(SUM(COUNTIFS('Planificación 2026-1'!F:F,"PRINCIPAL",'Planificación 2026-1'!W:W,C7,'Planificación 2026-1'!H:H,"AR"))>0,"P34"," ") | U7: =IF(SUM(COUNTIFS('Planificación 2026-1'!F:F,"PRINCIPAL",'Planificación 2026-1'!W:W,C7,'Planificación 2026-1'!H:H,"T1"))>0,"P35"," ") | V7: =IF(SUM(COUNTIFS('Planificación 2026-1'!F:F,"PRINCIPAL",'Planificación 2026-1'!W:W,C7,'Planificación 2026-1'!H:H,"T3"))>0,"P36"," ") | W7: =IF(SUM(COUNTIFS('Planificación 2026-1'!F:F,"PRINCIPAL",'Planificación 2026-1'!W:W,C7,'Planificación 2026-1'!H:H,"T2"))>0,"P37"," ") | X7: =IF(SUM(COUNTIFS('Planificación 2026-1'!F:F,"PRINCIPAL",'Planificación 2026-1'!W:W,C7,'Planificación 2026-1'!H:H,"AE"))>0,"P38"," ") | Y7: =IF(SUM(COUNTIFS('Planificación 2026-1'!F:F,"PRINCIPAL",'Planificación 2026-1'!W:W,C7,'Planificación 2026-1'!H:H,"T4"))>0,"P55"," ") | Z7: =IF(SUM(COUNTIFS('Planificación 2026-1'!F:F,"FILIAL",'Planificación 2026-1'!W:W,C7,'Planificación 2026-1'!H:H,"AF"))>0," P01"," ") | AA7: =IF(SUM(COUNTIFS('Planificación 2026-1'!F:F,"FILIAL",'Planificación 2026-1'!W:W,C7,'Planificación 2026-1'!H:H,"EN"))>0,"P02"," ") | AB7: =IF(SUM(COUNTIFS('Planificación 2026-1'!F:F,"FILIAL",'Planificación 2026-1'!W:W,C7,'Planificación 2026-1'!H:H,"IS"))>0,"P03"," ") | AC7: =IF(SUM(COUNTIFS('Planificación 2026-1'!F:F,"FILIAL",'Planificación 2026-1'!W:W,C7,'Planificación 2026-1'!H:H,"PS"))>0,"P04"," ") | AE7: =IF(SUM(COUNTIFS('Planificación 2026-1'!F:F,"FILIAL",'Planificación 2026-1'!W:W,C7,'Planificación 2026-1'!H:H,"IN"))>0,"P06"," ") | AF7: =IF(SUM(COUNTIFS('Planificación 2026-1'!F:F,"FILIAL",'Planificación 2026-1'!W:W,C7,'Planificación 2026-1'!H:H,"CA"))>0,"P07"," ") | AG7: =IF(SUM(COUNTIFS('Planificación 2026-1'!F:F,"FILIAL",'Planificación 2026-1'!W:W,C7,'Planificación 2026-1'!H:H,"DE"))>0,"P08"," ") | AH7: =IF(SUM(COUNTIFS('Planificación 2026-1'!F:F,"FILIAL",'Planificación 2026-1'!W:W,C7,'Planificación 2026-1'!H:H,"OB"))>0,"P09"," ") | AI7: =IF(SUM(COUNTIFS('Planificación 2026-1'!F:F,"FILIAL",'Planificación 2026-1'!W:W,C7,'Planificación 2026-1'!H:H,"MH"))>0,"P31"," ") | AJ7: =IF(SUM(COUNTIFS('Planificación 2026-1'!F:F,"FILIAL",'Planificación 2026-1'!W:W,C7,'Planificación 2026-1'!H:H,"IC"))>0,"P32"," ") | AK7: =IF(SUM(COUNTIFS('Planificación 2026-1'!F:F,"FILIAL",'Planificación 2026-1'!W:W,C7,'Planificación 2026-1'!H:H,"AR"))>0,"P34"," ") | AL7: =IF(SUM(COUNTIFS('Planificación 2026-1'!F:F,"FILIAL",'Planificación 2026-1'!W:W,C7,'Planificación 2026-1'!H:H,"T1"))>0,"P35"," ") | AM7: =IF(SUM(COUNTIFS('Planificación 2026-1'!F:F,"FILIAL",'Planificación 2026-1'!W:W,C7,'Planificación 2026-1'!H:H,"T3"))>0,"P36"," ") | AN7: =IF(SUM(COUNTIFS('Planificación 2026-1'!F:F,"FILIAL",'Planificación 2026-1'!W:W,C7,'Planificación 2026-1'!H:H,"T2"))>0,"P37"," ") | AO7: =IF(SUM(COUNTIFS('Planificación 2026-1'!F:F,"FILIAL",'Planificación 2026-1'!W:W,C7,'Planificación 2026-1'!H:H,"AE"))>0,"P38"," ") | AP7: =IF(SUM(COUNTIFS('Planificación 2026-1'!F:F,"FILIAL",'Planificación 2026-1'!W:W,C7,'Planificación 2026-1'!H:H,"T4"))>0,"P55"," ") | AQ7: =IF(SUM(COUNTIFS('Planificación 2026-1'!F:F,"SUNAMPE",'Planificación 2026-1'!W:W,C7,'Planificación 2026-1'!H:H,"AF"))>0," P01"," ") | AR7: =IF(SUM(COUNTIFS('Planificación 2026-1'!F:F,"SUNAMPE",'Planificación 2026-1'!W:W,C7,'Planificación 2026-1'!H:H,"EN"))>0,"P02"," ") | AS7: =IF(SUM(COUNTIFS('Planificación 2026-1'!F:F,"SUNAMPE",'Planificación 2026-1'!W:W,C7,'Planificación 2026-1'!H:H,"IS"))>0,"P03"," ") | AT7: =IF(SUM(COUNTIFS('Planificación 2026-1'!F:F,"SUNAMPE",'Planificación 2026-1'!W:W,C7,'Planificación 2026-1'!H:H,"PS"))>0,"P04"," ") | AV7: =IF(SUM(COUNTIFS('Planificación 2026-1'!F:F,"SUNAMPE",'Planificación 2026-1'!W:W,C7,'Planificación 2026-1'!H:H,"IN"))>0,"P06"," ") | AW7: =IF(SUM(COUNTIFS('Planificación 2026-1'!F:F,"SUNAMPE",'Planificación 2026-1'!W:W,C7,'Planificación 2026-1'!H:H,"CA"))>0,"P07"," ") | AX7: =IF(SUM(COUNTIFS('Planificación 2026-1'!F:F,"SUNAMPE",'Planificación 2026-1'!W:W,C7,'Planificación 2026-1'!H:H,"DE"))>0,"P08"," ") | AY7: =IF(SUM(COUNTIFS('Planificación 2026-1'!F:F,"SUNAMPE",'Planificación 2026-1'!W:W,C7,'Planificación 2026-1'!H:H,"OB"))>0,"P09"," ") | AZ7: =IF(SUM(COUNTIFS('Planificación 2026-1'!F:F,"SUNAMPE",'Planificación 2026-1'!W:W,C7,'Planificación 2026-1'!H:H,"MH"))>0,"P31"," ") | BA7: =IF(SUM(COUNTIFS('Planificación 2026-1'!F:F,"SUNAMPE",'Planificación 2026-1'!W:W,C7,'Planificación 2026-1'!H:H,"IC"))>0,"P32"," ") | BB7: =IF(SUM(COUNTIFS('Planificación 2026-1'!F:F,"SUNAMPE",'Planificación 2026-1'!W:W,C7,'Planificación 2026-1'!H:H,"AR"))>0,"P34"," ") | BC7: =IF(SUM(COUNTIFS('Planificación 2026-1'!F:F,"SUNAMPE",'Planificación 2026-1'!W:W,C7,'Planificación 2026-1'!H:H,"T1"))>0,"P35"," ") | BD7: =IF(SUM(COUNTIFS('Planificación 2026-1'!F:F,"SUNAMPE",'Planificación 2026-1'!W:W,C7,'Planificación 2026-1'!H:H,"T3"))>0,"P36"," ") | BE7: =IF(SUM(COUNTIFS('Planificación 2026-1'!F:F,"SUNAMPE",'Planificación 2026-1'!W:W,C7,'Planificación 2026-1'!H:H,"T2"))>0,"P37"," ") | BF7: =IF(SUM(COUNTIFS('Planificación 2026-1'!F:F,"SUNAMPE",'Planificación 2026-1'!W:W,C7,'Planificación 2026-1'!H:H,"AE"))>0,"P38"," ") | BG7: =IF(SUM(COUNTIFS('Planificación 2026-1'!F:F,"SUNAMPE",'Planificación 2026-1'!W:W,C7,'Planificación 2026-1'!H:H,"T4"))>0,"P55"," ") | BH7: =IF(SUM(COUNTIFS('Planificación 2026-1'!F:F,"HUAURA",'Planificación 2026-1'!W:W,C7,'Planificación 2026-1'!H:H,"AF"))>0," P01"," ") | BI7: =IF(SUM(COUNTIFS('Planificación 2026-1'!F:F,"HUAURA",'Planificación 2026-1'!W:W,C7,'Planificación 2026-1'!H:H,"EN"))>0,"P02"," ") | BJ7: =IF(SUM(COUNTIFS('Planificación 2026-1'!F:F,"HUAURA",'Planificación 2026-1'!W:W,C7,'Planificación 2026-1'!H:H,"IS"))>0,"P03"," ") | BK7: =IF(SUM(COUNTIFS('Planificación 2026-1'!F:F,"HUAURA",'Planificación 2026-1'!W:W,C7,'Planificación 2026-1'!H:H,"PS"))>0,"P04"," ") | BM7: =IF(SUM(COUNTIFS('Planificación 2026-1'!F:F,"HUAURA",'Planificación 2026-1'!W:W,C7,'Planificación 2026-1'!H:H,"IN"))>0,"P06"," ") | BN7: =IF(SUM(COUNTIFS('Planificación 2026-1'!F:F,"HUAURA",'Planificación 2026-1'!W:W,C7,'Planificación 2026-1'!H:H,"CA"))>0,"P07"," ") | BO7: =IF(SUM(COUNTIFS('Planificación 2026-1'!F:F,"HUAURA",'Planificación 2026-1'!W:W,C7,'Planificación 2026-1'!H:H,"DE"))>0,"P08"," ") | BP7: =IF(SUM(COUNTIFS('Planificación 2026-1'!F:F,"HUAURA",'Planificación 2026-1'!W:W,C7,'Planificación 2026-1'!H:H,"OB"))>0,"P09"," ") | BQ7: =IF(SUM(COUNTIFS('Planificación 2026-1'!F:F,"HUAURA",'Planificación 2026-1'!W:W,C7,'Planificación 2026-1'!H:H,"MH"))>0,"P31"," ") | BR7: =IF(SUM(COUNTIFS('Planificación 2026-1'!F:F,"HUAURA",'Planificación 2026-1'!W:W,C7,'Planificación 2026-1'!H:H,"IC"))>0,"P32"," ") | BS7: =IF(SUM(COUNTIFS('Planificación 2026-1'!F:F,"HUAURA",'Planificación 2026-1'!W:W,C7,'Planificación 2026-1'!H:H,"AR"))>0,"P34"," ") | BT7: =IF(SUM(COUNTIFS('Planificación 2026-1'!F:F,"HUAURA",'Planificación 2026-1'!W:W,C7,'Planificación 2026-1'!H:H,"T1"))>0,"P35"," ") | BU7: =IF(SUM(COUNTIFS('Planificación 2026-1'!F:F,"HUAURA",'Planificación 2026-1'!W:W,C7,'Planificación 2026-1'!H:H,"T3"))>0,"P36"," ") | BV7: =IF(SUM(COUNTIFS('Planificación 2026-1'!F:F,"HUAURA",'Planificación 2026-1'!W:W,C7,'Planificación 2026-1'!H:H,"T2"))>0,"P37"," ") | BW7: =IF(SUM(COUNTIFS('Planificación 2026-1'!F:F,"HUAURA",'Planificación 2026-1'!W:W,C7,'Planificación 2026-1'!H:H,"AE"))>0,"P38"," ") | BX7: =IF(SUM(COUNTIFS('Planificación 2026-1'!F:F,"HUAURA",'Planificación 2026-1'!W:W,C7,'Planificación 2026-1'!H:H,"T4"))>0,"P55"," ") | BY7: =SUMIFS('Planificación 2026-1'!R:R,'Planificación 2026-1'!W:W,C7,'Planificación 2026-1'!H:H,"AF",'Planificación 2026-1'!I:I,">2") -> 0 | BZ7: =SUMIFS('Planificación 2026-1'!R:R,'Planificación 2026-1'!W:W,C7,'Planificación 2026-1'!H:H,"EN",'Planificación 2026-1'!I:I,">2") -> 0 | CA7: =SUMIFS('Planificación 2026-1'!R:R,'Planificación 2026-1'!W:W,C7,'Planificación 2026-1'!H:H,"IS",'Planificación 2026-1'!I:I,">2") -> 0 | CB7: =SUMIFS('Planificación 2026-1'!R:R,'Planificación 2026-1'!W:W,C7,'Planificación 2026-1'!H:H,"PS",'Planificación 2026-1'!I:I,">2") -> 0 | CC7: =SUMIFS('Planificación 2026-1'!R:R,'Planificación 2026-1'!W:W,C7,'Planificación 2026-1'!H:H,"IN",'Planificación 2026-1'!I:I,">2") -> 19 | CD7: =SUMIFS('Planificación 2026-1'!R:R,'Planificación 2026-1'!W:W,C7,'Planificación 2026-1'!H:H,"CA",'Planificación 2026-1'!I:I,">2") -> 0 | CE7: =SUMIFS('Planificación 2026-1'!R:R,'Planificación 2026-1'!W:W,C7,'Planificación 2026-1'!H:H,"DE",'Planificación 2026-1'!I:I,">2") -> 0 | CF7: =SUMIFS('Planificación 2026-1'!R:R,'Planificación 2026-1'!W:W,C7,'Planificación 2026-1'!H:H,"OB",'Planificación 2026-1'!I:I,">2") -> 0 | CG7: =SUMIFS('Planificación 2026-1'!R:R,'Planificación 2026-1'!W:W,C7,'Planificación 2026-1'!H:H,"MH",'Planificación 2026-1'!I:I,">2") -> 0 | CH7: =SUMIFS('Planificación 2026-1'!R:R,'Planificación 2026-1'!W:W,C7,'Planificación 2026-1'!H:H,"IC",'Planificación 2026-1'!I:I,">2") -> 0 | CI7: =SUMIFS('Planificación 2026-1'!R:R,'Planificación 2026-1'!W:W,C7,'Planificación 2026-1'!H:H,"AR",'Planificación 2026-1'!I:I,">2") -> 0 | CJ7: =SUMIFS('Planificación 2026-1'!R:R,'Planificación 2026-1'!W:W,C7,'Planificación 2026-1'!H:H,"T1",'Planificación 2026-1'!I:I,">2") -> 0 | CK7: =SUMIFS('Planificación 2026-1'!R:R,'Planificación 2026-1'!W:W,C7,'Planificación 2026-1'!H:H,"T3",'Planificación 2026-1'!I:I,">2") -> 0 | CL7: =SUMIFS('Planificación 2026-1'!R:R,'Planificación 2026-1'!W:W,C7,'Planificación 2026-1'!H:H,"T2",'Planificación 2026-1'!I:I,">2") -> 0 | CM7: =SUMIFS('Planificación 2026-1'!R:R,'Planificación 2026-1'!W:W,C7,'Planificación 2026-1'!H:H,"AE",'Planificación 2026-1'!I:I,">2") -> 0 | CN7: =SUMIFS('Planificación 2026-1'!R:R,'Planificación 2026-1'!W:W,C7,'Planificación 2026-1'!H:H,"T4",'Planificación 2026-1'!I:I,">2") -> 0 | CO7: =SUMIFS('Planificación 2026-1'!R:R,'Planificación 2026-1'!W:W,C7,'Planificación 2026-1'!H:H,"AF",'Planificación 2026-1'!I:I,"<3") -> 0 | CP7: =SUMIFS('Planificación 2026-1'!R:R,'Planificación 2026-1'!W:W,C7,'Planificación 2026-1'!H:H,"EN",'Planificación 2026-1'!I:I,"<3") -> 0 | CQ7: =SUMIFS('Planificación 2026-1'!R:R,'Planificación 2026-1'!W:W,C7,'Planificación 2026-1'!H:H,"IS",'Planificación 2026-1'!I:I,"<3") -> 0 | CR7: =SUMIFS('Planificación 2026-1'!R:R,'Planificación 2026-1'!W:W,C7,'Planificación 2026-1'!H:H,"PS",'Planificación 2026-1'!I:I,"<3") -> 0 | CS7: =SUMIFS('Planificación 2026-1'!R:R,'Planificación 2026-1'!W:W,C7,'Planificación 2026-1'!H:H,"IN",'Planificación 2026-1'!I:I,"<3") -> 0 | CT7: =SUMIFS('Planificación 2026-1'!R:R,'Planificación 2026-1'!W:W,C7,'Planificación 2026-1'!H:H,"CA",'Planificación 2026-1'!I:I,"<3") -> 0 | CU7: =SUMIFS('Planificación 2026-1'!R:R,'Planificación 2026-1'!W:W,C7,'Planificación 2026-1'!H:H,"DE",'Planificación 2026-1'!I:I,"<3") -> 0 | CV7: =SUMIFS('Planificación 2026-1'!R:R,'Planificación 2026-1'!W:W,C7,'Planificación 2026-1'!H:H,"OB",'Planificación 2026-1'!I:I,"<3") -> 0 | CW7: =SUMIFS('Planificación 2026-1'!R:R,'Planificación 2026-1'!W:W,C7,'Planificación 2026-1'!H:H,"MH",'Planificación 2026-1'!I:I,"<3") -> 0 | CX7: =SUMIFS('Planificación 2026-1'!R:R,'Planificación 2026-1'!W:W,C7,'Planificación 2026-1'!H:H,"IC",'Planificación 2026-1'!I:I,"<3") -> 0 | CY7: =SUMIFS('Planificación 2026-1'!R:R,'Planificación 2026-1'!W:W,C7,'Planificación 2026-1'!H:H,"AR",'Planificación 2026-1'!I:I,"<3") -> 0 | CZ7: =SUMIFS('Planificación 2026-1'!R:R,'Planificación 2026-1'!W:W,C7,'Planificación 2026-1'!H:H,"T1",'Planificación 2026-1'!I:I,"<3") -> 0 | DA7: =SUMIFS('Planificación 2026-1'!R:R,'Planificación 2026-1'!W:W,C7,'Planificación 2026-1'!H:H,"T3",'Planificación 2026-1'!I:I,"<3") -> 0 | DB7: =SUMIFS('Planificación 2026-1'!R:R,'Planificación 2026-1'!W:W,C7,'Planificación 2026-1'!H:H,"T2",'Planificación 2026-1'!I:I,"<3") -> 0 | DC7: =SUMIFS('Planificación 2026-1'!R:R,'Planificación 2026-1'!W:W,C7,'Planificación 2026-1'!H:H,"AE",'Planificación 2026-1'!I:I,"<3") -> 0 | DD7: =SUMIFS('Planificación 2026-1'!R:R,'Planificación 2026-1'!W:W,C7,'Planificación 2026-1'!H:H,"T4",'Planificación 2026-1'!I:I,"<3") -> 0 | DE7: =TRIM(CONCATENATE(I7,J7,K7,L7,M7,N7,O7,P7,Q7,R7,S7,T7,U7,V7,W7,X7,Y7)) -> P06 | DF7: =IF(C7="","",SUMIFS('Planificación 2026-1'!R:R,'Planificación 2026-1'!W:W,C7,'Planificación 2026-1'!F:F,"PRINCIPAL",'Planificación 2026-1'!X:X,"VIRTUAL")) -> 0 | DG7: =IF(C7="","",SUMIFS('Planificación 2026-1'!R:R,'Planificación 2026-1'!W:W,C7,'Planificación 2026-1'!F:F,"PRINCIPAL",'Planificación 2026-1'!X:X,"PRESENCIAL")) -> 19 | DH7: =IF(C7="","",SUMIFS('Planificación 2026-1'!R:R,'Planificación 2026-1'!W:W,C7,'Planificación 2026-1'!F:F,"PRINCIPAL",'Planificación 2026-1'!X:X,"HIBRIDO PRESENCIAL")) -> 0 | DI7: =TRIM(CONCATENATE(Z7,AA7,AB7,AC7,AD7,AE7,AF7,AG7,AH7,AI7,AJ7,AK7,AL7,AM7,AN7,AO7,AP7)) | DJ7: =IF(C7="","",SUMIFS('Planificación 2026-1'!R:R,'Planificación 2026-1'!W:W,C7,'Planificación 2026-1'!F:F,"FILIAL",'Planificación 2026-1'!X:X,"VIRTUAL")) -> 0 | DK7: =IF(C7="","",SUMIFS('Planificación 2026-1'!R:R,'Planificación 2026-1'!W:W,C7,'Planificación 2026-1'!F:F,"FILIAL",'Planificación 2026-1'!X:X,"PRESENCIAL")) -> 0 | DL7: =IF(C7="","",SUMIFS('Planificación 2026-1'!R:R,'Planificación 2026-1'!W:W,C7,'Planificación 2026-1'!F:F,"FILIAL",'Planificación 2026-1'!X:X,"HIBRIDO PRESENCIAL")) -> 0 | DM7: =TRIM(CONCATENATE(AQ7,AR7,AS7,AT7,AU7,AV7,AW7,AX7,AY7,AZ7,BA7,BB7,BC7,BD7,BE7,BF7,BG7)) | DN7: =IF(C7="","",SUMIFS('Planificación 2026-1'!R:R,'Planificación 2026-1'!W:W,C7,'Planificación 2026-1'!F:F,"SUNAMPE",'Planificación 2026-1'!X:X,"VIRTUAL")) -> 0 | DO7: =IF(C7="","",SUMIFS('Planificación 2026-1'!R:R,'Planificación 2026-1'!W:W,C7,'Planificación 2026-1'!F:F,"SUNAMPE",'Planificación 2026-1'!X:X,"PRESENCIAL")) -> 0 | DP7: =TRIM(CONCATENATE(BH7,BI7,BJ7,BK7,BL7,BM7,BN7,BO7,BP7,BQ7,BR7,BS7,BT7,BU7,BV7,BW7,BX7)) | DQ7: =IF(C7="","",SUMIFS('Planificación 2026-1'!R:R,'Planificación 2026-1'!W:W,C7,'Planificación 2026-1'!F:F,"HUAURA",'Planificación 2026-1'!X:X,"VIRTUAL")) -> 0 | DR7: =IF(C7="","",SUMIFS('Planificación 2026-1'!R:R,'Planificación 2026-1'!W:W,C7,'Planificación 2026-1'!F:F,"HUAURA",'Planificación 2026-1'!X:X,"PRESENCIAL")) -> 0 | DS7: =SUMIFS('Planificación 2026-1'!R:R,'Planificación 2026-1'!W:W,C7,'Planificación 2026-1'!F:F,"PRINCIPAL",'Planificación 2026-1'!X:X,"VIRTUAL",'Planificación 2026-1'!I:I,">2") -> 0 | DT7: =SUMIFS('Planificación 2026-1'!R:R,'Planificación 2026-1'!W:W,C7,'Planificación 2026-1'!F:F,"PRINCIPAL",'Planificación 2026-1'!X:X,"<>VIRTUAL",'Planificación 2026-1'!I:I,">2") -> 19 | DU7: =SUMIFS('Planificación 2026-1'!R:R,'Planificación 2026-1'!W:W,C7,'Planificación 2026-1'!F:F,"SUNAMPE",'Planificación 2026-1'!X:X,"VIRTUAL",'Planificación 2026-1'!I:I,">2") -> 0 | DV7: =SUMIFS('Planificación 2026-1'!R:R,'Planificación 2026-1'!W:W,C7,'Planificación 2026-1'!F:F,"SUNAMPE",'Planificación 2026-1'!X:X,"<>VIRTUAL",'Planificación 2026-1'!I:I,">2") -> 0 | DW7: =SUMIFS('Planificación 2026-1'!R:R,'Planificación 2026-1'!W:W,C7,'Planificación 2026-1'!F:F,"FILIAL",'Planificación 2026-1'!X:X,"VIRTUAL",'Planificación 2026-1'!I:I,">2") -> 0 | DX7: =SUMIFS('Planificación 2026-1'!R:R,'Planificación 2026-1'!W:W,C7,'Planificación 2026-1'!F:F,"FILIAL",'Planificación 2026-1'!X:X,"<>VIRTUAL",'Planificación 2026-1'!I:I,">2") -> 0 | DY7: =SUMIFS('Planificación 2026-1'!R:R,'Planificación 2026-1'!W:W,C7,'Planificación 2026-1'!F:F,"PORUMA",'Planificación 2026-1'!X:X,"VIRTUAL",'Planificación 2026-1'!I:I,">2") -> 0 | DZ7: =SUMIFS('Planificación 2026-1'!R:R,'Planificación 2026-1'!W:W,C7,'Planificación 2026-1'!F:F,"PORUMA",'Planificación 2026-1'!X:X,"<>VIRTUAL",'Planificación 2026-1'!I:I,">2") -> 0 | EA7: =SUMIFS('Planificación 2026-1'!R:R,'Planificación 2026-1'!W:W,C7,'Planificación 2026-1'!F:F,"HUAURA",'Planificación 2026-1'!X:X,"VIRTUAL",'Planificación 2026-1'!I:I,">2") -> 0 | EB7: =SUMIFS('Planificación 2026-1'!R:R,'Planificación 2026-1'!W:W,C7,'Planificación 2026-1'!F:F,"HUAURA",'Planificación 2026-1'!X:X,"<>VIRTUAL",'Planificación 2026-1'!I:I,">2") -> 0 | EC7: =SUMIFS('Planificación 2026-1'!R:R,'Planificación 2026-1'!W:W,C7,'Planificación 2026-1'!F:F,"PRINCIPAL",'Planificación 2026-1'!X:X,"VIRTUAL",'Planificación 2026-1'!I:I,"<3") -> 0 | ED7: =SUMIFS('Planificación 2026-1'!R:R,'Planificación 2026-1'!W:W,C7,'Planificación 2026-1'!F:F,"PRINCIPAL",'Planificación 2026-1'!X:X,"<>VIRTUAL",'Planificación 2026-1'!I:I,"<3") -> 0 | EE7: =SUMIFS('Planificación 2026-1'!R:R,'Planificación 2026-1'!W:W,C7,'Planificación 2026-1'!F:F,"SUNAMPE",'Planificación 2026-1'!X:X,"VIRTUAL",'Planificación 2026-1'!I:I,"<3") -> 0 | EF7: =SUMIFS('Planificación 2026-1'!R:R,'Planificación 2026-1'!W:W,C7,'Planificación 2026-1'!F:F,"SUNAMPE",'Planificación 2026-1'!X:X,"<>VIRTUAL",'Planificación 2026-1'!I:I,"<3") -> 0 | EG7: =SUMIFS('Planificación 2026-1'!R:R,'Planificación 2026-1'!W:W,C7,'Planificación 2026-1'!F:F,"FILIAL",'Planificación 2026-1'!X:X,"VIRTUAL",'Planificación 2026-1'!I:I,"<3") -> 0 | EH7: =SUMIFS('Planificación 2026-1'!R:R,'Planificación 2026-1'!W:W,C7,'Planificación 2026-1'!F:F,"FILIAL",'Planificación 2026-1'!X:X,"<>VIRTUAL",'Planificación 2026-1'!I:I,"<3") -> 0 | EI7: =SUMIFS('Planificación 2026-1'!R:R,'Planificación 2026-1'!W:W,C7,'Planificación 2026-1'!F:F,"PORUMA",'Planificación 2026-1'!X:X,"VIRTUAL",'Planificación 2026-1'!I:I,"<3") -> 0 | EJ7: =SUMIFS('Planificación 2026-1'!R:R,'Planificación 2026-1'!W:W,C7,'Planificación 2026-1'!F:F,"PORUMA",'Planificación 2026-1'!X:X,"<>VIRTUAL",'Planificación 2026-1'!I:I,"<3") -> 0 | EK7: =SUMIFS('Planificación 2026-1'!R:R,'Planificación 2026-1'!W:W,C7,'Planificación 2026-1'!F:F,"HUAURA",'Planificación 2026-1'!X:X,"VIRTUAL",'Planificación 2026-1'!I:I,"<3") -> 0 | EL7: =SUMIFS('Planificación 2026-1'!R:R,'Planificación 2026-1'!W:W,C7,'Planificación 2026-1'!F:F,"HUAURA",'Planificación 2026-1'!X:X,"<>VIRTUAL",'Planificación 2026-1'!I:I,"<3") -> 0 | EN7: =DS7+DW7+EA7+EC7+EG7+EK7+DU7+EE7 -> 0 | EO7: =DT7+DX7+EB7+ED7+EH7+EL7+DV7+EF7 -> 19 | EP7: =EXACT(SUM(EN7:EO7),D7) -> TRUE | EQ7: =IF(AND(DT7=0,DX7=0,EB7=0),"",IF(COUNTIF(DT7:EB7,">0")=1,IF(DT7>0,"SEDE",IF(DX7>0,"FILIAL","HUAURA")),IF(COUNTIF(DT7:EB7,">0")=2,IF(AND(DT7>0,DX7>0),"SEDE-FILIAL",IF(AND(DT7>0,EB7>0),"SEDE-HUAURA","FILIAL-HUAURA")),"SEDE-FILIAL-HUAURA"))) -> SEDE | ER7: =IF(EN7=0,"PRESENCIAL",IF(EO7=0,"VIRTUAL",IF(EN7>EO7,"MAS VIRTUAL",IF(EO7>EN7,"MAS PRESENCIAL","AMBOS")))) -> PRESENCIAL
B8: 5 | C8: AGUIRRE ESPINOZA MONICA WENDY | D8: =SUMIF('Planificación 2026-1'!W:W,C8,'Planificación 2026-1'!R:R) -> 16 | E8: TP | F8: RENOVACIÓN | G8: FILIAL | H8: DERECHO | I8: =IF(SUM(COUNTIFS('Planificación 2026-1'!F:F,"PRINCIPAL",'Planificación 2026-1'!W:W,C8,'Planificación 2026-1'!H:H,"AF"))>0,"P01"," ") | J8: =IF(SUM(COUNTIFS('Planificación 2026-1'!F:F,"PRINCIPAL",'Planificación 2026-1'!W:W,C8,'Planificación 2026-1'!H:H,"EN"))>0,"P02"," ") | K8: =IF(SUM(COUNTIFS('Planificación 2026-1'!F:F,"PRINCIPAL",'Planificación 2026-1'!W:W,C8,'Planificación 2026-1'!H:H,"IS"))>0,"P03"," ") | L8: =IF(SUM(COUNTIFS('Planificación 2026-1'!F:F,"PRINCIPAL",'Planificación 2026-1'!W:W,C8,'Planificación 2026-1'!H:H,"PS"))>0,"P04"," ") | N8: =IF(SUM(COUNTIFS('Planificación 2026-1'!F:F,"PRINCIPAL",'Planificación 2026-1'!W:W,C8,'Planificación 2026-1'!H:H,"IN"))>0,"P06"," ") | O8: =IF(SUM(COUNTIFS('Planificación 2026-1'!F:F,"PRINCIPAL",'Planificación 2026-1'!W:W,C8,'Planificación 2026-1'!H:H,"CA"))>0,"P07"," ") | P8: =IF(SUM(COUNTIFS('Planificación 2026-1'!F:F,"PRINCIPAL",'Planificación 2026-1'!W:W,C8,'Planificación 2026-1'!H:H,"DE"))>0,"P08"," ") | Q8: =IF(SUM(COUNTIFS('Planificación 2026-1'!F:F,"PRINCIPAL",'Planificación 2026-1'!W:W,C8,'Planificación 2026-1'!H:H,"OB"))>0,"P09"," ") | R8: =IF(SUM(COUNTIFS('Planificación 2026-1'!F:F,"PRINCIPAL",'Planificación 2026-1'!W:W,C8,'Planificación 2026-1'!H:H,"MH"))>0,"P31"," ") | S8: =IF(SUM(COUNTIFS('Planificación 2026-1'!F:F,"PRINCIPAL",'Planificación 2026-1'!W:W,C8,'Planificación 2026-1'!H:H,"IC"))>0,"P32"," ") | T8: =IF(SUM(COUNTIFS('Planificación 2026-1'!F:F,"PRINCIPAL",'Planificación 2026-1'!W:W,C8,'Planificación 2026-1'!H:H,"AR"))>0,"P34"," ") | U8: =IF(SUM(COUNTIFS('Planificación 2026-1'!F:F,"PRINCIPAL",'Planificación 2026-1'!W:W,C8,'Planificación 2026-1'!H:H,"T1"))>0,"P35"," ") | V8: =IF(SUM(COUNTIFS('Planificación 2026-1'!F:F,"PRINCIPAL",'Planificación 2026-1'!W:W,C8,'Planificación 2026-1'!H:H,"T3"))>0,"P36"," ") | W8: =IF(SUM(COUNTIFS('Planificación 2026-1'!F:F,"PRINCIPAL",'Planificación 2026-1'!W:W,C8,'Planificación 2026-1'!H:H,"T2"))>0,"P37"," ") | X8: =IF(SUM(COUNTIFS('Planificación 2026-1'!F:F,"PRINCIPAL",'Planificación 2026-1'!W:W,C8,'Planificación 2026-1'!H:H,"AE"))>0,"P38"," ") | Y8: =IF(SUM(COUNTIFS('Planificación 2026-1'!F:F,"PRINCIPAL",'Planificación 2026-1'!W:W,C8,'Planificación 2026-1'!H:H,"T4"))>0,"P55"," ") | Z8: =IF(SUM(COUNTIFS('Planificación 2026-1'!F:F,"FILIAL",'Planificación 2026-1'!W:W,C8,'Planificación 2026-1'!H:H,"AF"))>0," P01"," ") | AA8: =IF(SUM(COUNTIFS('Planificación 2026-1'!F:F,"FILIAL",'Planificación 2026-1'!W:W,C8,'Planificación 2026-1'!H:H,"EN"))>0,"P02"," ") | AB8: =IF(SUM(COUNTIFS('Planificación 2026-1'!F:F,"FILIAL",'Planificación 2026-1'!W:W,C8,'Planificación 2026-1'!H:H,"IS"))>0,"P03"," ") | AC8: =IF(SUM(COUNTIFS('Planificación 2026-1'!F:F,"FILIAL",'Planificación 2026-1'!W:W,C8,'Planificación 2026-1'!H:H,"PS"))>0,"P04"," ") | AE8: =IF(SUM(COUNTIFS('Planificación 2026-1'!F:F,"FILIAL",'Planificación 2026-1'!W:W,C8,'Planificación 2026-1'!H:H,"IN"))>0,"P06"," ") | AF8: =IF(SUM(COUNTIFS('Planificación 2026-1'!F:F,"FILIAL",'Planificación 2026-1'!W:W,C8,'Planificación 2026-1'!H:H,"CA"))>0,"P07"," ") | AG8: =IF(SUM(COUNTIFS('Planificación 2026-1'!F:F,"FILIAL",'Planificación 2026-1'!W:W,C8,'Planificación 2026-1'!H:H,"DE"))>0,"P08"," ") -> P08 | AH8: =IF(SUM(COUNTIFS('Planificación 2026-1'!F:F,"FILIAL",'Planificación 2026-1'!W:W,C8,'Planificación 2026-1'!H:H,"OB"))>0,"P09"," ") | AI8: =IF(SUM(COUNTIFS('Planificación 2026-1'!F:F,"FILIAL",'Planificación 2026-1'!W:W,C8,'Planificación 2026-1'!H:H,"MH"))>0,"P31"," ") | AJ8: =IF(SUM(COUNTIFS('Planificación 2026-1'!F:F,"FILIAL",'Planificación 2026-1'!W:W,C8,'Planificación 2026-1'!H:H,"IC"))>0,"P32"," ") | AK8: =IF(SUM(COUNTIFS('Planificación 2026-1'!F:F,"FILIAL",'Planificación 2026-1'!W:W,C8,'Planificación 2026-1'!H:H,"AR"))>0,"P34"," ") | AL8: =IF(SUM(COUNTIFS('Planificación 2026-1'!F:F,"FILIAL",'Planificación 2026-1'!W:W,C8,'Planificación 2026-1'!H:H,"T1"))>0,"P35"," ") | AM8: =IF(SUM(COUNTIFS('Planificación 2026-1'!F:F,"FILIAL",'Planificación 2026-1'!W:W,C8,'Planificación 2026-1'!H:H,"T3"))>0,"P36"," ") | AN8: =IF(SUM(COUNTIFS('Planificación 2026-1'!F:F,"FILIAL",'Planificación 2026-1'!W:W,C8,'Planificación 2026-1'!H:H,"T2"))>0,"P37"," ") | AO8: =IF(SUM(COUNTIFS('Planificación 2026-1'!F:F,"FILIAL",'Planificación 2026-1'!W:W,C8,'Planificación 2026-1'!H:H,"AE"))>0,"P38"," ") | AP8: =IF(SUM(COUNTIFS('Planificación 2026-1'!F:F,"FILIAL",'Planificación 2026-1'!W:W,C8,'Planificación 2026-1'!H:H,"T4"))>0,"P55"," ") | AQ8: =IF(SUM(COUNTIFS('Planificación 2026-1'!F:F,"SUNAMPE",'Planificación 2026-1'!W:W,C8,'Planificación 2026-1'!H:H,"AF"))>0," P01"," ") | AR8: =IF(SUM(COUNTIFS('Planificación 2026-1'!F:F,"SUNAMPE",'Planificación 2026-1'!W:W,C8,'Planificación 2026-1'!H:H,"EN"))>0,"P02"," ") | AS8: =IF(SUM(COUNTIFS('Planificación 2026-1'!F:F,"SUNAMPE",'Planificación 2026-1'!W:W,C8,'Planificación 2026-1'!H:H,"IS"))>0,"P03"," ") | AT8: =IF(SUM(COUNTIFS('Planificación 2026-1'!F:F,"SUNAMPE",'Planificación 2026-1'!W:W,C8,'Planificación 2026-1'!H:H,"PS"))>0,"P04"," ") | AV8: =IF(SUM(COUNTIFS('Planificación 2026-1'!F:F,"SUNAMPE",'Planificación 2026-1'!W:W,C8,'Planificación 2026-1'!H:H,"IN"))>0,"P06"," ") | AW8: =IF(SUM(COUNTIFS('Planificación 2026-1'!F:F,"SUNAMPE",'Planificación 2026-1'!W:W,C8,'Planificación 2026-1'!H:H,"CA"))>0,"P07"," ") | AX8: =IF(SUM(COUNTIFS('Planificación 2026-1'!F:F,"SUNAMPE",'Planificación 2026-1'!W:W,C8,'Planificación 2026-1'!H:H,"DE"))>0,"P08"," ") | AY8: =IF(SUM(COUNTIFS('Planificación 2026-1'!F:F,"SUNAMPE",'Planificación 2026-1'!W:W,C8,'Planificación 2026-1'!H:H,"OB"))>0,"P09"," ") | AZ8: =IF(SUM(COUNTIFS('Planificación 2026-1'!F:F,"SUNAMPE",'Planificación 2026-1'!W:W,C8,'Planificación 2026-1'!H:H,"MH"))>0,"P31"," ") | BA8: =IF(SUM(COUNTIFS('Planificación 2026-1'!F:F,"SUNAMPE",'Planificación 2026-1'!W:W,C8,'Planificación 2026-1'!H:H,"IC"))>0,"P32"," ") | BB8: =IF(SUM(COUNTIFS('Planificación 2026-1'!F:F,"SUNAMPE",'Planificación 2026-1'!W:W,C8,'Planificación 2026-1'!H:H,"AR"))>0,"P34"," ") | BC8: =IF(SUM(COUNTIFS('Planificación 2026-1'!F:F,"SUNAMPE",'Planificación 2026-1'!W:W,C8,'Planificación 2026-1'!H:H,"T1"))>0,"P35"," ") | BD8: =IF(SUM(COUNTIFS('Planificación 2026-1'!F:F,"SUNAMPE",'Planificación 2026-1'!W:W,C8,'Planificación 2026-1'!H:H,"T3"))>0,"P36"," ") | BE8: =IF(SUM(COUNTIFS('Planificación 2026-1'!F:F,"SUNAMPE",'Planificación 2026-1'!W:W,C8,'Planificación 2026-1'!H:H,"T2"))>0,"P37"," ") | BF8: =IF(SUM(COUNTIFS('Planificación 2026-1'!F:F,"SUNAMPE",'Planificación 2026-1'!W:W,C8,'Planificación 2026-1'!H:H,"AE"))>0,"P38"," ") | BG8: =IF(SUM(COUNTIFS('Planificación 2026-1'!F:F,"SUNAMPE",'Planificación 2026-1'!W:W,C8,'Planificación 2026-1'!H:H,"T4"))>0,"P55"," ") | BH8: =IF(SUM(COUNTIFS('Planificación 2026-1'!F:F,"HUAURA",'Planificación 2026-1'!W:W,C8,'Planificación 2026-1'!H:H,"AF"))>0," P01"," ") | BI8: =IF(SUM(COUNTIFS('Planificación 2026-1'!F:F,"HUAURA",'Planificación 2026-1'!W:W,C8,'Planificación 2026-1'!H:H,"EN"))>0,"P02"," ") | BJ8: =IF(SUM(COUNTIFS('Planificación 2026-1'!F:F,"HUAURA",'Planificación 2026-1'!W:W,C8,'Planificación 2026-1'!H:H,"IS"))>0,"P03"," ") | BK8: =IF(SUM(COUNTIFS('Planificación 2026-1'!F:F,"HUAURA",'Planificación 2026-1'!W:W,C8,'Planificación 2026-1'!H:H,"PS"))>0,"P04"," ") | BM8: =IF(SUM(COUNTIFS('Planificación 2026-1'!F:F,"HUAURA",'Planificación 2026-1'!W:W,C8,'Planificación 2026-1'!H:H,"IN"))>0,"P06"," ") | BN8: =IF(SUM(COUNTIFS('Planificación 2026-1'!F:F,"HUAURA",'Planificación 2026-1'!W:W,C8,'Planificación 2026-1'!H:H,"CA"))>0,"P07"," ") | BO8: =IF(SUM(COUNTIFS('Planificación 2026-1'!F:F,"HUAURA",'Planificación 2026-1'!W:W,C8,'Planificación 2026-1'!H:H,"DE"))>0,"P08"," ") | BP8: =IF(SUM(COUNTIFS('Planificación 2026-1'!F:F,"HUAURA",'Planificación 2026-1'!W:W,C8,'Planificación 2026-1'!H:H,"OB"))>0,"P09"," ") | BQ8: =IF(SUM(COUNTIFS('Planificación 2026-1'!F:F,"HUAURA",'Planificación 2026-1'!W:W,C8,'Planificación 2026-1'!H:H,"MH"))>0,"P31"," ") | BR8: =IF(SUM(COUNTIFS('Planificación 2026-1'!F:F,"HUAURA",'Planificación 2026-1'!W:W,C8,'Planificación 2026-1'!H:H,"IC"))>0,"P32"," ") | BS8: =IF(SUM(COUNTIFS('Planificación 2026-1'!F:F,"HUAURA",'Planificación 2026-1'!W:W,C8,'Planificación 2026-1'!H:H,"AR"))>0,"P34"," ") | BT8: =IF(SUM(COUNTIFS('Planificación 2026-1'!F:F,"HUAURA",'Planificación 2026-1'!W:W,C8,'Planificación 2026-1'!H:H,"T1"))>0,"P35"," ") | BU8: =IF(SUM(COUNTIFS('Planificación 2026-1'!F:F,"HUAURA",'Planificación 2026-1'!W:W,C8,'Planificación 2026-1'!H:H,"T3"))>0,"P36"," ") | BV8: =IF(SUM(COUNTIFS('Planificación 2026-1'!F:F,"HUAURA",'Planificación 2026-1'!W:W,C8,'Planificación 2026-1'!H:H,"T2"))>0,"P37"," ") | BW8: =IF(SUM(COUNTIFS('Planificación 2026-1'!F:F,"HUAURA",'Planificación 2026-1'!W:W,C8,'Planificación 2026-1'!H:H,"AE"))>0,"P38"," ") | BX8: =IF(SUM(COUNTIFS('Planificación 2026-1'!F:F,"HUAURA",'Planificación 2026-1'!W:W,C8,'Planificación 2026-1'!H:H,"T4"))>0,"P55"," ") | BY8: =SUMIFS('Planificación 2026-1'!R:R,'Planificación 2026-1'!W:W,C8,'Planificación 2026-1'!H:H,"AF",'Planificación 2026-1'!I:I,">2") -> 0 | BZ8: =SUMIFS('Planificación 2026-1'!R:R,'Planificación 2026-1'!W:W,C8,'Planificación 2026-1'!H:H,"EN",'Planificación 2026-1'!I:I,">2") -> 0 | CA8: =SUMIFS('Planificación 2026-1'!R:R,'Planificación 2026-1'!W:W,C8,'Planificación 2026-1'!H:H,"IS",'Planificación 2026-1'!I:I,">2") -> 0 | CB8: =SUMIFS('Planificación 2026-1'!R:R,'Planificación 2026-1'!W:W,C8,'Planificación 2026-1'!H:H,"PS",'Planificación 2026-1'!I:I,">2") -> 0 | CC8: =SUMIFS('Planificación 2026-1'!R:R,'Planificación 2026-1'!W:W,C8,'Planificación 2026-1'!H:H,"IN",'Planificación 2026-1'!I:I,">2") -> 0 | CD8: =SUMIFS('Planificación 2026-1'!R:R,'Planificación 2026-1'!W:W,C8,'Planificación 2026-1'!H:H,"CA",'Planificación 2026-1'!I:I,">2") -> 0 | CE8: =SUMIFS('Planificación 2026-1'!R:R,'Planificación 2026-1'!W:W,C8,'Planificación 2026-1'!H:H,"DE",'Planificación 2026-1'!I:I,">2") -> 16 | CF8: =SUMIFS('Planificación 2026-1'!R:R,'Planificación 2026-1'!W:W,C8,'Planificación 2026-1'!H:H,"OB",'Planificación 2026-1'!I:I,">2") -> 0 | CG8: =SUMIFS('Planificación 2026-1'!R:R,'Planificación 2026-1'!W:W,C8,'Planificación 2026-1'!H:H,"MH",'Planificación 2026-1'!I:I,">2") -> 0 | CH8: =SUMIFS('Planificación 2026-1'!R:R,'Planificación 2026-1'!W:W,C8,'Planificación 2026-1'!H:H,"IC",'Planificación 2026-1'!I:I,">2") -> 0 | CI8: =SUMIFS('Planificación 2026-1'!R:R,'Planificación 2026-1'!W:W,C8,'Planificación 2026-1'!H:H,"AR",'Planificación 2026-1'!I:I,">2") -> 0 | CJ8: =SUMIFS('Planificación 2026-1'!R:R,'Planificación 2026-1'!W:W,C8,'Planificación 2026-1'!H:H,"T1",'Planificación 2026-1'!I:I,">2") -> 0 | CK8: =SUMIFS('Planificación 2026-1'!R:R,'Planificación 2026-1'!W:W,C8,'Planificación 2026-1'!H:H,"T3",'Planificación 2026-1'!I:I,">2") -> 0 | CL8: =SUMIFS('Planificación 2026-1'!R:R,'Planificación 2026-1'!W:W,C8,'Planificación 2026-1'!H:H,"T2",'Planificación 2026-1'!I:I,">2") -> 0 | CM8: =SUMIFS('Planificación 2026-1'!R:R,'Planificación 2026-1'!W:W,C8,'Planificación 2026-1'!H:H,"AE",'Planificación 2026-1'!I:I,">2") -> 0 | CN8: =SUMIFS('Planificación 2026-1'!R:R,'Planificación 2026-1'!W:W,C8,'Planificación 2026-1'!H:H,"T4",'Planificación 2026-1'!I:I,">2") -> 0 | CO8: =SUMIFS('Planificación 2026-1'!R:R,'Planificación 2026-1'!W:W,C8,'Planificación 2026-1'!H:H,"AF",'Planificación 2026-1'!I:I,"<3") -> 0 | CP8: =SUMIFS('Planificación 2026-1'!R:R,'Planificación 2026-1'!W:W,C8,'Planificación 2026-1'!H:H,"EN",'Planificación 2026-1'!I:I,"<3") -> 0 | CQ8: =SUMIFS('Planificación 2026-1'!R:R,'Planificación 2026-1'!W:W,C8,'Planificación 2026-1'!H:H,"IS",'Planificación 2026-1'!I:I,"<3") -> 0 | CR8: =SUMIFS('Planificación 2026-1'!R:R,'Planificación 2026-1'!W:W,C8,'Planificación 2026-1'!H:H,"PS",'Planificación 2026-1'!I:I,"<3") -> 0 | CS8: =SUMIFS('Planificación 2026-1'!R:R,'Planificación 2026-1'!W:W,C8,'Planificación 2026-1'!H:H,"IN",'Planificación 2026-1'!I:I,"<3") -> 0 | CT8: =SUMIFS('Planificación 2026-1'!R:R,'Planificación 2026-1'!W:W,C8,'Planificación 2026-1'!H:H,"CA",'Planificación 2026-1'!I:I,"<3") -> 0 | CU8: =SUMIFS('Planificación 2026-1'!R:R,'Planificación 2026-1'!W:W,C8,'Planificación 2026-1'!H:H,"DE",'Planificación 2026-1'!I:I,"<3") -> 0 | CV8: =SUMIFS('Planificación 2026-1'!R:R,'Planificación 2026-1'!W:W,C8,'Planificación 2026-1'!H:H,"OB",'Planificación 2026-1'!I:I,"<3") -> 0 | CW8: =SUMIFS('Planificación 2026-1'!R:R,'Planificación 2026-1'!W:W,C8,'Planificación 2026-1'!H:H,"MH",'Planificación 2026-1'!I:I,"<3") -> 0 | CX8: =SUMIFS('Planificación 2026-1'!R:R,'Planificación 2026-1'!W:W,C8,'Planificación 2026-1'!H:H,"IC",'Planificación 2026-1'!I:I,"<3") -> 0 | CY8: =SUMIFS('Planificación 2026-1'!R:R,'Planificación 2026-1'!W:W,C8,'Planificación 2026-1'!H:H,"AR",'Planificación 2026-1'!I:I,"<3") -> 0 | CZ8: =SUMIFS('Planificación 2026-1'!R:R,'Planificación 2026-1'!W:W,C8,'Planificación 2026-1'!H:H,"T1",'Planificación 2026-1'!I:I,"<3") -> 0 | DA8: =SUMIFS('Planificación 2026-1'!R:R,'Planificación 2026-1'!W:W,C8,'Planificación 2026-1'!H:H,"T3",'Planificación 2026-1'!I:I,"<3") -> 0 | DB8: =SUMIFS('Planificación 2026-1'!R:R,'Planificación 2026-1'!W:W,C8,'Planificación 2026-1'!H:H,"T2",'Planificación 2026-1'!I:I,"<3") -> 0 | DC8: =SUMIFS('Planificación 2026-1'!R:R,'Planificación 2026-1'!W:W,C8,'Planificación 2026-1'!H:H,"AE",'Planificación 2026-1'!I:I,"<3") -> 0 | DD8: =SUMIFS('Planificación 2026-1'!R:R,'Planificación 2026-1'!W:W,C8,'Planificación 2026-1'!H:H,"T4",'Planificación 2026-1'!I:I,"<3") -> 0 | DE8: =TRIM(CONCATENATE(I8,J8,K8,L8,M8,N8,O8,P8,Q8,R8,S8,T8,U8,V8,W8,X8,Y8)) | DF8: =IF(C8="","",SUMIFS('Planificación 2026-1'!R:R,'Planificación 2026-1'!W:W,C8,'Planificación 2026-1'!F:F,"PRINCIPAL",'Planificación 2026-1'!X:X,"VIRTUAL")) -> 0 | DG8: =IF(C8="","",SUMIFS('Planificación 2026-1'!R:R,'Planificación 2026-1'!W:W,C8,'Planificación 2026-1'!F:F,"PRINCIPAL",'Planificación 2026-1'!X:X,"PRESENCIAL")) -> 0 | DH8: =IF(C8="","",SUMIFS('Planificación 2026-1'!R:R,'Planificación 2026-1'!W:W,C8,'Planificación 2026-1'!F:F,"PRINCIPAL",'Planificación 2026-1'!X:X,"HIBRIDO PRESENCIAL")) -> 0 | DI8: =TRIM(CONCATENATE(Z8,AA8,AB8,AC8,AD8,AE8,AF8,AG8,AH8,AI8,AJ8,AK8,AL8,AM8,AN8,AO8,AP8)) -> P08 | DJ8: =IF(C8="","",SUMIFS('Planificación 2026-1'!R:R,'Planificación 2026-1'!W:W,C8,'Planificación 2026-1'!F:F,"FILIAL",'Planificación 2026-1'!X:X,"VIRTUAL")) -> 16 | DK8: =IF(C8="","",SUMIFS('Planificación 2026-1'!R:R,'Planificación 2026-1'!W:W,C8,'Planificación 2026-1'!F:F,"FILIAL",'Planificación 2026-1'!X:X,"PRESENCIAL")) -> 0 | DL8: =IF(C8="","",SUMIFS('Planificación 2026-1'!R:R,'Planificación 2026-1'!W:W,C8,'Planificación 2026-1'!F:F,"FILIAL",'Planificación 2026-1'!X:X,"HIBRIDO PRESENCIAL")) -> 0 | DM8: =TRIM(CONCATENATE(AQ8,AR8,AS8,AT8,AU8,AV8,AW8,AX8,AY8,AZ8,BA8,BB8,BC8,BD8,BE8,BF8,BG8)) | DN8: =IF(C8="","",SUMIFS('Planificación 2026-1'!R:R,'Planificación 2026-1'!W:W,C8,'Planificación 2026-1'!F:F,"SUNAMPE",'Planificación 2026-1'!X:X,"VIRTUAL")) -> 0 | DO8: =IF(C8="","",SUMIFS('Planificación 2026-1'!R:R,'Planificación 2026-1'!W:W,C8,'Planificación 2026-1'!F:F,"SUNAMPE",'Planificación 2026-1'!X:X,"PRESENCIAL")) -> 0 | DP8: =TRIM(CONCATENATE(BH8,BI8,BJ8,BK8,BL8,BM8,BN8,BO8,BP8,BQ8,BR8,BS8,BT8,BU8,BV8,BW8,BX8)) | DQ8: =IF(C8="","",SUMIFS('Planificación 2026-1'!R:R,'Planificación 2026-1'!W:W,C8,'Planificación 2026-1'!F:F,"HUAURA",'Planificación 2026-1'!X:X,"VIRTUAL")) -> 0 | DR8: =IF(C8="","",SUMIFS('Planificación 2026-1'!R:R,'Planificación 2026-1'!W:W,C8,'Planificación 2026-1'!F:F,"HUAURA",'Planificación 2026-1'!X:X,"PRESENCIAL")) -> 0 | DS8: =SUMIFS('Planificación 2026-1'!R:R,'Planificación 2026-1'!W:W,C8,'Planificación 2026-1'!F:F,"PRINCIPAL",'Planificación 2026-1'!X:X,"VIRTUAL",'Planificación 2026-1'!I:I,">2") -> 0 | DT8: =SUMIFS('Planificación 2026-1'!R:R,'Planificación 2026-1'!W:W,C8,'Planificación 2026-1'!F:F,"PRINCIPAL",'Planificación 2026-1'!X:X,"<>VIRTUAL",'Planificación 2026-1'!I:I,">2") -> 0 | DU8: =SUMIFS('Planificación 2026-1'!R:R,'Planificación 2026-1'!W:W,C8,'Planificación 2026-1'!F:F,"SUNAMPE",'Planificación 2026-1'!X:X,"VIRTUAL",'Planificación 2026-1'!I:I,">2") -> 0 | DV8: =SUMIFS('Planificación 2026-1'!R:R,'Planificación 2026-1'!W:W,C8,'Planificación 2026-1'!F:F,"SUNAMPE",'Planificación 2026-1'!X:X,"<>VIRTUAL",'Planificación 2026-1'!I:I,">2") -> 0 | DW8: =SUMIFS('Planificación 2026-1'!R:R,'Planificación 2026-1'!W:W,C8,'Planificación 2026-1'!F:F,"FILIAL",'Planificación 2026-1'!X:X,"VIRTUAL",'Planificación 2026-1'!I:I,">2") -> 16 | DX8: =SUMIFS('Planificación 2026-1'!R:R,'Planificación 2026-1'!W:W,C8,'Planificación 2026-1'!F:F,"FILIAL",'Planificación 2026-1'!X:X,"<>VIRTUAL",'Planificación 2026-1'!I:I,">2") -> 0 | DY8: =SUMIFS('Planificación 2026-1'!R:R,'Planificación 2026-1'!W:W,C8,'Planificación 2026-1'!F:F,"PORUMA",'Planificación 2026-1'!X:X,"VIRTUAL",'Planificación 2026-1'!I:I,">2") -> 0 | DZ8: =SUMIFS('Planificación 2026-1'!R:R,'Planificación 2026-1'!W:W,C8,'Planificación 2026-1'!F:F,"PORUMA",'Planificación 2026-1'!X:X,"<>VIRTUAL",'Planificación 2026-1'!I:I,">2") -> 0 | EA8: =SUMIFS('Planificación 2026-1'!R:R,'Planificación 2026-1'!W:W,C8,'Planificación 2026-1'!F:F,"HUAURA",'Planificación 2026-1'!X:X,"VIRTUAL",'Planificación 2026-1'!I:I,">2") -> 0 | EB8: =SUMIFS('Planificación 2026-1'!R:R,'Planificación 2026-1'!W:W,C8,'Planificación 2026-1'!F:F,"HUAURA",'Planificación 2026-1'!X:X,"<>VIRTUAL",'Planificación 2026-1'!I:I,">2") -> 0 | EC8: =SUMIFS('Planificación 2026-1'!R:R,'Planificación 2026-1'!W:W,C8,'Planificación 2026-1'!F:F,"PRINCIPAL",'Planificación 2026-1'!X:X,"VIRTUAL",'Planificación 2026-1'!I:I,"<3") -> 0 | ED8: =SUMIFS('Planificación 2026-1'!R:R,'Planificación 2026-1'!W:W,C8,'Planificación 2026-1'!F:F,"PRINCIPAL",'Planificación 2026-1'!X:X,"<>VIRTUAL",'Planificación 2026-1'!I:I,"<3") -> 0 | EE8: =SUMIFS('Planificación 2026-1'!R:R,'Planificación 2026-1'!W:W,C8,'Planificación 2026-1'!F:F,"SUNAMPE",'Planificación 2026-1'!X:X,"VIRTUAL",'Planificación 2026-1'!I:I,"<3") -> 0 | EF8: =SUMIFS('Planificación 2026-1'!R:R,'Planificación 2026-1'!W:W,C8,'Planificación 2026-1'!F:F,"SUNAMPE",'Planificación 2026-1'!X:X,"<>VIRTUAL",'Planificación 2026-1'!I:I,"<3") -> 0 | EG8: =SUMIFS('Planificación 2026-1'!R:R,'Planificación 2026-1'!W:W,C8,'Planificación 2026-1'!F:F,"FILIAL",'Planificación 2026-1'!X:X,"VIRTUAL",'Planificación 2026-1'!I:I,"<3") -> 0 | EH8: =SUMIFS('Planificación 2026-1'!R:R,'Planificación 2026-1'!W:W,C8,'Planificación 2026-1'!F:F,"FILIAL",'Planificación 2026-1'!X:X,"<>VIRTUAL",'Planificación 2026-1'!I:I,"<3") -> 0 | EI8: =SUMIFS('Planificación 2026-1'!R:R,'Planificación 2026-1'!W:W,C8,'Planificación 2026-1'!F:F,"PORUMA",'Planificación 2026-1'!X:X,"VIRTUAL",'Planificación 2026-1'!I:I,"<3") -> 0 | EJ8: =SUMIFS('Planificación 2026-1'!R:R,'Planificación 2026-1'!W:W,C8,'Planificación 2026-1'!F:F,"PORUMA",'Planificación 2026-1'!X:X,"<>VIRTUAL",'Planificación 2026-1'!I:I,"<3") -> 0 | EK8: =SUMIFS('Planificación 2026-1'!R:R,'Planificación 2026-1'!W:W,C8,'Planificación 2026-1'!F:F,"HUAURA",'Planificación 2026-1'!X:X,"VIRTUAL",'Planificación 2026-1'!I:I,"<3") -> 0 | EL8: =SUMIFS('Planificación 2026-1'!R:R,'Planificación 2026-1'!W:W,C8,'Planificación 2026-1'!F:F,"HUAURA",'Planificación 2026-1'!X:X,"<>VIRTUAL",'Planificación 2026-1'!I:I,"<3") -> 0 | EN8: =DS8+DW8+EA8+EC8+EG8+EK8+DU8+EE8 -> 16 | EO8: =DT8+DX8+EB8+ED8+EH8+EL8+DV8+EF8 -> 0 | EP8: =EXACT(SUM(EN8:EO8),D8) -> TRUE | EQ8: =IF(AND(DT8=0,DX8=0,EB8=0),"",IF(COUNTIF(DT8:EB8,">0")=1,IF(DT8>0,"SEDE",IF(DX8>0,"FILIAL","HUAURA")),IF(COUNTIF(DT8:EB8,">0")=2,IF(AND(DT8>0,DX8>0),"SEDE-FILIAL",IF(AND(DT8>0,EB8>0),"SEDE-HUAURA","FILIAL-HUAURA")),"SEDE-FILIAL-HUAURA"))) | ER8: =IF(EN8=0,"PRESENCIAL",IF(EO8=0,"VIRTUAL",IF(EN8>EO8,"MAS VIRTUAL",IF(EO8>EN8,"MAS PRESENCIAL","AMBOS")))) -> VIRTUAL
B9: 6 | C9: ALFARO CAYLLAHUA CARLOS HUGO | D9: =SUMIF('Planificación 2026-1'!W:W,C9,'Planificación 2026-1'!R:R) -> 15 | E9: TP | F9: RENOVACIÓN | G9: FILIAL | H9: INGENIERÍA CIVIL | I9: =IF(SUM(COUNTIFS('Planificación 2026-1'!F:F,"PRINCIPAL",'Planificación 2026-1'!W:W,C9,'Planificación 2026-1'!H:H,"AF"))>0,"P01"," ") | J9: =IF(SUM(COUNTIFS('Planificación 2026-1'!F:F,"PRINCIPAL",'Planificación 2026-1'!W:W,C9,'Planificación 2026-1'!H:H,"EN"))>0,"P02"," ") | K9: =IF(SUM(COUNTIFS('Planificación 2026-1'!F:F,"PRINCIPAL",'Planificación 2026-1'!W:W,C9,'Planificación 2026-1'!H:H,"IS"))>0,"P03"," ") | L9: =IF(SUM(COUNTIFS('Planificación 2026-1'!F:F,"PRINCIPAL",'Planificación 2026-1'!W:W,C9,'Planificación 2026-1'!H:H,"PS"))>0,"P04"," ") | N9: =IF(SUM(COUNTIFS('Planificación 2026-1'!F:F,"PRINCIPAL",'Planificación 2026-1'!W:W,C9,'Planificación 2026-1'!H:H,"IN"))>0,"P06"," ") | O9: =IF(SUM(COUNTIFS('Planificación 2026-1'!F:F,"PRINCIPAL",'Planificación 2026-1'!W:W,C9,'Planificación 2026-1'!H:H,"CA"))>0,"P07"," ") | P9: =IF(SUM(COUNTIFS('Planificación 2026-1'!F:F,"PRINCIPAL",'Planificación 2026-1'!W:W,C9,'Planificación 2026-1'!H:H,"DE"))>0,"P08"," ") | Q9: =IF(SUM(COUNTIFS('Planificación 2026-1'!F:F,"PRINCIPAL",'Planificación 2026-1'!W:W,C9,'Planificación 2026-1'!H:H,"OB"))>0,"P09"," ") | R9: =IF(SUM(COUNTIFS('Planificación 2026-1'!F:F,"PRINCIPAL",'Planificación 2026-1'!W:W,C9,'Planificación 2026-1'!H:H,"MH"))>0,"P31"," ") | S9: =IF(SUM(COUNTIFS('Planificación 2026-1'!F:F,"PRINCIPAL",'Planificación 2026-1'!W:W,C9,'Planificación 2026-1'!H:H,"IC"))>0,"P32"," ") | T9: =IF(SUM(COUNTIFS('Planificación 2026-1'!F:F,"PRINCIPAL",'Planificación 2026-1'!W:W,C9,'Planificación 2026-1'!H:H,"AR"))>0,"P34"," ") | U9: =IF(SUM(COUNTIFS('Planificación 2026-1'!F:F,"PRINCIPAL",'Planificación 2026-1'!W:W,C9,'Planificación 2026-1'!H:H,"T1"))>0,"P35"," ") | V9: =IF(SUM(COUNTIFS('Planificación 2026-1'!F:F,"PRINCIPAL",'Planificación 2026-1'!W:W,C9,'Planificación 2026-1'!H:H,"T3"))>0,"P36"," ") | W9: =IF(SUM(COUNTIFS('Planificación 2026-1'!F:F,"PRINCIPAL",'Planificación 2026-1'!W:W,C9,'Planificación 2026-1'!H:H,"T2"))>0,"P37"," ") | X9: =IF(SUM(COUNTIFS('Planificación 2026-1'!F:F,"PRINCIPAL",'Planificación 2026-1'!W:W,C9,'Planificación 2026-1'!H:H,"AE"))>0,"P38"," ") | Y9: =IF(SUM(COUNTIFS('Planificación 2026-1'!F:F,"PRINCIPAL",'Planificación 2026-1'!W:W,C9,'Planificación 2026-1'!H:H,"T4"))>0,"P55"," ") | Z9: =IF(SUM(COUNTIFS('Planificación 2026-1'!F:F,"FILIAL",'Planificación 2026-1'!W:W,C9,'Planificación 2026-1'!H:H,"AF"))>0," P01"," ") | AA9: =IF(SUM(COUNTIFS('Planificación 2026-1'!F:F,"FILIAL",'Planificación 2026-1'!W:W,C9,'Planificación 2026-1'!H:H,"EN"))>0,"P02"," ") | AB9: =IF(SUM(COUNTIFS('Planificación 2026-1'!F:F,"FILIAL",'Planificación 2026-1'!W:W,C9,'Planificación 2026-1'!H:H,"IS"))>0,"P03"," ") | AC9: =IF(SUM(COUNTIFS('Planificación 2026-1'!F:F,"FILIAL",'Planificación 2026-1'!W:W,C9,'Planificación 2026-1'!H:H,"PS"))>0,"P04"," ") | AE9: =IF(SUM(COUNTIFS('Planificación 2026-1'!F:F,"FILIAL",'Planificación 2026-1'!W:W,C9,'Planificación 2026-1'!H:H,"IN"))>0,"P06"," ") -> P06 | AF9: =IF(SUM(COUNTIFS('Planificación 2026-1'!F:F,"FILIAL",'Planificación 2026-1'!W:W,C9,'Planificación 2026-1'!H:H,"CA"))>0,"P07"," ") | AG9: =IF(SUM(COUNTIFS('Planificación 2026-1'!F:F,"FILIAL",'Planificación 2026-1'!W:W,C9,'Planificación 2026-1'!H:H,"DE"))>0,"P08"," ") | AH9: =IF(SUM(COUNTIFS('Planificación 2026-1'!F:F,"FILIAL",'Planificación 2026-1'!W:W,C9,'Planificación 2026-1'!H:H,"OB"))>0,"P09"," ") | AI9: =IF(SUM(COUNTIFS('Planificación 2026-1'!F:F,"FILIAL",'Planificación 2026-1'!W:W,C9,'Planificación 2026-1'!H:H,"MH"))>0,"P31"," ") | AJ9: =IF(SUM(COUNTIFS('Planificación 2026-1'!F:F,"FILIAL",'Planificación 2026-1'!W:W,C9,'Planificación 2026-1'!H:H,"IC"))>0,"P32"," ") -> P32 | AK9: =IF(SUM(COUNTIFS('Planificación 2026-1'!F:F,"FILIAL",'Planificación 2026-1'!W:W,C9,'Planificación 2026-1'!H:H,"AR"))>0,"P34"," ") | AL9: =IF(SUM(COUNTIFS('Planificación 2026-1'!F:F,"FILIAL",'Planificación 2026-1'!W:W,C9,'Planificación 2026-1'!H:H,"T1"))>0,"P35"," ") | AM9: =IF(SUM(COUNTIFS('Planificación 2026-1'!F:F,"FILIAL",'Planificación 2026-1'!W:W,C9,'Planificación 2026-1'!H:H,"T3"))>0,"P36"," ") | AN9: =IF(SUM(COUNTIFS('Planificación 2026-1'!F:F,"FILIAL",'Planificación 2026-1'!W:W,C9,'Planificación 2026-1'!H:H,"T2"))>0,"P37"," ") | AO9: =IF(SUM(COUNTIFS('Planificación 2026-1'!F:F,"FILIAL",'Planificación 2026-1'!W:W,C9,'Planificación 2026-1'!H:H,"AE"))>0,"P38"," ") | AP9: =IF(SUM(COUNTIFS('Planificación 2026-1'!F:F,"FILIAL",'Planificación 2026-1'!W:W,C9,'Planificación 2026-1'!H:H,"T4"))>0,"P55"," ") | AQ9: =IF(SUM(COUNTIFS('Planificación 2026-1'!F:F,"SUNAMPE",'Planificación 2026-1'!W:W,C9,'Planificación 2026-1'!H:H,"AF"))>0," P01"," ") | AR9: =IF(SUM(COUNTIFS('Planificación 2026-1'!F:F,"SUNAMPE",'Planificación 2026-1'!W:W,C9,'Planificación 2026-1'!H:H,"EN"))>0,"P02"," ") | AS9: =IF(SUM(COUNTIFS('Planificación 2026-1'!F:F,"SUNAMPE",'Planificación 2026-1'!W:W,C9,'Planificación 2026-1'!H:H,"IS"))>0,"P03"," ") | AT9: =IF(SUM(COUNTIFS('Planificación 2026-1'!F:F,"SUNAMPE",'Planificación 2026-1'!W:W,C9,'Planificación 2026-1'!H:H,"PS"))>0,"P04"," ") | AV9: =IF(SUM(COUNTIFS('Planificación 2026-1'!F:F,"SUNAMPE",'Planificación 2026-1'!W:W,C9,'Planificación 2026-1'!H:H,"IN"))>0,"P06"," ") | AW9: =IF(SUM(COUNTIFS('Planificación 2026-1'!F:F,"SUNAMPE",'Planificación 2026-1'!W:W,C9,'Planificación 2026-1'!H:H,"CA"))>0,"P07"," ") | AX9: =IF(SUM(COUNTIFS('Planificación 2026-1'!F:F,"SUNAMPE",'Planificación 2026-1'!W:W,C9,'Planificación 2026-1'!H:H,"DE"))>0,"P08"," ") | AY9: =IF(SUM(COUNTIFS('Planificación 2026-1'!F:F,"SUNAMPE",'Planificación 2026-1'!W:W,C9,'Planificación 2026-1'!H:H,"OB"))>0,"P09"," ") | AZ9: =IF(SUM(COUNTIFS('Planificación 2026-1'!F:F,"SUNAMPE",'Planificación 2026-1'!W:W,C9,'Planificación 2026-1'!H:H,"MH"))>0,"P31"," ") | BA9: =IF(SUM(COUNTIFS('Planificación 2026-1'!F:F,"SUNAMPE",'Planificación 2026-1'!W:W,C9,'Planificación 2026-1'!H:H,"IC"))>0,"P32"," ") | BB9: =IF(SUM(COUNTIFS('Planificación 2026-1'!F:F,"SUNAMPE",'Planificación 2026-1'!W:W,C9,'Planificación 2026-1'!H:H,"AR"))>0,"P34"," ") | BC9: =IF(SUM(COUNTIFS('Planificación 2026-1'!F:F,"SUNAMPE",'Planificación 2026-1'!W:W,C9,'Planificación 2026-1'!H:H,"T1"))>0,"P35"," ") | BD9: =IF(SUM(COUNTIFS('Planificación 2026-1'!F:F,"SUNAMPE",'Planificación 2026-1'!W:W,C9,'Planificación 2026-1'!H:H,"T3"))>0,"P36"," ") | BE9: =IF(SUM(COUNTIFS('Planificación 2026-1'!F:F,"SUNAMPE",'Planificación 2026-1'!W:W,C9,'Planificación 2026-1'!H:H,"T2"))>0,"P37"," ") | BF9: =IF(SUM(COUNTIFS('Planificación 2026-1'!F:F,"SUNAMPE",'Planificación 2026-1'!W:W,C9,'Planificación 2026-1'!H:H,"AE"))>0,"P38"," ") | BG9: =IF(SUM(COUNTIFS('Planificación 2026-1'!F:F,"SUNAMPE",'Planificación 2026-1'!W:W,C9,'Planificación 2026-1'!H:H,"T4"))>0,"P55"," ") | BH9: =IF(SUM(COUNTIFS('Planificación 2026-1'!F:F,"HUAURA",'Planificación 2026-1'!W:W,C9,'Planificación 2026-1'!H:H,"AF"))>0," P01"," ") | BI9: =IF(SUM(COUNTIFS('Planificación 2026-1'!F:F,"HUAURA",'Planificación 2026-1'!W:W,C9,'Planificación 2026-1'!H:H,"EN"))>0,"P02"," ") | BJ9: =IF(SUM(COUNTIFS('Planificación 2026-1'!F:F,"HUAURA",'Planificación 2026-1'!W:W,C9,'Planificación 2026-1'!H:H,"IS"))>0,"P03"," ") | BK9: =IF(SUM(COUNTIFS('Planificación 2026-1'!F:F,"HUAURA",'Planificación 2026-1'!W:W,C9,'Planificación 2026-1'!H:H,"PS"))>0,"P04"," ") | BM9: =IF(SUM(COUNTIFS('Planificación 2026-1'!F:F,"HUAURA",'Planificación 2026-1'!W:W,C9,'Planificación 2026-1'!H:H,"IN"))>0,"P06"," ") | BN9: =IF(SUM(COUNTIFS('Planificación 2026-1'!F:F,"HUAURA",'Planificación 2026-1'!W:W,C9,'Planificación 2026-1'!H:H,"CA"))>0,"P07"," ") | BO9: =IF(SUM(COUNTIFS('Planificación 2026-1'!F:F,"HUAURA",'Planificación 2026-1'!W:W,C9,'Planificación 2026-1'!H:H,"DE"))>0,"P08"," ") | BP9: =IF(SUM(COUNTIFS('Planificación 2026-1'!F:F,"HUAURA",'Planificación 2026-1'!W:W,C9,'Planificación 2026-1'!H:H,"OB"))>0,"P09"," ") | BQ9: =IF(SUM(COUNTIFS('Planificación 2026-1'!F:F,"HUAURA",'Planificación 2026-1'!W:W,C9,'Planificación 2026-1'!H:H,"MH"))>0,"P31"," ") | BR9: =IF(SUM(COUNTIFS('Planificación 2026-1'!F:F,"HUAURA",'Planificación 2026-1'!W:W,C9,'Planificación 2026-1'!H:H,"IC"))>0,"P32"," ") | BS9: =IF(SUM(COUNTIFS('Planificación 2026-1'!F:F,"HUAURA",'Planificación 2026-1'!W:W,C9,'Planificación 2026-1'!H:H,"AR"))>0,"P34"," ") | BT9: =IF(SUM(COUNTIFS('Planificación 2026-1'!F:F,"HUAURA",'Planificación 2026-1'!W:W,C9,'Planificación 2026-1'!H:H,"T1"))>0,"P35"," ") | BU9: =IF(SUM(COUNTIFS('Planificación 2026-1'!F:F,"HUAURA",'Planificación 2026-1'!W:W,C9,'Planificación 2026-1'!H:H,"T3"))>0,"P36"," ") | BV9: =IF(SUM(COUNTIFS('Planificación 2026-1'!F:F,"HUAURA",'Planificación 2026-1'!W:W,C9,'Planificación 2026-1'!H:H,"T2"))>0,"P37"," ") | BW9: =IF(SUM(COUNTIFS('Planificación 2026-1'!F:F,"HUAURA",'Planificación 2026-1'!W:W,C9,'Planificación 2026-1'!H:H,"AE"))>0,"P38"," ") | BX9: =IF(SUM(COUNTIFS('Planificación 2026-1'!F:F,"HUAURA",'Planificación 2026-1'!W:W,C9,'Planificación 2026-1'!H:H,"T4"))>0,"P55"," ") | BY9: =SUMIFS('Planificación 2026-1'!R:R,'Planificación 2026-1'!W:W,C9,'Planificación 2026-1'!H:H,"AF",'Planificación 2026-1'!I:I,">2") -> 0 | BZ9: =SUMIFS('Planificación 2026-1'!R:R,'Planificación 2026-1'!W:W,C9,'Planificación 2026-1'!H:H,"EN",'Planificación 2026-1'!I:I,">2") -> 0 | CA9: =SUMIFS('Planificación 2026-1'!R:R,'Planificación 2026-1'!W:W,C9,'Planificación 2026-1'!H:H,"IS",'Planificación 2026-1'!I:I,">2") -> 0 | CB9: =SUMIFS('Planificación 2026-1'!R:R,'Planificación 2026-1'!W:W,C9,'Planificación 2026-1'!H:H,"PS",'Planificación 2026-1'!I:I,">2") -> 0 | CC9: =SUMIFS('Planificación 2026-1'!R:R,'Planificación 2026-1'!W:W,C9,'Planificación 2026-1'!H:H,"IN",'Planificación 2026-1'!I:I,">2") -> 5 | CD9: =SUMIFS('Planificación 2026-1'!R:R,'Planificación 2026-1'!W:W,C9,'Planificación 2026-1'!H:H,"CA",'Planificación 2026-1'!I:I,">2") -> 0 | CE9: =SUMIFS('Planificación 2026-1'!R:R,'Planificación 2026-1'!W:W,C9,'Planificación 2026-1'!H:H,"DE",'Planificación 2026-1'!I:I,">2") -> 0 | CF9: =SUMIFS('Planificación 2026-1'!R:R,'Planificación 2026-1'!W:W,C9,'Planificación 2026-1'!H:H,"OB",'Planificación 2026-1'!I:I,">2") -> 0 | CG9: =SUMIFS('Planificación 2026-1'!R:R,'Planificación 2026-1'!W:W,C9,'Planificación 2026-1'!H:H,"MH",'Planificación 2026-1'!I:I,">2") -> 0 | CH9: =SUMIFS('Planificación 2026-1'!R:R,'Planificación 2026-1'!W:W,C9,'Planificación 2026-1'!H:H,"IC",'Planificación 2026-1'!I:I,">2") -> 10 | CI9: =SUMIFS('Planificación 2026-1'!R:R,'Planificación 2026-1'!W:W,C9,'Planificación 2026-1'!H:H,"AR",'Planificación 2026-1'!I:I,">2") -> 0 | CJ9: =SUMIFS('Planificación 2026-1'!R:R,'Planificación 2026-1'!W:W,C9,'Planificación 2026-1'!H:H,"T1",'Planificación 2026-1'!I:I,">2") -> 0 | CK9: =SUMIFS('Planificación 2026-1'!R:R,'Planificación 2026-1'!W:W,C9,'Planificación 2026-1'!H:H,"T3",'Planificación 2026-1'!I:I,">2") -> 0 | CL9: =SUMIFS('Planificación 2026-1'!R:R,'Planificación 2026-1'!W:W,C9,'Planificación 2026-1'!H:H,"T2",'Planificación 2026-1'!I:I,">2") -> 0 | CM9: =SUMIFS('Planificación 2026-1'!R:R,'Planificación 2026-1'!W:W,C9,'Planificación 2026-1'!H:H,"AE",'Planificación 2026-1'!I:I,">2") -> 0 | CN9: =SUMIFS('Planificación 2026-1'!R:R,'Planificación 2026-1'!W:W,C9,'Planificación 2026-1'!H:H,"T4",'Planificación 2026-1'!I:I,">2") -> 0 | CO9: =SUMIFS('Planificación 2026-1'!R:R,'Planificación 2026-1'!W:W,C9,'Planificación 2026-1'!H:H,"AF",'Planificación 2026-1'!I:I,"<3") -> 0 | CP9: =SUMIFS('Planificación 2026-1'!R:R,'Planificación 2026-1'!W:W,C9,'Planificación 2026-1'!H:H,"EN",'Planificación 2026-1'!I:I,"<3") -> 0 | CQ9: =SUMIFS('Planificación 2026-1'!R:R,'Planificación 2026-1'!W:W,C9,'Planificación 2026-1'!H:H,"IS",'Planificación 2026-1'!I:I,"<3") -> 0 | CR9: =SUMIFS('Planificación 2026-1'!R:R,'Planificación 2026-1'!W:W,C9,'Planificación 2026-1'!H:H,"PS",'Planificación 2026-1'!I:I,"<3") -> 0 | CS9: =SUMIFS('Planificación 2026-1'!R:R,'Planificación 2026-1'!W:W,C9,'Planificación 2026-1'!H:H,"IN",'Planificación 2026-1'!I:I,"<3") -> 0 | CT9: =SUMIFS('Planificación 2026-1'!R:R,'Planificación 2026-1'!W:W,C9,'Planificación 2026-1'!H:H,"CA",'Planificación 2026-1'!I:I,"<3") -> 0 | CU9: =SUMIFS('Planificación 2026-1'!R:R,'Planificación 2026-1'!W:W,C9,'Planificación 2026-1'!H:H,"DE",'Planificación 2026-1'!I:I,"<3") -> 0 | CV9: =SUMIFS('Planificación 2026-1'!R:R,'Planificación 2026-1'!W:W,C9,'Planificación 2026-1'!H:H,"OB",'Planificación 2026-1'!I:I,"<3") -> 0 | CW9: =SUMIFS('Planificación 2026-1'!R:R,'Planificación 2026-1'!W:W,C9,'Planificación 2026-1'!H:H,"MH",'Planificación 2026-1'!I:I,"<3") -> 0 | CX9: =SUMIFS('Planificación 2026-1'!R:R,'Planificación 2026-1'!W:W,C9,'Planificación 2026-1'!H:H,"IC",'Planificación 2026-1'!I:I,"<3") -> 0 | CY9: =SUMIFS('Planificación 2026-1'!R:R,'Planificación 2026-1'!W:W,C9,'Planificación 2026-1'!H:H,"AR",'Planificación 2026-1'!I:I,"<3") -> 0 | CZ9: =SUMIFS('Planificación 2026-1'!R:R,'Planificación 2026-1'!W:W,C9,'Planificación 2026-1'!H:H,"T1",'Planificación 2026-1'!I:I,"<3") -> 0 | DA9: =SUMIFS('Planificación 2026-1'!R:R,'Planificación 2026-1'!W:W,C9,'Planificación 2026-1'!H:H,"T3",'Planificación 2026-1'!I:I,"<3") -> 0 | DB9: =SUMIFS('Planificación 2026-1'!R:R,'Planificación 2026-1'!W:W,C9,'Planificación 2026-1'!H:H,"T2",'Planificación 2026-1'!I:I,"<3") -> 0 | DC9: =SUMIFS('Planificación 2026-1'!R:R,'Planificación 2026-1'!W:W,C9,'Planificación 2026-1'!H:H,"AE",'Planificación 2026-1'!I:I,"<3") -> 0 | DD9: =SUMIFS('Planificación 2026-1'!R:R,'Planificación 2026-1'!W:W,C9,'Planificación 2026-1'!H:H,"T4",'Planificación 2026-1'!I:I,"<3") -> 0 | DE9: =TRIM(CONCATENATE(I9,J9,K9,L9,M9,N9,O9,P9,Q9,R9,S9,T9,U9,V9,W9,X9,Y9)) | DF9: =IF(C9="","",SUMIFS('Planificación 2026-1'!R:R,'Planificación 2026-1'!W:W,C9,'Planificación 2026-1'!F:F,"PRINCIPAL",'Planificación 2026-1'!X:X,"VIRTUAL")) -> 0 | DG9: =IF(C9="","",SUMIFS('Planificación 2026-1'!R:R,'Planificación 2026-1'!W:W,C9,'Planificación 2026-1'!F:F,"PRINCIPAL",'Planificación 2026-1'!X:X,"PRESENCIAL")) -> 0 | DH9: =IF(C9="","",SUMIFS('Planificación 2026-1'!R:R,'Planificación 2026-1'!W:W,C9,'Planificación 2026-1'!F:F,"PRINCIPAL",'Planificación 2026-1'!X:X,"HIBRIDO PRESENCIAL")) -> 0 | DI9: =TRIM(CONCATENATE(Z9,AA9,AB9,AC9,AD9,AE9,AF9,AG9,AH9,AI9,AJ9,AK9,AL9,AM9,AN9,AO9,AP9)) -> P06 P32 | DJ9: =IF(C9="","",SUMIFS('Planificación 2026-1'!R:R,'Planificación 2026-1'!W:W,C9,'Planificación 2026-1'!F:F,"FILIAL",'Planificación 2026-1'!X:X,"VIRTUAL")) -> 0 | DK9: =IF(C9="","",SUMIFS('Planificación 2026-1'!R:R,'Planificación 2026-1'!W:W,C9,'Planificación 2026-1'!F:F,"FILIAL",'Planificación 2026-1'!X:X,"PRESENCIAL")) -> 10 | DL9: =IF(C9="","",SUMIFS('Planificación 2026-1'!R:R,'Planificación 2026-1'!W:W,C9,'Planificación 2026-1'!F:F,"FILIAL",'Planificación 2026-1'!X:X,"HIBRIDO PRESENCIAL")) -> 0 | DM9: =TRIM(CONCATENATE(AQ9,AR9,AS9,AT9,AU9,AV9,AW9,AX9,AY9,AZ9,BA9,BB9,BC9,BD9,BE9,BF9,BG9)) | DN9: =IF(C9="","",SUMIFS('Planificación 2026-1'!R:R,'Planificación 2026-1'!W:W,C9,'Planificación 2026-1'!F:F,"SUNAMPE",'Planificación 2026-1'!X:X,"VIRTUAL")) -> 0 | DO9: =IF(C9="","",SUMIFS('Planificación 2026-1'!R:R,'Planificación 2026-1'!W:W,C9,'Planificación 2026-1'!F:F,"SUNAMPE",'Planificación 2026-1'!X:X,"PRESENCIAL")) -> 0 | DP9: =TRIM(CONCATENATE(BH9,BI9,BJ9,BK9,BL9,BM9,BN9,BO9,BP9,BQ9,BR9,BS9,BT9,BU9,BV9,BW9,BX9)) | DQ9: =IF(C9="","",SUMIFS('Planificación 2026-1'!R:R,'Planificación 2026-1'!W:W,C9,'Planificación 2026-1'!F:F,"HUAURA",'Planificación 2026-1'!X:X,"VIRTUAL")) -> 0 | DR9: =IF(C9="","",SUMIFS('Planificación 2026-1'!R:R,'Planificación 2026-1'!W:W,C9,'Planificación 2026-1'!F:F,"HUAURA",'Planificación 2026-1'!X:X,"PRESENCIAL")) -> 0 | DS9: =SUMIFS('Planificación 2026-1'!R:R,'Planificación 2026-1'!W:W,C9,'Planificación 2026-1'!F:F,"PRINCIPAL",'Planificación 2026-1'!X:X,"VIRTUAL",'Planificación 2026-1'!I:I,">2") -> 0 | DT9: =SUMIFS('Planificación 2026-1'!R:R,'Planificación 2026-1'!W:W,C9,'Planificación 2026-1'!F:F,"PRINCIPAL",'Planificación 2026-1'!X:X,"<>VIRTUAL",'Planificación 2026-1'!I:I,">2") -> 0 | DU9: =SUMIFS('Planificación 2026-1'!R:R,'Planificación 2026-1'!W:W,C9,'Planificación 2026-1'!F:F,"SUNAMPE",'Planificación 2026-1'!X:X,"VIRTUAL",'Planificación 2026-1'!I:I,">2") -> 0 | DV9: =SUMIFS('Planificación 2026-1'!R:R,'Planificación 2026-1'!W:W,C9,'Planificación 2026-1'!F:F,"SUNAMPE",'Planificación 2026-1'!X:X,"<>VIRTUAL",'Planificación 2026-1'!I:I,">2") -> 0 | DW9: =SUMIFS('Planificación 2026-1'!R:R,'Planificación 2026-1'!W:W,C9,'Planificación 2026-1'!F:F,"FILIAL",'Planificación 2026-1'!X:X,"VIRTUAL",'Planificación 2026-1'!I:I,">2") -> 0 | DX9: =SUMIFS('Planificación 2026-1'!R:R,'Planificación 2026-1'!W:W,C9,'Planificación 2026-1'!F:F,"FILIAL",'Planificación 2026-1'!X:X,"<>VIRTUAL",'Planificación 2026-1'!I:I,">2") -> 15 | DY9: =SUMIFS('Planificación 2026-1'!R:R,'Planificación 2026-1'!W:W,C9,'Planificación 2026-1'!F:F,"PORUMA",'Planificación 2026-1'!X:X,"VIRTUAL",'Planificación 2026-1'!I:I,">2") -> 0 | DZ9: =SUMIFS('Planificación 2026-1'!R:R,'Planificación 2026-1'!W:W,C9,'Planificación 2026-1'!F:F,"PORUMA",'Planificación 2026-1'!X:X,"<>VIRTUAL",'Planificación 2026-1'!I:I,">2") -> 0 | EA9: =SUMIFS('Planificación 2026-1'!R:R,'Planificación 2026-1'!W:W,C9,'Planificación 2026-1'!F:F,"HUAURA",'Planificación 2026-1'!X:X,"VIRTUAL",'Planificación 2026-1'!I:I,">2") -> 0 | EB9: =SUMIFS('Planificación 2026-1'!R:R,'Planificación 2026-1'!W:W,C9,'Planificación 2026-1'!F:F,"HUAURA",'Planificación 2026-1'!X:X,"<>VIRTUAL",'Planificación 2026-1'!I:I,">2") -> 0 | EC9: =SUMIFS('Planificación 2026-1'!R:R,'Planificación 2026-1'!W:W,C9,'Planificación 2026-1'!F:F,"PRINCIPAL",'Planificación 2026-1'!X:X,"VIRTUAL",'Planificación 2026-1'!I:I,"<3") -> 0 | ED9: =SUMIFS('Planificación 2026-1'!R:R,'Planificación 2026-1'!W:W,C9,'Planificación 2026-1'!F:F,"PRINCIPAL",'Planificación 2026-1'!X:X,"<>VIRTUAL",'Planificación 2026-1'!I:I,"<3") -> 0 | EE9: =SUMIFS('Planificación 2026-1'!R:R,'Planificación 2026-1'!W:W,C9,'Planificación 2026-1'!F:F,"SUNAMPE",'Planificación 2026-1'!X:X,"VIRTUAL",'Planificación 2026-1'!I:I,"<3") -> 0 | EF9: =SUMIFS('Planificación 2026-1'!R:R,'Planificación 2026-1'!W:W,C9,'Planificación 2026-1'!F:F,"SUNAMPE",'Planificación 2026-1'!X:X,"<>VIRTUAL",'Planificación 2026-1'!I:I,"<3") -> 0 | EG9: =SUMIFS('Planificación 2026-1'!R:R,'Planificación 2026-1'!W:W,C9,'Planificación 2026-1'!F:F,"FILIAL",'Planificación 2026-1'!X:X,"VIRTUAL",'Planificación 2026-1'!I:I,"<3") -> 0 | EH9: =SUMIFS('Planificación 2026-1'!R:R,'Planificación 2026-1'!W:W,C9,'Planificación 2026-1'!F:F,"FILIAL",'Planificación 2026-1'!X:X,"<>VIRTUAL",'Planificación 2026-1'!I:I,"<3") -> 0 | EI9: =SUMIFS('Planificación 2026-1'!R:R,'Planificación 2026-1'!W:W,C9,'Planificación 2026-1'!F:F,"PORUMA",'Planificación 2026-1'!X:X,"VIRTUAL",'Planificación 2026-1'!I:I,"<3") -> 0 | EJ9: =SUMIFS('Planificación 2026-1'!R:R,'Planificación 2026-1'!W:W,C9,'Planificación 2026-1'!F:F,"PORUMA",'Planificación 2026-1'!X:X,"<>VIRTUAL",'Planificación 2026-1'!I:I,"<3") -> 0 | EK9: =SUMIFS('Planificación 2026-1'!R:R,'Planificación 2026-1'!W:W,C9,'Planificación 2026-1'!F:F,"HUAURA",'Planificación 2026-1'!X:X,"VIRTUAL",'Planificación 2026-1'!I:I,"<3") -> 0 | EL9: =SUMIFS('Planificación 2026-1'!R:R,'Planificación 2026-1'!W:W,C9,'Planificación 2026-1'!F:F,"HUAURA",'Planificación 2026-1'!X:X,"<>VIRTUAL",'Planificación 2026-1'!I:I,"<3") -> 0 | EN9: =DS9+DW9+EA9+EC9+EG9+EK9+DU9+EE9 -> 0 | EO9: =DT9+DX9+EB9+ED9+EH9+EL9+DV9+EF9 -> 15 | EP9: =EXACT(SUM(EN9:EO9),D9) -> TRUE | EQ9: =IF(AND(DT9=0,DX9=0,EB9=0),"",IF(COUNTIF(DT9:EB9,">0")=1,IF(DT9>0,"SEDE",IF(DX9>0,"FILIAL","HUAURA")),IF(COUNTIF(DT9:EB9,">0")=2,IF(AND(DT9>0,DX9>0),"SEDE-FILIAL",IF(AND(DT9>0,EB9>0),"SEDE-HUAURA","FILIAL-HUAURA")),"SEDE-FILIAL-HUAURA"))) -> FILIAL | ER9: =IF(EN9=0,"PRESENCIAL",IF(EO9=0,"VIRTUAL",IF(EN9>EO9,"MAS VIRTUAL",IF(EO9>EN9,"MAS PRESENCIAL","AMBOS")))) -> PRESENCIAL
B10: 7 | C10: ALIAGA RUIZ MINA ANGELICA | D10: =SUMIF('Planificación 2026-1'!W:W,C10,'Planificación 2026-1'!R:R) -> 0 | E10: TP | F10: RENOVACIÓN | G10: SEDE | H10: PSICOLOGÍA | I10: =IF(SUM(COUNTIFS('Planificación 2026-1'!F:F,"PRINCIPAL",'Planificación 2026-1'!W:W,C10,'Planificación 2026-1'!H:H,"AF"))>0,"P01"," ") | J10: =IF(SUM(COUNTIFS('Planificación 2026-1'!F:F,"PRINCIPAL",'Planificación 2026-1'!W:W,C10,'Planificación 2026-1'!H:H,"EN"))>0,"P02"," ") | K10: =IF(SUM(COUNTIFS('Planificación 2026-1'!F:F,"PRINCIPAL",'Planificación 2026-1'!W:W,C10,'Planificación 2026-1'!H:H,"IS"))>0,"P03"," ") | L10: =IF(SUM(COUNTIFS('Planificación 2026-1'!F:F,"PRINCIPAL",'Planificación 2026-1'!W:W,C10,'Planificación 2026-1'!H:H,"PS"))>0,"P04"," ") | N10: =IF(SUM(COUNTIFS('Planificación 2026-1'!F:F,"PRINCIPAL",'Planificación 2026-1'!W:W,C10,'Planificación 2026-1'!H:H,"IN"))>0,"P06"," ") | O10: =IF(SUM(COUNTIFS('Planificación 2026-1'!F:F,"PRINCIPAL",'Planificación 2026-1'!W:W,C10,'Planificación 2026-1'!H:H,"CA"))>0,"P07"," ") | P10: =IF(SUM(COUNTIFS('Planificación 2026-1'!F:F,"PRINCIPAL",'Planificación 2026-1'!W:W,C10,'Planificación 2026-1'!H:H,"DE"))>0,"P08"," ") | Q10: =IF(SUM(COUNTIFS('Planificación 2026-1'!F:F,"PRINCIPAL",'Planificación 2026-1'!W:W,C10,'Planificación 2026-1'!H:H,"OB"))>0,"P09"," ") | R10: =IF(SUM(COUNTIFS('Planificación 2026-1'!F:F,"PRINCIPAL",'Planificación 2026-1'!W:W,C10,'Planificación 2026-1'!H:H,"MH"))>0,"P31"," ") | S10: =IF(SUM(COUNTIFS('Planificación 2026-1'!F:F,"PRINCIPAL",'Planificación 2026-1'!W:W,C10,'Planificación 2026-1'!H:H,"IC"))>0,"P32"," ") | T10: =IF(SUM(COUNTIFS('Planificación 2026-1'!F:F,"PRINCIPAL",'Planificación 2026-1'!W:W,C10,'Planificación 2026-1'!H:H,"AR"))>0,"P34"," ") | U10: =IF(SUM(COUNTIFS('Planificación 2026-1'!F:F,"PRINCIPAL",'Planificación 2026-1'!W:W,C10,'Planificación 2026-1'!H:H,"T1"))>0,"P35"," ") | V10: =IF(SUM(COUNTIFS('Planificación 2026-1'!F:F,"PRINCIPAL",'Planificación 2026-1'!W:W,C10,'Planificación 2026-1'!H:H,"T3"))>0,"P36"," ") | W10: =IF(SUM(COUNTIFS('Planificación 2026-1'!F:F,"PRINCIPAL",'Planificación 2026-1'!W:W,C10,'Planificación 2026-1'!H:H,"T2"))>0,"P37"," ") | X10: =IF(SUM(COUNTIFS('Planificación 2026-1'!F:F,"PRINCIPAL",'Planificación 2026-1'!W:W,C10,'Planificación 2026-1'!H:H,"AE"))>0,"P38"," ") | Y10: =IF(SUM(COUNTIFS('Planificación 2026-1'!F:F,"PRINCIPAL",'Planificación 2026-1'!W:W,C10,'Planificación 2026-1'!H:H,"T4"))>0,"P55"," ") | Z10: =IF(SUM(COUNTIFS('Planificación 2026-1'!F:F,"FILIAL",'Planificación 2026-1'!W:W,C10,'Planificación 2026-1'!H:H,"AF"))>0," P01"," ") | AA10: =IF(SUM(COUNTIFS('Planificación 2026-1'!F:F,"FILIAL",'Planificación 2026-1'!W:W,C10,'Planificación 2026-1'!H:H,"EN"))>0,"P02"," ") | AB10: =IF(SUM(COUNTIFS('Planificación 2026-1'!F:F,"FILIAL",'Planificación 2026-1'!W:W,C10,'Planificación 2026-1'!H:H,"IS"))>0,"P03"," ") | AC10: =IF(SUM(COUNTIFS('Planificación 2026-1'!F:F,"FILIAL",'Planificación 2026-1'!W:W,C10,'Planificación 2026-1'!H:H,"PS"))>0,"P04"," ") | AE10: =IF(SUM(COUNTIFS('Planificación 2026-1'!F:F,"FILIAL",'Planificación 2026-1'!W:W,C10,'Planificación 2026-1'!H:H,"IN"))>0,"P06"," ") | AF10: =IF(SUM(COUNTIFS('Planificación 2026-1'!F:F,"FILIAL",'Planificación 2026-1'!W:W,C10,'Planificación 2026-1'!H:H,"CA"))>0,"P07"," ") | AG10: =IF(SUM(COUNTIFS('Planificación 2026-1'!F:F,"FILIAL",'Planificación 2026-1'!W:W,C10,'Planificación 2026-1'!H:H,"DE"))>0,"P08"," ") | AH10: =IF(SUM(COUNTIFS('Planificación 2026-1'!F:F,"FILIAL",'Planificación 2026-1'!W:W,C10,'Planificación 2026-1'!H:H,"OB"))>0,"P09"," ") | AI10: =IF(SUM(COUNTIFS('Planificación 2026-1'!F:F,"FILIAL",'Planificación 2026-1'!W:W,C10,'Planificación 2026-1'!H:H,"MH"))>0,"P31"," ") | AJ10: =IF(SUM(COUNTIFS('Planificación 2026-1'!F:F,"FILIAL",'Planificación 2026-1'!W:W,C10,'Planificación 2026-1'!H:H,"IC"))>0,"P32"," ") | AK10: =IF(SUM(COUNTIFS('Planificación 2026-1'!F:F,"FILIAL",'Planificación 2026-1'!W:W,C10,'Planificación 2026-1'!H:H,"AR"))>0,"P34"," ") | AL10: =IF(SUM(COUNTIFS('Planificación 2026-1'!F:F,"FILIAL",'Planificación 2026-1'!W:W,C10,'Planificación 2026-1'!H:H,"T1"))>0,"P35"," ") | AM10: =IF(SUM(COUNTIFS('Planificación 2026-1'!F:F,"FILIAL",'Planificación 2026-1'!W:W,C10,'Planificación 2026-1'!H:H,"T3"))>0,"P36"," ") | AN10: =IF(SUM(COUNTIFS('Planificación 2026-1'!F:F,"FILIAL",'Planificación 2026-1'!W:W,C10,'Planificación 2026-1'!H:H,"T2"))>0,"P37"," ") | AO10: =IF(SUM(COUNTIFS('Planificación 2026-1'!F:F,"FILIAL",'Planificación 2026-1'!W:W,C10,'Planificación 2026-1'!H:H,"AE"))>0,"P38"," ") | AP10: =IF(SUM(COUNTIFS('Planificación 2026-1'!F:F,"FILIAL",'Planificación 2026-1'!W:W,C10,'Planificación 2026-1'!H:H,"T4"))>0,"P55"," ") | AQ10: =IF(SUM(COUNTIFS('Planificación 2026-1'!F:F,"SUNAMPE",'Planificación 2026-1'!W:W,C10,'Planificación 2026-1'!H:H,"AF"))>0," P01"," ") | AR10: =IF(SUM(COUNTIFS('Planificación 2026-1'!F:F,"SUNAMPE",'Planificación 2026-1'!W:W,C10,'Planificación 2026-1'!H:H,"EN"))>0,"P02"," ") | AS10: =IF(SUM(COUNTIFS('Planificación 2026-1'!F:F,"SUNAMPE",'Planificación 2026-1'!W:W,C10,'Planificación 2026-1'!H:H,"IS"))>0,"P03"," ") | AT10: =IF(SUM(COUNTIFS('Planificación 2026-1'!F:F,"SUNAMPE",'Planificación 2026-1'!W:W,C10,'Planificación 2026-1'!H:H,"PS"))>0,"P04"," ") | AV10: =IF(SUM(COUNTIFS('Planificación 2026-1'!F:F,"SUNAMPE",'Planificación 2026-1'!W:W,C10,'Planificación 2026-1'!H:H,"IN"))>0,"P06"," ") | AW10: =IF(SUM(COUNTIFS('Planificación 2026-1'!F:F,"SUNAMPE",'Planificación 2026-1'!W:W,C10,'Planificación 2026-1'!H:H,"CA"))>0,"P07"," ") | AX10: =IF(SUM(COUNTIFS('Planificación 2026-1'!F:F,"SUNAMPE",'Planificación 2026-1'!W:W,C10,'Planificación 2026-1'!H:H,"DE"))>0,"P08"," ") | AY10: =IF(SUM(COUNTIFS('Planificación 2026-1'!F:F,"SUNAMPE",'Planificación 2026-1'!W:W,C10,'Planificación 2026-1'!H:H,"OB"))>0,"P09"," ") | AZ10: =IF(SUM(COUNTIFS('Planificación 2026-1'!F:F,"SUNAMPE",'Planificación 2026-1'!W:W,C10,'Planificación 2026-1'!H:H,"MH"))>0,"P31"," ") | BA10: =IF(SUM(COUNTIFS('Planificación 2026-1'!F:F,"SUNAMPE",'Planificación 2026-1'!W:W,C10,'Planificación 2026-1'!H:H,"IC"))>0,"P32"," ") | BB10: =IF(SUM(COUNTIFS('Planificación 2026-1'!F:F,"SUNAMPE",'Planificación 2026-1'!W:W,C10,'Planificación 2026-1'!H:H,"AR"))>0,"P34"," ") | BC10: =IF(SUM(COUNTIFS('Planificación 2026-1'!F:F,"SUNAMPE",'Planificación 2026-1'!W:W,C10,'Planificación 2026-1'!H:H,"T1"))>0,"P35"," ") | BD10: =IF(SUM(COUNTIFS('Planificación 2026-1'!F:F,"SUNAMPE",'Planificación 2026-1'!W:W,C10,'Planificación 2026-1'!H:H,"T3"))>0,"P36"," ") | BE10: =IF(SUM(COUNTIFS('Planificación 2026-1'!F:F,"SUNAMPE",'Planificación 2026-1'!W:W,C10,'Planificación 2026-1'!H:H,"T2"))>0,"P37"," ") | BF10: =IF(SUM(COUNTIFS('Planificación 2026-1'!F:F,"SUNAMPE",'Planificación 2026-1'!W:W,C10,'Planificación 2026-1'!H:H,"AE"))>0,"P38"," ") | BG10: =IF(SUM(COUNTIFS('Planificación 2026-1'!F:F,"SUNAMPE",'Planificación 2026-1'!W:W,C10,'Planificación 2026-1'!H:H,"T4"))>0,"P55"," ") | BH10: =IF(SUM(COUNTIFS('Planificación 2026-1'!F:F,"HUAURA",'Planificación 2026-1'!W:W,C10,'Planificación 2026-1'!H:H,"AF"))>0," P01"," ") | BI10: =IF(SUM(COUNTIFS('Planificación 2026-1'!F:F,"HUAURA",'Planificación 2026-1'!W:W,C10,'Planificación 2026-1'!H:H,"EN"))>0,"P02"," ") | BJ10: =IF(SUM(COUNTIFS('Planificación 2026-1'!F:F,"HUAURA",'Planificación 2026-1'!W:W,C10,'Planificación 2026-1'!H:H,"IS"))>0,"P03"," ") | BK10: =IF(SUM(COUNTIFS('Planificación 2026-1'!F:F,"HUAURA",'Planificación 2026-1'!W:W,C10,'Planificación 2026-1'!H:H,"PS"))>0,"P04"," ") | BM10: =IF(SUM(COUNTIFS('Planificación 2026-1'!F:F,"HUAURA",'Planificación 2026-1'!W:W,C10,'Planificación 2026-1'!H:H,"IN"))>0,"P06"," ") | BN10: =IF(SUM(COUNTIFS('Planificación 2026-1'!F:F,"HUAURA",'Planificación 2026-1'!W:W,C10,'Planificación 2026-1'!H:H,"CA"))>0,"P07"," ") | BO10: =IF(SUM(COUNTIFS('Planificación 2026-1'!F:F,"HUAURA",'Planificación 2026-1'!W:W,C10,'Planificación 2026-1'!H:H,"DE"))>0,"P08"," ") | BP10: =IF(SUM(COUNTIFS('Planificación 2026-1'!F:F,"HUAURA",'Planificación 2026-1'!W:W,C10,'Planificación 2026-1'!H:H,"OB"))>0,"P09"," ") | BQ10: =IF(SUM(COUNTIFS('Planificación 2026-1'!F:F,"HUAURA",'Planificación 2026-1'!W:W,C10,'Planificación 2026-1'!H:H,"MH"))>0,"P31"," ") | BR10: =IF(SUM(COUNTIFS('Planificación 2026-1'!F:F,"HUAURA",'Planificación 2026-1'!W:W,C10,'Planificación 2026-1'!H:H,"IC"))>0,"P32"," ") | BS10: =IF(SUM(COUNTIFS('Planificación 2026-1'!F:F,"HUAURA",'Planificación 2026-1'!W:W,C10,'Planificación 2026-1'!H:H,"AR"))>0,"P34"," ") | BT10: =IF(SUM(COUNTIFS('Planificación 2026-1'!F:F,"HUAURA",'Planificación 2026-1'!W:W,C10,'Planificación 2026-1'!H:H,"T1"))>0,"P35"," ") | BU10: =IF(SUM(COUNTIFS('Planificación 2026-1'!F:F,"HUAURA",'Planificación 2026-1'!W:W,C10,'Planificación 2026-1'!H:H,"T3"))>0,"P36"," ") | BV10: =IF(SUM(COUNTIFS('Planificación 2026-1'!F:F,"HUAURA",'Planificación 2026-1'!W:W,C10,'Planificación 2026-1'!H:H,"T2"))>0,"P37"," ") | BW10: =IF(SUM(COUNTIFS('Planificación 2026-1'!F:F,"HUAURA",'Planificación 2026-1'!W:W,C10,'Planificación 2026-1'!H:H,"AE"))>0,"P38"," ") | BX10: =IF(SUM(COUNTIFS('Planificación 2026-1'!F:F,"HUAURA",'Planificación 2026-1'!W:W,C10,'Planificación 2026-1'!H:H,"T4"))>0,"P55"," ") | BY10: =SUMIFS('Planificación 2026-1'!R:R,'Planificación 2026-1'!W:W,C10,'Planificación 2026-1'!H:H,"AF",'Planificación 2026-1'!I:I,">2") -> 0 | BZ10: =SUMIFS('Planificación 2026-1'!R:R,'Planificación 2026-1'!W:W,C10,'Planificación 2026-1'!H:H,"EN",'Planificación 2026-1'!I:I,">2") -> 0 | CA10: =SUMIFS('Planificación 2026-1'!R:R,'Planificación 2026-1'!W:W,C10,'Planificación 2026-1'!H:H,"IS",'Planificación 2026-1'!I:I,">2") -> 0 | CB10: =SUMIFS('Planificación 2026-1'!R:R,'Planificación 2026-1'!W:W,C10,'Planificación 2026-1'!H:H,"PS",'Planificación 2026-1'!I:I,">2") -> 0 | CC10: =SUMIFS('Planificación 2026-1'!R:R,'Planificación 2026-1'!W:W,C10,'Planificación 2026-1'!H:H,"IN",'Planificación 2026-1'!I:I,">2") -> 0 | CD10: =SUMIFS('Planificación 2026-1'!R:R,'Planificación 2026-1'!W:W,C10,'Planificación 2026-1'!H:H,"CA",'Planificación 2026-1'!I:I,">2") -> 0 | CE10: =SUMIFS('Planificación 2026-1'!R:R,'Planificación 2026-1'!W:W,C10,'Planificación 2026-1'!H:H,"DE",'Planificación 2026-1'!I:I,">2") -> 0 | CF10: =SUMIFS('Planificación 2026-1'!R:R,'Planificación 2026-1'!W:W,C10,'Planificación 2026-1'!H:H,"OB",'Planificación 2026-1'!I:I,">2") -> 0 | CG10: =SUMIFS('Planificación 2026-1'!R:R,'Planificación 2026-1'!W:W,C10,'Planificación 2026-1'!H:H,"MH",'Planificación 2026-1'!I:I,">2") -> 0 | CH10: =SUMIFS('Planificación 2026-1'!R:R,'Planificación 2026-1'!W:W,C10,'Planificación 2026-1'!H:H,"IC",'Planificación 2026-1'!I:I,">2") -> 0 | CI10: =SUMIFS('Planificación 2026-1'!R:R,'Planificación 2026-1'!W:W,C10,'Planificación 2026-1'!H:H,"AR",'Planificación 2026-1'!I:I,">2") -> 0 | CJ10: =SUMIFS('Planificación 2026-1'!R:R,'Planificación 2026-1'!W:W,C10,'Planificación 2026-1'!H:H,"T1",'Planificación 2026-1'!I:I,">2") -> 0 | CK10: =SUMIFS('Planificación 2026-1'!R:R,'Planificación 2026-1'!W:W,C10,'Planificación 2026-1'!H:H,"T3",'Planificación 2026-1'!I:I,">2") -> 0 | CL10: =SUMIFS('Planificación 2026-1'!R:R,'Planificación 2026-1'!W:W,C10,'Planificación 2026-1'!H:H,"T2",'Planificación 2026-1'!I:I,">2") -> 0 | CM10: =SUMIFS('Planificación 2026-1'!R:R,'Planificación 2026-1'!W:W,C10,'Planificación 2026-1'!H:H,"AE",'Planificación 2026-1'!I:I,">2") -> 0 | CN10: =SUMIFS('Planificación 2026-1'!R:R,'Planificación 2026-1'!W:W,C10,'Planificación 2026-1'!H:H,"T4",'Planificación 2026-1'!I:I,">2") -> 0 | CO10: =SUMIFS('Planificación 2026-1'!R:R,'Planificación 2026-1'!W:W,C10,'Planificación 2026-1'!H:H,"AF",'Planificación 2026-1'!I:I,"<3") -> 0 | CP10: =SUMIFS('Planificación 2026-1'!R:R,'Planificación 2026-1'!W:W,C10,'Planificación 2026-1'!H:H,"EN",'Planificación 2026-1'!I:I,"<3") -> 0 | CQ10: =SUMIFS('Planificación 2026-1'!R:R,'Planificación 2026-1'!W:W,C10,'Planificación 2026-1'!H:H,"IS",'Planificación 2026-1'!I:I,"<3") -> 0 | CR10: =SUMIFS('Planificación 2026-1'!R:R,'Planificación 2026-1'!W:W,C10,'Planificación 2026-1'!H:H,"PS",'Planificación 2026-1'!I:I,"<3") -> 0 | CS10: =SUMIFS('Planificación 2026-1'!R:R,'Planificación 2026-1'!W:W,C10,'Planificación 2026-1'!H:H,"IN",'Planificación 2026-1'!I:I,"<3") -> 0 | CT10: =SUMIFS('Planificación 2026-1'!R:R,'Planificación 2026-1'!W:W,C10,'Planificación 2026-1'!H:H,"CA",'Planificación 2026-1'!I:I,"<3") -> 0 | CU10: =SUMIFS('Planificación 2026-1'!R:R,'Planificación 2026-1'!W:W,C10,'Planificación 2026-1'!H:H,"DE",'Planificación 2026-1'!I:I,"<3") -> 0 | CV10: =SUMIFS('Planificación 2026-1'!R:R,'Planificación 2026-1'!W:W,C10,'Planificación 2026-1'!H:H,"OB",'Planificación 2026-1'!I:I,"<3") -> 0 | CW10: =SUMIFS('Planificación 2026-1'!R:R,'Planificación 2026-1'!W:W,C10,'Planificación 2026-1'!H:H,"MH",'Planificación 2026-1'!I:I,"<3") -> 0 | CX10: =SUMIFS('Planificación 2026-1'!R:R,'Planificación 2026-1'!W:W,C10,'Planificación 2026-1'!H:H,"IC",'Planificación 2026-1'!I:I,"<3") -> 0 | CY10: =SUMIFS('Planificación 2026-1'!R:R,'Planificación 2026-1'!W:W,C10,'Planificación 2026-1'!H:H,"AR",'Planificación 2026-1'!I:I,"<3") -> 0 | CZ10: =SUMIFS('Planificación 2026-1'!R:R,'Planificación 2026-1'!W:W,C10,'Planificación 2026-1'!H:H,"T1",'Planificación 2026-1'!I:I,"<3") -> 0 | DA10: =SUMIFS('Planificación 2026-1'!R:R,'Planificación 2026-1'!W:W,C10,'Planificación 2026-1'!H:H,"T3",'Planificación 2026-1'!I:I,"<3") -> 0 | DB10: =SUMIFS('Planificación 2026-1'!R:R,'Planificación 2026-1'!W:W,C10,'Planificación 2026-1'!H:H,"T2",'Planificación 2026-1'!I:I,"<3") -> 0 | DC10: =SUMIFS('Planificación 2026-1'!R:R,'Planificación 2026-1'!W:W,C10,'Planificación 2026-1'!H:H,"AE",'Planificación 2026-1'!I:I,"<3") -> 0 | DD10: =SUMIFS('Planificación 2026-1'!R:R,'Planificación 2026-1'!W:W,C10,'Planificación 2026-1'!H:H,"T4",'Planificación 2026-1'!I:I,"<3") -> 0 | DE10: =TRIM(CONCATENATE(I10,J10,K10,L10,M10,N10,O10,P10,Q10,R10,S10,T10,U10,V10,W10,X10,Y10)) | DF10: =IF(C10="","",SUMIFS('Planificación 2026-1'!R:R,'Planificación 2026-1'!W:W,C10,'Planificación 2026-1'!F:F,"PRINCIPAL",'Planificación 2026-1'!X:X,"VIRTUAL")) -> 0 | DG10: =IF(C10="","",SUMIFS('Planificación 2026-1'!R:R,'Planificación 2026-1'!W:W,C10,'Planificación 2026-1'!F:F,"PRINCIPAL",'Planificación 2026-1'!X:X,"PRESENCIAL")) -> 0 | DH10: =IF(C10="","",SUMIFS('Planificación 2026-1'!R:R,'Planificación 2026-1'!W:W,C10,'Planificación 2026-1'!F:F,"PRINCIPAL",'Planificación 2026-1'!X:X,"HIBRIDO PRESENCIAL")) -> 0 | DI10: =TRIM(CONCATENATE(Z10,AA10,AB10,AC10,AD10,AE10,AF10,AG10,AH10,AI10,AJ10,AK10,AL10,AM10,AN10,AO10,AP10)) | DJ10: =IF(C10="","",SUMIFS('Planificación 2026-1'!R:R,'Planificación 2026-1'!W:W,C10,'Planificación 2026-1'!F:F,"FILIAL",'Planificación 2026-1'!X:X,"VIRTUAL")) -> 0 | DK10: =IF(C10="","",SUMIFS('Planificación 2026-1'!R:R,'Planificación 2026-1'!W:W,C10,'Planificación 2026-1'!F:F,"FILIAL",'Planificación 2026-1'!X:X,"PRESENCIAL")) -> 0 | DL10: =IF(C10="","",SUMIFS('Planificación 2026-1'!R:R,'Planificación 2026-1'!W:W,C10,'Planificación 2026-1'!F:F,"FILIAL",'Planificación 2026-1'!X:X,"HIBRIDO PRESENCIAL")) -> 0 | DM10: =TRIM(CONCATENATE(AQ10,AR10,AS10,AT10,AU10,AV10,AW10,AX10,AY10,AZ10,BA10,BB10,BC10,BD10,BE10,BF10,BG10)) | DN10: =IF(C10="","",SUMIFS('Planificación 2026-1'!R:R,'Planificación 2026-1'!W:W,C10,'Planificación 2026-1'!F:F,"SUNAMPE",'Planificación 2026-1'!X:X,"VIRTUAL")) -> 0 | DO10: =IF(C10="","",SUMIFS('Planificación 2026-1'!R:R,'Planificación 2026-1'!W:W,C10,'Planificación 2026-1'!F:F,"SUNAMPE",'Planificación 2026-1'!X:X,"PRESENCIAL")) -> 0 | DP10: =TRIM(CONCATENATE(BH10,BI10,BJ10,BK10,BL10,BM10,BN10,BO10,BP10,BQ10,BR10,BS10,BT10,BU10,BV10,BW10,BX10)) | DQ10: =IF(C10="","",SUMIFS('Planificación 2026-1'!R:R,'Planificación 2026-1'!W:W,C10,'Planificación 2026-1'!F:F,"HUAURA",'Planificación 2026-1'!X:X,"VIRTUAL")) -> 0 | DR10: =IF(C10="","",SUMIFS('Planificación 2026-1'!R:R,'Planificación 2026-1'!W:W,C10,'Planificación 2026-1'!F:F,"HUAURA",'Planificación 2026-1'!X:X,"PRESENCIAL")) -> 0 | DS10: =SUMIFS('Planificación 2026-1'!R:R,'Planificación 2026-1'!W:W,C10,'Planificación 2026-1'!F:F,"PRINCIPAL",'Planificación 2026-1'!X:X,"VIRTUAL",'Planificación 2026-1'!I:I,">2") -> 0 | DT10: =SUMIFS('Planificación 2026-1'!R:R,'Planificación 2026-1'!W:W,C10,'Planificación 2026-1'!F:F,"PRINCIPAL",'Planificación 2026-1'!X:X,"<>VIRTUAL",'Planificación 2026-1'!I:I,">2") -> 0 | DU10: =SUMIFS('Planificación 2026-1'!R:R,'Planificación 2026-1'!W:W,C10,'Planificación 2026-1'!F:F,"SUNAMPE",'Planificación 2026-1'!X:X,"VIRTUAL",'Planificación 2026-1'!I:I,">2") -> 0 | DV10: =SUMIFS('Planificación 2026-1'!R:R,'Planificación 2026-1'!W:W,C10,'Planificación 2026-1'!F:F,"SUNAMPE",'Planificación 2026-1'!X:X,"<>VIRTUAL",'Planificación 2026-1'!I:I,">2") -> 0 | DW10: =SUMIFS('Planificación 2026-1'!R:R,'Planificación 2026-1'!W:W,C10,'Planificación 2026-1'!F:F,"FILIAL",'Planificación 2026-1'!X:X,"VIRTUAL",'Planificación 2026-1'!I:I,">2") -> 0 | DX10: =SUMIFS('Planificación 2026-1'!R:R,'Planificación 2026-1'!W:W,C10,'Planificación 2026-1'!F:F,"FILIAL",'Planificación 2026-1'!X:X,"<>VIRTUAL",'Planificación 2026-1'!I:I,">2") -> 0 | DY10: =SUMIFS('Planificación 2026-1'!R:R,'Planificación 2026-1'!W:W,C10,'Planificación 2026-1'!F:F,"PORUMA",'Planificación 2026-1'!X:X,"VIRTUAL",'Planificación 2026-1'!I:I,">2") -> 0 | DZ10: =SUMIFS('Planificación 2026-1'!R:R,'Planificación 2026-1'!W:W,C10,'Planificación 2026-1'!F:F,"PORUMA",'Planificación 2026-1'!X:X,"<>VIRTUAL",'Planificación 2026-1'!I:I,">2") -> 0 | EA10: =SUMIFS('Planificación 2026-1'!R:R,'Planificación 2026-1'!W:W,C10,'Planificación 2026-1'!F:F,"HUAURA",'Planificación 2026-1'!X:X,"VIRTUAL",'Planificación 2026-1'!I:I,">2") -> 0 | EB10: =SUMIFS('Planificación 2026-1'!R:R,'Planificación 2026-1'!W:W,C10,'Planificación 2026-1'!F:F,"HUAURA",'Planificación 2026-1'!X:X,"<>VIRTUAL",'Planificación 2026-1'!I:I,">2") -> 0 | EC10: =SUMIFS('Planificación 2026-1'!R:R,'Planificación 2026-1'!W:W,C10,'Planificación 2026-1'!F:F,"PRINCIPAL",'Planificación 2026-1'!X:X,"VIRTUAL",'Planificación 2026-1'!I:I,"<3") -> 0 | ED10: =SUMIFS('Planificación 2026-1'!R:R,'Planificación 2026-1'!W:W,C10,'Planificación 2026-1'!F:F,"PRINCIPAL",'Planificación 2026-1'!X:X,"<>VIRTUAL",'Planificación 2026-1'!I:I,"<3") -> 0 | EE10: =SUMIFS('Planificación 2026-1'!R:R,'Planificación 2026-1'!W:W,C10,'Planificación 2026-1'!F:F,"SUNAMPE",'Planificación 2026-1'!X:X,"VIRTUAL",'Planificación 2026-1'!I:I,"<3") -> 0 | EF10: =SUMIFS('Planificación 2026-1'!R:R,'Planificación 2026-1'!W:W,C10,'Planificación 2026-1'!F:F,"SUNAMPE",'Planificación 2026-1'!X:X,"<>VIRTUAL",'Planificación 2026-1'!I:I,"<3") -> 0 | EG10: =SUMIFS('Planificación 2026-1'!R:R,'Planificación 2026-1'!W:W,C10,'Planificación 2026-1'!F:F,"FILIAL",'Planificación 2026-1'!X:X,"VIRTUAL",'Planificación 2026-1'!I:I,"<3") -> 0 | EH10: =SUMIFS('Planificación 2026-1'!R:R,'Planificación 2026-1'!W:W,C10,'Planificación 2026-1'!F:F,"FILIAL",'Planificación 2026-1'!X:X,"<>VIRTUAL",'Planificación 2026-1'!I:I,"<3") -> 0 | EI10: =SUMIFS('Planificación 2026-1'!R:R,'Planificación 2026-1'!W:W,C10,'Planificación 2026-1'!F:F,"PORUMA",'Planificación 2026-1'!X:X,"VIRTUAL",'Planificación 2026-1'!I:I,"<3") -> 0 | EJ10: =SUMIFS('Planificación 2026-1'!R:R,'Planificación 2026-1'!W:W,C10,'Planificación 2026-1'!F:F,"PORUMA",'Planificación 2026-1'!X:X,"<>VIRTUAL",'Planificación 2026-1'!I:I,"<3") -> 0 | EK10: =SUMIFS('Planificación 2026-1'!R:R,'Planificación 2026-1'!W:W,C10,'Planificación 2026-1'!F:F,"HUAURA",'Planificación 2026-1'!X:X,"VIRTUAL",'Planificación 2026-1'!I:I,"<3") -> 0 | EL10: =SUMIFS('Planificación 2026-1'!R:R,'Planificación 2026-1'!W:W,C10,'Planificación 2026-1'!F:F,"HUAURA",'Planificación 2026-1'!X:X,"<>VIRTUAL",'Planificación 2026-1'!I:I,"<3") -> 0 | EN10: =DS10+DW10+EA10+EC10+EG10+EK10+DU10+EE10 -> 0 | EO10: =DT10+DX10+EB10+ED10+EH10+EL10+DV10+EF10 -> 0 | EP10: =EXACT(SUM(EN10:EO10),D10) -> TRUE | EQ10: =IF(AND(DT10=0,DX10=0,EB10=0),"",IF(COUNTIF(DT10:EB10,">0")=1,IF(DT10>0,"SEDE",IF(DX10>0,"FILIAL","HUAURA")),IF(COUNTIF(DT10:EB10,">0")=2,IF(AND(DT10>0,DX10>0),"SEDE-FILIAL",IF(AND(DT10>0,EB10>0),"SEDE-HUAURA","FILIAL-HUAURA")),"SEDE-FILIAL-HUAURA"))) | ER10: =IF(EN10=0,"PRESENCIAL",IF(EO10=0,"VIRTUAL",IF(EN10>EO10,"MAS VIRTUAL",IF(EO10>EN10,"MAS PRESENCIAL","AMBOS")))) -> PRESENCIAL
B11: 8 | C11: ALMEYDA AVALOS CESAR AUGUSTO | D11: =SUMIF('Planificación 2026-1'!W:W,C11,'Planificación 2026-1'!R:R) -> 33 | E11: TC | F11: RENOVACIÓN | G11: FILIAL | H11: DERECHO | I11: =IF(SUM(COUNTIFS('Planificación 2026-1'!F:F,"PRINCIPAL",'Planificación 2026-1'!W:W,C11,'Planificación 2026-1'!H:H,"AF"))>0,"P01"," ") | J11: =IF(SUM(COUNTIFS('Planificación 2026-1'!F:F,"PRINCIPAL",'Planificación 2026-1'!W:W,C11,'Planificación 2026-1'!H:H,"EN"))>0,"P02"," ") | K11: =IF(SUM(COUNTIFS('Planificación 2026-1'!F:F,"PRINCIPAL",'Planificación 2026-1'!W:W,C11,'Planificación 2026-1'!H:H,"IS"))>0,"P03"," ") | L11: =IF(SUM(COUNTIFS('Planificación 2026-1'!F:F,"PRINCIPAL",'Planificación 2026-1'!W:W,C11,'Planificación 2026-1'!H:H,"PS"))>0,"P04"," ") | N11: =IF(SUM(COUNTIFS('Planificación 2026-1'!F:F,"PRINCIPAL",'Planificación 2026-1'!W:W,C11,'Planificación 2026-1'!H:H,"IN"))>0,"P06"," ") -> P06 | O11: =IF(SUM(COUNTIFS('Planificación 2026-1'!F:F,"PRINCIPAL",'Planificación 2026-1'!W:W,C11,'Planificación 2026-1'!H:H,"CA"))>0,"P07"," ") | P11: =IF(SUM(COUNTIFS('Planificación 2026-1'!F:F,"PRINCIPAL",'Planificación 2026-1'!W:W,C11,'Planificación 2026-1'!H:H,"DE"))>0,"P08"," ") -> P08 | Q11: =IF(SUM(COUNTIFS('Planificación 2026-1'!F:F,"PRINCIPAL",'Planificación 2026-1'!W:W,C11,'Planificación 2026-1'!H:H,"OB"))>0,"P09"," ") | R11: =IF(SUM(COUNTIFS('Planificación 2026-1'!F:F,"PRINCIPAL",'Planificación 2026-1'!W:W,C11,'Planificación 2026-1'!H:H,"MH"))>0,"P31"," ") | S11: =IF(SUM(COUNTIFS('Planificación 2026-1'!F:F,"PRINCIPAL",'Planificación 2026-1'!W:W,C11,'Planificación 2026-1'!H:H,"IC"))>0,"P32"," ") | T11: =IF(SUM(COUNTIFS('Planificación 2026-1'!F:F,"PRINCIPAL",'Planificación 2026-1'!W:W,C11,'Planificación 2026-1'!H:H,"AR"))>0,"P34"," ") | U11: =IF(SUM(COUNTIFS('Planificación 2026-1'!F:F,"PRINCIPAL",'Planificación 2026-1'!W:W,C11,'Planificación 2026-1'!H:H,"T1"))>0,"P35"," ") | V11: =IF(SUM(COUNTIFS('Planificación 2026-1'!F:F,"PRINCIPAL",'Planificación 2026-1'!W:W,C11,'Planificación 2026-1'!H:H,"T3"))>0,"P36"," ") | W11: =IF(SUM(COUNTIFS('Planificación 2026-1'!F:F,"PRINCIPAL",'Planificación 2026-1'!W:W,C11,'Planificación 2026-1'!H:H,"T2"))>0,"P37"," ") | X11: =IF(SUM(COUNTIFS('Planificación 2026-1'!F:F,"PRINCIPAL",'Planificación 2026-1'!W:W,C11,'Planificación 2026-1'!H:H,"AE"))>0,"P38"," ") | Y11: =IF(SUM(COUNTIFS('Planificación 2026-1'!F:F,"PRINCIPAL",'Planificación 2026-1'!W:W,C11,'Planificación 2026-1'!H:H,"T4"))>0,"P55"," ") | Z11: =IF(SUM(COUNTIFS('Planificación 2026-1'!F:F,"FILIAL",'Planificación 2026-1'!W:W,C11,'Planificación 2026-1'!H:H,"AF"))>0," P01"," ") | AA11: =IF(SUM(COUNTIFS('Planificación 2026-1'!F:F,"FILIAL",'Planificación 2026-1'!W:W,C11,'Planificación 2026-1'!H:H,"EN"))>0,"P02"," ") | AB11: =IF(SUM(COUNTIFS('Planificación 2026-1'!F:F,"FILIAL",'Planificación 2026-1'!W:W,C11,'Planificación 2026-1'!H:H,"IS"))>0,"P03"," ") | AC11: =IF(SUM(COUNTIFS('Planificación 2026-1'!F:F,"FILIAL",'Planificación 2026-1'!W:W,C11,'Planificación 2026-1'!H:H,"PS"))>0,"P04"," ") | AE11: =IF(SUM(COUNTIFS('Planificación 2026-1'!F:F,"FILIAL",'Planificación 2026-1'!W:W,C11,'Planificación 2026-1'!H:H,"IN"))>0,"P06"," ") | AF11: =IF(SUM(COUNTIFS('Planificación 2026-1'!F:F,"FILIAL",'Planificación 2026-1'!W:W,C11,'Planificación 2026-1'!H:H,"CA"))>0,"P07"," ") | AG11: =IF(SUM(COUNTIFS('Planificación 2026-1'!F:F,"FILIAL",'Planificación 2026-1'!W:W,C11,'Planificación 2026-1'!H:H,"DE"))>0,"P08"," ") -> P08 | AH11: =IF(SUM(COUNTIFS('Planificación 2026-1'!F:F,"FILIAL",'Planificación 2026-1'!W:W,C11,'Planificación 2026-1'!H:H,"OB"))>0,"P09"," ") | AI11: =IF(SUM(COUNTIFS('Planificación 2026-1'!F:F,"FILIAL",'Planificación 2026-1'!W:W,C11,'Planificación 2026-1'!H:H,"MH"))>0,"P31"," ") | AJ11: =IF(SUM(COUNTIFS('Planificación 2026-1'!F:F,"FILIAL",'Planificación 2026-1'!W:W,C11,'Planificación 2026-1'!H:H,"IC"))>0,"P32"," ") | AK11: =IF(SUM(COUNTIFS('Planificación 2026-1'!F:F,"FILIAL",'Planificación 2026-1'!W:W,C11,'Planificación 2026-1'!H:H,"AR"))>0,"P34"," ") | AL11: =IF(SUM(COUNTIFS('Planificación 2026-1'!F:F,"FILIAL",'Planificación 2026-1'!W:W,C11,'Planificación 2026-1'!H:H,"T1"))>0,"P35"," ") | AM11: =IF(SUM(COUNTIFS('Planificación 2026-1'!F:F,"FILIAL",'Planificación 2026-1'!W:W,C11,'Planificación 2026-1'!H:H,"T3"))>0,"P36"," ") | AN11: =IF(SUM(COUNTIFS('Planificación 2026-1'!F:F,"FILIAL",'Planificación 2026-1'!W:W,C11,'Planificación 2026-1'!H:H,"T2"))>0,"P37"," ") | AO11: =IF(SUM(COUNTIFS('Planificación 2026-1'!F:F,"FILIAL",'Planificación 2026-1'!W:W,C11,'Planificación 2026-1'!H:H,"AE"))>0,"P38"," ") | AP11: =IF(SUM(COUNTIFS('Planificación 2026-1'!F:F,"FILIAL",'Planificación 2026-1'!W:W,C11,'Planificación 2026-1'!H:H,"T4"))>0,"P55"," ") | AQ11: =IF(SUM(COUNTIFS('Planificación 2026-1'!F:F,"SUNAMPE",'Planificación 2026-1'!W:W,C11,'Planificación 2026-1'!H:H,"AF"))>0," P01"," ") | AR11: =IF(SUM(COUNTIFS('Planificación 2026-1'!F:F,"SUNAMPE",'Planificación 2026-1'!W:W,C11,'Planificación 2026-1'!H:H,"EN"))>0,"P02"," ") | AS11: =IF(SUM(COUNTIFS('Planificación 2026-1'!F:F,"SUNAMPE",'Planificación 2026-1'!W:W,C11,'Planificación 2026-1'!H:H,"IS"))>0,"P03"," ") | AT11: =IF(SUM(COUNTIFS('Planificación 2026-1'!F:F,"SUNAMPE",'Planificación 2026-1'!W:W,C11,'Planificación 2026-1'!H:H,"PS"))>0,"P04"," ") | AV11: =IF(SUM(COUNTIFS('Planificación 2026-1'!F:F,"SUNAMPE",'Planificación 2026-1'!W:W,C11,'Planificación 2026-1'!H:H,"IN"))>0,"P06"," ") | AW11: =IF(SUM(COUNTIFS('Planificación 2026-1'!F:F,"SUNAMPE",'Planificación 2026-1'!W:W,C11,'Planificación 2026-1'!H:H,"CA"))>0,"P07"," ") | AX11: =IF(SUM(COUNTIFS('Planificación 2026-1'!F:F,"SUNAMPE",'Planificación 2026-1'!W:W,C11,'Planificación 2026-1'!H:H,"DE"))>0,"P08"," ") | AY11: =IF(SUM(COUNTIFS('Planificación 2026-1'!F:F,"SUNAMPE",'Planificación 2026-1'!W:W,C11,'Planificación 2026-1'!H:H,"OB"))>0,"P09"," ") | AZ11: =IF(SUM(COUNTIFS('Planificación 2026-1'!F:F,"SUNAMPE",'Planificación 2026-1'!W:W,C11,'Planificación 2026-1'!H:H,"MH"))>0,"P31"," ") | BA11: =IF(SUM(COUNTIFS('Planificación 2026-1'!F:F,"SUNAMPE",'Planificación 2026-1'!W:W,C11,'Planificación 2026-1'!H:H,"IC"))>0,"P32"," ") | BB11: =IF(SUM(COUNTIFS('Planificación 2026-1'!F:F,"SUNAMPE",'Planificación 2026-1'!W:W,C11,'Planificación 2026-1'!H:H,"AR"))>0,"P34"," ") | BC11: =IF(SUM(COUNTIFS('Planificación 2026-1'!F:F,"SUNAMPE",'Planificación 2026-1'!W:W,C11,'Planificación 2026-1'!H:H,"T1"))>0,"P35"," ") | BD11: =IF(SUM(COUNTIFS('Planificación 2026-1'!F:F,"SUNAMPE",'Planificación 2026-1'!W:W,C11,'Planificación 2026-1'!H:H,"T3"))>0,"P36"," ") | BE11: =IF(SUM(COUNTIFS('Planificación 2026-1'!F:F,"SUNAMPE",'Planificación 2026-1'!W:W,C11,'Planificación 2026-1'!H:H,"T2"))>0,"P37"," ") | BF11: =IF(SUM(COUNTIFS('Planificación 2026-1'!F:F,"SUNAMPE",'Planificación 2026-1'!W:W,C11,'Planificación 2026-1'!H:H,"AE"))>0,"P38"," ") | BG11: =IF(SUM(COUNTIFS('Planificación 2026-1'!F:F,"SUNAMPE",'Planificación 2026-1'!W:W,C11,'Planificación 2026-1'!H:H,"T4"))>0,"P55"," ") | BH11: =IF(SUM(COUNTIFS('Planificación 2026-1'!F:F,"HUAURA",'Planificación 2026-1'!W:W,C11,'Planificación 2026-1'!H:H,"AF"))>0," P01"," ") | BI11: =IF(SUM(COUNTIFS('Planificación 2026-1'!F:F,"HUAURA",'Planificación 2026-1'!W:W,C11,'Planificación 2026-1'!H:H,"EN"))>0,"P02"," ") | BJ11: =IF(SUM(COUNTIFS('Planificación 2026-1'!F:F,"HUAURA",'Planificación 2026-1'!W:W,C11,'Planificación 2026-1'!H:H,"IS"))>0,"P03"," ") | BK11: =IF(SUM(COUNTIFS('Planificación 2026-1'!F:F,"HUAURA",'Planificación 2026-1'!W:W,C11,'Planificación 2026-1'!H:H,"PS"))>0,"P04"," ") | BM11: =IF(SUM(COUNTIFS('Planificación 2026-1'!F:F,"HUAURA",'Planificación 2026-1'!W:W,C11,'Planificación 2026-1'!H:H,"IN"))>0,"P06"," ") | BN11: =IF(SUM(COUNTIFS('Planificación 2026-1'!F:F,"HUAURA",'Planificación 2026-1'!W:W,C11,'Planificación 2026-1'!H:H,"CA"))>0,"P07"," ") | BO11: =IF(SUM(COUNTIFS('Planificación 2026-1'!F:F,"HUAURA",'Planificación 2026-1'!W:W,C11,'Planificación 2026-1'!H:H,"DE"))>0,"P08"," ") | BP11: =IF(SUM(COUNTIFS('Planificación 2026-1'!F:F,"HUAURA",'Planificación 2026-1'!W:W,C11,'Planificación 2026-1'!H:H,"OB"))>0,"P09"," ") | BQ11: =IF(SUM(COUNTIFS('Planificación 2026-1'!F:F,"HUAURA",'Planificación 2026-1'!W:W,C11,'Planificación 2026-1'!H:H,"MH"))>0,"P31"," ") | BR11: =IF(SUM(COUNTIFS('Planificación 2026-1'!F:F,"HUAURA",'Planificación 2026-1'!W:W,C11,'Planificación 2026-1'!H:H,"IC"))>0,"P32"," ") | BS11: =IF(SUM(COUNTIFS('Planificación 2026-1'!F:F,"HUAURA",'Planificación 2026-1'!W:W,C11,'Planificación 2026-1'!H:H,"AR"))>0,"P34"," ") | BT11: =IF(SUM(COUNTIFS('Planificación 2026-1'!F:F,"HUAURA",'Planificación 2026-1'!W:W,C11,'Planificación 2026-1'!H:H,"T1"))>0,"P35"," ") | BU11: =IF(SUM(COUNTIFS('Planificación 2026-1'!F:F,"HUAURA",'Planificación 2026-1'!W:W,C11,'Planificación 2026-1'!H:H,"T3"))>0,"P36"," ") | BV11: =IF(SUM(COUNTIFS('Planificación 2026-1'!F:F,"HUAURA",'Planificación 2026-1'!W:W,C11,'Planificación 2026-1'!H:H,"T2"))>0,"P37"," ") | BW11: =IF(SUM(COUNTIFS('Planificación 2026-1'!F:F,"HUAURA",'Planificación 2026-1'!W:W,C11,'Planificación 2026-1'!H:H,"AE"))>0,"P38"," ") | BX11: =IF(SUM(COUNTIFS('Planificación 2026-1'!F:F,"HUAURA",'Planificación 2026-1'!W:W,C11,'Planificación 2026-1'!H:H,"T4"))>0,"P55"," ") | BY11: =SUMIFS('Planificación 2026-1'!R:R,'Planificación 2026-1'!W:W,C11,'Planificación 2026-1'!H:H,"AF",'Planificación 2026-1'!I:I,">2") -> 0 | BZ11: =SUMIFS('Planificación 2026-1'!R:R,'Planificación 2026-1'!W:W,C11,'Planificación 2026-1'!H:H,"EN",'Planificación 2026-1'!I:I,">2") -> 0 | CA11: =SUMIFS('Planificación 2026-1'!R:R,'Planificación 2026-1'!W:W,C11,'Planificación 2026-1'!H:H,"IS",'Planificación 2026-1'!I:I,">2") -> 0 | CB11: =SUMIFS('Planificación 2026-1'!R:R,'Planificación 2026-1'!W:W,C11,'Planificación 2026-1'!H:H,"PS",'Planificación 2026-1'!I:I,">2") -> 0 | CC11: =SUMIFS('Planificación 2026-1'!R:R,'Planificación 2026-1'!W:W,C11,'Planificación 2026-1'!H:H,"IN",'Planificación 2026-1'!I:I,">2") -> 4 | CD11: =SUMIFS('Planificación 2026-1'!R:R,'Planificación 2026-1'!W:W,C11,'Planificación 2026-1'!H:H,"CA",'Planificación 2026-1'!I:I,">2") -> 0 | CE11: =SUMIFS('Planificación 2026-1'!R:R,'Planificación 2026-1'!W:W,C11,'Planificación 2026-1'!H:H,"DE",'Planificación 2026-1'!I:I,">2") -> 29 | CF11: =SUMIFS('Planificación 2026-1'!R:R,'Planificación 2026-1'!W:W,C11,'Planificación 2026-1'!H:H,"OB",'Planificación 2026-1'!I:I,">2") -> 0 | CG11: =SUMIFS('Planificación 2026-1'!R:R,'Planificación 2026-1'!W:W,C11,'Planificación 2026-1'!H:H,"MH",'Planificación 2026-1'!I:I,">2") -> 0 | CH11: =SUMIFS('Planificación 2026-1'!R:R,'Planificación 2026-1'!W:W,C11,'Planificación 2026-1'!H:H,"IC",'Planificación 2026-1'!I:I,">2") -> 0 | CI11: =SUMIFS('Planificación 2026-1'!R:R,'Planificación 2026-1'!W:W,C11,'Planificación 2026-1'!H:H,"AR",'Planificación 2026-1'!I:I,">2") -> 0 | CJ11: =SUMIFS('Planificación 2026-1'!R:R,'Planificación 2026-1'!W:W,C11,'Planificación 2026-1'!H:H,"T1",'Planificación 2026-1'!I:I,">2") -> 0 | CK11: =SUMIFS('Planificación 2026-1'!R:R,'Planificación 2026-1'!W:W,C11,'Planificación 2026-1'!H:H,"T3",'Planificación 2026-1'!I:I,">2") -> 0 | CL11: =SUMIFS('Planificación 2026-1'!R:R,'Planificación 2026-1'!W:W,C11,'Planificación 2026-1'!H:H,"T2",'Planificación 2026-1'!I:I,">2") -> 0 | CM11: =SUMIFS('Planificación 2026-1'!R:R,'Planificación 2026-1'!W:W,C11,'Planificación 2026-1'!H:H,"AE",'Planificación 2026-1'!I:I,">2") -> 0 | CN11: =SUMIFS('Planificación 2026-1'!R:R,'Planificación 2026-1'!W:W,C11,'Planificación 2026-1'!H:H,"T4",'Planificación 2026-1'!I:I,">2") -> 0 | CO11: =SUMIFS('Planificación 2026-1'!R:R,'Planificación 2026-1'!W:W,C11,'Planificación 2026-1'!H:H,"AF",'Planificación 2026-1'!I:I,"<3") -> 0 | CP11: =SUMIFS('Planificación 2026-1'!R:R,'Planificación 2026-1'!W:W,C11,'Planificación 2026-1'!H:H,"EN",'Planificación 2026-1'!I:I,"<3") -> 0 | CQ11: =SUMIFS('Planificación 2026-1'!R:R,'Planificación 2026-1'!W:W,C11,'Planificación 2026-1'!H:H,"IS",'Planificación 2026-1'!I:I,"<3") -> 0 | CR11: =SUMIFS('Planificación 2026-1'!R:R,'Planificación 2026-1'!W:W,C11,'Planificación 2026-1'!H:H,"PS",'Planificación 2026-1'!I:I,"<3") -> 0 | CS11: =SUMIFS('Planificación 2026-1'!R:R,'Planificación 2026-1'!W:W,C11,'Planificación 2026-1'!H:H,"IN",'Planificación 2026-1'!I:I,"<3") -> 0 | CT11: =SUMIFS('Planificación 2026-1'!R:R,'Planificación 2026-1'!W:W,C11,'Planificación 2026-1'!H:H,"CA",'Planificación 2026-1'!I:I,"<3") -> 0 | CU11: =SUMIFS('Planificación 2026-1'!R:R,'Planificación 2026-1'!W:W,C11,'Planificación 2026-1'!H:H,"DE",'Planificación 2026-1'!I:I,"<3") -> 0 | CV11: =SUMIFS('Planificación 2026-1'!R:R,'Planificación 2026-1'!W:W,C11,'Planificación 2026-1'!H:H,"OB",'Planificación 2026-1'!I:I,"<3") -> 0 | CW11: =SUMIFS('Planificación 2026-1'!R:R,'Planificación 2026-1'!W:W,C11,'Planificación 2026-1'!H:H,"MH",'Planificación 2026-1'!I:I,"<3") -> 0 | CX11: =SUMIFS('Planificación 2026-1'!R:R,'Planificación 2026-1'!W:W,C11,'Planificación 2026-1'!H:H,"IC",'Planificación 2026-1'!I:I,"<3") -> 0 | CY11: =SUMIFS('Planificación 2026-1'!R:R,'Planificación 2026-1'!W:W,C11,'Planificación 2026-1'!H:H,"AR",'Planificación 2026-1'!I:I,"<3") -> 0 | CZ11: =SUMIFS('Planificación 2026-1'!R:R,'Planificación 2026-1'!W:W,C11,'Planificación 2026-1'!H:H,"T1",'Planificación 2026-1'!I:I,"<3") -> 0 | DA11: =SUMIFS('Planificación 2026-1'!R:R,'Planificación 2026-1'!W:W,C11,'Planificación 2026-1'!H:H,"T3",'Planificación 2026-1'!I:I,"<3") -> 0 | DB11: =SUMIFS('Planificación 2026-1'!R:R,'Planificación 2026-1'!W:W,C11,'Planificación 2026-1'!H:H,"T2",'Planificación 2026-1'!I:I,"<3") -> 0 | DC11: =SUMIFS('Planificación 2026-1'!R:R,'Planificación 2026-1'!W:W,C11,'Planificación 2026-1'!H:H,"AE",'Planificación 2026-1'!I:I,"<3") -> 0 | DD11: =SUMIFS('Planificación 2026-1'!R:R,'Planificación 2026-1'!W:W,C11,'Planificación 2026-1'!H:H,"T4",'Planificación 2026-1'!I:I,"<3") -> 0 | DE11: =TRIM(CONCATENATE(I11,J11,K11,L11,M11,N11,O11,P11,Q11,R11,S11,T11,U11,V11,W11,X11,Y11)) -> P06 P08 | DF11: =IF(C11="","",SUMIFS('Planificación 2026-1'!R:R,'Planificación 2026-1'!W:W,C11,'Planificación 2026-1'!F:F,"PRINCIPAL",'Planificación 2026-1'!X:X,"VIRTUAL")) -> 5 | DG11: =IF(C11="","",SUMIFS('Planificación 2026-1'!R:R,'Planificación 2026-1'!W:W,C11,'Planificación 2026-1'!F:F,"PRINCIPAL",'Planificación 2026-1'!X:X,"PRESENCIAL")) -> 20 | DH11: =IF(C11="","",SUMIFS('Planificación 2026-1'!R:R,'Planificación 2026-1'!W:W,C11,'Planificación 2026-1'!F:F,"PRINCIPAL",'Planificación 2026-1'!X:X,"HIBRIDO PRESENCIAL")) -> 0 | DI11: =TRIM(CONCATENATE(Z11,AA11,AB11,AC11,AD11,AE11,AF11,AG11,AH11,AI11,AJ11,AK11,AL11,AM11,AN11,AO11,AP11)) -> P08 | DJ11: =IF(C11="","",SUMIFS('Planificación 2026-1'!R:R,'Planificación 2026-1'!W:W,C11,'Planificación 2026-1'!F:F,"FILIAL",'Planificación 2026-1'!X:X,"VIRTUAL")) -> 4 | DK11: =IF(C11="","",SUMIFS('Planificación 2026-1'!R:R,'Planificación 2026-1'!W:W,C11,'Planificación 2026-1'!F:F,"FILIAL",'Planificación 2026-1'!X:X,"PRESENCIAL")) -> 0 | DL11: =IF(C11="","",SUMIFS('Planificación 2026-1'!R:R,'Planificación 2026-1'!W:W,C11,'Planificación 2026-1'!F:F,"FILIAL",'Planificación 2026-1'!X:X,"HIBRIDO PRESENCIAL")) -> 0 | DM11: =TRIM(CONCATENATE(AQ11,AR11,AS11,AT11,AU11,AV11,AW11,AX11,AY11,AZ11,BA11,BB11,BC11,BD11,BE11,BF11,BG11)) | DN11: =IF(C11="","",SUMIFS('Planificación 2026-1'!R:R,'Planificación 2026-1'!W:W,C11,'Planificación 2026-1'!F:F,"SUNAMPE",'Planificación 2026-1'!X:X,"VIRTUAL")) -> 0 | DO11: =IF(C11="","",SUMIFS('Planificación 2026-1'!R:R,'Planificación 2026-1'!W:W,C11,'Planificación 2026-1'!F:F,"SUNAMPE",'Planificación 2026-1'!X:X,"PRESENCIAL")) -> 0 | DP11: =TRIM(CONCATENATE(BH11,BI11,BJ11,BK11,BL11,BM11,BN11,BO11,BP11,BQ11,BR11,BS11,BT11,BU11,BV11,BW11,BX11)) | DQ11: =IF(C11="","",SUMIFS('Planificación 2026-1'!R:R,'Planificación 2026-1'!W:W,C11,'Planificación 2026-1'!F:F,"HUAURA",'Planificación 2026-1'!X:X,"VIRTUAL")) -> 0 | DR11: =IF(C11="","",SUMIFS('Planificación 2026-1'!R:R,'Planificación 2026-1'!W:W,C11,'Planificación 2026-1'!F:F,"HUAURA",'Planificación 2026-1'!X:X,"PRESENCIAL")) -> 0 | DS11: =SUMIFS('Planificación 2026-1'!R:R,'Planificación 2026-1'!W:W,C11,'Planificación 2026-1'!F:F,"PRINCIPAL",'Planificación 2026-1'!X:X,"VIRTUAL",'Planificación 2026-1'!I:I,">2") -> 5 | DT11: =SUMIFS('Planificación 2026-1'!R:R,'Planificación 2026-1'!W:W,C11,'Planificación 2026-1'!F:F,"PRINCIPAL",'Planificación 2026-1'!X:X,"<>VIRTUAL",'Planificación 2026-1'!I:I,">2") -> 24 | DU11: =SUMIFS('Planificación 2026-1'!R:R,'Planificación 2026-1'!W:W,C11,'Planificación 2026-1'!F:F,"SUNAMPE",'Planificación 2026-1'!X:X,"VIRTUAL",'Planificación 2026-1'!I:I,">2") -> 0 | DV11: =SUMIFS('Planificación 2026-1'!R:R,'Planificación 2026-1'!W:W,C11,'Planificación 2026-1'!F:F,"SUNAMPE",'Planificación 2026-1'!X:X,"<>VIRTUAL",'Planificación 2026-1'!I:I,">2") -> 0 | DW11: =SUMIFS('Planificación 2026-1'!R:R,'Planificación 2026-1'!W:W,C11,'Planificación 2026-1'!F:F,"FILIAL",'Planificación 2026-1'!X:X,"VIRTUAL",'Planificación 2026-1'!I:I,">2") -> 4 | DX11: =SUMIFS('Planificación 2026-1'!R:R,'Planificación 2026-1'!W:W,C11,'Planificación 2026-1'!F:F,"FILIAL",'Planificación 2026-1'!X:X,"<>VIRTUAL",'Planificación 2026-1'!I:I,">2") -> 0 | DY11: =SUMIFS('Planificación 2026-1'!R:R,'Planificación 2026-1'!W:W,C11,'Planificación 2026-1'!F:F,"PORUMA",'Planificación 2026-1'!X:X,"VIRTUAL",'Planificación 2026-1'!I:I,">2") -> 0 | DZ11: =SUMIFS('Planificación 2026-1'!R:R,'Planificación 2026-1'!W:W,C11,'Planificación 2026-1'!F:F,"PORUMA",'Planificación 2026-1'!X:X,"<>VIRTUAL",'Planificación 2026-1'!I:I,">2") -> 0 | EA11: =SUMIFS('Planificación 2026-1'!R:R,'Planificación 2026-1'!W:W,C11,'Planificación 2026-1'!F:F,"HUAURA",'Planificación 2026-1'!X:X,"VIRTUAL",'Planificación 2026-1'!I:I,">2") -> 0 | EB11: =SUMIFS('Planificación 2026-1'!R:R,'Planificación 2026-1'!W:W,C11,'Planificación 2026-1'!F:F,"HUAURA",'Planificación 2026-1'!X:X,"<>VIRTUAL",'Planificación 2026-1'!I:I,">2") -> 0 | EC11: =SUMIFS('Planificación 2026-1'!R:R,'Planificación 2026-1'!W:W,C11,'Planificación 2026-1'!F:F,"PRINCIPAL",'Planificación 2026-1'!X:X,"VIRTUAL",'Planificación 2026-1'!I:I,"<3") -> 0 | ED11: =SUMIFS('Planificación 2026-1'!R:R,'Planificación 2026-1'!W:W,C11,'Planificación 2026-1'!F:F,"PRINCIPAL",'Planificación 2026-1'!X:X,"<>VIRTUAL",'Planificación 2026-1'!I:I,"<3") -> 0 | EE11: =SUMIFS('Planificación 2026-1'!R:R,'Planificación 2026-1'!W:W,C11,'Planificación 2026-1'!F:F,"SUNAMPE",'Planificación 2026-1'!X:X,"VIRTUAL",'Planificación 2026-1'!I:I,"<3") -> 0 | EF11: =SUMIFS('Planificación 2026-1'!R:R,'Planificación 2026-1'!W:W,C11,'Planificación 2026-1'!F:F,"SUNAMPE",'Planificación 2026-1'!X:X,"<>VIRTUAL",'Planificación 2026-1'!I:I,"<3") -> 0 | EG11: =SUMIFS('Planificación 2026-1'!R:R,'Planificación 2026-1'!W:W,C11,'Planificación 2026-1'!F:F,"FILIAL",'Planificación 2026-1'!X:X,"VIRTUAL",'Planificación 2026-1'!I:I,"<3") -> 0 | EH11: =SUMIFS('Planificación 2026-1'!R:R,'Planificación 2026-1'!W:W,C11,'Planificación 2026-1'!F:F,"FILIAL",'Planificación 2026-1'!X:X,"<>VIRTUAL",'Planificación 2026-1'!I:I,"<3") -> 0 | EI11: =SUMIFS('Planificación 2026-1'!R:R,'Planificación 2026-1'!W:W,C11,'Planificación 2026-1'!F:F,"PORUMA",'Planificación 2026-1'!X:X,"VIRTUAL",'Planificación 2026-1'!I:I,"<3") -> 0 | EJ11: =SUMIFS('Planificación 2026-1'!R:R,'Planificación 2026-1'!W:W,C11,'Planificación 2026-1'!F:F,"PORUMA",'Planificación 2026-1'!X:X,"<>VIRTUAL",'Planificación 2026-1'!I:I,"<3") -> 0 | EK11: =SUMIFS('Planificación 2026-1'!R:R,'Planificación 2026-1'!W:W,C11,'Planificación 2026-1'!F:F,"HUAURA",'Planificación 2026-1'!X:X,"VIRTUAL",'Planificación 2026-1'!I:I,"<3") -> 0 | EL11: =SUMIFS('Planificación 2026-1'!R:R,'Planificación 2026-1'!W:W,C11,'Planificación 2026-1'!F:F,"HUAURA",'Planificación 2026-1'!X:X,"<>VIRTUAL",'Planificación 2026-1'!I:I,"<3") -> 0 | EN11: =DS11+DW11+EA11+EC11+EG11+EK11+DU11+EE11 -> 9 | EO11: =DT11+DX11+EB11+ED11+EH11+EL11+DV11+EF11 -> 24 | EP11: =EXACT(SUM(EN11:EO11),D11) -> TRUE | EQ11: =IF(AND(DT11=0,DX11=0,EB11=0),"",IF(COUNTIF(DT11:EB11,">0")=1,IF(DT11>0,"SEDE",IF(DX11>0,"FILIAL","HUAURA")),IF(COUNTIF(DT11:EB11,">0")=2,IF(AND(DT11>0,DX11>0),"SEDE-FILIAL",IF(AND(DT11>0,EB11>0),"SEDE-HUAURA","FILIAL-HUAURA")),"SEDE-FILIAL-HUAURA"))) -> FILIAL-HUAURA | ER11: =IF(EN11=0,"PRESENCIAL",IF(EO11=0,"VIRTUAL",IF(EN11>EO11,"MAS VIRTUAL",IF(EO11>EN11,"MAS PRESENCIAL","AMBOS")))) -> MAS PRESENCIAL
B12: 9 | C12: ALMEYDA CARBAJAL JOSE ARMANDO | D12: =SUMIF('Planificación 2026-1'!W:W,C12,'Planificación 2026-1'!R:R) -> 39 | E12: TC | F12: RENOVACIÓN | G12: SEDE | H12: INGENIERÍA INDUSTRIAL - EEGG | I12: =IF(SUM(COUNTIFS('Planificación 2026-1'!F:F,"PRINCIPAL",'Planificación 2026-1'!W:W,C12,'Planificación 2026-1'!H:H,"AF"))>0,"P01"," ") | J12: =IF(SUM(COUNTIFS('Planificación 2026-1'!F:F,"PRINCIPAL",'Planificación 2026-1'!W:W,C12,'Planificación 2026-1'!H:H,"EN"))>0,"P02"," ") | K12: =IF(SUM(COUNTIFS('Planificación 2026-1'!F:F,"PRINCIPAL",'Planificación 2026-1'!W:W,C12,'Planificación 2026-1'!H:H,"IS"))>0,"P03"," ") -> P03 | L12: =IF(SUM(COUNTIFS('Planificación 2026-1'!F:F,"PRINCIPAL",'Planificación 2026-1'!W:W,C12,'Planificación 2026-1'!H:H,"PS"))>0,"P04"," ") | N12: =IF(SUM(COUNTIFS('Planificación 2026-1'!F:F,"PRINCIPAL",'Planificación 2026-1'!W:W,C12,'Planificación 2026-1'!H:H,"IN"))>0,"P06"," ") -> P06 | O12: =IF(SUM(COUNTIFS('Planificación 2026-1'!F:F,"PRINCIPAL",'Planificación 2026-1'!W:W,C12,'Planificación 2026-1'!H:H,"CA"))>0,"P07"," ") | P12: =IF(SUM(COUNTIFS('Planificación 2026-1'!F:F,"PRINCIPAL",'Planificación 2026-1'!W:W,C12,'Planificación 2026-1'!H:H,"DE"))>0,"P08"," ") | Q12: =IF(SUM(COUNTIFS('Planificación 2026-1'!F:F,"PRINCIPAL",'Planificación 2026-1'!W:W,C12,'Planificación 2026-1'!H:H,"OB"))>0,"P09"," ") | R12: =IF(SUM(COUNTIFS('Planificación 2026-1'!F:F,"PRINCIPAL",'Planificación 2026-1'!W:W,C12,'Planificación 2026-1'!H:H,"MH"))>0,"P31"," ") | S12: =IF(SUM(COUNTIFS('Planificación 2026-1'!F:F,"PRINCIPAL",'Planificación 2026-1'!W:W,C12,'Planificación 2026-1'!H:H,"IC"))>0,"P32"," ") -> P32 | T12: =IF(SUM(COUNTIFS('Planificación 2026-1'!F:F,"PRINCIPAL",'Planificación 2026-1'!W:W,C12,'Planificación 2026-1'!H:H,"AR"))>0,"P34"," ") | U12: =IF(SUM(COUNTIFS('Planificación 2026-1'!F:F,"PRINCIPAL",'Planificación 2026-1'!W:W,C12,'Planificación 2026-1'!H:H,"T1"))>0,"P35"," ") | V12: =IF(SUM(COUNTIFS('Planificación 2026-1'!F:F,"PRINCIPAL",'Planificación 2026-1'!W:W,C12,'Planificación 2026-1'!H:H,"T3"))>0,"P36"," ") | W12: =IF(SUM(COUNTIFS('Planificación 2026-1'!F:F,"PRINCIPAL",'Planificación 2026-1'!W:W,C12,'Planificación 2026-1'!H:H,"T2"))>0,"P37"," ") | X12: =IF(SUM(COUNTIFS('Planificación 2026-1'!F:F,"PRINCIPAL",'Planificación 2026-1'!W:W,C12,'Planificación 2026-1'!H:H,"AE"))>0,"P38"," ") | Y12: =IF(SUM(COUNTIFS('Planificación 2026-1'!F:F,"PRINCIPAL",'Planificación 2026-1'!W:W,C12,'Planificación 2026-1'!H:H,"T4"))>0,"P55"," ") | Z12: =IF(SUM(COUNTIFS('Planificación 2026-1'!F:F,"FILIAL",'Planificación 2026-1'!W:W,C12,'Planificación 2026-1'!H:H,"AF"))>0," P01"," ") | AA12: =IF(SUM(COUNTIFS('Planificación 2026-1'!F:F,"FILIAL",'Planificación 2026-1'!W:W,C12,'Planificación 2026-1'!H:H,"EN"))>0,"P02"," ") | AB12: =IF(SUM(COUNTIFS('Planificación 2026-1'!F:F,"FILIAL",'Planificación 2026-1'!W:W,C12,'Planificación 2026-1'!H:H,"IS"))>0,"P03"," ") | AC12: =IF(SUM(COUNTIFS('Planificación 2026-1'!F:F,"FILIAL",'Planificación 2026-1'!W:W,C12,'Planificación 2026-1'!H:H,"PS"))>0,"P04"," ") | AE12: =IF(SUM(COUNTIFS('Planificación 2026-1'!F:F,"FILIAL",'Planificación 2026-1'!W:W,C12,'Planificación 2026-1'!H:H,"IN"))>0,"P06"," ") | AF12: =IF(SUM(COUNTIFS('Planificación 2026-1'!F:F,"FILIAL",'Planificación 2026-1'!W:W,C12,'Planificación 2026-1'!H:H,"CA"))>0,"P07"," ") | AG12: =IF(SUM(COUNTIFS('Planificación 2026-1'!F:F,"FILIAL",'Planificación 2026-1'!W:W,C12,'Planificación 2026-1'!H:H,"DE"))>0,"P08"," ") | AH12: =IF(SUM(COUNTIFS('Planificación 2026-1'!F:F,"FILIAL",'Planificación 2026-1'!W:W,C12,'Planificación 2026-1'!H:H,"OB"))>0,"P09"," ") | AI12: =IF(SUM(COUNTIFS('Planificación 2026-1'!F:F,"FILIAL",'Planificación 2026-1'!W:W,C12,'Planificación 2026-1'!H:H,"MH"))>0,"P31"," ") | AJ12: =IF(SUM(COUNTIFS('Planificación 2026-1'!F:F,"FILIAL",'Planificación 2026-1'!W:W,C12,'Planificación 2026-1'!H:H,"IC"))>0,"P32"," ") -> P32 | AK12: =IF(SUM(COUNTIFS('Planificación 2026-1'!F:F,"FILIAL",'Planificación 2026-1'!W:W,C12,'Planificación 2026-1'!H:H,"AR"))>0,"P34"," ") | AL12: =IF(SUM(COUNTIFS('Planificación 2026-1'!F:F,"FILIAL",'Planificación 2026-1'!W:W,C12,'Planificación 2026-1'!H:H,"T1"))>0,"P35"," ") | AM12: =IF(SUM(COUNTIFS('Planificación 2026-1'!F:F,"FILIAL",'Planificación 2026-1'!W:W,C12,'Planificación 2026-1'!H:H,"T3"))>0,"P36"," ") | AN12: =IF(SUM(COUNTIFS('Planificación 2026-1'!F:F,"FILIAL",'Planificación 2026-1'!W:W,C12,'Planificación 2026-1'!H:H,"T2"))>0,"P37"," ") | AO12: =IF(SUM(COUNTIFS('Planificación 2026-1'!F:F,"FILIAL",'Planificación 2026-1'!W:W,C12,'Planificación 2026-1'!H:H,"AE"))>0,"P38"," ") | AP12: =IF(SUM(COUNTIFS('Planificación 2026-1'!F:F,"FILIAL",'Planificación 2026-1'!W:W,C12,'Planificación 2026-1'!H:H,"T4"))>0,"P55"," ") | AQ12: =IF(SUM(COUNTIFS('Planificación 2026-1'!F:F,"SUNAMPE",'Planificación 2026-1'!W:W,C12,'Planificación 2026-1'!H:H,"AF"))>0," P01"," ") | AR12: =IF(SUM(COUNTIFS('Planificación 2026-1'!F:F,"SUNAMPE",'Planificación 2026-1'!W:W,C12,'Planificación 2026-1'!H:H,"EN"))>0,"P02"," ") | AS12: =IF(SUM(COUNTIFS('Planificación 2026-1'!F:F,"SUNAMPE",'Planificación 2026-1'!W:W,C12,'Planificación 2026-1'!H:H,"IS"))>0,"P03"," ") | AT12: =IF(SUM(COUNTIFS('Planificación 2026-1'!F:F,"SUNAMPE",'Planificación 2026-1'!W:W,C12,'Planificación 2026-1'!H:H,"PS"))>0,"P04"," ") | AV12: =IF(SUM(COUNTIFS('Planificación 2026-1'!F:F,"SUNAMPE",'Planificación 2026-1'!W:W,C12,'Planificación 2026-1'!H:H,"IN"))>0,"P06"," ") | AW12: =IF(SUM(COUNTIFS('Planificación 2026-1'!F:F,"SUNAMPE",'Planificación 2026-1'!W:W,C12,'Planificación 2026-1'!H:H,"CA"))>0,"P07"," ") | AX12: =IF(SUM(COUNTIFS('Planificación 2026-1'!F:F,"SUNAMPE",'Planificación 2026-1'!W:W,C12,'Planificación 2026-1'!H:H,"DE"))>0,"P08"," ") | AY12: =IF(SUM(COUNTIFS('Planificación 2026-1'!F:F,"SUNAMPE",'Planificación 2026-1'!W:W,C12,'Planificación 2026-1'!H:H,"OB"))>0,"P09"," ") | AZ12: =IF(SUM(COUNTIFS('Planificación 2026-1'!F:F,"SUNAMPE",'Planificación 2026-1'!W:W,C12,'Planificación 2026-1'!H:H,"MH"))>0,"P31"," ") | BA12: =IF(SUM(COUNTIFS('Planificación 2026-1'!F:F,"SUNAMPE",'Planificación 2026-1'!W:W,C12,'Planificación 2026-1'!H:H,"IC"))>0,"P32"," ") | BB12: =IF(SUM(COUNTIFS('Planificación 2026-1'!F:F,"SUNAMPE",'Planificación 2026-1'!W:W,C12,'Planificación 2026-1'!H:H,"AR"))>0,"P34"," ") | BC12: =IF(SUM(COUNTIFS('Planificación 2026-1'!F:F,"SUNAMPE",'Planificación 2026-1'!W:W,C12,'Planificación 2026-1'!H:H,"T1"))>0,"P35"," ") | BD12: =IF(SUM(COUNTIFS('Planificación 2026-1'!F:F,"SUNAMPE",'Planificación 2026-1'!W:W,C12,'Planificación 2026-1'!H:H,"T3"))>0,"P36"," ") | BE12: =IF(SUM(COUNTIFS('Planificación 2026-1'!F:F,"SUNAMPE",'Planificación 2026-1'!W:W,C12,'Planificación 2026-1'!H:H,"T2"))>0,"P37"," ") | BF12: =IF(SUM(COUNTIFS('Planificación 2026-1'!F:F,"SUNAMPE",'Planificación 2026-1'!W:W,C12,'Planificación 2026-1'!H:H,"AE"))>0,"P38"," ") | BG12: =IF(SUM(COUNTIFS('Planificación 2026-1'!F:F,"SUNAMPE",'Planificación 2026-1'!W:W,C12,'Planificación 2026-1'!H:H,"T4"))>0,"P55"," ") | BH12: =IF(SUM(COUNTIFS('Planificación 2026-1'!F:F,"HUAURA",'Planificación 2026-1'!W:W,C12,'Planificación 2026-1'!H:H,"AF"))>0," P01"," ") | BI12: =IF(SUM(COUNTIFS('Planificación 2026-1'!F:F,"HUAURA",'Planificación 2026-1'!W:W,C12,'Planificación 2026-1'!H:H,"EN"))>0,"P02"," ") | BJ12: =IF(SUM(COUNTIFS('Planificación 2026-1'!F:F,"HUAURA",'Planificación 2026-1'!W:W,C12,'Planificación 2026-1'!H:H,"IS"))>0,"P03"," ") | BK12: =IF(SUM(COUNTIFS('Planificación 2026-1'!F:F,"HUAURA",'Planificación 2026-1'!W:W,C12,'Planificación 2026-1'!H:H,"PS"))>0,"P04"," ") | BM12: =IF(SUM(COUNTIFS('Planificación 2026-1'!F:F,"HUAURA",'Planificación 2026-1'!W:W,C12,'Planificación 2026-1'!H:H,"IN"))>0,"P06"," ") | BN12: =IF(SUM(COUNTIFS('Planificación 2026-1'!F:F,"HUAURA",'Planificación 2026-1'!W:W,C12,'Planificación 2026-1'!H:H,"CA"))>0,"P07"," ") | BO12: =IF(SUM(COUNTIFS('Planificación 2026-1'!F:F,"HUAURA",'Planificación 2026-1'!W:W,C12,'Planificación 2026-1'!H:H,"DE"))>0,"P08"," ") | BP12: =IF(SUM(COUNTIFS('Planificación 2026-1'!F:F,"HUAURA",'Planificación 2026-1'!W:W,C12,'Planificación 2026-1'!H:H,"OB"))>0,"P09"," ") | BQ12: =IF(SUM(COUNTIFS('Planificación 2026-1'!F:F,"HUAURA",'Planificación 2026-1'!W:W,C12,'Planificación 2026-1'!H:H,"MH"))>0,"P31"," ") | BR12: =IF(SUM(COUNTIFS('Planificación 2026-1'!F:F,"HUAURA",'Planificación 2026-1'!W:W,C12,'Planificación 2026-1'!H:H,"IC"))>0,"P32"," ") | BS12: =IF(SUM(COUNTIFS('Planificación 2026-1'!F:F,"HUAURA",'Planificación 2026-1'!W:W,C12,'Planificación 2026-1'!H:H,"AR"))>0,"P34"," ") | BT12: =IF(SUM(COUNTIFS('Planificación 2026-1'!F:F,"HUAURA",'Planificación 2026-1'!W:W,C12,'Planificación 2026-1'!H:H,"T1"))>0,"P35"," ") | BU12: =IF(SUM(COUNTIFS('Planificación 2026-1'!F:F,"HUAURA",'Planificación 2026-1'!W:W,C12,'Planificación 2026-1'!H:H,"T3"))>0,"P36"," ") | BV12: =IF(SUM(COUNTIFS('Planificación 2026-1'!F:F,"HUAURA",'Planificación 2026-1'!W:W,C12,'Planificación 2026-1'!H:H,"T2"))>0,"P37"," ") | BW12: =IF(SUM(COUNTIFS('Planificación 2026-1'!F:F,"HUAURA",'Planificación 2026-1'!W:W,C12,'Planificación 2026-1'!H:H,"AE"))>0,"P38"," ") | BX12: =IF(SUM(COUNTIFS('Planificación 2026-1'!F:F,"HUAURA",'Planificación 2026-1'!W:W,C12,'Planificación 2026-1'!H:H,"T4"))>0,"P55"," ") | BY12: =SUMIFS('Planificación 2026-1'!R:R,'Planificación 2026-1'!W:W,C12,'Planificación 2026-1'!H:H,"AF",'Planificación 2026-1'!I:I,">2") -> 0 | BZ12: =SUMIFS('Planificación 2026-1'!R:R,'Planificación 2026-1'!W:W,C12,'Planificación 2026-1'!H:H,"EN",'Planificación 2026-1'!I:I,">2") -> 0 | CA12: =SUMIFS('Planificación 2026-1'!R:R,'Planificación 2026-1'!W:W,C12,'Planificación 2026-1'!H:H,"IS",'Planificación 2026-1'!I:I,">2") -> 0 | CB12: =SUMIFS('Planificación 2026-1'!R:R,'Planificación 2026-1'!W:W,C12,'Planificación 2026-1'!H:H,"PS",'Planificación 2026-1'!I:I,">2") -> 0 | CC12: =SUMIFS('Planificación 2026-1'!R:R,'Planificación 2026-1'!W:W,C12,'Planificación 2026-1'!H:H,"IN",'Planificación 2026-1'!I:I,">2") -> 0 | CD12: =SUMIFS('Planificación 2026-1'!R:R,'Planificación 2026-1'!W:W,C12,'Planificación 2026-1'!H:H,"CA",'Planificación 2026-1'!I:I,">2") -> 0 | CE12: =SUMIFS('Planificación 2026-1'!R:R,'Planificación 2026-1'!W:W,C12,'Planificación 2026-1'!H:H,"DE",'Planificación 2026-1'!I:I,">2") -> 0 | CF12: =SUMIFS('Planificación 2026-1'!R:R,'Planificación 2026-1'!W:W,C12,'Planificación 2026-1'!H:H,"OB",'Planificación 2026-1'!I:I,">2") -> 0 | CG12: =SUMIFS('Planificación 2026-1'!R:R,'Planificación 2026-1'!W:W,C12,'Planificación 2026-1'!H:H,"MH",'Planificación 2026-1'!I:I,">2") -> 0 | CH12: =SUMIFS('Planificación 2026-1'!R:R,'Planificación 2026-1'!W:W,C12,'Planificación 2026-1'!H:H,"IC",'Planificación 2026-1'!I:I,">2") -> 4 | CI12: =SUMIFS('Planificación 2026-1'!R:R,'Planificación 2026-1'!W:W,C12,'Planificación 2026-1'!H:H,"AR",'Planificación 2026-1'!I:I,">2") -> 0 | CJ12: =SUMIFS('Planificación 2026-1'!R:R,'Planificación 2026-1'!W:W,C12,'Planificación 2026-1'!H:H,"T1",'Planificación 2026-1'!I:I,">2") -> 0 | CK12: =SUMIFS('Planificación 2026-1'!R:R,'Planificación 2026-1'!W:W,C12,'Planificación 2026-1'!H:H,"T3",'Planificación 2026-1'!I:I,">2") -> 0 | CL12: =SUMIFS('Planificación 2026-1'!R:R,'Planificación 2026-1'!W:W,C12,'Planificación 2026-1'!H:H,"T2",'Planificación 2026-1'!I:I,">2") -> 0 | CM12: =SUMIFS('Planificación 2026-1'!R:R,'Planificación 2026-1'!W:W,C12,'Planificación 2026-1'!H:H,"AE",'Planificación 2026-1'!I:I,">2") -> 0 | CN12: =SUMIFS('Planificación 2026-1'!R:R,'Planificación 2026-1'!W:W,C12,'Planificación 2026-1'!H:H,"T4",'Planificación 2026-1'!I:I,">2") -> 0 | CO12: =SUMIFS('Planificación 2026-1'!R:R,'Planificación 2026-1'!W:W,C12,'Planificación 2026-1'!H:H,"AF",'Planificación 2026-1'!I:I,"<3") -> 0 | CP12: =SUMIFS('Planificación 2026-1'!R:R,'Planificación 2026-1'!W:W,C12,'Planificación 2026-1'!H:H,"EN",'Planificación 2026-1'!I:I,"<3") -> 0 | CQ12: =SUMIFS('Planificación 2026-1'!R:R,'Planificación 2026-1'!W:W,C12,'Planificación 2026-1'!H:H,"IS",'Planificación 2026-1'!I:I,"<3") -> 5 | CR12: =SUMIFS('Planificación 2026-1'!R:R,'Planificación 2026-1'!W:W,C12,'Planificación 2026-1'!H:H,"PS",'Planificación 2026-1'!I:I,"<3") -> 0 | CS12: =SUMIFS('Planificación 2026-1'!R:R,'Planificación 2026-1'!W:W,C12,'Planificación 2026-1'!H:H,"IN",'Planificación 2026-1'!I:I,"<3") -> 30 | CT12: =SUMIFS('Planificación 2026-1'!R:R,'Planificación 2026-1'!W:W,C12,'Planificación 2026-1'!H:H,"CA",'Planificación 2026-1'!I:I,"<3") -> 0 | CU12: =SUMIFS('Planificación 2026-1'!R:R,'Planificación 2026-1'!W:W,C12,'Planificación 2026-1'!H:H,"DE",'Planificación 2026-1'!I:I,"<3") -> 0 | CV12: =SUMIFS('Planificación 2026-1'!R:R,'Planificación 2026-1'!W:W,C12,'Planificación 2026-1'!H:H,"OB",'Planificación 2026-1'!I:I,"<3") -> 0 | CW12: =SUMIFS('Planificación 2026-1'!R:R,'Planificación 2026-1'!W:W,C12,'Planificación 2026-1'!H:H,"MH",'Planificación 2026-1'!I:I,"<3") -> 0 | CX12: =SUMIFS('Planificación 2026-1'!R:R,'Planificación 2026-1'!W:W,C12,'Planificación 2026-1'!H:H,"IC",'Planificación 2026-1'!I:I,"<3") -> 0 | CY12: =SUMIFS('Planificación 2026-1'!R:R,'Planificación 2026-1'!W:W,C12,'Planificación 2026-1'!H:H,"AR",'Planificación 2026-1'!I:I,"<3") -> 0 | CZ12: =SUMIFS('Planificación 2026-1'!R:R,'Planificación 2026-1'!W:W,C12,'Planificación 2026-1'!H:H,"T1",'Planificación 2026-1'!I:I,"<3") -> 0 | DA12: =SUMIFS('Planificación 2026-1'!R:R,'Planificación 2026-1'!W:W,C12,'Planificación 2026-1'!H:H,"T3",'Planificación 2026-1'!I:I,"<3") -> 0 | DB12: =SUMIFS('Planificación 2026-1'!R:R,'Planificación 2026-1'!W:W,C12,'Planificación 2026-1'!H:H,"T2",'Planificación 2026-1'!I:I,"<3") -> 0 | DC12: =SUMIFS('Planificación 2026-1'!R:R,'Planificación 2026-1'!W:W,C12,'Planificación 2026-1'!H:H,"AE",'Planificación 2026-1'!I:I,"<3") -> 0 | DD12: =SUMIFS('Planificación 2026-1'!R:R,'Planificación 2026-1'!W:W,C12,'Planificación 2026-1'!H:H,"T4",'Planificación 2026-1'!I:I,"<3") -> 0 | DE12: =TRIM(CONCATENATE(I12,J12,K12,L12,M12,N12,O12,P12,Q12,R12,S12,T12,U12,V12,W12,X12,Y12)) -> P03 P06 P32 | DF12: =IF(C12="","",SUMIFS('Planificación 2026-1'!R:R,'Planificación 2026-1'!W:W,C12,'Planificación 2026-1'!F:F,"PRINCIPAL",'Planificación 2026-1'!X:X,"VIRTUAL")) -> 4 | DG12: =IF(C12="","",SUMIFS('Planificación 2026-1'!R:R,'Planificación 2026-1'!W:W,C12,'Planificación 2026-1'!F:F,"PRINCIPAL",'Planificación 2026-1'!X:X,"PRESENCIAL")) -> 5 | DH12: =IF(C12="","",SUMIFS('Planificación 2026-1'!R:R,'Planificación 2026-1'!W:W,C12,'Planificación 2026-1'!F:F,"PRINCIPAL",'Planificación 2026-1'!X:X,"HIBRIDO PRESENCIAL")) -> 10 | DI12: =TRIM(CONCATENATE(Z12,AA12,AB12,AC12,AD12,AE12,AF12,AG12,AH12,AI12,AJ12,AK12,AL12,AM12,AN12,AO12,AP12)) -> P32 | DJ12: =IF(C12="","",SUMIFS('Planificación 2026-1'!R:R,'Planificación 2026-1'!W:W,C12,'Planificación 2026-1'!F:F,"FILIAL",'Planificación 2026-1'!X:X,"VIRTUAL")) -> 0 | DK12: =IF(C12="","",SUMIFS('Planificación 2026-1'!R:R,'Planificación 2026-1'!W:W,C12,'Planificación 2026-1'!F:F,"FILIAL",'Planificación 2026-1'!X:X,"PRESENCIAL")) -> 0 | DL12: =IF(C12="","",SUMIFS('Planificación 2026-1'!R:R,'Planificación 2026-1'!W:W,C12,'Planificación 2026-1'!F:F,"FILIAL",'Planificación 2026-1'!X:X,"HIBRIDO PRESENCIAL")) -> 0 | DM12: =TRIM(CONCATENATE(AQ12,AR12,AS12,AT12,AU12,AV12,AW12,AX12,AY12,AZ12,BA12,BB12,BC12,BD12,BE12,BF12,BG12)) | DN12: =IF(C12="","",SUMIFS('Planificación 2026-1'!R:R,'Planificación 2026-1'!W:W,C12,'Planificación 2026-1'!F:F,"SUNAMPE",'Planificación 2026-1'!X:X,"VIRTUAL")) -> 0 | DO12: =IF(C12="","",SUMIFS('Planificación 2026-1'!R:R,'Planificación 2026-1'!W:W,C12,'Planificación 2026-1'!F:F,"SUNAMPE",'Planificación 2026-1'!X:X,"PRESENCIAL")) -> 0 | DP12: =TRIM(CONCATENATE(BH12,BI12,BJ12,BK12,BL12,BM12,BN12,BO12,BP12,BQ12,BR12,BS12,BT12,BU12,BV12,BW12,BX12)) | DQ12: =IF(C12="","",SUMIFS('Planificación 2026-1'!R:R,'Planificación 2026-1'!W:W,C12,'Planificación 2026-1'!F:F,"HUAURA",'Planificación 2026-1'!X:X,"VIRTUAL")) -> 0 | DR12: =IF(C12="","",SUMIFS('Planificación 2026-1'!R:R,'Planificación 2026-1'!W:W,C12,'Planificación 2026-1'!F:F,"HUAURA",'Planificación 2026-1'!X:X,"PRESENCIAL")) -> 0 | DS12: =SUMIFS('Planificación 2026-1'!R:R,'Planificación 2026-1'!W:W,C12,'Planificación 2026-1'!F:F,"PRINCIPAL",'Planificación 2026-1'!X:X,"VIRTUAL",'Planificación 2026-1'!I:I,">2") -> 4 | DT12: =SUMIFS('Planificación 2026-1'!R:R,'Planificación 2026-1'!W:W,C12,'Planificación 2026-1'!F:F,"PRINCIPAL",'Planificación 2026-1'!X:X,"<>VIRTUAL",'Planificación 2026-1'!I:I,">2") -> 0 | DU12: =SUMIFS('Planificación 2026-1'!R:R,'Planificación 2026-1'!W:W,C12,'Planificación 2026-1'!F:F,"SUNAMPE",'Planificación 2026-1'!X:X,"VIRTUAL",'Planificación 2026-1'!I:I,">2") -> 0 | DV12: =SUMIFS('Planificación 2026-1'!R:R,'Planificación 2026-1'!W:W,C12,'Planificación 2026-1'!F:F,"SUNAMPE",'Planificación 2026-1'!X:X,"<>VIRTUAL",'Planificación 2026-1'!I:I,">2") -> 0 | DW12: =SUMIFS('Planificación 2026-1'!R:R,'Planificación 2026-1'!W:W,C12,'Planificación 2026-1'!F:F,"FILIAL",'Planificación 2026-1'!X:X,"VIRTUAL",'Planificación 2026-1'!I:I,">2") -> 0 | DX12: =SUMIFS('Planificación 2026-1'!R:R,'Planificación 2026-1'!W:W,C12,'Planificación 2026-1'!F:F,"FILIAL",'Planificación 2026-1'!X:X,"<>VIRTUAL",'Planificación 2026-1'!I:I,">2") -> 0 | DY12: =SUMIFS('Planificación 2026-1'!R:R,'Planificación 2026-1'!W:W,C12,'Planificación 2026-1'!F:F,"PORUMA",'Planificación 2026-1'!X:X,"VIRTUAL",'Planificación 2026-1'!I:I,">2") -> 0 | DZ12: =SUMIFS('Planificación 2026-1'!R:R,'Planificación 2026-1'!W:W,C12,'Planificación 2026-1'!F:F,"PORUMA",'Planificación 2026-1'!X:X,"<>VIRTUAL",'Planificación 2026-1'!I:I,">2") -> 0 | EA12: =SUMIFS('Planificación 2026-1'!R:R,'Planificación 2026-1'!W:W,C12,'Planificación 2026-1'!F:F,"HUAURA",'Planificación 2026-1'!X:X,"VIRTUAL",'Planificación 2026-1'!I:I,">2") -> 0 | EB12: =SUMIFS('Planificación 2026-1'!R:R,'Planificación 2026-1'!W:W,C12,'Planificación 2026-1'!F:F,"HUAURA",'Planificación 2026-1'!X:X,"<>VIRTUAL",'Planificación 2026-1'!I:I,">2") -> 0 | EC12: =SUMIFS('Planificación 2026-1'!R:R,'Planificación 2026-1'!W:W,C12,'Planificación 2026-1'!F:F,"PRINCIPAL",'Planificación 2026-1'!X:X,"VIRTUAL",'Planificación 2026-1'!I:I,"<3") -> 0 | ED12: =SUMIFS('Planificación 2026-1'!R:R,'Planificación 2026-1'!W:W,C12,'Planificación 2026-1'!F:F,"PRINCIPAL",'Planificación 2026-1'!X:X,"<>VIRTUAL",'Planificación 2026-1'!I:I,"<3") -> 35 | EE12: =SUMIFS('Planificación 2026-1'!R:R,'Planificación 2026-1'!W:W,C12,'Planificación 2026-1'!F:F,"SUNAMPE",'Planificación 2026-1'!X:X,"VIRTUAL",'Planificación 2026-1'!I:I,"<3") -> 0 | EF12: =SUMIFS('Planificación 2026-1'!R:R,'Planificación 2026-1'!W:W,C12,'Planificación 2026-1'!F:F,"SUNAMPE",'Planificación 2026-1'!X:X,"<>VIRTUAL",'Planificación 2026-1'!I:I,"<3") -> 0 | EG12: =SUMIFS('Planificación 2026-1'!R:R,'Planificación 2026-1'!W:W,C12,'Planificación 2026-1'!F:F,"FILIAL",'Planificación 2026-1'!X:X,"VIRTUAL",'Planificación 2026-1'!I:I,"<3") -> 0 | EH12: =SUMIFS('Planificación 2026-1'!R:R,'Planificación 2026-1'!W:W,C12,'Planificación 2026-1'!F:F,"FILIAL",'Planificación 2026-1'!X:X,"<>VIRTUAL",'Planificación 2026-1'!I:I,"<3") -> 0 | EI12: =SUMIFS('Planificación 2026-1'!R:R,'Planificación 2026-1'!W:W,C12,'Planificación 2026-1'!F:F,"PORUMA",'Planificación 2026-1'!X:X,"VIRTUAL",'Planificación 2026-1'!I:I,"<3") -> 0 | EJ12: =SUMIFS('Planificación 2026-1'!R:R,'Planificación 2026-1'!W:W,C12,'Planificación 2026-1'!F:F,"PORUMA",'Planificación 2026-1'!X:X,"<>VIRTUAL",'Planificación 2026-1'!I:I,"<3") -> 0 | EK12: =SUMIFS('Planificación 2026-1'!R:R,'Planificación 2026-1'!W:W,C12,'Planificación 2026-1'!F:F,"HUAURA",'Planificación 2026-1'!X:X,"VIRTUAL",'Planificación 2026-1'!I:I,"<3") -> 0 | EL12: =SUMIFS('Planificación 2026-1'!R:R,'Planificación 2026-1'!W:W,C12,'Planificación 2026-1'!F:F,"HUAURA",'Planificación 2026-1'!X:X,"<>VIRTUAL",'Planificación 2026-1'!I:I,"<3") -> 0 | EN12: =DS12+DW12+EA12+EC12+EG12+EK12+DU12+EE12 -> 4 | EO12: =DT12+DX12+EB12+ED12+EH12+EL12+DV12+EF12 -> 35 | EP12: =EXACT(SUM(EN12:EO12),D12) -> TRUE | EQ12: =IF(AND(DT12=0,DX12=0,EB12=0),"",IF(COUNTIF(DT12:EB12,">0")=1,IF(DT12>0,"SEDE",IF(DX12>0,"FILIAL","HUAURA")),IF(COUNTIF(DT12:EB12,">0")=2,IF(AND(DT12>0,DX12>0),"SEDE-FILIAL",IF(AND(DT12>0,EB12>0),"SEDE-HUAURA","FILIAL-HUAURA")),"SEDE-FILIAL-HUAURA"))) | ER12: =IF(EN12=0,"PRESENCIAL",IF(EO12=0,"VIRTUAL",IF(EN12>EO12,"MAS VIRTUAL",IF(EO12>EN12,"MAS PRESENCIAL","AMBOS")))) -> MAS PRESENCIAL
